Workbook
Name \A: #REF!
Name \B: '[1]My Worksheet'!#REF!
Name \C: #REF!
Name \D: #REF!
Name \E: #REF!
Name \F: [2]LIIncSt!#REF!
Name \G: [2]LIIncSt!#REF!
Name \H: [2]LIIncSt!#REF!
Name \I: #REF!
Name \K: '[3]PAGE 7'!#REF!
Name \L: [2]LIIncSt!#REF!
Name \M: #REF!
Name \N: #REF!
Name \O: #REF!
Name \P: #REF!
Name \Q: [2]LIIncSt!#REF!
Name \R: #REF!
Name \S: #REF!
Name \T: #REF!
Name \V: '[4]Var. Anal.'!#REF!
Name \W: #REF!
Name \Z: #REF!
Name ______BUV2: '[5]FYTD 12 Gas'!$E$346
Name ______SEG2: '[5]FYTD 12 Gas'!$B$347
Name _____BUV2: '[5]FYTD 12 Elec '!$E$386
Name _____FYR10: #REF!
Name _____FYR11: #REF!
Name _____FYR12: #REF!
Name _____FYR2: #REF!
Name _____FYR3: #REF!
Name _____FYR4: #REF!
Name _____FYR5: #REF!
Name _____FYR6: #REF!
Name _____FYR7: #REF!
Name _____FYR8: #REF!
Name _____FYR9: #REF!
Name _____PC1: #REF!
Name _____PC10: #REF!
Name _____PC11: #REF!
Name _____PC12: #REF!
Name _____PC2: #REF!
Name _____PC3: #REF!
Name _____PC4: #REF!
Name _____PC5: #REF!
Name _____PC6: #REF!
Name _____PC7: #REF!
Name _____PC8: #REF!
Name _____PC9: #REF!
Name _____PER1: #REF!
Name _____PER10: #REF!
Name _____PER11: #REF!
Name _____PER12: #REF!
Name _____PER2: #REF!
Name _____PER3: #REF!
Name _____PER4: #REF!
Name _____PER5: #REF!
Name _____PER6: #REF!
Name _____PER7: #REF!
Name _____PER8: #REF!
Name _____PER9: #REF!

Sheet Exhibit 1, Page 1
I1: Massachusetts Electric Company
I2: Nantucket Electric Company
I3: d/b/a National Grid
I4: D.P.U 26-71
I5: Exhibit 1
I6: Page 1 of 2
D7: Residential Transmission Heat Pump Rate Design | I7: H.O. _______
A9: Line
A10: 1 | B10: Assumptions:
A11: =IF(ISBLANK(B11),"",MAX($A$9:A10)+1)
A12: =IF(ISBLANK(B12),"",MAX($A$9:A11)+1) -> 2 | B12: R-1: Residential | C12: Proposed Rate
A13: =IF(ISBLANK(B13),"",MAX($A$9:A12)+1) -> 3 | B13: Net Transmission Charge | C13: 0.05464
A14: =IF(ISBLANK(B14),"",MAX($A$9:A13)+1)
A15: =IF(ISBLANK(B15),"",MAX($A$9:A14)+1) -> 4 | B15: Average Monthly kWh - Test Year | C15: R-1 Average Monthly Use (kWh) (a) | D15: Normal Therm UPC (b) | E15: Therms (Heating Load) (c) | F15: Avg. Temp COP (d) | G15: kWh Conversion (e) | H15: kWh Usage (f) | I15: Avg. Monthly Use with Heat Pump (kWh) (g)
A16: =IF(ISBLANK(B16),"",MAX($A$9:A15)+1) -> 5 | B16: January | C16: 610.63541 | D16: 132 | E16: =D16-$E$29 -> 114 | F16: 2.6071487 | G16: =E16*$E$30 -> 3340.2 | H16: =G16/F16 -> 1281.1697 | I16: =C16+H16 -> 1891.8051
A17: =IF(ISBLANK(B17),"",MAX($A$9:A16)+1) -> 6 | B17: February | C17: 530.69348 | D17: 149 | E17: =D17-$E$29 -> 131 | F17: 2.6612302 | G17: =E17*$E$30 -> 3838.3 | H17: =G17/F17 -> 1442.3029 | I17: =C17+H17 -> 1972.9964
A18: =IF(ISBLANK(B18),"",MAX($A$9:A17)+1) -> 7 | B18: March | C18: 530.1181 | D18: 133 | E18: =D18-$E$29 -> 115 | F18: 2.8506093 | G18: =E18*$E$30 -> 3369.5 | H18: =G18/F18 -> 1182.028 | I18: =C18+H18 -> 1712.1461
A19: =IF(ISBLANK(B19),"",MAX($A$9:A18)+1) -> 8 | B19: April | C19: 454.90082 | D19: 90 | E19: =D19-$E$29 -> 72 | F19: 3.1191852 | G19: =E19*$E$30 -> 2109.6 | H19: =G19/F19 -> 676.33048 | I19: =C19+H19 -> 1131.2313
A20: =IF(ISBLANK(B20),"",MAX($A$9:A19)+1) -> 9 | B20: May | C20: 484.5277 | D20: 46 | I20: =C20+H20 -> 484.5277
A21: =IF(ISBLANK(B21),"",MAX($A$9:A20)+1) -> 10 | B21: June | C21: 586.91619 | D21: 23 | I21: =C21+H21 -> 586.91619
A22: =IF(ISBLANK(B22),"",MAX($A$9:A21)+1) -> 11 | B22: July | C22: 770.46363 | D22: 18 | I22: =C22+H22 -> 770.46363
A23: =IF(ISBLANK(B23),"",MAX($A$9:A22)+1) -> 12 | B23: August | C23: 762.80177 | D23: 15 | I23: =C23+H23 -> 762.80177
A24: =IF(ISBLANK(B24),"",MAX($A$9:A23)+1) -> 13 | B24: September | C24: 536.15882 | D24: 16 | I24: =C24+H24 -> 536.15882
A25: =IF(ISBLANK(B25),"",MAX($A$9:A24)+1) -> 14 | B25: October | C25: 457.55933 | D25: 20 | I25: =C25+H25 -> 457.55933
A26: =IF(ISBLANK(B26),"",MAX($A$9:A25)+1) -> 15 | B26: November | C26: 494.2623 | D26: 47 | E26: =D26-$E$29 -> 29 | F26: 2.999 | G26: =E26*$E$30 -> 849.7 | H26: =G26/F26 -> 283.32778 | I26: =C26+H26 -> 777.59007
A27: =IF(ISBLANK(B27),"",MAX($A$9:A26)+1) -> 16 | B27: December | C27: 641.47874 | D27: 93 | E27: =D27-$E$29 -> 75 | F27: 2.7641308 | G27: =E27*$E$30 -> 2197.5 | H27: =G27/F27 -> 795.00579 | I27: =C27+H27 -> 1436.4845
A28: =IF(ISBLANK(C28),"",MAX($A$9:A27)+1) -> 17 | C28: =SUM(C16:C27) -> 6860.5163 | H28: =SUM(H16:H27) -> 5660.1646 | I28: =SUM(I16:I27) -> 12520.681
A29: =IF(ISBLANK(E29),"",MAX($A$9:A28)+1) -> 18 | D29: Summer Base Load | E29: =AVERAGE(D21:D24) -> 18
A30: =IF(ISBLANK(B30),"",MAX($A$9:A29)+1) -> 19 | B30: Derrivation of Heat Pump Rate Adjustment Factor | D30: Therm to kWH Factor | E30: 29.3
A31: =IF(ISBLANK(#REF!),"",MAX($A$9:A30)+1) -> 20
A32: =IF(ISBLANK(B33),"",MAX($A$9:A31)+1) -> 21 | B32: Summer Heat Pump Adjustment Factor | C32: =SUM(I20:I25)/SUM(C20:C25) -> 1
A33: =IF(ISBLANK(B32),"",MAX($A$9:A32)+1) -> 22 | B33: Winter Heat Pump Adjustment Factor | C33: =SUM(I16:I19,I26:I27)/SUM(C16:C19,C26:C27) -> 2.735135
C35: (h) | I35: (i)
A36: =IF(ISBLANK(B36),"",MAX($A$9:A33)+1) | C36: Proposed Heat Pump Net Transmission Charge (Nov 2026-Feb 2027) | I36: Normalized Annual Heat Pump Net Transmission Charge
A38: =IF(ISBLANK(B38),"",MAX($A$9:A35)+1) -> 23 | B38: Forecasted Sales kWh - Winter (Mar - April 2026) | C38: =SUM('Exhibit 1, Page 2'!C43:D44) -> 1355657791
A39: =IF(ISBLANK(B39),"",MAX($A$9:A38)+1) -> 24 | B39: Forecasted Sales kWh - Summer (May - October 2026) | C39: =SUM('Exhibit 1, Page 2'!C45:D50) -> 4011473697 | E39: Forecasted Sales kWh - Summer (Mar - October 2026) | I39: =C39 -> 4011473697
A40: =IF(ISBLANK(B40),"",MAX($A$9:A39)+1) -> 25 | B40: Forecasted Sales kWh - Winter (November 2026 - February 2027) | C40: =SUM('Exhibit 1, Page 2'!C51:D54) -> 3088811862 | E40: Forecasted Sales kWh - Winter (March-April 2026, November 2026 - February 2027) | I40: =C40+C38 -> 4444469653
A41: =IF(ISBLANK(B41),"",MAX($A$9:A40)+1) -> 26 | B41: Total Annual Forecasted kWh | C41: =SUM(C38:C40) -> 8455943350 | E41: Total Annual Forecasted kWh | I41: =SUM(I39:I40) -> 8455943350
A42: =IF(ISBLANK(B42),"",MAX($A$9:A41)+1) -> 27 | B42: Forecasted kWh - Winter - Mar - Apr HP Adjusted | C42: =C38*C33 -> 3.7079071e+09
A43: =IF(ISBLANK(B43),"",MAX($A$9:A42)+1) -> 28 | B43: Forecasted kWh - Summer - HP Adjusted | C43: =C32*C39 -> 4011473697 | E43: Forecasted kWh - Summer - HP Adjusted | I43: =I39*C32 -> 4011473697
A44: =IF(ISBLANK(B44),"",MAX($A$9:A43)+1) -> 29 | B44: Forecasted kWh - Winter -Nov - Feb HP Adjusted | C44: =C33*C40 -> 8.4483176e+09 | E44: Forecasted kWh - Winter -HP Adjusted | I44: =I40*C33 -> 1.2156225e+10
A45: =IF(ISBLANK(B45),"",MAX($A$9:A44)+1) -> 30 | B45: Total Annual Forecasted kWh - HP Adjusted | C45: =SUM(C42:C44) -> 1.6167698e+10 | E45: Total Annual Forecasted kWh - HP Adjusted | I45: =SUM(I43:I44) -> 1.6167698e+10
A46: =IF(ISBLANK(B46),"",MAX($A$9:A45)+1)
A47: =IF(ISBLANK(B47),"",MAX($A$9:A46)+1) -> 31 | B47: Energy Revenue -- Winter Mar - Apr '26 | C47: =+C42*C55 -> 2.0260005e+08
A48: =IF(ISBLANK(B48),"",MAX($A$9:A47)+1) -> 32 | B48: Energy Revenue - Summer | C48: =C43*C55 -> 2.1918692e+08 | E48: Energy Revenue - Summer | I48: =I43*I55 -> 2.1918692e+08
A49: =IF(ISBLANK(B49),"",MAX($A$9:A48)+1) -> 33 | B49: Energy Revenue - Winter Nov '26 - Feb '27 | C49: =+C50-C48-C47 -> 40262030 | E49: Energy Revenue - Winter | I49: =I44*I56 -> 2.4286208e+08
A50: =IF(ISBLANK(B50),"",MAX($A$9:A49)+1) -> 34 | B50: Total Net Transmission Charge Revenue | C50: =+C51 -> 4.62049e+08 | E50: Total Net Transmission Charge Revenue | I50: =SUM(I48:I49) -> 4.62049e+08
A51: =IF(ISBLANK(B51),"",MAX($A$9:A50)+1) -> 35 | B51: Target R-1/R-2 Net Transmission Charge Revenue (DPU 26-02) | C51: 4.62049e+08 | E51: Target R-1/R-2 Net Transmission Charge Revenue (DPU 26-02) | I51: =C51 -> 4.62049e+08
A53: =IF(ISBLANK(B53),"",MAX($A$9:A52)+1) -> 36 | B53: Results | E53: Results
A54: =IF(ISBLANK(B54),"",MAX($A$9:A53)+1) -> 37 | B54: R-1/R-2: Residential Heat Pump Service | E54: R-1/R-2: Residential Heat Pump Service (Normalized) - Annual Basis
A55: =IF(ISBLANK(B55),"",MAX($A$9:A54)+1) -> 38 | B55: Transmission Charge - Summer | C55: =C13 -> 0.05464 | E55: Transmission Charge - Summer | I55: =C55 -> 0.05464
A56: =IF(ISBLANK(B56),"",MAX($A$9:A55)+1) -> 39 | B56: Transmission Charge - Winter | C56: =+C49/C44 -> 0.0047656861 | E56: Transmission Charge - Winter | I56: =(I51-I48)/I44 -> 0.019978413
A57: =IF(ISBLANK(B57),"",MAX($A$9:A56)+1)
A58: =IF(ISBLANK(B58),"",MAX($A$9:A57)+1)
B59: Line (3) DPU 26-02 PP-9, Page 1, Line (10), Column (b)
B60: Column (a) Lines (5)-(16): D.P.U. 23-150, Workpaper NG-PP-3 (REV-2) page 2, line 2 (a)-(l) ÷ line 1 (a)-(l)
B61: Column (b) Company Records for average gas customer usage
B62: Column (c) = Column (b) - Column (c) Line (18)
B63: Column (d) Electrification Load Profile assumptions from the Company's Electric Load Forecast
B64: Column (e) = Column (c) Lines (5)-(16) X Column (c) Line (19)
B65: Column (f)=Column (e) / Column (d)
B66: Column (g)= Column (a) + Column (f)
B67: Line (18) =Column (c) = Average of Lines (11)-(14) Column (c)
B68: Line (19) Column (c) = Therm to kWh conversion factor
B69: Line (21) = Sum of Column (g) May - October / Sum of Column (a) May - October
B70: Line (22) = Sum of Column (g) November - April / Sum of Column (a) November - April
... B83: Line (39) (h) = Line (33)/ Line (29); Line (39) (i) = (Line (35) - Line (32)) / Line (29)

Sheet Exhibit 1, Page 2
M1: ='Exhibit 1, Page 1'!I1 -> Massachusetts Electric Company
M2: ='Exhibit 1, Page 1'!I2 -> Nantucket Electric Company
M3: ='Exhibit 1, Page 1'!I3 -> d/b/a National Grid
M4: ='Exhibit 1, Page 1'!I4 -> D.P.U 26-71
M5: Exhibit 1
M6: Page 2 of 2
D7: Residential Transmission Heat Pump Rate Design | M7: H.O. _______
A8: FORECAST
A11: MECO
A12: YEAR | B12: MONTH | C12: R1 | D12: R2 | E12: G1 | F12: G2 | G12: G3 | H12: SL | I12: Total
A13: 2026 | B13: 3 | C13: 601415111 | D13: 121486303 | E13: 185095846 | F13: 224906754 | G13: 542158392 | H13: 5649475 | I13: =SUM(C13:H13) -> 1680711881 | J13: 1680711881 | K13: =I13-J13 -> 0
A14: =+A13 -> 2026 | B14: 4 | C14: 509433879 | D14: 103086996 | E14: 174845611 | F14: 213378135 | G14: 523016918 | H14: 5232654 | I14: =SUM(C14:H14) -> 1528994193 | J14: 1528994193 | K14: =I14-J14 -> 0
A15: =+A14 -> 2026 | B15: 5 | C15: 435617451 | D15: 88272701 | E15: 172374281 | F15: 210386314 | G15: 511310793 | H15: 4707992 | I15: =SUM(C15:H15) -> 1422669532 | J15: 1422669532 | K15: =I15-J15 -> 0
A16: =+A15 -> 2026 | B16: 6 | C16: 487462853 | D16: 99071158 | E16: 178574363 | F16: 217460365 | G16: 524157078 | H16: 4770497 | I16: =SUM(C16:H16) -> 1511496314 | J16: 1511496314 | K16: =I16-J16 -> 0
A17: =+A16 -> 2026 | B17: 7 | C17: 620701494 | D17: 126566348 | E17: 197825755 | F17: 239865967 | G17: 569406738 | H17: 4909711 | I17: =SUM(C17:H17) -> 1759276013 | J17: 1759276013 | K17: =I17-J17 -> 0
A18: =+A17 -> 2026 | B18: 8 | C18: 671831574 | D18: 137383428 | E18: 197832779 | F18: 240307094 | G18: 580150990 | H18: 5222756 | I18: =SUM(C18:H18) -> 1832728621 | J18: 1832728621 | K18: =I18-J18 -> 0
A19: =+A18 -> 2026 | B19: 9 | C19: 598283927 | D19: 122552371 | E19: 196215282 | F19: 238311745 | G19: 570108857 | H19: 5654291 | I19: =SUM(C19:H19) -> 1731126473 | J19: 1731126473 | K19: =I19-J19 -> 0
A20: =+A19 -> 2026 | B20: 10 | C20: 456992432 | D20: 93739131 | E20: 172867405 | F20: 210431456 | G20: 505157969 | H20: 5797043 | I20: =SUM(C20:H20) -> 1444985436 | J20: 1444985436 | K20: =I20-J20 -> 0
A21: =+A20 -> 2026 | B21: 11 | C21: 497450176 | D21: 102340273 | E21: 172248168 | F21: 209875859 | G21: 509698364 | H21: 6318337 | I21: =SUM(C21:H21) -> 1497931177 | J21: 1497931177 | K21: =I21-J21 -> 0
A22: =+A21 -> 2026 | B22: 12 | C22: 632761312 | D22: 130608702 | E22: 186255139 | F22: 225731174 | G22: 537993174 | H22: 6710687 | I22: =SUM(C22:H22) -> 1720060188 | J22: 1720060188 | K22: =I22-J22 -> 0
A23: 2027 | B23: 1 | C23: 718806634 | D23: 148778526 | E23: 194660260 | F23: 235299905 | G23: 556258482 | H23: 6686784 | I23: =SUM(C23:H23) -> 1860490591 | J23: 1860490591 | K23: =I23-J23 -> 0
A24: =+A23 -> 2027 | B24: 2 | C24: 675146768 | D24: 140022937 | E24: 192648310 | F24: 232976589 | G24: 549835303 | H24: 6550583 | I24: =SUM(C24:H24) -> 1797180490 | J24: 1797180490 | K24: =I24-J24 -> 0
I25: =SUM(I13:I24) -> 19787650909
A26: NANT
A27: YEAR | B27: MONTH | C27: R1 | D27: R2 | E27: G1 | F27: G2 | G27: G3 | H27: SL
A28: =A13 -> 2026 | B28: =B13 -> 3 | C28: 10692813 | D28: 195690 | E28: 2057221 | F28: 1589669 | G28: 996991 | H28: 22229 | I28: =SUM(C28:H28) -> 15554613 | J28: 15554613 | K28: =I28-J28 -> 0
A29: =A14 -> 2026 | B29: =B14 -> 4 | C29: 9179045 | D29: 167954 | E29: 1891768 | F29: 1462749 | G29: 907290 | H29: 21392 | I29: =SUM(C29:H29) -> 13630198 | J29: 13630198 | K29: =I29-J29 -> 0
A30: =A15 -> 2026 | B30: =B15 -> 5 | C30: 8077094 | D30: 147786 | E30: 1682466 | F30: 1300276 | G30: 796802 | H30: 17164 | I30: =SUM(C30:H30) -> 12021588 | J30: 12021588 | K30: =I30-J30 -> 0
A31: =A16 -> 2026 | B31: =B16 -> 6 | C31: 9275305 | D31: 169700 | E31: 1970608 | F31: 1523670 | G31: 935727 | H31: 17185 | I31: =SUM(C31:H31) -> 13892195 | J31: 13892195 | K31: =I31-J31 -> 0
A32: =A17 -> 2026 | B32: =B17 -> 7 | C32: 13634352 | D32: 249497 | E32: 2726370 | F32: 2105955 | G32: 1295455 | H32: 17078 | I32: =SUM(C32:H32) -> 20028707 | J32: 20028707 | K32: =I32-J32 -> 0
A33: =A18 -> 2026 | B33: =B18 -> 8 | C33: 16478793 | D33: 301661 | E33: 2861230 | F33: 2203851 | G33: 1353987 | H33: 18305 | I33: =SUM(C33:H33) -> 23217827 | J33: 23217827 | K33: =I33-J33 -> 0
A34: =A19 -> 2026 | B34: =B19 -> 9 | C34: 14223164 | D34: 260347 | E34: 2555361 | F34: 1969759 | G34: 1211361 | H34: 20942 | I34: =SUM(C34:H34) -> 20240934 | J34: 20240934 | K34: =I34-J34 -> 0
A35: =A20 -> 2026 | B35: =B20 -> 10 | C35: 9998299 | D35: 182831 | E35: 2495782 | F35: 1935566 | G35: 1198610 | H35: 23827 | I35: =SUM(C35:H35) -> 15834915 | J35: 15834915 | K35: =I35-J35 -> 0
A36: =A21 -> 2026 | B36: =B21 -> 11 | C36: 8030252 | D36: 146877 | E36: 1873972 | F36: 1453117 | G36: 913778 | H36: 25383 | I36: =SUM(C36:H36) -> 12443379 | J36: 12443379 | K36: =I36-J36 -> 0
A37: =A22 -> 2026 | B37: =B22 -> 12 | C37: 10348253 | D37: 189362 | E37: 2075669 | F37: 1606022 | G37: 1016660 | H37: 28473 | I37: =SUM(C37:H37) -> 15264439 | J37: 15264439 | K37: =I37-J37 -> 0
A38: =A23 -> 2027 | B38: =B23 -> 1 | C38: 11970387 | D38: 219099 | E38: 2196485 | F38: 1696359 | G38: 1070966 | H38: 29818 | I38: =SUM(C38:H38) -> 17183114 | J38: 17183114 | K38: =I38-J38 -> 0
A39: =A24 -> 2027 | B39: =B24 -> 2 | C39: 11776698 | D39: 215606 | E39: 1962699 | F39: 1512342 | G39: 950278 | H39: 25515 | I39: =SUM(C39:H39) -> 16443138 | J39: 16443138 | K39: =I39-J39 -> 0
C40: =SUM(F23:F26,F33:F34)/SUM(C23:C26,C33:C34) -> 0.33162414 | I40: =SUM(I28:I39) -> 195755047
A42: Combined | C42: R1 | D42: R2 | E42: G1 | F42: G2 | G42: G3 | H42: SL | I42: Total
A43: =A28 -> 2026 | B43: =B28 -> 3 | C43: =C28+C13 -> 612107924 | D43: =D28+D13 -> 121681993 | E43: =E28+E13 -> 187153067 | F43: =F28+F13 -> 226496423 | G43: =G28+G13 -> 543155383 | H43: =H28+H13 -> 5671704 | I43: =SUM(C43:H43) -> 1696266494 | J43: =I43-I28-I13 -> 0
A44: =A29 -> 2026 | B44: =B29 -> 4 | C44: =C29+C14 -> 518612924 | D44: =D29+D14 -> 103254950 | E44: =E29+E14 -> 176737379 | F44: =F29+F14 -> 214840884 | G44: =G29+G14 -> 523924208 | H44: =H29+H14 -> 5254046 | I44: =SUM(C44:H44) -> 1542624391 | J44: =I44-I29-I14 -> 0
A45: =A30 -> 2026 | B45: =B30 -> 5 | C45: =C30+C15 -> 443694545 | D45: =D30+D15 -> 88420487 | E45: =E30+E15 -> 174056747 | F45: =F30+F15 -> 211686590 | G45: =G30+G15 -> 512107595 | H45: =H30+H15 -> 4725156 | I45: =SUM(C45:H45) -> 1434691120 | J45: =I45-I30-I15 -> 0
A46: =A31 -> 2026 | B46: =B31 -> 6 | C46: =C31+C16 -> 496738158 | D46: =D31+D16 -> 99240858 | E46: =E31+E16 -> 180544971 | F46: =F31+F16 -> 218984035 | G46: =G31+G16 -> 525092805 | H46: =H31+H16 -> 4787682 | I46: =SUM(C46:H46) -> 1525388509 | J46: =I46-I31-I16 -> 0
A47: =A32 -> 2026 | B47: =B32 -> 7 | C47: =C32+C17 -> 634335846 | D47: =D32+D17 -> 126815845 | E47: =E32+E17 -> 200552125 | F47: =F32+F17 -> 241971922 | G47: =G32+G17 -> 570702193 | H47: =H32+H17 -> 4926789 | I47: =SUM(C47:H47) -> 1779304720 | J47: =I47-I32-I17 -> 0
A48: =A33 -> 2026 | B48: =B33 -> 8 | C48: =C33+C18 -> 688310367 | D48: =D33+D18 -> 137685089 | E48: =E33+E18 -> 200694009 | F48: =F33+F18 -> 242510945 | G48: =G33+G18 -> 581504977 | H48: =H33+H18 -> 5241061 | I48: =SUM(C48:H48) -> 1855946448 | J48: =I48-I33-I18 -> 0
A49: =A34 -> 2026 | B49: =B34 -> 9 | C49: =C34+C19 -> 612507091 | D49: =D34+D19 -> 122812718 | E49: =E34+E19 -> 198770643 | F49: =F34+F19 -> 240281504 | G49: =G34+G19 -> 571320218 | H49: =H34+H19 -> 5675233 | I49: =SUM(C49:H49) -> 1751367407 | J49: =I49-I34-I19 -> 0
A50: =A35 -> 2026 | B50: =B35 -> 10 | C50: =C35+C20 -> 466990731 | D50: =D35+D20 -> 93921962 | E50: =E35+E20 -> 175363187 | F50: =F35+F20 -> 212367022 | G50: =G35+G20 -> 506356579 | H50: =H35+H20 -> 5820870 | I50: =SUM(C50:H50) -> 1460820351 | J50: =I50-I35-I20 -> 0
A51: =A36 -> 2026 | B51: =B36 -> 11 | C51: =C36+C21 -> 505480428 | D51: =D36+D21 -> 102487150 | E51: =E36+E21 -> 174122140 | F51: =F36+F21 -> 211328976 | G51: =G36+G21 -> 510612142 | H51: =H36+H21 -> 6343720 | I51: =SUM(C51:H51) -> 1510374556 | J51: =I51-I36-I21 -> 0
A52: =A37 -> 2026 | B52: =B37 -> 12 | C52: =C37+C22 -> 643109565 | D52: =D37+D22 -> 130798064 | E52: =E37+E22 -> 188330808 | F52: =F37+F22 -> 227337196 | G52: =G37+G22 -> 539009834 | H52: =H37+H22 -> 6739160 | I52: =SUM(C52:H52) -> 1735324627 | J52: =I52-I37-I22 -> 0
A53: =A38 -> 2027 | B53: =B38 -> 1 | C53: =C38+C23 -> 730777021 | D53: =D38+D23 -> 148997625 | E53: =E38+E23 -> 196856745 | F53: =F38+F23 -> 236996264 | G53: =G38+G23 -> 557329448 | H53: =H38+H23 -> 6716602 | I53: =SUM(C53:H53) -> 1877673705 | J53: =I53-I38-I23 -> 0
A54: =A39 -> 2027 | B54: =B39 -> 2 | C54: =C39+C24 -> 686923466 | D54: =D39+D24 -> 140238543 | E54: =E39+E24 -> 194611009 | F54: =F39+F24 -> 234488931 | G54: =G39+G24 -> 550785581 | H54: =H39+H24 -> 6576098 | I54: =SUM(C54:H54) -> 1813623628 | J54: =I54-I39-I24 -> 0
A56: Total kWh | B56: R-1/R-2: Residential Heat Pump Service | C56: =SUM(C43:C54) -> 7039588066 | D56: =SUM(D43:D54) -> 1416355284 | E56: =SUM(E43:E54) -> 2247792830 | F56: =SUM(F43:F54) -> 2719290692 | G56: =SUM(G43:G54) -> 6491900963 | H56: =SUM(H43:H54) -> 68478121 | I56: =SUM(I43:I54) -> 19983405956 | J56: =I56-I40-I25 -> 0

Sheet Exhibit 2, Page 1
G1: ='Exhibit 1, Page 2'!M1 -> Massachusetts Electric Company
G2: ='Exhibit 1, Page 2'!M2 -> Nantucket Electric Company
G3: ='Exhibit 1, Page 2'!M3 -> d/b/a National Grid
G4: ='Exhibit 1, Page 2'!M4 -> D.P.U 26-71
G5: Exhibit 2
G6: Page 1 of 4
G7: ='Exhibit 1, Page 2'!M7 -> H.O. _______
A10: Massachusetts Electric Company
A11: Nantucket Electric Company
A12: Calculation of Illustrative R-1 Base Distribution and Transmission Heat-Pump Rate Customer Bill Impacts
C14: 3 Ton Heat-Pump | F14: 5 Ton Heat-Pump
C15: 1,652 kWh usage (November)* | D15: 2,269 kWh usage (January)** | F15: 2,443 kWh usage (November)*** | G15: 3,341 kWh usage (January)****
C16: (a) | D16: (b) | F16: (c) | G16: (d)
A18: -1 | B18: Illustrative R-1 Heat-Pump Customer Monthly Bill | C18: ='Exhibit 2, Page 3'!$H$56 -> 583.11 | D18: ='Exhibit 2, Page 3'!$I$56 -> 797.16 | F18: ='Exhibit 2, Page 4'!$H$56 -> 857.52 | G18: ='Exhibit 2, Page 4'!$I$56 -> 1169.06
A20: =A18-1 -> -2 | B20: Illustrative Typical Residential R-1 Monthly Bill | C20: ='Exhibit 2, Page 3'!$D$56 -> 640.38 | D20: ='Exhibit 2, Page 3'!$E$56 -> 875.81 | F20: ='Exhibit 2, Page 4'!$D$56 -> 942.2 | G20: ='Exhibit 2, Page 4'!$E$56 -> 1284.86
A22: =A20-1 -> -3 | B22: Illustrative R-1 Heat-Pump Customer Monthly Bill $ Increase/(Decrease) | C22: =C18-C20 -> -57.27 | D22: =D18-D20 -> -78.65 | F22: =F18-F20 -> -84.68 | G22: =G18-G20 -> -115.8
A24: =A22-1 -> -4 | B24: Illustrative R-1 Heat-Pump Customer Monthly Bill % Increase/(Decrease) | C24: =C22/C20 -> -0.089431275 | D24: =D22/D20 -> -0.089802583 | F24: =F22/F20 -> -0.089874761 | G24: =G22/G20 -> -0.090126551
A28: (1) (a) | B28: Page 3, Line 34, Column (e)
A29: (2) (a) | B29: Page 3, Line 34, Column (b)
A30: (1) (b) | B30: Page 3, Line 34, Column (f)
A31: (2) (b) | B31: Page 3, Line 34, Column (c)
A32: (1) (c) | B32: Page 4, Line 34, Column (e)
A33: (2) (c) | B33: Page 4, Line 34, Column (b)
A34: (1) (d) | B34: Page 4, Line 34, Column (f)
A35: (2) (d) | B35: Page 4, Line 34, Column (c)
A36: -3 | B36: Line (1) - Line (2)
A37: =A36-1 -> -4 | B37: Line (3) ÷ Line (2)
A38: * | B38: 1,652 kWh is equal to average residential customer usage in the month of November (600 kWh), plus 3-ton heat-pump usage in the same month
A39: ** | B39: 2,269 kWh is equal to average residential customer usage in the month of January (600 kWh), plus 3-ton heat-pump usage in the same month
A40: *** | B40: 2,443 kWh is equal to average residential customer usage in the month of November (600 kWh), plus 5-ton heat-pump usage in the same month
A41: **** | B41: 3,341 kWh is equal to average residential customer usage in the month of January (600 kWh), plus 5-ton heat-pump usage in the same month

Sheet Exhibit 2, Page 2
G1: ='Exhibit 2, Page 1'!G1 -> Massachusetts Electric Company
G2: ='Exhibit 2, Page 1'!G2 -> Nantucket Electric Company
G3: ='Exhibit 2, Page 1'!G3 -> d/b/a National Grid
G4: ='Exhibit 2, Page 1'!G4 -> D.P.U 26-71
G5: ='Exhibit 2, Page 1'!G5 -> Exhibit 2
G6: Page 2 of 4
G7: ='Exhibit 2, Page 1'!G7 -> H.O. _______
A10: Massachusetts Electric Company
A11: Nantucket Electric Company
A12: Calculation of Illustrative R-2 Base Distribution and Transmission Heat-Pump Rate Customer Bill Impacts
C14: 3 Ton Heat-Pump | F14: 5 Ton Heat-Pump
C15: 1,652 kWh usage (November)* | D15: 2,269 kWh usage (January)** | F15: 2,443 kWh usage (November)*** | G15: 3,341 kWh usage (January)****
C16: (a) | D16: (b) | F16: (c) | G16: (d)
A19: -1 | B19: Illustrative R-2 Heat-Pump Customer Monthly Bill - 32% discount rate | C19: ='Exhibit 2, Page 3'!H60 -> 396.5148 | D19: ='Exhibit 2, Page 3'!I60 -> 542.0688 | F19: ='Exhibit 2, Page 4'!H60 -> 583.1136 | G19: ='Exhibit 2, Page 4'!I60 -> 794.9608
A21: =A19-1 -> -2 | B21: Illustrative R-2 Residential Monthly Bill - 32% discount rate | C21: ='Exhibit 2, Page 3'!D60 -> 435.4584 | D21: ='Exhibit 2, Page 3'!E60 -> 595.5508 | F21: ='Exhibit 2, Page 4'!D60 -> 640.696 | G21: ='Exhibit 2, Page 4'!E60 -> 873.7048
A23: =A21-1 -> -3 | B23: Illustrative R-2 Heat-Pump Customer Monthly Bill $ Increase/(Decrease) - 32% discount rate | C23: =C19-C21 -> -38.9436 | D23: =D19-D21 -> -53.482 | F23: =F19-F21 -> -57.5824 | G23: =G19-G21 -> -78.744
A25: =A23-1 -> -4 | B25: Illustrative R-2 Heat-Pump Customer Monthly Bill % Increase/(Decrease) -32% discount rate | C25: =C23/C21 -> -0.089431275 | D25: =D23/D21 -> -0.089802583 | F25: =F23/F21 -> -0.089874761 | G25: =G23/G21 -> -0.090126551
A27: =A25-1 -> -5 | B27: Illustrative R-2 Heat-Pump Customer Monthly Bill - 91% discount rate | C27: ='Exhibit 2, Page 3'!H64 -> 52.4799 | D27: ='Exhibit 2, Page 3'!I64 -> 71.7444 | F27: ='Exhibit 2, Page 4'!H64 -> 77.1768 | G27: ='Exhibit 2, Page 4'!I64 -> 105.2154
A29: =A27-1 -> -6 | B29: Illustrative R-2 Residential Monthly Bill - 91% discount rate | C29: ='Exhibit 2, Page 3'!D64 -> 57.6342 | D29: ='Exhibit 2, Page 3'!E64 -> 78.8229 | F29: ='Exhibit 2, Page 4'!D64 -> 84.798 | G29: ='Exhibit 2, Page 4'!E64 -> 115.6374
A31: =A29-1 -> -7 | B31: Illustrative R-2 Heat-Pump Customer Monthly Bill $ Increase/(Decrease) - 91% discount rate | C31: =C27-C29 -> -5.1543 | D31: =D27-D29 -> -7.0785 | F31: =F27-F29 -> -7.6212 | G31: =G27-G29 -> -10.422
A33: =A31-1 -> -8 | B33: Illustrative R-2 Heat-Pump Customer Monthly Bill % Increase/(Decrease) -91% discount rate | C33: =C31/C29 -> -0.089431275 | D33: =D31/D29 -> -0.089802583 | F33: =F31/F29 -> -0.089874761 | G33: =G31/G29 -> -0.090126551
A36: (1) (a) | B36: Page 3, Line 36, Column (e)
A37: (2) (a) | B37: Page 3, Line 36, Column (b)
A38: (1) (b) | B38: Page 3, Line 36, Column (f)
A39: (2) (b) | B39: Page 3, Line 36, Column (c)
A40: (1) (c) | B40: Page 4, Line 36, Column (e)
A41: (2) (c) | B41: Page 4, Line 36, Column (b)
A42: (1) (d) | B42: Page 4, Line 36, Column (f)
A43: (2) (d) | B43: Page 4, Line 36, Column (c)
A44: -3 | B44: Line (1) - Line (2)
A45: =A44-1 -> -4 | B45: Line (3) ÷ Line (2)
A46: (5) (a) | B46: Page 3, Line 38, Column (e)
A47: (6) (a) | B47: Page 3, Line 38, Column (b)
A48: (5) (b) | B48: Page 3, Line 38, Column (f)
A49: (6) (b) | B49: Page 3, Line 38, Column (c)
A50: (5) (c) | B50: Page 4, Line 38, Column (e)
A51: (6) (c) | B51: Page 4, Line 38, Column (b)
A52: (5) (d) | B52: Page 4, Line 38, Column (f)
A53: (6) (d) | B53: Page 4, Line 38, Column (c)
A54: * | B54: 1,652 kWh is equal to average residential customer usage in the month of November (600 kWh), plus 3-ton heat-pump usage in the same month
A55: ** | B55: 2,269 kWh is equal to average residential customer usage in the month of January (600 kWh), plus 3-ton heat-pump usage in the same month
A56: *** | B56: 2,443 kWh is equal to average residential customer usage in the month of November (600 kWh), plus 5-ton heat-pump usage in the same month
A57: **** | B57: 3,341 kWh is equal to average residential customer usage in the month of January (600 kWh), plus 5-ton heat-pump usage in the same month

Sheet Exhibit 2, Page 3
I1: ='Exhibit 2, Page 2'!G1 -> Massachusetts Electric Company
I2: ='Exhibit 2, Page 2'!G2 -> Nantucket Electric Company
I3: ='Exhibit 2, Page 2'!G3 -> d/b/a National Grid
I4: ='Exhibit 2, Page 2'!G4 -> D.P.U 26-71
I5: ='Exhibit 2, Page 2'!G5 -> Exhibit 2
I6: Page 3 of 4
I7: ='Exhibit 2, Page 2'!G7 -> H.O. _______
A9: Massachusetts Electric Company
A10: Nantucket Electric Company
A11: Calculation of Monthly Residential Bills for Customers with 3 Ton Heat-Pump
C13: Residential (non-Heat-Pump) Customer Typical Bill | G13: Residential Heat-Pump Rate Customer Typical Bill
C14: Effective | G14: Effective
C15: Rate | D15: Amount (1,652 kWh November usage) | E15: Amount (2,269 kWh January usage) | G15: Rate | H15: Amount (1,652 kWh November usage) | I15: Amount (2,269 kWh January usage)
C16: (a) | D16: (b) | E16: (c) | G16: (d) | H16: (e) | I16: (f)
B18: Delivery Service
A19: -1 | B19: Customer Charge | D19: 10 | E19: =D19 -> 10 | H19: =D19 -> 10 | I19: =H19 -> 10
A20: =+A19-1 -> -2 | B20: Base Distribution Charge | C20: 0.06677 | G20: =C20 -> 0.06677
A21: =+A20-1 -> -3 | B21: Basic Service Adjustment Factor | C21: 0.00051 | G21: =C21 -> 0.00051
A22: =+A21-1 -> -4 | B22: Residential Assistance Adjustment Factor | C22: 0.02389 | G22: =C22 -> 0.02389
A23: =+A22-1 -> -5 | B23: Storm Fund Replenishment Factor | C23: 0.00406 | G23: =C23 -> 0.00406
A24: =+A23-1 -> -6 | B24: Pension/PBOP Factor | C24: 0.0002 | G24: =C24 -> 0.0002
A25: =+A24-1 -> -7 | B25: Revenue Decoupling Mechanism Adjustment Factor | C25: -0.00281 | G25: =C25 -> -0.00281
A26: =+A25-1 -> -8 | B26: Attorney General Consulting Expense Factor | C26: 2e-05 | G26: =C26 -> 2e-05
A27: =+A26-1 -> -9 | B27: Solar Cost Adjustment Factor | C27: -0.00035 | G27: =C27 -> -0.00035
A28: =+A27-1 -> -10 | B28: Smart Grid Distribution Adjustment Factor | C28: 0 | G28: =C28 -> 0
A29: =A28-1 -> -11 | B29: Renewable Energy Recovery Factor | C29: 0.00022 | G29: =C29 -> 0.00022
A30: =+A29-1 -> -12 | B30: Tax Act Credit Factor | C30: 0 | G30: =C30 -> 0
A31: =+A30-1 -> -13 | B31: Vegetation Management Factor | C31: 6e-05 | G31: =C31 -> 6e-05
A32: =+A31-1 -> -14 | B32: Grid Modernization Factor | C32: 0.00399 | G32: =C32 -> 0.00399
A33: =+A32-1 -> -15 | B33: Exogenous Storm Fund Factor | C33: 0.00214 | G33: =C33 -> 0.00214
A34: =+A33-1 -> -16 | B34: Advanced Metering Infrastructure Factor | C34: 0.00318 | G34: =C34 -> 0.00318
A35: =+A34-1 -> -17 | B35: Electronic Payment Recovery Factor | C35: 0.00026 | G35: =C35 -> 0.00026
A36: =+A35-1 -> -18 | B36: Infrastructure, Safety, Reliability and Electrification Factor | C36: 0.00156 | G36: =C36 -> 0.00156
A37: =+A36-1 -> -19 | B37: Winter Relief Recovery Factor | C37: 0.00658 | G37: =C37 -> 0.00658
A38: =A37-1 -> -20 | B38: Total Distribution Energy Charge | C38: =SUM(C20:C37) -> 0.11028 | D38: =ROUND(C38*1652,2) -> 182.18 | E38: =ROUND(C38*2269,2) -> 250.23 | G38: =SUM(G20:G37) -> 0.11028 | H38: =ROUND(G38*1652,2) -> 182.18 | I38: =ROUND(G38*2269,2) -> 250.23
A40: =+A38-1 -> -21 | B40: SMART Factor | C40: 0.00935 | D40: =ROUND(C40*1652,2) -> 15.45 | E40: =ROUND(C40*2269,2) -> 21.22 | G40: =C40 -> 0.00935 | H40: =ROUND(G40*1652,2) -> 15.45 | I40: =ROUND(G40*2269,2) -> 21.22
A41: =+A40-1 -> -22 | B41: Electric Vehicle Program Factor | C41: 0.00174 | D41: =ROUND(C41*1652,2) -> 2.87 | E41: =ROUND(C41*2269,2) -> 3.95 | G41: =C41 -> 0.00174 | H41: =ROUND(G41*1652,2) -> 2.87 | I41: =ROUND(G41*2269,2) -> 3.95
A42: =+A41-1 -> -23 | B42: Transition Charge | C42: -0.00029 | D42: =ROUND(C42*1652,2) -> -0.48 | E42: =ROUND(C42*2269,2) -> -0.66 | G42: =C42 -> -0.00029 | H42: =ROUND(G42*1652,2) -> -0.48 | I42: =ROUND(G42*2269,2) -> -0.66
A43: =+A42-1 -> -24 | B43: Net Transmission Charge | C43: ='Exhibit 1, Page 1'!C13 -> 0.05464 | D43: =ROUND(C43*1652,2) -> 90.27 | E43: =ROUND(C43*2269,2) -> 123.98 | G43: ='Exhibit 1, Page 1'!I56 -> 0.019978413 | H43: =ROUND(G43*1652,2) -> 33 | I43: =ROUND(G43*2269,2) -> 45.33
A44: =+A43-1 -> -25 | B44: Energy Efficiency Charge | C44: 0.02713 | D44: =ROUND(C44*1652,2) -> 44.82 | E44: =ROUND(C44*2269,2) -> 61.56 | G44: =C44 -> 0.02713 | H44: =ROUND(G44*1652,2) -> 44.82 | I44: =ROUND(G44*2269,2) -> 61.56
A45: =+A44-1 -> -26 | B45: Net Metering Recovery Surcharge | C45: 0.02451 | D45: =ROUND(C45*1652,2) -> 40.49 | E45: =ROUND(C45*2269,2) -> 55.61 | G45: =C45 -> 0.02451 | H45: =ROUND(G45*1652,2) -> 40.49 | I45: =ROUND(G45*2269,2) -> 55.61
A46: =+A45-1 -> -27 | B46: Renewables Charge | C46: 0.0005 | D46: =ROUND(C46*1652,2) -> 0.83 | E46: =ROUND(C46*2269,2) -> 1.13 | G46: =C46 -> 0.0005 | H46: =ROUND(G46*1652,2) -> 0.83 | I46: =ROUND(G46*2269,2) -> 1.13
A47: =+A46-1 -> -28 | B47: Electric Sector Modernization Plan Factor | C47: 0 | D47: =ROUND(C47*1652,2) -> 0 | E47: =ROUND(C47*2269,2) -> 0 | G47: =C47 -> 0 | H47: =ROUND(G47*1652,2) -> 0 | I47: =ROUND(G47*2269,2) -> 0
A48: =+A47-1 -> -29 | B48: Subtotal Delivery Charges | D48: =SUM(D19:D47) -> 386.43 | E48: =SUM(E19:E47) -> 527.02 | H48: =SUM(H19:H47) -> 329.16 | I48: =SUM(I19:I47) -> 448.37
B50: Supply Service
A51: =+A48-1 -> -30 | B51: Base Basic Service Charge | C51: 0.14751 | G51: =C51 -> 0.14751
A52: =+A51-1 -> -31 | B52: Basic Service Admin Cost Factor | C52: 0.00621 | G52: =C52 -> 0.00621
A53: =+A52-1 -> -32 | B53: Smart Grid Customer Cost Adjustment Factor | C53: 0 | G53: =C53 -> 0
A54: =+A53-1 -> -33 | B54: Subtotal Commodity | C54: =SUM(C51:C53) -> 0.15372 | D54: =ROUND(C54*1652,2) -> 253.95 | E54: =ROUND(C54*2269,2) -> 348.79 | G54: =C54 -> 0.15372 | H54: =ROUND(G54*1652,2) -> 253.95 | I54: =ROUND(G54*2269,2) -> 348.79
A56: =+A54-1 -> -34 | B56: Total R-1 Residential Typical Bill | D56: =D48+D54 -> 640.38 | E56: =E48+E54 -> 875.81 | H56: =H48+H54 -> 583.11 | I56: =I48+I54 -> 797.16
A58: =A56-1 -> -35 | B58: R-2 Low Income Discount - 32% | C58: 0.32 | D58: =D56*C58 -> 204.9216 | E58: =E56*C58 -> 280.2592 | H58: =H56*C58 -> 186.5952 | I58: =I56*C58 -> 255.0912
A60: =A58-1 -> -36 | B60: Total R-2 Residential Typical Bill on 32% discount rate | D60: =D56-D58 -> 435.4584 | E60: =E56-E58 -> 595.5508 | H60: =H56-H58 -> 396.5148 | I60: =I56-I58 -> 542.0688
A62: =A60-1 -> -37 | B62: R-2 Low Income Discount -91% | C62: 0.91 | D62: =D56*C62 -> 582.7458 | E62: =E56*C62 -> 796.9871 | H62: =H56*C62 -> 530.6301 | I62: =I56*C62 -> 725.4156
A64: =A62-1 -> -38 | B64: Total R-2 Residential Typical Bill on 91% discount rate | D64: =D56-D62 -> 57.6342 | E64: =E56-E62 -> 78.8229 | H64: =H56-H62 -> 52.4799 | I64: =I56-I62 -> 71.7444
A67: (a), (d) | B67: Per M.D.P.U. No. 1-26-F; exept Line (24) (d) = Exhibit 1 , Page 1, Line (39) Col. (i)
A68: (b),(c), (e), (f) | B68: Line (1): Per M.D.P.U. No. 1-26-G (proposed)
A69: (b),(c), (e), (f) | B69: Lines (20) through (27), Line (32): kWh x Column (a)
A70: (b),(c), (e), (f) | B70: Line (29) = SUM (Lines (20) through (28))
A71: (b),(c), (e), (f) | B71: Line (34): Line (29) + Line (33)
A72: (b),(c), (e), (f) | B72: Line (35): Line (34) x Line (35), Column (a)
A73: (b),(c), (e), (f) | B73: Line (36): Line (34) - Line (35)

Sheet Exhibit 2, Page 4
I1: ='Exhibit 2, Page 3'!I1 -> Massachusetts Electric Company
I2: ='Exhibit 2, Page 3'!I2 -> Nantucket Electric Company
I3: ='Exhibit 2, Page 3'!I3 -> d/b/a National Grid
I4: ='Exhibit 2, Page 3'!I4 -> D.P.U 26-71
I5: ='Exhibit 2, Page 3'!I5 -> Exhibit 2
I6: Page 4 of 4
I7: ='Exhibit 2, Page 3'!I7 -> H.O. _______
A9: Massachusetts Electric Company
A10: Nantucket Electric Company
A11: Calculation of Monthly Residential Bills for Customers with 5 Ton Heat-Pump
C13: Residential (non-Heat-Pump) Customer Typical Bill | G13: Residential Heat-Pump Rate Customer Typical Bill
C14: Effective | G14: Effective
C15: Rate | D15: Amount (2,443 kWh November usage) | E15: Amount (3,341 kWh January usage) | G15: Rate | H15: Amount (2,443 kWh November usage) | I15: Amount (3,341 kWh January usage)
C16: (a) | D16: (b) | E16: (c) | G16: (d) | H16: (e) | I16: (f)
B18: Delivery Service
A19: -1 | B19: Customer Charge | D19: 10 | E19: =D19 -> 10 | H19: =D19 -> 10 | I19: =H19 -> 10
A20: =+A19-1 -> -2 | B20: Base Distribution Charge | C20: ='Exhibit 2, Page 3'!C20 -> 0.06677 | G20: ='Exhibit 2, Page 3'!G20 -> 0.06677
A21: =+A20-1 -> -3 | B21: Basic Service Adjustment Factor | C21: ='Exhibit 2, Page 3'!C21 -> 0.00051 | G21: ='Exhibit 2, Page 3'!G21 -> 0.00051
A22: =+A21-1 -> -4 | B22: Residential Assistance Adjustment Factor | C22: ='Exhibit 2, Page 3'!C22 -> 0.02389 | G22: ='Exhibit 2, Page 3'!G22 -> 0.02389
A23: =+A22-1 -> -5 | B23: Storm Fund Replenishment Factor | C23: ='Exhibit 2, Page 3'!C23 -> 0.00406 | G23: ='Exhibit 2, Page 3'!G23 -> 0.00406
A24: =+A23-1 -> -6 | B24: Pension/PBOP Factor | C24: ='Exhibit 2, Page 3'!C24 -> 0.0002 | G24: ='Exhibit 2, Page 3'!G24 -> 0.0002
A25: =+A24-1 -> -7 | B25: Revenue Decoupling Mechanism Adjustment Factor | C25: ='Exhibit 2, Page 3'!C25 -> -0.00281 | G25: ='Exhibit 2, Page 3'!G25 -> -0.00281
A26: =+A25-1 -> -8 | B26: Attorney General Consulting Expense Factor | C26: ='Exhibit 2, Page 3'!C26 -> 2e-05 | G26: ='Exhibit 2, Page 3'!G26 -> 2e-05
A27: =+A26-1 -> -9 | B27: Solar Cost Adjustment Factor | C27: ='Exhibit 2, Page 3'!C27 -> -0.00035 | G27: ='Exhibit 2, Page 3'!G27 -> -0.00035
A28: =+A27-1 -> -10 | B28: Smart Grid Distribution Adjustment Factor | C28: ='Exhibit 2, Page 3'!C28 -> 0 | G28: ='Exhibit 2, Page 3'!G28 -> 0
A29: =A28-1 -> -11 | B29: Renewable Energy Recovery Factor | C29: ='Exhibit 2, Page 3'!C29 -> 0.00022 | G29: ='Exhibit 2, Page 3'!G29 -> 0.00022
A30: =+A29-1 -> -12 | B30: Tax Act Credit Factor | C30: ='Exhibit 2, Page 3'!C30 -> 0 | G30: ='Exhibit 2, Page 3'!G30 -> 0
A31: =+A30-1 -> -13 | B31: Vegetation Management Factor | C31: ='Exhibit 2, Page 3'!C31 -> 6e-05 | G31: ='Exhibit 2, Page 3'!G31 -> 6e-05
A32: =+A31-1 -> -14 | B32: Grid Modernization Factor | C32: ='Exhibit 2, Page 3'!C32 -> 0.00399 | G32: ='Exhibit 2, Page 3'!G32 -> 0.00399
A33: =+A32-1 -> -15 | B33: Exogenous Storm Fund Factor | C33: ='Exhibit 2, Page 3'!C33 -> 0.00214 | G33: ='Exhibit 2, Page 3'!G33 -> 0.00214
A34: =+A33-1 -> -16 | B34: Advanced Metering Infrastructure Factor | C34: ='Exhibit 2, Page 3'!C34 -> 0.00318 | G34: ='Exhibit 2, Page 3'!G34 -> 0.00318
A35: =+A34-1 -> -17 | B35: Electronic Payment Recovery Factor | C35: ='Exhibit 2, Page 3'!C35 -> 0.00026 | G35: ='Exhibit 2, Page 3'!G35 -> 0.00026
A36: =+A35-1 -> -18 | B36: Infrastructure, Safety, Reliability and Electrification Factor | C36: ='Exhibit 2, Page 3'!C36 -> 0.00156 | G36: ='Exhibit 2, Page 3'!G36 -> 0.00156
A37: =+A36-1 -> -19 | B37: ='Exhibit 2, Page 3'!B37 -> Winter Relief Recovery Factor | C37: ='Exhibit 2, Page 3'!C37 -> 0.00658 | G37: ='Exhibit 2, Page 3'!G37 -> 0.00658
A38: =+A37-1 -> -20 | B38: Total Distribution Energy Charge | C38: =SUM(C20:C37) -> 0.11028 | D38: =ROUND(C38*2443,2) -> 269.41 | E38: =ROUND(C38*3341,2) -> 368.45 | G38: =SUM(G20:G37) -> 0.11028 | H38: =ROUND(G38*2443,2) -> 269.41 | I38: =ROUND(G38*3341,2) -> 368.45
A40: =+A38-1 -> -21 | B40: SMART Factor | C40: ='Exhibit 2, Page 3'!C40 -> 0.00935 | D40: =ROUND(C40*2443,2) -> 22.84 | E40: =ROUND(C40*3341,2) -> 31.24 | G40: ='Exhibit 2, Page 3'!G40 -> 0.00935 | H40: =ROUND(G40*2443,2) -> 22.84 | I40: =ROUND(G40*3341,2) -> 31.24
A41: =+A40-1 -> -22 | B41: Electric Vehicle Program Factor | C41: ='Exhibit 2, Page 3'!C41 -> 0.00174 | D41: =ROUND(C41*2443,2) -> 4.25 | E41: =ROUND(C41*3341,2) -> 5.81 | G41: ='Exhibit 2, Page 3'!G41 -> 0.00174 | H41: =ROUND(G41*2443,2) -> 4.25 | I41: =ROUND(G41*3341,2) -> 5.81
A42: =+A41-1 -> -23 | B42: Transition Charge | C42: ='Exhibit 2, Page 3'!C42 -> -0.00029 | D42: =ROUND(C42*2443,2) -> -0.71 | E42: =ROUND(C42*3341,2) -> -0.97 | G42: ='Exhibit 2, Page 3'!G42 -> -0.00029 | H42: =ROUND(G42*2443,2) -> -0.71 | I42: =ROUND(G42*3341,2) -> -0.97
A43: =+A42-1 -> -24 | B43: Transmission Service Adjustment Factor | C43: ='Exhibit 2, Page 3'!C43 -> 0.05464 | D43: =ROUND(C43*2443,2) -> 133.49 | E43: =ROUND(C43*3341,2) -> 182.55 | G43: ='Exhibit 2, Page 3'!G43 -> 0.019978413 | H43: =ROUND(G43*2443,2) -> 48.81 | I43: =ROUND(G43*3341,2) -> 66.75
A44: =+A43-1 -> -25 | B44: Energy Efficiency Charge | C44: ='Exhibit 2, Page 3'!C44 -> 0.02713 | D44: =ROUND(C44*2443,2) -> 66.28 | E44: =ROUND(C44*3341,2) -> 90.64 | G44: ='Exhibit 2, Page 3'!G44 -> 0.02713 | H44: =ROUND(G44*2443,2) -> 66.28 | I44: =ROUND(G44*3341,2) -> 90.64
A45: =+A44-1 -> -26 | B45: Net Metering Recovery Surcharge | C45: ='Exhibit 2, Page 3'!C45 -> 0.02451 | D45: =ROUND(C45*2443,2) -> 59.88 | E45: =ROUND(C45*3341,2) -> 81.89 | G45: ='Exhibit 2, Page 3'!G45 -> 0.02451 | H45: =ROUND(G45*2443,2) -> 59.88 | I45: =ROUND(G45*3341,2) -> 81.89
A46: =+A45-1 -> -27 | B46: Renewables Charge | C46: ='Exhibit 2, Page 3'!C46 -> 0.0005 | D46: =ROUND(C46*2443,2) -> 1.22 | E46: =ROUND(C46*3341,2) -> 1.67 | G46: ='Exhibit 2, Page 3'!G46 -> 0.0005 | H46: =ROUND(G46*2443,2) -> 1.22 | I46: =ROUND(G46*3341,2) -> 1.67
A47: =+A46-1 -> -28 | B47: ='Exhibit 2, Page 3'!B47 -> Electric Sector Modernization Plan Factor | C47: ='Exhibit 2, Page 3'!C47 -> 0 | D47: =ROUND(C47*2443,2) -> 0 | E47: =ROUND(C47*3341,2) -> 0 | G47: ='Exhibit 2, Page 3'!G47 -> 0 | H47: =ROUND(G47*2443,2) -> 0 | I47: =ROUND(G47*3341,2) -> 0
A48: =+A47-1 -> -29 | B48: Subtotal Delivery Charges | D48: =SUM(D19:D47) -> 566.66 | E48: =SUM(E19:E47) -> 771.28 | H48: =SUM(H19:H47) -> 481.98 | I48: =SUM(I19:I47) -> 655.48
B50: Supply Service
A51: =+A48-1 -> -30 | B51: Base Basic Service Charge | C51: ='Exhibit 2, Page 3'!C51 -> 0.14751 | G51: ='Exhibit 2, Page 3'!G51 -> 0.14751
A52: =+A51-1 -> -31 | B52: Basic Service Admin Cost Factor | C52: ='Exhibit 2, Page 3'!C52 -> 0.00621 | G52: ='Exhibit 2, Page 3'!G52 -> 0.00621
A53: =+A52-1 -> -32 | B53: Smart Grid Customer Cost Adjustment Factor | C53: ='Exhibit 2, Page 3'!C53 -> 0 | G53: ='Exhibit 2, Page 3'!G53 -> 0
A54: =+A53-1 -> -33 | B54: Subtotal Commodity | C54: =SUM(C51:C53) -> 0.15372 | D54: =ROUND(C54*2443,2) -> 375.54 | E54: =ROUND(C54*3341,2) -> 513.58 | G54: =C54 -> 0.15372 | H54: =ROUND(G54*2443,2) -> 375.54 | I54: =ROUND(G54*3341,2) -> 513.58
A56: =+A54-1 -> -34 | B56: Total R-1 Residential Typical Bill | D56: =D48+D54 -> 942.2 | E56: =E48+E54 -> 1284.86 | H56: =H48+H54 -> 857.52 | I56: =I48+I54 -> 1169.06
A58: =A56-1 -> -35 | B58: R-2 Low Income Discount | C58: 0.32 | D58: =D56*C58 -> 301.504 | E58: =E56*C58 -> 411.1552 | H58: =H56*C58 -> 274.4064 | I58: =I56*C58 -> 374.0992
A60: =A58-1 -> -36 | B60: Total R-2 Residential Typical Bill | D60: =D56-D58 -> 640.696 | E60: =E56-E58 -> 873.7048 | H60: =H56-H58 -> 583.1136 | I60: =I56-I58 -> 794.9608
A62: =A60-1 -> -37 | B62: R-2 Low Income Discount -91% | C62: 0.91 | D62: =D56*C62 -> 857.402 | E62: =E56*C62 -> 1169.2226 | H62: =H56*C62 -> 780.3432 | I62: =I56*C62 -> 1063.8446
A64: =A62-1 -> -38 | B64: Total R-2 Residential Typical Bill on 91% discount rate | D64: =D56-D62 -> 84.798 | E64: =E56-E62 -> 115.6374 | H64: =H56-H62 -> 77.1768 | I64: =I56-I62 -> 105.2154
A67: (a), (d) | B67: ='Exhibit 2, Page 3'!B67 -> Per M.D.P.U. No. 1-26-F; exept Line (24) (d) = Exhibit 1 , Page 1, Line (39) Col. (i)
A68: (b),(c), (e), (f) | B68: Line (1): Per M.D.P.U. No. 1-26-G (proposed)
A69: (b),(c), (e), (f) | B69: Lines (20) through (27), Line (32): kWh x Column (a)
A70: (b),(c), (e), (f) | B70: Line (29) = SUM (Lines (20) through (28))
A71: (b),(c), (e), (f) | B71: Line (34): Line (29) + Line (33)
A72: (b),(c), (e), (f) | B72: Line (35): Line (34) x Line (35), Column (a)
A73: (b),(c), (e), (f) | B73: Line (36): Line (34) - Line (35)

Sheet Exhibit 3, Page 1
G1: ='Exhibit 1, Page 2'!M1 -> Massachusetts Electric Company
G2: ='Exhibit 1, Page 2'!M2 -> Nantucket Electric Company
G3: ='Exhibit 1, Page 2'!M3 -> d/b/a National Grid
G4: ='Exhibit 1, Page 2'!M4 -> D.P.U 26-71
G5: Exhibit 3
G6: Page 1 of 4
G7: ='Exhibit 2, Page 4'!I7 -> H.O. _______
A10: Massachusetts Electric Company
A11: Nantucket Electric Company
A12: Calculation of Illustrative R-1 Base Distribution and Transmission Heat-Pump Rate Customer Bill Impacts
C14: 3 Ton Heat-Pump | F14: 5 Ton Heat-Pump
C15: 1,652 kWh usage (November)* | D15: 2,269 kWh usage (January)** | F15: 2,443 kWh usage (November)*** | G15: 3,341 kWh usage (January)****
C16: (a) | D16: (b) | F16: (c) | G16: (d)
A18: -1 | B18: Illustrative R-1 Heat-Pump Customer Monthly Bill | C18: ='Exhibit 3, Page 3'!$H$56 -> 513.7 | D18: ='Exhibit 3, Page 3'!$I$56 -> 701.81 | F18: ='Exhibit 3, Page 4'!$H$56 -> 754.87 | G18: ='Exhibit 3, Page 4'!$I$56 -> 1028.67
A20: =A18-1 -> -2 | B20: Illustrative Typical Residential R-1 Monthly Bill | C20: ='Exhibit 3, Page 3'!$D$56 -> 640.38 | D20: ='Exhibit 3, Page 3'!$E$56 -> 875.81 | F20: ='Exhibit 3, Page 4'!$D$56 -> 944.55 | G20: ='Exhibit 3, Page 4'!$E$56 -> 1288.06
A22: =A20-1 -> -3 | B22: Illustrative R-1 Heat-Pump Customer Monthly Bill $ Increase/(Decrease) | C22: =C18-C20 -> -126.68 | D22: =D18-D20 -> -174 | F22: =F18-F20 -> -189.68 | G22: =G18-G20 -> -259.39
A24: =A22-1 -> -4 | B24: Illustrative R-1 Heat-Pump Customer Monthly Bill % Increase/(Decrease) | C24: =C22/C20 -> -0.19782004 | D24: =D22/D20 -> -0.19867323 | F24: =F22/F20 -> -0.2008152 | G24: =G22/G20 -> -0.20138037
A28: (1) (a) | B28: Page 3, Line 34, Column (e)
A29: (2) (a) | B29: Page 3, Line 34, Column (b)
A30: (1) (b) | B30: Page 3, Line 34, Column (f)
A31: (2) (b) | B31: Page 3, Line 34, Column (c)
A32: (1) (c) | B32: Page 4, Line 34, Column (e)
A33: (2) (c) | B33: Page 4, Line 34, Column (b)
A34: (1) (d) | B34: Page 4, Line 34, Column (f)
A35: (2) (d) | B35: Page 4, Line 34, Column (c)
A36: -3 | B36: Line (1) - Line (2)
A37: =A36-1 -> -4 | B37: Line (3) ÷ Line (2)
A38: * | B38: 1,652 kWh is equal to average residential customer usage in the month of November (600 kWh), plus 3-ton heat-pump usage in the same month
A39: ** | B39: 2,269 kWh is equal to average residential customer usage in the month of January (600 kWh), plus 3-ton heat-pump usage in the same month
A40: *** | B40: 2,443 kWh is equal to average residential customer usage in the month of November (600 kWh), plus 5-ton heat-pump usage in the same month
A41: **** | B41: 3,341 kWh is equal to average residential customer usage in the month of January (600 kWh), plus 5-ton heat-pump usage in the same month

Sheet Exhibit 3, Page 2
G1: ='Exhibit 3, Page 1'!G1 -> Massachusetts Electric Company
G2: ='Exhibit 3, Page 1'!G2 -> Nantucket Electric Company
G3: ='Exhibit 3, Page 1'!G3 -> d/b/a National Grid
G4: ='Exhibit 3, Page 1'!G4 -> D.P.U 26-71
G5: ='Exhibit 3, Page 1'!G5 -> Exhibit 3
G6: Page 2 of 4
G7: ='Exhibit 3, Page 1'!G7 -> H.O. _______
A10: Massachusetts Electric Company
A11: Nantucket Electric Company
A12: Calculation of Illustrative R-2 Base Distribution and Transmission Heat-Pump Rate Customer Bill Impacts
C14: 3 Ton Heat-Pump | F14: 5 Ton Heat-Pump
C15: 1,652 kWh usage (November)* | D15: 2,269 kWh usage (January)** | F15: 2,443 kWh usage (November)*** | G15: 3,341 kWh usage (January)****
C16: (a) | D16: (b) | F16: (c) | G16: (d)
A19: -1 | B19: Illustrative R-2 Heat-Pump Customer Monthly Bill - 32% discount rate | C19: ='Exhibit 3, Page 3'!H60 -> 349.316 | D19: ='Exhibit 3, Page 3'!I60 -> 477.2308 | F19: ='Exhibit 3, Page 4'!H60 -> 513.3116 | G19: ='Exhibit 3, Page 4'!I60 -> 699.4956
A21: =A19-1 -> -2 | B21: Illustrative R-2 Residential Monthly Bill - 32% discount rate | C21: ='Exhibit 3, Page 3'!D60 -> 435.4584 | D21: ='Exhibit 3, Page 3'!E60 -> 595.5508 | F21: ='Exhibit 3, Page 4'!D60 -> 642.294 | G21: ='Exhibit 3, Page 4'!E60 -> 875.8808
A23: =A21-1 -> -3 | B23: Illustrative R-2 Heat-Pump Customer Monthly Bill $ Increase/(Decrease) - 32% discount rate | C23: =C19-C21 -> -86.1424 | D23: =D19-D21 -> -118.32 | F23: =F19-F21 -> -128.9824 | G23: =G19-G21 -> -176.3852
A25: =A23-1 -> -4 | B25: Illustrative R-2 Heat-Pump Customer Monthly Bill % Increase/(Decrease) -32% discount rate | C25: =C23/C21 -> -0.19782004 | D25: =D23/D21 -> -0.19867323 | F25: =F23/F21 -> -0.2008152 | G25: =G23/G21 -> -0.20138037
A27: =A25-1 -> -5 | B27: Illustrative R-2 Heat-Pump Customer Monthly Bill - 91% discount rate | C27: ='Exhibit 3, Page 3'!H64 -> 46.233 | D27: ='Exhibit 3, Page 3'!I64 -> 63.1629 | F27: ='Exhibit 3, Page 4'!H64 -> 67.9383 | G27: ='Exhibit 3, Page 4'!I64 -> 92.5803
A29: =A27-1 -> -6 | B29: Illustrative R-2 Residential Monthly Bill - 91% discount rate | C29: ='Exhibit 3, Page 3'!D64 -> 57.6342 | D29: ='Exhibit 3, Page 3'!E64 -> 78.8229 | F29: ='Exhibit 3, Page 4'!D64 -> 85.0095 | G29: ='Exhibit 3, Page 4'!E64 -> 115.9254
A31: =A29-1 -> -7 | B31: Illustrative R-2 Heat-Pump Customer Monthly Bill $ Increase/(Decrease) - 91% discount rate | C31: =C27-C29 -> -11.4012 | D31: =D27-D29 -> -15.66 | F31: =F27-F29 -> -17.0712 | G31: =G27-G29 -> -23.3451
A33: =A31-1 -> -8 | B33: Illustrative R-2 Heat-Pump Customer Monthly Bill % Increase/(Decrease) -91% discount rate | C33: =C31/C29 -> -0.19782004 | D33: =D31/D29 -> -0.19867323 | F33: =F31/F29 -> -0.2008152 | G33: =G31/G29 -> -0.20138037
A36: (1) (a) | B36: Page 3, Line 36, Column (e)
A37: (2) (a) | B37: Page 3, Line 36, Column (b)
A38: (1) (b) | B38: Page 3, Line 36, Column (f)
A39: (2) (b) | B39: Page 3, Line 36, Column (c)
A40: (1) (c) | B40: Page 4, Line 36, Column (e)
A41: (2) (c) | B41: Page 4, Line 36, Column (b)
A42: (1) (d) | B42: Page 4, Line 36, Column (f)
A43: (2) (d) | B43: Page 4, Line 36, Column (c)
A44: -3 | B44: Line (1) - Line (2)
A45: =A44-1 -> -4 | B45: Line (3) ÷ Line (2)
A46: (5) (a) | B46: Page 3, Line 38, Column (e)
A47: (6) (a) | B47: Page 3, Line 38, Column (b)
A48: (5) (b) | B48: Page 3, Line 38, Column (f)
A49: (6) (b) | B49: Page 3, Line 38, Column (c)
A50: (5) (c) | B50: Page 4, Line 38, Column (e)
A51: (6) (c) | B51: Page 4, Line 38, Column (b)
A52: (5) (d) | B52: Page 4, Line 38, Column (f)
A53: (6) (d) | B53: Page 4, Line 38, Column (c)
A54: * | B54: 1,652 kWh is equal to average residential customer usage in the month of November (600 kWh), plus 3-ton heat-pump usage in the same month
A55: ** | B55: 2,269 kWh is equal to average residential customer usage in the month of January (600 kWh), plus 3-ton heat-pump usage in the same month
A56: *** | B56: 2,443 kWh is equal to average residential customer usage in the month of November (600 kWh), plus 5-ton heat-pump usage in the same month
A57: **** | B57: 3,341 kWh is equal to average residential customer usage in the month of January (600 kWh), plus 5-ton heat-pump usage in the same month

Sheet Exhibit 3, Page 3
I1: ='Exhibit 3, Page 2'!G1 -> Massachusetts Electric Company
I2: ='Exhibit 3, Page 2'!G2 -> Nantucket Electric Company
I3: ='Exhibit 3, Page 2'!G3 -> d/b/a National Grid
I4: ='Exhibit 3, Page 2'!G4 -> D.P.U 26-71
I5: ='Exhibit 3, Page 2'!G5 -> Exhibit 3
I6: Page 3 of 4
I7: ='Exhibit 3, Page 2'!G7 -> H.O. _______
A9: Massachusetts Electric Company
A10: Nantucket Electric Company
A11: Calculation of Monthly Residential Bills for Customers with 3 Ton Heat-Pump
C13: Residential (non-Heat-Pump) Customer Typical Bill | G13: Residential Heat-Pump Rate Customer Typical Bill
C14: Effective | G14: Effective
C15: Rate | D15: Amount (1,652 kWh November usage) | E15: Amount (2,269 kWh January usage) | G15: Rate | H15: Amount (1,652 kWh November usage) | I15: Amount (2,269 kWh January usage)
C16: (a) | D16: (b) | E16: (c) | G16: (d) | H16: (e) | I16: (f)
B18: Delivery Service
A19: -1 | B19: Customer Charge | D19: 10 | E19: =D19 -> 10 | H19: =D19 -> 10 | I19: =H19 -> 10
A20: =+A19-1 -> -2 | B20: Base Distribution Charge | C20: 0.06773 | G20: 0.02475
A21: =+A20-1 -> -3 | B21: Basic Service Adjustment Factor | C21: ='Exhibit 2, Page 3'!C21 -> 0.00051 | G21: =C21 -> 0.00051
A22: =+A21-1 -> -4 | B22: Residential Assistance Adjustment Factor | C22: ='Exhibit 2, Page 3'!C22 -> 0.02389 | G22: =C22 -> 0.02389
A23: =+A22-1 -> -5 | B23: Storm Fund Replenishment Factor | C23: ='Exhibit 2, Page 3'!C23 -> 0.00406 | G23: =C23 -> 0.00406
A24: =+A23-1 -> -6 | B24: Pension/PBOP Factor | C24: ='Exhibit 2, Page 3'!C24 -> 0.0002 | G24: =C24 -> 0.0002
A25: =+A24-1 -> -7 | B25: Revenue Decoupling Mechanism Adjustment Factor | C25: ='Exhibit 2, Page 3'!C25 -> -0.00281 | G25: =C25 -> -0.00281
A26: =+A25-1 -> -8 | B26: Attorney General Consulting Expense Factor | C26: ='Exhibit 2, Page 3'!C26 -> 2e-05 | G26: =C26 -> 2e-05
A27: =+A26-1 -> -9 | B27: Solar Cost Adjustment Factor | C27: ='Exhibit 2, Page 3'!C27 -> -0.00035 | G27: =C27 -> -0.00035
A28: =+A27-1 -> -10 | B28: Smart Grid Distribution Adjustment Factor | C28: ='Exhibit 2, Page 3'!C28 -> 0 | G28: =C28 -> 0
A29: =A28-1 -> -11 | B29: Renewable Energy Recovery Factor | C29: ='Exhibit 2, Page 3'!C29 -> 0.00022 | G29: =C29 -> 0.00022
A30: =+A29-1 -> -12 | B30: Tax Act Credit Factor | C30: ='Exhibit 2, Page 3'!C30 -> 0 | G30: =C30 -> 0
A31: =+A30-1 -> -13 | B31: Vegetation Management Factor | C31: ='Exhibit 2, Page 3'!C31 -> 6e-05 | G31: =C31 -> 6e-05
A32: =+A31-1 -> -14 | B32: Grid Modernization Factor | C32: ='Exhibit 2, Page 3'!C32 -> 0.00399 | G32: =C32 -> 0.00399
A33: =+A32-1 -> -15 | B33: Exogenous Storm Fund Factor | C33: ='Exhibit 2, Page 3'!C33 -> 0.00214 | G33: =C33 -> 0.00214
A34: =+A33-1 -> -16 | B34: Advanced Metering Infrastructure Factor | C34: ='Exhibit 2, Page 3'!C34 -> 0.00318 | G34: =C34 -> 0.00318
A35: =+A34-1 -> -17 | B35: Electronic Payment Recovery Factor | C35: ='Exhibit 2, Page 3'!C35 -> 0.00026 | G35: =C35 -> 0.00026
A36: =+A35-1 -> -18 | B36: Infrastructure, Safety, Reliability and Electrification Factor | C36: ='Exhibit 2, Page 3'!C36 -> 0.00156 | G36: =C36 -> 0.00156
A37: =+A36-1 -> -19 | B37: Winter Relief Recovery Factor | C37: ='Exhibit 2, Page 3'!C37 -> 0.00658 | G37: =C37 -> 0.00658
A38: =A37-1 -> -20 | B38: Total Distribution Energy Charge | C38: ='Exhibit 2, Page 3'!C38 -> 0.11028 | D38: =ROUND(C38*1652,2) -> 182.18 | E38: =ROUND(C38*2269,2) -> 250.23 | G38: =SUM(G20:G37) -> 0.06826 | H38: =ROUND(G38*1652,2) -> 112.77 | I38: =ROUND(G38*2269,2) -> 154.88
A40: =+A38-1 -> -21 | B40: SMART Factor | C40: ='Exhibit 2, Page 3'!C40 -> 0.00935 | D40: =ROUND(C40*1652,2) -> 15.45 | E40: =ROUND(C40*2269,2) -> 21.22 | G40: =C40 -> 0.00935 | H40: =ROUND(G40*1652,2) -> 15.45 | I40: =ROUND(G40*2269,2) -> 21.22
A41: =+A40-1 -> -22 | B41: Electric Vehicle Program Factor | C41: ='Exhibit 2, Page 3'!C41 -> 0.00174 | D41: =ROUND(C41*1652,2) -> 2.87 | E41: =ROUND(C41*2269,2) -> 3.95 | G41: =C41 -> 0.00174 | H41: =ROUND(G41*1652,2) -> 2.87 | I41: =ROUND(G41*2269,2) -> 3.95
A42: =+A41-1 -> -23 | B42: Transition Charge | C42: ='Exhibit 2, Page 3'!C42 -> -0.00029 | D42: =ROUND(C42*1652,2) -> -0.48 | E42: =ROUND(C42*2269,2) -> -0.66 | G42: =C42 -> -0.00029 | H42: =ROUND(G42*1652,2) -> -0.48 | I42: =ROUND(G42*2269,2) -> -0.66
A43: =+A42-1 -> -24 | B43: Net Transmission Charge | C43: ='Exhibit 2, Page 3'!C43 -> 0.05464 | D43: =ROUND(C43*1652,2) -> 90.27 | E43: =ROUND(C43*2269,2) -> 123.98 | G43: ='Exhibit 1, Page 1'!I56 -> 0.019978413 | H43: =ROUND(G43*1652,2) -> 33 | I43: =ROUND(G43*2269,2) -> 45.33
A44: =+A43-1 -> -25 | B44: Energy Efficiency Charge | C44: ='Exhibit 2, Page 3'!C44 -> 0.02713 | D44: =ROUND(C44*1652,2) -> 44.82 | E44: =ROUND(C44*2269,2) -> 61.56 | G44: =C44 -> 0.02713 | H44: =ROUND(G44*1652,2) -> 44.82 | I44: =ROUND(G44*2269,2) -> 61.56
A45: =+A44-1 -> -26 | B45: Net Metering Recovery Surcharge | C45: ='Exhibit 2, Page 3'!C45 -> 0.02451 | D45: =ROUND(C45*1652,2) -> 40.49 | E45: =ROUND(C45*2269,2) -> 55.61 | G45: =C45 -> 0.02451 | H45: =ROUND(G45*1652,2) -> 40.49 | I45: =ROUND(G45*2269,2) -> 55.61
A46: =+A45-1 -> -27 | B46: Renewables Charge | C46: ='Exhibit 2, Page 3'!C46 -> 0.0005 | D46: =ROUND(C46*1652,2) -> 0.83 | E46: =ROUND(C46*2269,2) -> 1.13 | G46: =C46 -> 0.0005 | H46: =ROUND(G46*1652,2) -> 0.83 | I46: =ROUND(G46*2269,2) -> 1.13
A47: =+A46-1 -> -28 | B47: Electric Sector Modernization Plan Factor | C47: ='Exhibit 2, Page 3'!C47 -> 0 | D47: =ROUND(C47*1652,2) -> 0 | E47: =ROUND(C47*2269,2) -> 0 | G47: =C47 -> 0 | H47: =ROUND(G47*1652,2) -> 0 | I47: =ROUND(G47*2269,2) -> 0
A48: =+A47-1 -> -29 | B48: Subtotal Delivery Charges | D48: =SUM(D19:D47) -> 386.43 | E48: =SUM(E19:E47) -> 527.02 | H48: =SUM(H19:H47) -> 259.75 | I48: =SUM(I19:I47) -> 353.02
B50: Supply Service
A51: =+A48-1 -> -30 | B51: Base Basic Service Charge | C51: 0.14751 | G51: =C51 -> 0.14751
A52: =+A51-1 -> -31 | B52: Basic Service Admin Cost Factor | C52: 0.00621 | G52: =C52 -> 0.00621
A53: =+A52-1 -> -32 | B53: Smart Grid Customer Cost Adjustment Factor | C53: 0 | G53: =C53 -> 0
A54: =+A53-1 -> -33 | B54: Subtotal Commodity | C54: =SUM(C51:C53) -> 0.15372 | D54: =ROUND(C54*1652,2) -> 253.95 | E54: =ROUND(C54*2269,2) -> 348.79 | G54: =C54 -> 0.15372 | H54: =ROUND(G54*1652,2) -> 253.95 | I54: =ROUND(G54*2269,2) -> 348.79
A56: =+A54-1 -> -34 | B56: Total R-1 Residential Typical Bill | D56: =D48+D54 -> 640.38 | E56: =E48+E54 -> 875.81 | H56: =H48+H54 -> 513.7 | I56: =I48+I54 -> 701.81
A58: =A56-1 -> -35 | B58: R-2 Low Income Discount - 32% | C58: 0.32 | D58: =D56*C58 -> 204.9216 | E58: =E56*C58 -> 280.2592 | H58: =H56*C58 -> 164.384 | I58: =I56*C58 -> 224.5792
A60: =A58-1 -> -36 | B60: Total R-2 Residential Typical Bill on 32% discount rate | D60: =D56-D58 -> 435.4584 | E60: =E56-E58 -> 595.5508 | H60: =H56-H58 -> 349.316 | I60: =I56-I58 -> 477.2308
A62: =A60-1 -> -37 | B62: R-2 Low Income Discount -91% | C62: 0.91 | D62: =D56*C62 -> 582.7458 | E62: =E56*C62 -> 796.9871 | H62: =H56*C62 -> 467.467 | I62: =I56*C62 -> 638.6471
A64: =A62-1 -> -38 | B64: Total R-2 Residential Typical Bill on 91% discount rate | D64: =D56-D62 -> 57.6342 | E64: =E56-E62 -> 78.8229 | H64: =H56-H62 -> 46.233 | I64: =I56-I62 -> 63.1629
A67: (a), (d) | B67: Per M.D.P.U. No. 1-26-F; exept Line (24) (d) = Exhibit 1 , Page 1, Line (39) (i), Line (2) = D.P.U.26-XX, Exhibit 4, Page 1, Line 3&6
A68: (b),(c), (e), (f) | B68: Line (1): Per M.D.P.U. No. 1-26-G (proposed)
A69: (b),(c), (e), (f) | B69: Lines (20) through (27), Line (32): kWh x Column (a)
A70: (b),(c), (e), (f) | B70: Line (29) = SUM (Lines (20) through (28))
A71: (b),(c), (e), (f) | B71: Line (34): Line (29) + Line (33)
A72: (b),(c), (e), (f) | B72: Line (35): Line (34) x Line (35), Column (a)
A73: (b),(c), (e), (f) | B73: Line (36): Line (34) - Line (35)

Sheet Exhibit 3, Page 4
I1: ='Exhibit 3, Page 3'!I1 -> Massachusetts Electric Company
I2: ='Exhibit 3, Page 3'!I2 -> Nantucket Electric Company
I3: ='Exhibit 3, Page 3'!I3 -> d/b/a National Grid
I4: ='Exhibit 3, Page 3'!I4 -> D.P.U 26-71
I5: ='Exhibit 3, Page 3'!I5 -> Exhibit 3
I6: Page 4 of 4
I7: ='Exhibit 3, Page 3'!I7 -> H.O. _______
A9: Massachusetts Electric Company
A10: Nantucket Electric Company
A11: Calculation of Monthly Residential Bills for Customers with 5 Ton Heat-Pump
C13: Residential (non-Heat-Pump) Customer Typical Bill | G13: Residential Heat-Pump Rate Customer Typical Bill
C14: Effective | G14: Effective
C15: Rate | D15: Amount (2,443 kWh November usage) | E15: Amount (3,341 kWh January usage) | G15: Rate | H15: Amount (2,443 kWh November usage) | I15: Amount (3,341 kWh January usage)
C16: (a) | D16: (b) | E16: (c) | G16: (d) | H16: (e) | I16: (f)
B18: Delivery Service
A19: -1 | B19: Customer Charge | D19: 10 | E19: =D19 -> 10 | H19: =D19 -> 10 | I19: =H19 -> 10
A20: =+A19-1 -> -2 | B20: Base Distribution Charge | C20: ='Exhibit 3, Page 3'!C20 -> 0.06773 | G20: ='Exhibit 3, Page 3'!G20 -> 0.02475
A21: =+A20-1 -> -3 | B21: Basic Service Adjustment Factor | C21: ='Exhibit 3, Page 3'!C21 -> 0.00051 | G21: ='Exhibit 3, Page 3'!G21 -> 0.00051
A22: =+A21-1 -> -4 | B22: Residential Assistance Adjustment Factor | C22: ='Exhibit 3, Page 3'!C22 -> 0.02389 | G22: ='Exhibit 3, Page 3'!G22 -> 0.02389
A23: =+A22-1 -> -5 | B23: Storm Fund Replenishment Factor | C23: ='Exhibit 3, Page 3'!C23 -> 0.00406 | G23: ='Exhibit 3, Page 3'!G23 -> 0.00406
A24: =+A23-1 -> -6 | B24: Pension/PBOP Factor | C24: ='Exhibit 3, Page 3'!C24 -> 0.0002 | G24: ='Exhibit 3, Page 3'!G24 -> 0.0002
A25: =+A24-1 -> -7 | B25: Revenue Decoupling Mechanism Adjustment Factor | C25: ='Exhibit 3, Page 3'!C25 -> -0.00281 | G25: ='Exhibit 3, Page 3'!G25 -> -0.00281
A26: =+A25-1 -> -8 | B26: Attorney General Consulting Expense Factor | C26: ='Exhibit 3, Page 3'!C26 -> 2e-05 | G26: ='Exhibit 3, Page 3'!G26 -> 2e-05
A27: =+A26-1 -> -9 | B27: Solar Cost Adjustment Factor | C27: ='Exhibit 3, Page 3'!C27 -> -0.00035 | G27: ='Exhibit 3, Page 3'!G27 -> -0.00035
A28: =+A27-1 -> -10 | B28: Smart Grid Distribution Adjustment Factor | C28: ='Exhibit 3, Page 3'!C28 -> 0 | G28: ='Exhibit 3, Page 3'!G28 -> 0
A29: =A28-1 -> -11 | B29: Renewable Energy Recovery Factor | C29: ='Exhibit 3, Page 3'!C29 -> 0.00022 | G29: ='Exhibit 3, Page 3'!G29 -> 0.00022
A30: =+A29-1 -> -12 | B30: Tax Act Credit Factor | C30: ='Exhibit 3, Page 3'!C30 -> 0 | G30: ='Exhibit 3, Page 3'!G30 -> 0
A31: =+A30-1 -> -13 | B31: Vegetation Management Factor | C31: ='Exhibit 3, Page 3'!C31 -> 6e-05 | G31: ='Exhibit 3, Page 3'!G31 -> 6e-05
A32: =+A31-1 -> -14 | B32: Grid Modernization Factor | C32: ='Exhibit 3, Page 3'!C32 -> 0.00399 | G32: ='Exhibit 3, Page 3'!G32 -> 0.00399
A33: =+A32-1 -> -15 | B33: Exogenous Storm Fund Factor | C33: ='Exhibit 3, Page 3'!C33 -> 0.00214 | G33: ='Exhibit 3, Page 3'!G33 -> 0.00214
A34: =+A33-1 -> -16 | B34: Advanced Metering Infrastructure Factor | C34: ='Exhibit 3, Page 3'!C34 -> 0.00318 | G34: ='Exhibit 3, Page 3'!G34 -> 0.00318
A35: =+A34-1 -> -17 | B35: Electronic Payment Recovery Factor | C35: ='Exhibit 3, Page 3'!C35 -> 0.00026 | G35: ='Exhibit 3, Page 3'!G35 -> 0.00026
A36: =+A35-1 -> -18 | B36: Infrastructure, Safety, Reliability and Electrification Factor | C36: ='Exhibit 3, Page 3'!C36 -> 0.00156 | G36: ='Exhibit 3, Page 3'!G36 -> 0.00156
A37: =+A36-1 -> -19 | B37: ='Exhibit 3, Page 3'!B37 -> Winter Relief Recovery Factor | C37: ='Exhibit 3, Page 3'!C37 -> 0.00658 | G37: ='Exhibit 3, Page 3'!G37 -> 0.00658
A38: =+A37-1 -> -20 | B38: Total Distribution Energy Charge | C38: =SUM(C20:C37) -> 0.11124 | D38: =ROUND(C38*2443,2) -> 271.76 | E38: =ROUND(C38*3341,2) -> 371.65 | G38: =SUM(G20:G37) -> 0.06826 | H38: =ROUND(G38*2443,2) -> 166.76 | I38: =ROUND(G38*3341,2) -> 228.06
A40: =+A38-1 -> -21 | B40: SMART Factor | C40: ='Exhibit 3, Page 3'!C40 -> 0.00935 | D40: =ROUND(C40*2443,2) -> 22.84 | E40: =ROUND(C40*3341,2) -> 31.24 | G40: ='Exhibit 3, Page 3'!G40 -> 0.00935 | H40: =ROUND(G40*2443,2) -> 22.84 | I40: =ROUND(G40*3341,2) -> 31.24
A41: =+A40-1 -> -22 | B41: Electric Vehicle Program Factor | C41: ='Exhibit 3, Page 3'!C41 -> 0.00174 | D41: =ROUND(C41*2443,2) -> 4.25 | E41: =ROUND(C41*3341,2) -> 5.81 | G41: ='Exhibit 3, Page 3'!G41 -> 0.00174 | H41: =ROUND(G41*2443,2) -> 4.25 | I41: =ROUND(G41*3341,2) -> 5.81
A42: =+A41-1 -> -23 | B42: Transition Charge | C42: ='Exhibit 3, Page 3'!C42 -> -0.00029 | D42: =ROUND(C42*2443,2) -> -0.71 | E42: =ROUND(C42*3341,2) -> -0.97 | G42: ='Exhibit 3, Page 3'!G42 -> -0.00029 | H42: =ROUND(G42*2443,2) -> -0.71 | I42: =ROUND(G42*3341,2) -> -0.97
A43: =+A42-1 -> -24 | B43: Transmission Service Adjustment Factor | C43: ='Exhibit 3, Page 3'!C43 -> 0.05464 | D43: =ROUND(C43*2443,2) -> 133.49 | E43: =ROUND(C43*3341,2) -> 182.55 | G43: ='Exhibit 1, Page 1'!I56 -> 0.019978413 | H43: =ROUND(G43*2443,2) -> 48.81 | I43: =ROUND(G43*3341,2) -> 66.75
A44: =+A43-1 -> -25 | B44: Energy Efficiency Charge | C44: ='Exhibit 3, Page 3'!C44 -> 0.02713 | D44: =ROUND(C44*2443,2) -> 66.28 | E44: =ROUND(C44*3341,2) -> 90.64 | G44: ='Exhibit 3, Page 3'!G44 -> 0.02713 | H44: =ROUND(G44*2443,2) -> 66.28 | I44: =ROUND(G44*3341,2) -> 90.64
A45: =+A44-1 -> -26 | B45: Net Metering Recovery Surcharge | C45: ='Exhibit 3, Page 3'!C45 -> 0.02451 | D45: =ROUND(C45*2443,2) -> 59.88 | E45: =ROUND(C45*3341,2) -> 81.89 | G45: ='Exhibit 3, Page 3'!G45 -> 0.02451 | H45: =ROUND(G45*2443,2) -> 59.88 | I45: =ROUND(G45*3341,2) -> 81.89
A46: =+A45-1 -> -27 | B46: Renewables Charge | C46: ='Exhibit 3, Page 3'!C46 -> 0.0005 | D46: =ROUND(C46*2443,2) -> 1.22 | E46: =ROUND(C46*3341,2) -> 1.67 | G46: ='Exhibit 3, Page 3'!G46 -> 0.0005 | H46: =ROUND(G46*2443,2) -> 1.22 | I46: =ROUND(G46*3341,2) -> 1.67
A47: =+A46-1 -> -28 | B47: ='Exhibit 3, Page 3'!B47 -> Electric Sector Modernization Plan Factor | C47: ='Exhibit 3, Page 3'!C47 -> 0 | D47: =ROUND(C47*2443,2) -> 0 | E47: =ROUND(C47*3341,2) -> 0 | G47: ='Exhibit 3, Page 3'!G47 -> 0 | H47: =ROUND(G47*2443,2) -> 0 | I47: =ROUND(G47*3341,2) -> 0
A48: =+A47-1 -> -29 | B48: Subtotal Delivery Charges | D48: =SUM(D19:D47) -> 569.01 | E48: =SUM(E19:E47) -> 774.48 | H48: =SUM(H19:H47) -> 379.33 | I48: =SUM(I19:I47) -> 515.09
B50: Supply Service
A51: =+A48-1 -> -30 | B51: Base Basic Service Charge | C51: ='Exhibit 3, Page 3'!C51 -> 0.14751 | G51: ='Exhibit 3, Page 3'!G51 -> 0.14751
A52: =+A51-1 -> -31 | B52: Basic Service Admin Cost Factor | C52: ='Exhibit 3, Page 3'!C52 -> 0.00621 | G52: ='Exhibit 3, Page 3'!G52 -> 0.00621
A53: =+A52-1 -> -32 | B53: Smart Grid Customer Cost Adjustment Factor | C53: ='Exhibit 3, Page 3'!C53 -> 0 | G53: ='Exhibit 3, Page 3'!G53 -> 0
A54: =+A53-1 -> -33 | B54: Subtotal Commodity | C54: =SUM(C51:C53) -> 0.15372 | D54: =ROUND(C54*2443,2) -> 375.54 | E54: =ROUND(C54*3341,2) -> 513.58 | G54: =C54 -> 0.15372 | H54: =ROUND(G54*2443,2) -> 375.54 | I54: =ROUND(G54*3341,2) -> 513.58
A56: =+A54-1 -> -34 | B56: Total R-1 Residential Typical Bill | D56: =D48+D54 -> 944.55 | E56: =E48+E54 -> 1288.06 | H56: =H48+H54 -> 754.87 | I56: =I48+I54 -> 1028.67
A58: =A56-1 -> -35 | B58: R-2 Low Income Discount | C58: 0.32 | D58: =D56*C58 -> 302.256 | E58: =E56*C58 -> 412.1792 | H58: =H56*C58 -> 241.5584 | I58: =I56*C58 -> 329.1744
A60: =A58-1 -> -36 | B60: Total R-2 Residential Typical Bill | D60: =D56-D58 -> 642.294 | E60: =E56-E58 -> 875.8808 | H60: =H56-H58 -> 513.3116 | I60: =I56-I58 -> 699.4956
A62: =A60-1 -> -37 | B62: R-2 Low Income Discount -91% | C62: 0.91 | D62: =D56*C62 -> 859.5405 | E62: =E56*C62 -> 1172.1346 | H62: =H56*C62 -> 686.9317 | I62: =I56*C62 -> 936.0897
A64: =A62-1 -> -38 | B64: Total R-2 Residential Typical Bill on 91% discount rate | D64: =D56-D62 -> 85.0095 | E64: =E56-E62 -> 115.9254 | H64: =H56-H62 -> 67.9383 | I64: =I56-I62 -> 92.5803
A67: (a), (d) | B67: ='Exhibit 3, Page 3'!B67 -> Per M.D.P.U. No. 1-26-F; exept Line (24) (d) = Exhibit 1 , Page 1, Line (39) (i), Line (2) = D.P.U.26-XX, Exhibit 4, Page 1, Line 3&6
A68: (b),(c), (e), (f) | B68: Line (1): Per M.D.P.U. No. 1-26-G (proposed)
A69: (b),(c), (e), (f) | B69: Lines (20) through (27), Line (32): kWh x Column (a)
A70: (b),(c), (e), (f) | B70: Line (29) = SUM (Lines (20) through (28))
A71: (b),(c), (e), (f) | B71: Line (34): Line (29) + Line (33)
A72: (b),(c), (e), (f) | B72: Line (35): Line (34) x Line (35), Column (a)
A73: (b),(c), (e), (f) | B73: Line (36): Line (34) - Line (35)
