Workbook

Sheet Summary
A1: FITCHBURG GAS AND ELECTRIC LIGHT COMPANY D/B/A UNITIL
A2: RESIDENTIAL HEAT PUMP TRANSMISSION RATE DESIGN
A3: - ELECTRIC DIVISION -
A6: Line No. | B6: Distribution Rate Design (HP-RES / HP-RES LI) | C6: Current 6/1/26
A7: 1 | B7: Customer Charge | C7: 8.5
A8: =A7+1 -> 2 | B8: Distribution Energy Charge - Summer (May - Oct) | C8: 0.10176
A9: =A8+1 -> 3 | B9: Distribution Energy Charge - Winter (Nov - Apr) | C9: 0.03633
A10: =A9+1 -> 4
A11: =A10+1 -> 5 | B11: Winter Heat Pump Adj. Factor (Line 2 / Line 3) | C11: =C8/C9 -> 2.8009909
A12: =A11+1 -> 6 | B12: Summer Heat Pump Adj. Factor | C12: 1
A13: =A12+1 -> 7
A14: =A13+1 -> 8 | D14: Internal
A15: =A14+1 -> 9 | C15: Internal | D15: Transmission | E15: External | F15: Total
A16: =A15+1 -> 10 | B16: Transmission Rate Design (HP-RES / HP-RES LI) | C16: Transmission | D16: Service Cost Adj | E16: Transmission | F16: Transmission
A17: =A16+1 -> 11 | B17: Transmission Energy Charge - Summer (May - Oct) Line 29, 30, 31 | C17: 0.00394 | D17: -0.00211 | E17: 0.04018 | F17: =C17+D17+E17 -> 0.04201
A18: =A17+1 -> 12 | B18: Transmission Energy Charge - Winter (Nov - Apr) | C18: =TRUNC(((C31-C28)/C21),5) -> 0.0014 | D18: =TRUNC(((D31-D28)/D21),5) -> -0.00075 | E18: =TRUNC(((E31-E28)/E21),5) -> 0.01434 | F18: =C18+D18+E18 -> 0.01499
A19: =A18+1 -> 13
A20: =A19+1 -> 14 | B20: 2026 Forecast Sales - Summer - HP adjusted (Line 18) | C20: =C24*$C$12 -> 80837113 | D20: =D24*$C$12 -> 80837113 | E20: =E24*$C$12 -> 80837113 | F20: =F24*$C$12 -> 80837113
A21: =A20+1 -> 15 | B21: 2026 Forecast Sales - Winter - HP adjusted (Line 19 * Line 5) | C21: =C25*$C$11 -> 2.5356987e+08 | D21: =D25*$C$11 -> 2.5356987e+08 | E21: =E25*$C$11 -> 2.5356987e+08 | F21: =F25*$C$11 -> 2.5356987e+08
A22: =A21+1 -> 16 | B22: 2026 Forecast Sales (kWh) - HP Adjusted | C22: =C21+C20 -> 3.3440698e+08 | D22: =D21+D20 -> 3.3440698e+08 | E22: =E21+E20 -> 3.3440698e+08 | F22: =F21+F20 -> 3.3440698e+08
A23: =A22+1 -> 17
A24: =A23+1 -> 18 | B24: 2026 Residential Forecast Sales - Summer | C24: =SUM('Forecasted Sales'!G10:L10) -> 80837113 | D24: =SUM('Forecasted Sales'!G10:L10) -> 80837113 | E24: =SUM('Forecasted Sales'!G10:L10) -> 80837113 | F24: =SUM('Forecasted Sales'!G10:L10) -> 80837113
A25: =A24+1 -> 19 | B25: 2026 Residential Forecast Sales - Winter | C25: =C26-C24 -> 90528629 | D25: =D26-D24 -> 90528629 | E25: =E26-E24 -> 90528629 | F25: =F26-F24 -> 90528629
A26: =A25+1 -> 20 | B26: 2026 Residential Forecast Annual Sales (kWh) | C26: ='Forecasted Sales'!O10 -> 1.7136574e+08 | D26: ='Forecasted Sales'!O10 -> 1.7136574e+08 | E26: ='Forecasted Sales'!O10 -> 1.7136574e+08 | F26: ='Forecasted Sales'!O10 -> 1.7136574e+08
A27: =A26+1 -> 21
A28: =A27+1 -> 22 | B28: Transmission Energy Revenue - Summer (Line 11 * Line 14) | C28: =C17*C20 -> 318498.23 | D28: =D17*D20 -> -170566.31 | E28: =E17*E20 -> 3248035.2 | F28: =F17*F20 -> 3395967.1
A29: =A28+1 -> 23 | B29: Transmission Energy Revenue - Winter (Line 12 * Line 15) | C29: =C18*C21 -> 354997.82 | D29: =D18*D21 -> -190177.4 | E29: =E18*E21 -> 3636191.9 | F29: =F18*F21 -> 3801012.3
A30: =A29+1 -> 24 | B30: Total Transmission Residential Rate Revenue | C30: =SUM(C28:C29) -> 673496.04 | D30: =SUM(D28:D29) -> -360743.71 | E30: =SUM(E28:E29) -> 6884227.1 | F30: =SUM(F28:F29) -> 7196979.5
A31: =A30+1 -> 25 | B31: 2026 Estimated Transmission Revenue (DPU 25-168) (Line 29, 30, 31) | C31: =C35 -> 675181.03 | D31: =C36 -> -362701.44 | E31: =C37 -> 6886316.6 | F31: =C38 -> 7198796.2
A32: =A31+1 -> 26 | B32: Difference from Target due to Truncation | C32: =+C30-C31 -> -1684.9837 | D32: =+D30-D31 -> 1957.7267 | E32: =+E30-E31 -> -2089.4495 | F32: =+F30-F31 -> -1816.7065
A33: =A32+1 -> 27
A34: =A33+1 -> 28 | B34: D.P.U. 25-168 (RD-1 and RD-2 Allocated Transmission Costs) | C34: Amount | D34: Current Rates 1/1/26
A35: =A34+1 -> 29 | B35: Schedule SED-4: Internal Transmission | C35: =C26*0.00394 -> 675181.03 | D35: =TRUNC(C35/C26,5) -> 0.00394
A36: =A35+1 -> 30 | B36: Schedule SED-4: Internal Transmission Service Cost Adjustment | C36: -362701.44 | D36: =TRUNC(C36/C26,5) -> -0.00211
A37: =A36+1 -> 31 | B37: Schedule SED-3: External Transmission | C37: 6886316.6 | D37: =TRUNC(C37/C26,5) -> 0.04018
A38: =A37+1 -> 32 | B38: Total Estimated Residential Transmission Cost | C38: =SUM(C35:C37) -> 7198796.2 | D38: =D37+D35+D36 -> 0.04201

Sheet Forecasted Sales
A1: FITCHBURG GAS AND ELECTRIC LIGHT COMPANY D/B/A UNITIL
A2: RESIDENTIAL SALES FORECAST
A3: - ELECTRIC DIVISION -
C5: Winter | D5: Winter | E5: Winter | F5: Winter | G5: Summer | H5: Summer | I5: Summer | J5: Summer | K5: Summer | L5: Summer | M5: Winter | N5: Winter
C6: Forecast | D6: Forecast | E6: Forecast | F6: Forecast | G6: Forecast | H6: Forecast | I6: Forecast | J6: Forecast | K6: Forecast | L6: Forecast | M6: Forecast | N6: Forecast | O6: Forecast
A7: Line No. | B7: Description | C7: 46023 | D7: 46054 | E7: 46082 | F7: 46113 | G7: 46143 | H7: 46174 | I7: 46204 | J7: 46235 | K7: 46266 | L7: 46296 | M7: 46327 | N7: 46357 | O7: Total
A8: 1 | B8: Rate RD-1 | C8: 14141128 | D8: 13210212 | E8: 11942611 | F8: 9326444.3 | G8: 8756368.8 | H8: 9627325.1 | I8: 12555869 | J8: 12609566 | K8: 10649911 | L8: 8944880.1 | M8: 9718510.3 | N8: 12568547
A9: =A8+1 -> 2 | B9: Rate RD-2 | C9: 3729798.8 | D9: 3688062 | E9: 3484734.7 | F9: 2834653.8 | G9: 2518072.2 | H9: 2739365.6 | I9: 3341951.6 | J9: 3473647.3 | K9: 3067020.4 | L9: 2553136.2 | M9: 2559764.8 | N9: 3324163.5
A10: =A9+1 -> 3 | B10: Total Rate RD-1 & RD-2 | C10: =C8+C9 -> 17870927 | D10: =D8+D9 -> 16898273 | E10: =E8+E9 -> 15427345 | F10: =F8+F9 -> 12161098 | G10: =G8+G9 -> 11274441 | H10: =H8+H9 -> 12366691 | I10: =I8+I9 -> 15897821 | J10: =J8+J9 -> 16083213 | ... N10: =N8+N9 -> 15892710 | O10: =SUM(C10:N10) -> 1.7136574e+08
