Workbook

Sheet Index
A1: Fitchburg Gas and Electric Light Company
A2: Electric Revenue Apportionment and Rate Design
A3: Table of Contents
A5: Line No. | B5: Worksheet | C5: Exhibit No. | D5: Schedule No. | E5: Schedule Description | F5: Schedule Full Description
B6: Index
B7: Revenue Apportionment | C7: Exhibit Unitil-JDT-4 | D7: Schedule 1 | E7: Revenue Apportionment | F7: =CONCATENATE(D7," - ",E7) -> Schedule 1 - Revenue Apportionment
B8: Rate Design | C8: Exhibit Unitil-JDT-4 | D8: Schedule 2 | E8: Revenue Proof and Rate Design | F8: =CONCATENATE(D8," - ",E8) -> Schedule 2 - Revenue Proof and Rate Design
B9: Heat Pump Rate Design | C9: Exhibit Unitil-JDT-6 | E9: Residential Heat Pump Rate Design | F9: =E9 -> Residential Heat Pump Rate Design
B10: Rate Design Lighting | C10: Exhibit Unitil-JDT-4 | D10: Schedule 2 | E10: Revenue Proof and Rate Design | F10: =CONCATENATE(D10," - ",E10) -> Schedule 2 - Revenue Proof and Rate Design
B11: Rates | C11: Workpaper to Exhibit Unitil-JDT-4, Schedule 2 | D11: WP | E11: Current and Proposed Rates | F11: =CONCATENATE(D11," - ",E11) -> WP - Current and Proposed Rates
B12: EV-RES Rate | C12: Exhibit Unitil-JDT-7 | E12: Residential Electric Vehicle Annualized Rate | F12: Residential Electric Vehicle Annualized Rate
B13: Annual EV-RES | C13: Exhibit Unitil-JDT-7
B14: Demand Charge Alternative | C14: Exhibit Unitil-JDT-8 | E14: General Service EV Demand Charge Alternative Rates | F14: =E14 -> General Service EV Demand Charge Alternative Rates
B15: Decoupling Target | C15: Exhibit Unitil-JDT-9 | E15: Revenue Decoupling Annual Target Revenue | F15: =E15 -> Revenue Decoupling Annual Target Revenue
B16: CONFIDENTIAL | D16: CONFIDENTIAL Workpaper to Exhibit Unitil-JDT-4 | E16: Special Contract Data and Rate Change | F16: =CONCATENATE(D16," - ",E16) -> CONFIDENTIAL Workpaper to Exhibit Unitil-JDT-4 - Special Contract Data and Rate Change | G16: REDACTED
B17: FGE Bill Impact Tabs ---> | F17: =CONCATENATE(D17," - ",E17) -> -
B18: RD-1 | C18: Exhibit Unitil-JDT-5 | E18: Bill Impact | F18: =E18 -> Bill Impact
B19: RD-2 | C19: Exhibit Unitil-JDT-5 | E19: Bill Impact | F19: =E19 -> Bill Impact
B20: GD-1 | C20: Exhibit Unitil-JDT-5 | E20: Bill Impact | F20: =E20 -> Bill Impact
B21: GD-2 | C21: Exhibit Unitil-JDT-5 | E21: Bill Impact | F21: =E21 -> Bill Impact
B22: GD-3 | C22: Exhibit Unitil-JDT-5 | E22: Bill Impact | F22: =E22 -> Bill Impact
B23: GD-4 | C23: Exhibit Unitil-JDT-5 | E23: Bill Impact | F23: =E23 -> Bill Impact
B24: GD-5 | C24: Exhibit Unitil-JDT-5 | E24: Bill Impact | F24: =E24 -> Bill Impact
B25: SD | C25: Exhibit Unitil-JDT-5 | E25: Bill Impact | F25: =E25 -> Bill Impact
B26: SDC | C26: Exhibit Unitil-JDT-5 | E26: Bill Impact | F26: =E26 -> Bill Impact
B27: Support Files ---> | F27: =CONCATENATE(D27," - ",E27) -> -
B28: ProForma Revenue | C28: INCLUDED IN WORKPAPERS TO EXHIBIT UNITIL-JDT-3 | F28: =CONCATENATE(D28," - ",E28) -> - | G28: REDACTED
B29: Unitil LED Light Summary | C29: Workpaper to Exhibit Unitil-JDT-4, Schedule 2 | D29: WP | E29: Cost Based Analysis of LED Lighting Fixtures | F29: =CONCATENATE(D29," - ",E29) -> WP - Cost Based Analysis of LED Lighting Fixtures
B30: Rev_Billing_Det | C30: Workpaper to Exhibit Unitil-JDT-4, Schedule 2 | D30: WP | E30: Per Books Accuracy Report | F30: =CONCATENATE(D30," - ",E30) -> WP - Per Books Accuracy Report | G30: REDACTED
B31: Outdoor Lighting Update | C31: Workpaper to Exhibit Unitil-JDT-4, Schedule 2 | D31: WP | E31: 2022 Annual Outdoor Lighting Summary | F31: =CONCATENATE(D31," - ",E31) -> WP - 2022 Annual Outdoor Lighting Summary
B32: Atrium + Updated Rates | C32: Workpaper to Exhibit Unitil-JDT-4, Schedule 2 | D32: WP | E32: June 2023 Annualized Outdoor Lighting Fixtures | F32: =CONCATENATE(D32," - ",E32) -> WP - June 2023 Annualized Outdoor Lighting Fixtures
B33: Customer Owned Lights | C33: Workpaper to Exhibit Unitil-JDT-4, Schedule 2 | D33: WP | E33: Fitchburg/Lunenburg Customer Owned Lights | F33: =CONCATENATE(D33," - ",E33) -> WP - Fitchburg/Lunenburg Customer Owned Lights
B34: Rates and Eff Dates | C34: Workpaper to Exhibit Unitil-JDT-4, Schedule 2 | D34: WP | E34: Tariff Rates and Effective Dates | F34: =CONCATENATE(D34," - ",E34) -> WP - Tariff Rates and Effective Dates
B35: Total Revenues by Class | C35: Workpaper to Exhibit Unitil-JDT-4, Schedule 1 | D35: WP | E35: Computation of Total Current Revenues by Rate Class using test year average Basic Service | F35: =CONCATENATE(D35," - ",E35) -> WP - Computation of Total Current Revenues by Rate Class using test year average Basic Service
B36: Rider_Revenue | C36: Workpaper to Exhibit Unitil-JDT-4, Schedule 1 | D36: WP | E36: Rider Revenue Rolled into Base Rates | F36: =CONCATENATE(D36," - ",E36) -> WP - Rider Revenue Rolled into Base Rates
B37: For Bill Impacts | C37: Workpaper to Exhibit Unitil-JDT-5 | D37: WP | E37: Change to Reconciliation Mechanisms for Bill Impacts | F37: =CONCATENATE(D37," - ",E37) -> WP - Change to Reconciliation Mechanisms for Bill Impacts

Sheet Revenue Apportionment
A1: Fitchburg Gas and Electric Light Company
A2: Exhibit Unitil-JDT-4
A3: Schedule 1 - Revenue Apportionment
A7: (A) | B7: (B) | C7: (C) | D7: (D) | E7: (E) | F7: (F) | G7: (G) | H7: (H) | I7: (I) | J7: (J) | K7: (K) | L7: (L) | M7: (M) | N7: (N) | O7: (O) | P7: (P)
A9: Line | B9: Class | D9: Pro Forma Distribution Revenue | E9: Cost to Serve at Equal Rates of Return | F9: Increase (Decrease) @ 8.03% ROR | G9: 150% Overall System Increase | H9: Above 150% Overall Increase | I9: 10% Cap on Total Revenue | J9: Above 10% Cap on Total Revenue | K9: Increase Limited by Caps / No Decrease | L9: Reallocation of Excess | M9: Proposed Increase (Decrease) | N9: Proposed Margin | O9: Percentage Change | P9: Still within 150% Cap
A10: 1 | B10: Residential, Low Income | C10: RD-1/RD-2 | D10: ='Rate Design'!$E$21 -> 17394497 | E10: 22701838 | F10: =E10-D10 -> 5307340.7 | G10: =D10*$H$21 -> 3538423.9 | H10: =IF(F10>G10,"Yes","No") -> Yes | I10: =F29 -> 5903915.3 | J10: =IF(H10="yes",IF(G10>I10,"Yes","No"),IF(F10>I10,"Yes","No")) -> No | K10: =IF(AND(H10="No",J10="No",F10>0),F10,IF(J10="yes",I10,IF(H10="Yes",G10,0))) -> 3538423.9 | L10: =IF(H10="No", $L$22*(E10/SUMIF($H$10:$H$17, "No", $E$10:$E$17)),0) -> 0 | M10: =K10+L10 -> 3538423.9 | N10: =M10+D10 -> 20932921 | O10: =M10/D10 -> 0.20342203 | P10: =IF(M10>G10, "No", "Yes") -> Yes
A11: 2 | B11: Small General | C11: GD-1 | D11: ='Rate Design'!$E$29 -> 823493.82 | E11: 1445084.2 | F11: =E11-D11 -> 621590.37 | G11: =D11*$H$21 -> 167516.78 | H11: =IF(F11>G11,"Yes","No") -> Yes | I11: =F30 -> 211736.36 | J11: =IF(H11="yes",IF(G11>I11,"Yes","No"),IF(F11>I11,"Yes","No")) -> No | K11: =IF(AND(H11="No",J11="No",F11>0),F11,IF(J11="yes",I11,IF(H11="Yes",G11,0))) -> 167516.78 | L11: =IF(H11="No", $L$22*(E11/SUMIF($H$10:$H$17, "No", $E$10:$E$17)),0) -> 0 | M11: =K11+L11 -> 167516.78 | N11: =M11+D11 -> 991010.6 | O11: =M11/D11 -> 0.20342203 | P11: =IF(M11>G11, "No", "Yes") -> Yes
A12: 3 | B12: Regular General | C12: GD-2 | D12: ='Rate Design'!$E$39 -> 6129339.3 | E12: =D12*$D$22/$D$21 -> 4400753.8 | F12: =E12-D12 -> -1728585.5 | G12: =D12*$H$21 -> 1246842.7 | H12: =IF(F12>G12,"Yes","No") -> No | I12: =F31 -> 2639546.9 | J12: =IF(H12="yes",IF(G12>I12,"Yes","No"),IF(F12>I12,"Yes","No")) -> No | K12: =IF(AND(H12="No",J12="No",F12>0),F12,IF(J12="yes",I12,IF(H12="Yes",G12,0))) -> 0 | L12: =IF(H12="No", $L$22*(E12/SUMIF($H$10:$H$17, "No", $E$10:$E$17)),0) -> 128933.05 | M12: =K12+L12 -> 128933.05 | N12: =M12+D12 -> 6258272.4 | O12: =M12/D12 -> 0.021035391 | P12: =IF(M12>G12, "No", "Yes") -> Yes
A13: 4 | B13: Large General | C13: GD-3 | D13: ='Rate Design'!$E$48 -> 4134127.2 | E13: 3832874.6 | F13: =E13-D13 -> -301252.59 | G13: =D13*$H$21 -> 840972.55 | H13: =IF(F13>G13,"Yes","No") -> No | I13: =F32 -> 2739293.3 | J13: =IF(H13="yes",IF(G13>I13,"Yes","No"),IF(F13>I13,"Yes","No")) -> No | K13: =IF(AND(H13="No",J13="No",F13>0),F13,IF(J13="yes",I13,IF(H13="Yes",G13,0))) -> 0 | L13: =IF(H13="No", $L$22*(E13/SUMIF($H$10:$H$17, "No", $E$10:$E$17)),0) -> 112295.35 | M13: =K13+L13 -> 112295.35 | N13: =M13+D13 -> 4246422.6 | O13: =M13/D13 -> 0.027163014 | P13: =IF(M13>G13, "No", "Yes") -> Yes
A14: 5 | B14: Regular General Optional TOU | C14: GD-4 | D14: ='Rate Design'!$E$62 -> 8851.1352 | E14: =D14*$D$22/$D$21 -> 6354.9536 | F14: =E14-D14 -> -2496.1816 | G14: =D14*$H$21 -> 1800.5159 | H14: =IF(F14>G14,"Yes","No") -> No | I14: =F33 -> 7782.3829 | J14: =IF(H14="yes",IF(G14>I14,"Yes","No"),IF(F14>I14,"Yes","No")) -> No | K14: =IF(AND(H14="No",J14="No",F14>0),F14,IF(J14="yes",I14,IF(H14="Yes",G14,0))) -> 0 | L14: =IF(H14="No", $L$22*(E14/SUMIF($H$10:$H$17, "No", $E$10:$E$17)),0) -> 186.18709 | M14: =K14+L14 -> 186.18709 | N14: =M14+D14 -> 9037.3223 | O14: =M14/D14 -> 0.021035391 | P14: =IF(M14>G14, "No", "Yes") -> Yes
A15: 6 | B15: Water and/or Space Heating Rider | C15: GD-5 | D15: ='Rate Design'!$E$74 -> 23656.225 | E15: =D15*$D$22/$D$21 -> 16984.738 | F15: =E15-D15 -> -6671.4868 | G15: =D15*$H$21 -> 4812.1972 | H15: =IF(F15>G15,"Yes","No") -> No | I15: =F34 -> 10376.253 | J15: =IF(H15="yes",IF(G15>I15,"Yes","No"),IF(F15>I15,"Yes","No")) -> No | K15: =IF(AND(H15="No",J15="No",F15>0),F15,IF(J15="yes",I15,IF(H15="Yes",G15,0))) -> 0 | L15: =IF(H15="No", $L$22*(E15/SUMIF($H$10:$H$17, "No", $E$10:$E$17)),0) -> 497.61794 | M15: =K15+L15 -> 497.61794 | N15: =M15+D15 -> 24153.842 | O15: =M15/D15 -> 0.021035391 | P15: =IF(M15>G15, "No", "Yes") -> Yes
A16: 7 | B16: Lighting Company Owned | C16: SD | D16: ='Rate Design'!$E$91 -> 266880.39 | E16: 413273.59 | F16: =E16-D16 -> 146393.2 | G16: =D16*$H$21 -> 54289.35 | H16: =IF(F16>G16,"Yes","No") -> Yes | I16: =F35 -> 52187.196 | J16: =IF(H16="yes",IF(G16>I16,"Yes","No"),IF(F16>I16,"Yes","No")) -> Yes | K16: =IF(AND(H16="No",J16="No",F16>0),F16,IF(J16="yes",I16,IF(H16="Yes",G16,0))) -> 52187.196 | L16: =IF(H16="No", $L$22*(E16/SUMIF($H$10:$H$17, "No", $E$10:$E$17)),0) -> 0 | M16: =K16+L16 -> 52187.196 | N16: =M16+D16 -> 319067.58 | O16: =M16/D16 -> 0.19554526 | P16: =IF(M16>G16, "No", "Yes") -> Yes
A17: 8 | B17: Lighting Customer Owned | C17: SDC | D17: ='Rate Design'!$E$92 -> 46202.774 | E17: 111660.93 | F17: =E17-D17 -> 65458.156 | G17: =D17*$H$21 -> 9398.6621 | H17: =IF(F17>G17,"Yes","No") -> Yes | I17: =F36 -> 19097.933 | J17: =IF(H17="yes",IF(G17>I17,"Yes","No"),IF(F17>I17,"Yes","No")) -> No | K17: =IF(AND(H17="No",J17="No",F17>0),F17,IF(J17="yes",I17,IF(H17="Yes",G17,0))) -> 9398.6621 | L17: =IF(H17="No", $L$22*(E17/SUMIF($H$10:$H$17, "No", $E$10:$E$17)),0) -> 0 | M17: =K17+L17 -> 9398.6621 | N17: =M17+D17 -> 55601.436 | O17: =M17/D17 -> 0.20342203 | P17: =IF(M17>G17, "No", "Yes") -> Yes
A18: 9 | B18: Miscellaneous Revenues | D18: 1418766.1 | E18: =D18 -> 1418766.1 | F18: 0 | M18: =L21 -> 92337.829 | N18: =E18+L21 -> 1511103.9 | O18: =M18/D18 -> 0.065083194
A19: 10 | B19: System Total | D19: =SUM(D10:D18) -> 30245814 | E19: =SUM(E10:E18) -> 34347591 | F19: =SUM(F10:F18) -> 4101776.6 | K19: =SUM(K10:K18) -> 3767526.6 | L19: =SUM(L10:L18) -> 241912.21 | M19: =SUM(M10:M18) -> 4101776.6 | N19: =SUM(N10:N18) -> 34347591
A20: 11 | B20: GD-2, GD-4, GD-5: Regular General | G20: Overall System Increase | H20: =F19/D19 -> 0.13561469 | L20: =F19-K19 -> 334250.04 | M20: Required Additional Increase
A21: 12 | B21: Pro Forma Distribution Revenue | D21: =D12+D14+D15 -> 6161846.7 | G21: 150% Overall System System | H21: =H20*150% -> 0.20342203 | L21: 92337.829 | M21: Change in Misc. Revenues
A22: 13 | B22: Revenue @ Equal ROR | D22: 4424093.5 | L22: =L20-L21 -> 241912.21 | M22: Required Additional Increase
A23: 14
A24: 15 | M24: GD-2, GD-4, GD-5: Regular General | N24: =SUM(N12,N14,N15) -> 6291463.6
A25: 16 | M25: OL Combined | N25: =SUM(N16:N17) -> 374669.02
A26: (A) | B26: (B) | C26: (C) | D26: (D) | E26: (E) | F26: (F) | G26: (G) | H26: (H)
A28: Line | B28: Class | D28: 10% Cap on Total Revenue | E28: Changes to Reconciliation Mechanisms | F28: Revised Cap w/ Changes to Reconciliation Mechanism | G28: Proposed Increase (Decrease) | H28: Under 10% Cap on Total Revenue
A29: =+A25+1 -> 17 | B29: Residential, Low Income | C29: RD-1/RD-2 | D29: ='Total Revenues by Class'!L11 -> 6370957 | E29: =SUM(E41:E42) -> 467041.67 | F29: =D29-E29 -> 5903915.3 | G29: =M10 -> 3538423.9 | H29: =IF(G29>F29, "No", "Yes") -> Yes
A30: =+A29+1 -> 18 | B30: Small General | C30: GD-1 | D30: ='Total Revenues by Class'!L15 -> 223856.67 | E30: =+Rider_Revenue!O11 -> 12120.311 | F30: =D30-E30 -> 211736.36 | G30: =M11 -> 167516.78 | H30: =IF(G30>F30, "No", "Yes") -> Yes
A31: =+A30+1 -> 19 | B31: Regular General | C31: GD-2 | D31: ='Total Revenues by Class'!L19 -> 2817542.2 | E31: =+Rider_Revenue!O12 -> 177995.33 | F31: =D31-E31 -> 2639546.9 | G31: =M12 -> 128933.05 | H31: =IF(G31>F31, "No", "Yes") -> Yes
A32: =+A31+1 -> 20 | B32: Large General | C32: GD-3 | D32: ='Total Revenues by Class'!L25 -> 2793064.7 | E32: =+Rider_Revenue!O13 -> 53771.363 | F32: =D32-E32 -> 2739293.3 | G32: =M13 -> 112295.35 | H32: =IF(G32>F32, "No", "Yes") -> Yes
A33: =+A32+1 -> 21 | B33: Regular General Optional TOU | C33: GD-4 | D33: ='Total Revenues by Class'!L31 -> 8389.0701 | E33: =+Rider_Revenue!O14 -> 606.68725 | F33: =D33-E33 -> 7782.3829 | G33: =M14 -> 186.18709 | H33: =IF(G33>F33, "No", "Yes") -> Yes
A34: =+A33+1 -> 22 | B34: Water and/or Space Heating Rider | C34: GD-5 | D34: ='Total Revenues by Class'!L38 -> 11079.796 | E34: =+Rider_Revenue!O15 -> 703.5436 | F34: =D34-E34 -> 10376.253 | G34: =M15 -> 497.61794 | H34: =IF(G34>F34, "No", "Yes") -> Yes
A35: =+A34+1 -> 23 | B35: Lighting Company Owned | C35: SD | D35: ='Total Revenues by Class'!L44 -> 54186.743 | E35: =+Rider_Revenue!O16 -> 1999.5475 | F35: =D35-E35 -> 52187.196 | G35: =M16 -> 52187.196 | H35: =IF(G35>F35, "No", "Yes") -> Yes
A36: =+A35+1 -> 24 | B36: Lighting Customer Owned | C36: SDC | D36: ='Total Revenues by Class'!L45 -> 20238.301 | E36: =+Rider_Revenue!O17 -> 1140.3686 | F36: =D36-E36 -> 19097.933 | G36: =M17 -> 9398.6621 | H36: =IF(G36>F36, "No", "Yes") -> Yes
A37: =+A36+1 -> 25 | B37: Miscellaneous Revenues | G37: =M18 -> 92337.829
A38: =+A37+1 -> 26 | D38: =SUM(D29:D37) -> 12299314 | E38: =SUM(E29:E37) -> 715378.82 | F38: =SUM(F29:F37) -> 11583936 | G38: =M19 -> 4101776.6
E40: Changes to Reconciliation Mechanisms
D41: RD-1 | E41: =+Rider_Revenue!O9 -> 372016.85
D42: RD-2 | E42: =+Rider_Revenue!O10 -> 95024.817

Sheet Rate Design
A1: Fitchburg Gas and Electric Light Company
A2: Exhibit Unitil-JDT-4
A3: Schedule 2 - Revenue Proof and Rate Design
A6: Line No. | B6: Description | C6: TY Billing Determinants | D6: Current Rate | E6: Current Total Distribution Revenue | G6: Proposed Rate | H6: Proposed Total Distribution Revenue | J6: Difference ($) | K6: Difference (%)
A7: =IF(AND(B7="",E7=""),"",MAX(A$1:A6)+1) -> 1 | B7: RD-1: Residential
A8: =IF(AND(B8="",E8=""),"",MAX(A$1:A7)+1) -> 2 | B8: Customer Charge | C8: =SUMIFS(Rev_Billing_Det!$C$180:$C$186,Rev_Billing_Det!$A$180:$A$186,LEFT($B7,4)) -> 254959.9 | D8: =Rates!C8 -> 7 | E8: =D8*C8 -> 1784719.3 | G8: =G18 -> 8.5 | H8: =C8*G8 -> 2167159.1 | J8: =H8-E8 -> 382439.85 | K8: =J8/E8 -> 0.21428571 | M8: RD-1: Residential
A9: =IF(AND(B9="",E9=""),"",MAX(A$1:A8)+1) -> 3 | B9: Distribution Charge | C9: =SUMIFS(Rev_Billing_Det!$E$180:$E$186,Rev_Billing_Det!$A$180:$A$186,LEFT($B7,4)) -> 137275588 | D9: =Rates!C9 -> 0.07903 | E9: =D9*C9 -> 10848890 | G9: =G19 -> 0.10585 | H9: =C9*G9 -> 14530621 | J9: =H9-E9 -> 3681731.3 | K9: =J9/E9 -> 0.3393648 | M9: RD-1: Residential
A10: =IF(AND(B10="",E10=""),"",MAX(A$1:A9)+1) -> 4 | B10: Riders | E10: =-Rider_Revenue!N9 -> 1242344.1 | H10: 0 | J10: =H10-E10 -> -1242344.1
A11: =IF(AND(B11="",E11=""),"",MAX(A$1:A10)+1) -> 5 | E11: =SUM(E8:E10) -> 13875953 | H11: =SUM(H8:H10) -> 16697780 | J11: =H11-E11 -> 2821827 | K11: =J11/E11 -> 0.20336095
A12: =IF(AND(B12="",E12=""),"",MAX(A$1:A11)+1) -> 6 | B12: RD-2: Residential, Low Income
A13: =IF(AND(B13="",E13=""),"",MAX(A$1:A12)+1) -> 7 | B13: Customer Charge | C13: =SUMIFS(Rev_Billing_Det!$C$180:$C$186,Rev_Billing_Det!$A$180:$A$186,LEFT($B12,4)) -> 61437.474 | D13: =Rates!C12 -> 7 | E13: =D13*C13 -> 430062.32 | G13: =G18 -> 8.5 | H13: =C13*G13 -> 522218.53 | J13: =H13-E13 -> 92156.211 | K13: =J13/E13 -> 0.21428571 | M13: RD-2: Residential, Low Income
A14: =IF(AND(B14="",E14=""),"",MAX(A$1:A13)+1) -> 8 | B14: Distribution Charge | C14: =SUMIFS(Rev_Billing_Det!$E$180:$E$186,Rev_Billing_Det!$A$180:$A$186,LEFT($B12,4)) -> 35064508 | D14: =Rates!C13 -> 0.07903 | E14: =D14*C14 -> 2771148.1 | G14: =G19 -> 0.10585 | H14: =C14*G14 -> 3711578.2 | J14: =H14-E14 -> 940430.1 | K14: =J14/E14 -> 0.3393648 | M14: RD-2: Residential, Low Income
A15: =IF(AND(B15="",E15=""),"",MAX(A$1:A14)+1) -> 9 | B15: Riders | E15: =-Rider_Revenue!N10 -> 317333.8 | H15: 0 | J15: =H15-E15 -> -317333.8
A16: =IF(AND(B16="",E16=""),"",MAX(A$1:A15)+1) -> 10 | E16: =SUM(E13:E15) -> 3518544.2 | H16: =SUM(H13:H15) -> 4233796.7 | J16: =H16-E16 -> 715252.52 | K16: =J16/E16 -> 0.20328081
A17: =IF(AND(B17="",E17=""),"",MAX(A$1:A16)+1) -> 11 | B17: Total_R-1, R-2: Residential
A18: =IF(AND(B18="",E18=""),"",MAX(A$1:A17)+1) -> 12 | B18: Total Customer Charge | C18: =C8+C13 -> 316397.37 | E18: =E8+E13 -> 2214781.6 | G18: =Rates!M8 -> 8.5 | H18: =H8+H13 -> 2689377.7 | J18: =H18-E18 -> 474596.06 | K18: =J18/E18 -> 0.21428571
A19: =IF(AND(B19="",E19=""),"",MAX(A$1:A18)+1) -> 13 | B19: Total Distribution Charge | C19: =C9+C14 -> 172340096 | E19: =E9+E14 -> 13620038 | G19: =TRUNC((H23-H18)/C19,5) -> 0.10585 | H19: =G19*C19 -> 18242199 | J19: =H19-E19 -> 4622161.4 | K19: =J19/E19 -> 0.3393648
A20: =IF(AND(B20="",E20=""),"",MAX(A$1:A19)+1) -> 14 | B20: Riders | E20: =E10+E15 -> 1559677.9 | H20: =G20*C20 -> 0 | J20: =H20-E20 -> -1559677.9
A21: =IF(AND(B21="",E21=""),"",MAX(A$1:A20)+1) -> 15 | E21: =SUM(E18:E20) -> 17394497 | H21: =SUM(H18:H20) -> 20931577 | J21: =H21-E21 -> 3537079.6 | K21: =J21/E21 -> 0.20334474
A22: =IF(AND(B22="",E22=""),"",MAX(A$1:A21)+1)
A23: =IF(AND(B23="",E23=""),"",MAX(A$1:A22)+1) -> 16 | B23: Revenue Target_R-1, R-2: Residential | H23: ='Revenue Apportionment'!N10 -> 20932921
A24: =IF(AND(B24="",E24=""),"",MAX(A$1:A23)+1) -> 17 | B24: Difference | H24: =H23-H21 -> 1344.3775
A25: =IF(AND(B25="",E25=""),"",MAX(A$1:A24)+1) -> 18 | B25: GD-1: Small General
A26: =IF(AND(B26="",E26=""),"",MAX(A$1:A25)+1) -> 19 | B26: Customer Charge | C26: =SUMIFS(Rev_Billing_Det!$C$180:$C$186,Rev_Billing_Det!$A$180:$A$186,LEFT($B25,4)) -> 30492.186 | D26: =Rates!C16 -> 10 | E26: =D26*C26 -> 304921.86 | G26: =Rates!M9 -> 12 | H26: =C26*G26 -> 365906.23 | J26: =H26-E26 -> 60984.372 | K26: =J26/E26 -> 0.2 | M26: GD-1: Small General
A27: =IF(AND(B27="",E27=""),"",MAX(A$1:A26)+1) -> 20 | B27: Distribution Charge | C27: =SUMIFS(Rev_Billing_Det!$E$180:$E$186,Rev_Billing_Det!$A$180:$A$186,LEFT($B25,4)) -> 5912347 | D27: =Rates!C17 -> 0.0785 | E27: =D27*C27 -> 464119.24 | G27: =TRUNC((H31-H26)/C27,5) -> 0.10572 | H27: =G27*C27 -> 625053.32 | J27: =H27-E27 -> 160934.09 | K27: =J27/E27 -> 0.34675159 | M27: GD-1: Small General
A28: =IF(AND(B28="",E28=""),"",MAX(A$1:A27)+1) -> 21 | B28: Riders | E28: =-Rider_Revenue!N11 -> 54452.716 | H28: 0
A29: =IF(AND(B29="",E29=""),"",MAX(A$1:A28)+1) -> 22 | E29: =SUM(E26:E28) -> 823493.82 | H29: =SUM(H26:H28) -> 990959.56 | J29: =SUM(J26:J27) -> 221918.46 | K29: =J29/E29 -> 0.26948406
A30: =IF(AND(B30="",E30=""),"",MAX(A$1:A29)+1)
A31: =IF(AND(B31="",E31=""),"",MAX(A$1:A30)+1) -> 23 | B31: =CONCATENATE("Revenue Target_",B25) -> Revenue Target_GD-1: Small General | H31: ='Revenue Apportionment'!N11 -> 991010.6
A32: =IF(AND(B32="",E32=""),"",MAX(A$1:A31)+1) -> 24 | B32: Difference | H32: =H31-H29 -> 51.04213
A33: =IF(AND(B33="",E33=""),"",MAX(A$1:A32)+1) -> 25 | B33: GD-2: Regular General
A34: =IF(AND(B34="",E34=""),"",MAX(A$1:A33)+1) -> 26 | B34: Customer Charge | C34: =SUMIFS(Rev_Billing_Det!$C$180:$C$186,Rev_Billing_Det!$A$180:$A$186,LEFT($B33,4)) -> 18164.621 | D34: =Rates!C20 -> 10 | E34: =C34*D34 -> 181646.21 | G34: =Rates!M10 -> 12 | H34: =C34*G34 -> 217975.45 | J34: =H34-E34 -> 36329.242 | K34: =J34/E34 -> 0.2 | M34: GD-2: Regular General
A35: =IF(AND(B35="",E35=""),"",MAX(A$1:A34)+1) -> 27 | B35: Demand Charge | C35: =SUMIFS(Rev_Billing_Det!$M$180:$M$186,Rev_Billing_Det!$A$180:$A$186,LEFT($B33,4)) -> 323618.5 | D35: =Rates!C21 -> 9.81 | E35: =C35*D35 -> 3174697.5 | G35: =Rates!M11 -> 10 | H35: =C35*G35 -> 3236185 | J35: =H35-E35 -> 61487.515 | K35: =J35/E35 -> 0.019367992 | M35: GD-2: Regular General
A36: =IF(AND(B36="",E36=""),"",MAX(A$1:A35)+1) -> 28 | B36: Distribution Charge | C36: =SUMIFS(Rev_Billing_Det!$E$180:$E$186,Rev_Billing_Det!$A$180:$A$186,LEFT($B33,4)) -> 86826989 | D36: =Rates!C22 -> 0.02377 | E36: =C36*D36 -> 2063877.5 | G36: =TRUNC((H41-H34-H35-H37)/C36,5) -> 0.03234 | H36: =C36*G36 -> 2807984.8 | J36: =H36-E36 -> 744107.3 | K36: =J36/E36 -> 0.36053849 | M36: GD-2: Regular General
A37: =IF(AND(B37="",E37=""),"",MAX(A$1:A36)+1) -> 29 | B37: Transformer Credit | C37: =E37/D37 -> 24209.105 | D37: =$D$82 -> -0.19 | E37: ='ProForma Revenue'!E28 -> -4599.73 | G37: =D37 -> -0.19 | H37: =C37*G37 -> -4599.73 | J37: =H37-E37 -> 0 | K37: =J37/E37 -> 0 | M37: GD-2: Regular General
A38: =IF(AND(B38="",E38=""),"",MAX(A$1:A37)+1) -> 30 | B38: Riders | E38: =-Rider_Revenue!N12 -> 713717.85 | H38: 0
A39: =IF(AND(B39="",E39=""),"",MAX(A$1:A38)+1) -> 31 | E39: =SUM(E34:E38) -> 6129339.3 | H39: =SUM(H34:H38) -> 6257545.5 | J39: =H39-E39 -> 128206.2 | K39: =J39/E39 -> 0.020916806
A40: =IF(AND(B40="",E40=""),"",MAX(A$1:A39)+1)
A41: =IF(AND(B41="",E41=""),"",MAX(A$1:A40)+1) -> 32 | B41: =CONCATENATE("Revenue Target_",B33) -> Revenue Target_GD-2: Regular General | H41: ='Revenue Apportionment'!N12 -> 6258272.4
A42: =IF(AND(B42="",E42=""),"",MAX(A$1:A41)+1) -> 33 | B42: Difference | H42: =H41-H39 -> 726.84706
A43: =IF(AND(B43="",E43=""),"",MAX(A$1:A42)+1) -> 34 | B43: GD-3: Large General
A44: =IF(AND(B44="",E44=""),"",MAX(A$1:A43)+1) -> 35 | B44: Customer Charge | C44: =SUMIFS(Rev_Billing_Det!$C$180:$C$186,Rev_Billing_Det!$A$180:$A$186,LEFT($B43,4)) -> 339 | D44: =Rates!C26 -> 300 | E44: =C44*D44 -> 101700 | G44: =Rates!M12 -> 338.75 | H44: =C44*G44 -> 114836.25 | J44: =H44-E44 -> 13136.25 | K44: =J44/E44 -> 0.12916667 | M44: GD-3: Large General
A45: =IF(AND(B45="",E45=""),"",MAX(A$1:A44)+1) -> 36 | B45: Demand Charge | C45: =SUMIFS(Rev_Billing_Det!$M$180:$M$186,Rev_Billing_Det!$A$180:$A$186,LEFT($B43,4)) -> 296936 | D45: =Rates!C27 -> 8.07 | E45: =C45*D45 -> 2396273.5 | G45: =Rates!M13 -> 9.75 | H45: =C45*G45 -> 2895126 | J45: =H45-E45 -> 498852.48 | K45: =J45/E45 -> 0.20817844 | M45: GD-3: Large General
A46: =IF(AND(B46="",E46=""),"",MAX(A$1:A45)+1) -> 37 | B46: Distribution Charge | C46: =C52 -> 128027055 | E46: =E52 -> 1319926.9 | H46: =H52 -> 1235793.9 | J46: =H46-E46 -> -84132.929 | K46: =J46/E46 -> -0.063740599 | M46: GD-3: Large General
A47: =IF(AND(B47="",E47=""),"",MAX(A$1:A46)+1) -> 38 | B47: Riders | E47: =-Rider_Revenue!N13 -> 316226.83 | H47: 0
A48: =IF(AND(B48="",E48=""),"",MAX(A$1:A47)+1) -> 39 | E48: =SUM(E44:E47) -> 4134127.2 | H48: =SUM(H44:H47) -> 4245756.2 | J48: =H48-E48 -> 111628.98 | K48: =J48/E48 -> 0.027001824 | M48: GD-3: Large General
A49: =IF(AND(B49="",E49=""),"",MAX(A$1:A48)+1) -> 40 | B49: Distribution Charge
A50: =IF(AND(B50="",E50=""),"",MAX(A$1:A49)+1) -> 41 | B50: On Peak Billed kWh | C50: =SUMIFS(Rev_Billing_Det!$E$180:$E$186,Rev_Billing_Det!$A$180:$A$186,LEFT($B43,4)) -> 50297243 | D50: =Rates!C29 -> 0.01952 | E50: =C50*D50 -> 981802.18 | G50: =TRUNC((H54-H44-H45)*E50/(E50+E51)/C50,5) -> 0.01828 | H50: =C50*G50 -> 919433.6 | J50: =H50-E50 -> -62368.581 | K50: =J50/E50 -> -0.06352459 | M50: GD-3: Large General
A51: =IF(AND(B51="",E51=""),"",MAX(A$1:A50)+1) -> 42 | B51: Off Peak Billed kWh | C51: =SUMIFS(Rev_Billing_Det!$F$180:$F$186,Rev_Billing_Det!$A$180:$A$186,LEFT($B43,4)) -> 77729812 | D51: =Rates!C30 -> 0.00435 | E51: =C51*D51 -> 338124.68 | G51: =TRUNC((H54-H44-H45-H50)/C51,5) -> 0.00407 | H51: =C51*G51 -> 316360.33 | J51: =H51-E51 -> -21764.347 | K51: =J51/E51 -> -0.064367816 | M51: GD-3: Large General
A52: =IF(AND(B52="",E52=""),"",MAX(A$1:A51)+1) -> 43 | C52: =SUM(C50:C51) -> 128027055 | E52: =SUM(E50:E51) -> 1319926.9 | H52: =SUM(H50:H51) -> 1235793.9 | M52: GD-3: Large General
A53: =IF(AND(B53="",E53=""),"",MAX(A$1:A52)+1)
A54: =IF(AND(B54="",E54=""),"",MAX(A$1:A53)+1) -> 44 | B54: =CONCATENATE("Revenue Target_",B43) -> Revenue Target_GD-3: Large General | H54: ='Revenue Apportionment'!N13 -> 4246422.6
A55: =IF(AND(B55="",E55=""),"",MAX(A$1:A54)+1) -> 45 | B55: Difference | H55: =H54-H48 -> 666.37947
A56: =IF(AND(B56="",E56=""),"",MAX(A$1:A55)+1) -> 46 | B56: GD-4: Regular General Optional TOU
A57: =IF(AND(B57="",E57=""),"",MAX(A$1:A56)+1) -> 47 | B57: Customer Charge | C57: =SUMIFS(Rev_Billing_Det!$C$180:$C$186,Rev_Billing_Det!$A$180:$A$186,LEFT($B56,4)) -> 33 | D57: =Rates!C34 -> 10 | E57: =C57*D57 -> 330 | G57: =Rates!M14 -> 12 | H57: =C57*G57 -> 396 | J57: =H57-E57 -> 66 | K57: =J57/E57 -> 0.2 | M57: GD-4: Regular General Optional TOU
A58: =IF(AND(B58="",E58=""),"",MAX(A$1:A57)+1) -> 48 | B58: Demand Charge | C58: =SUMIFS(Rev_Billing_Det!$M$180:$M$186,Rev_Billing_Det!$A$180:$A$186,LEFT($B56,4)) -> 1329.5 | D58: =Rates!C35 -> 3.92 | E58: =C58*D58 -> 5211.64 | G58: =Rates!M15 -> 4.75 | H58: =C58*G58 -> 6315.125 | J58: =H58-E58 -> 1103.485 | K58: =J58/E58 -> 0.21173469 | M58: GD-4: Regular General Optional TOU
A59: =IF(AND(B59="",E59=""),"",MAX(A$1:A58)+1) -> 49 | B59: Distribution Charge | C59: =C66 -> 295945 | E59: =E66 -> 1097.7273 | H59: =H66 -> 2545.5095 | J59: =H59-E59 -> 1447.7822 | K59: =J59/E59 -> 1.3188906 | M59: GD-4: Regular General Optional TOU
A60: =IF(AND(B60="",E60=""),"",MAX(A$1:A59)+1) -> 50 | B60: Transformer Credit | C60: =E60/D60 -> 1162.6316 | D60: =$D$82 -> -0.19 | E60: ='ProForma Revenue'!E43 -> -220.9 | G60: =D60 -> -0.19 | H60: =C60*G60 -> -220.9 | J60: =H60-E60 -> 0 | K60: =J60/E60 -> 0
A61: =IF(AND(B61="",E61=""),"",MAX(A$1:A60)+1) -> 51 | B61: Riders | E61: =-Rider_Revenue!N14 -> 2432.6679 | H61: 0
A62: =IF(AND(B62="",E62=""),"",MAX(A$1:A61)+1) -> 52 | E62: =SUM(E57:E61) -> 8851.1352 | H62: =SUM(H57:H61) -> 9035.7345 | J62: =H62-E62 -> 184.59929 | K62: =J62/E62 -> 0.020856002 | M62: GD-4: Regular General Optional TOU
A63: =IF(AND(B63="",E63=""),"",MAX(A$1:A62)+1) -> 53 | B63: Distribution Charge | M63: GD-4: Regular General Optional TOU
A64: =IF(AND(B64="",E64=""),"",MAX(A$1:A63)+1) -> 54 | B64: On Peak Billed kWh | C64: =SUMIFS(Rev_Billing_Det!$E$180:$E$186,Rev_Billing_Det!$A$180:$A$186,LEFT($B56,4)) -> 54449 | D64: =Rates!C37 -> 0.01027 | E64: =C64*D64 -> 559.19123 | G64: =TRUNC((H68-H57-H58-H60)*E64/(E64+E65)/C64,5) -> 0.02382 | H64: =C64*G64 -> 1296.9752 | J64: =H64-E64 -> 737.78395 | K64: =J64/E64 -> 1.3193768 | M64: GD-4: Regular General Optional TOU
A65: =IF(AND(B65="",E65=""),"",MAX(A$1:A64)+1) -> 55 | B65: Off Peak Billed kWh | C65: =SUMIFS(Rev_Billing_Det!$F$180:$F$186,Rev_Billing_Det!$A$180:$A$186,LEFT($B56,4)) -> 241496 | D65: =Rates!C38 -> 0.00223 | E65: =C65*D65 -> 538.53608 | G65: =TRUNC((H68-H57-H58-H60-H64)/C65,5) -> 0.00517 | H65: =C65*G65 -> 1248.5343 | J65: =H65-E65 -> 709.99824 | K65: =J65/E65 -> 1.3183857 | M65: GD-4: Regular General Optional TOU
A66: =IF(AND(B66="",E66=""),"",MAX(A$1:A65)+1) -> 56 | C66: =SUM(C64:C65) -> 295945 | E66: =SUM(E64:E65) -> 1097.7273 | H66: =SUM(H64:H65) -> 2545.5095 | M66: GD-4: Regular General Optional TOU
A67: =IF(AND(B67="",E67=""),"",MAX(A$1:A66)+1)
A68: =IF(AND(B68="",E68=""),"",MAX(A$1:A67)+1) -> 57 | B68: =CONCATENATE("Revenue Target_",B56) -> Revenue Target_GD-4: Regular General Optional TOU | H68: ='Revenue Apportionment'!N14 -> 9037.3223
A69: =IF(AND(B69="",E69=""),"",MAX(A$1:A68)+1) -> 58 | B69: Difference | H69: =H68-H62 -> 1.5878007
A70: =IF(AND(B70="",E70=""),"",MAX(A$1:A69)+1) -> 59 | B70: GD-5: Water and/or Space Heating Rider
A71: =IF(AND(B71="",E71=""),"",MAX(A$1:A70)+1) -> 60 | B71: Customer Charge | C71: =SUMIFS(Rev_Billing_Det!$C$180:$C$186,Rev_Billing_Det!$A$180:$A$186,LEFT($B70,4)) -> 78 | D71: =Rates!C42 -> 0 | E71: =C71*D71 -> 0 | G71: =D71 -> 0 | H71: =C71*G71 -> 0 | J71: =H71-E71 -> 0 | K71: =J71/E71 -> #DIV/0! | M71: GD-5: Water and/or Space Heating Rider
A72: =IF(AND(B72="",E72=""),"",MAX(A$1:A71)+1) -> 61 | B72: Distribution Charge | C72: =SUMIFS(Rev_Billing_Det!$E$180:$E$186,Rev_Billing_Det!$A$180:$A$186,LEFT($B70,4)) -> 343192 | D72: =Rates!C43 -> 0.06071 | E72: =C72*D72 -> 20835.186 | G72: =TRUNC((H76-H71)/C72,5) -> 0.07037 | H72: =C72*G72 -> 24150.421 | J72: =H72-E72 -> 3315.2347 | K72: =J72/E72 -> 0.15911711 | M72: GD-5: Water and/or Space Heating Rider
A73: =IF(AND(B73="",E73=""),"",MAX(A$1:A72)+1) -> 62 | B73: Riders | E73: =-Rider_Revenue!N15 -> 2821.0382 | H73: 0
A74: =IF(AND(B74="",E74=""),"",MAX(A$1:A73)+1) -> 63 | E74: =SUM(E71:E73) -> 23656.225 | H74: =SUM(H71:H73) -> 24150.421 | J74: =H74-E74 -> 494.19648 | K74: =J74/E74 -> 0.020890759 | M74: GD-5: Water and/or Space Heating Rider
A75: =IF(AND(B75="",E75=""),"",MAX(A$1:A74)+1)
A76: =IF(AND(B76="",E76=""),"",MAX(A$1:A75)+1) -> 64 | B76: =CONCATENATE("Revenue Target_",B70) -> Revenue Target_GD-5: Water and/or Space Heating Rider | H76: ='Revenue Apportionment'!N15 -> 24153.842
A77: =IF(AND(B77="",E77=""),"",MAX(A$1:A76)+1) -> 65 | B77: Difference | H77: =H76-H74 -> 3.4214554
A78: =IF(AND(B78="",E78=""),"",MAX(A$1:A77)+1) -> 66 | B78: Total_GD-2, GD-4, GD-5 Regular General
A79: =IF(AND(B79="",E79=""),"",MAX(A$1:A78)+1) -> 67 | B79: Customer Charge | C79: =C34+C57+C71 -> 18275.621 | E79: =E34+E57+E71 -> 181976.21 | H79: =H34+H57+H71 -> 218371.45 | J79: =H79-E79 -> 36395.242 | K79: =J79/E79 -> 0.2
A80: =IF(AND(B80="",E80=""),"",MAX(A$1:A79)+1) -> 68 | B80: Demand Charge | C80: =C35+C58 -> 324948 | E80: =E35+E58 -> 3179909.1 | H80: =H35+H58 -> 3242500.1 | J80: =H80-E80 -> 62591 | K80: =J80/E80 -> 0.019683267
A81: =IF(AND(B81="",E81=""),"",MAX(A$1:A80)+1) -> 69 | B81: Distribution Charge | C81: =C36+C59+C72 -> 87466126 | E81: =E36+E59+E72 -> 2085810.4 | H81: =H36+H59+H72 -> 2834680.8 | J81: =H81-E81 -> 748870.31 | K81: =J81/E81 -> 0.35903086
A82: =IF(AND(B82="",E82=""),"",MAX(A$1:A81)+1) -> 70 | B82: Transformer Credit | D82: -0.19 | E82: =E37+E60 -> -4820.63 | H82: =H37+H60 -> -4820.63 | J82: =H82-E82 -> 0 | K82: =J82/E82 -> 0
A83: =IF(AND(B83="",E83=""),"",MAX(A$1:A82)+1) -> 71 | B83: Riders | E83: =E28+E38+E61+E73 -> 773424.27 | H83: 0
A84: =IF(AND(B84="",E84=""),"",MAX(A$1:A83)+1) -> 72 | E84: =SUM(E79:E83) -> 6216299.4 | H84: =SUM(H79:H83) -> 6290731.7 | J84: =H84-E84 -> 74432.283 | K84: =J84/E84 -> 0.011973729
A85: =IF(AND(B85="",E85=""),"",MAX(A$1:A84)+1)
A86: =IF(AND(B86="",E86=""),"",MAX(A$1:A85)+1) -> 73 | B86: Revenue Target_2,4,5 | H86: ='Revenue Apportionment'!N24 -> 6291463.6
A87: =IF(AND(B87="",E87=""),"",MAX(A$1:A86)+1) -> 74 | B87: Difference | H87: =H86-H84 -> 731.85632
A88: =IF(AND(B88="",E88=""),"",MAX(A$1:A87)+1)
B91: Lighting Company Owned - SD | E91: ='Rate Design Lighting'!F72 -> 266880.39 | H91: ='Rate Design Lighting'!I72 -> 319014.61
B92: Lighting Customer Owned - SDC | E92: ='Rate Design Lighting'!F80 -> 46202.774 | H92: ='Rate Design Lighting'!I78 -> 55598.948

Sheet Rate Design Lighting
A1: Fitchburg Gas and Electric Light Company
A2: Exhibit Unitil-JDT-4
A3: Schedule 2 - Revenue Proof and Rate Design
A5: Line No. | D5: TY Billing | E5: Current | F5: Current | H5: Proposed | I5: Proposed
B6: Outdoor Lighting | D6: Determinants | E6: Rates | F6: Revenue | H6: Rates | I6: Revenue
A7: =IF(B7="","",MAX(A$6:A6)+1) -> 1 | B7: SD: Outdoor Lighting - Company Owned
A8: =IF(B8="","",MAX(A$6:A7)+1)
A9: =IF(B9="","",MAX(A$6:A8)+1) -> 2 | B9: Energy | C9: Company Owned - All kWh | D9: ='ProForma Revenue'!G105 -> 1041430.9 | E9: ='Rates and Eff Dates'!D46 -> 0 | F9: =D9*E9 -> 0 | H9: =TRUNC(E9*($I$76),5) -> 0 | I9: =H9*D9 -> 0
A10: =IF(B10="","",MAX(A$6:A9)+1)
A11: =IF(B11="","",MAX(A$6:A10)+1) -> 3 | B11: Lumens | C11: Luminaire
A12: =IF(B12="","",MAX(A$6:A11)+1) -> 4 | B12: Mercury Vapor:
A13: =IF(B13="","",MAX(A$6:A12)+1) -> 5 | B13: 3500 | C13: Street and Highway Type | D13: ='ProForma Revenue'!G53 -> 48 | E13: ='Rates and Eff Dates'!E53 -> 13.54 | F13: =D13*E13 -> 649.92 | H13: =TRUNC(E13*($I$76),2) -> 17.3 | I13: =H13*D13 -> 830.4
A14: =IF(B14="","",MAX(A$6:A13)+1) -> 6 | B14: 7000 | C14: Street and Highway Type | D14: ='ProForma Revenue'!G54 -> 84 | E14: ='Rates and Eff Dates'!E54 -> 15.02 | F14: =D14*E14 -> 1261.68 | H14: =TRUNC(E14*($I$76),2) -> 19.19 | I14: =H14*D14 -> 1611.96
A15: =IF(B15="","",MAX(A$6:A14)+1) -> 7 | B15: 20000 | C15: Street and Highway Type | D15: ='ProForma Revenue'!G55 -> 0 | E15: ='Rates and Eff Dates'!E55 -> 27.29 | F15: =D15*E15 -> 0 | H15: =TRUNC(E15*($I$76),2) -> 34.88 | I15: =H15*D15 -> 0
A16: =IF(B16="","",MAX(A$6:A15)+1) -> 8 | B16: 60000 | C16: Street and Highway Type | D16: ='ProForma Revenue'!G56 -> 84 | E16: ='Rates and Eff Dates'!E56 -> 52.18 | F16: =D16*E16 -> 4383.12 | H16: =TRUNC(E16*($I$76),2) -> 66.69 | I16: =H16*D16 -> 5601.96
A17: =IF(B17="","",MAX(A$6:A16)+1) -> 9 | B17: 20000 | C17: Flood Light Type | D17: ='ProForma Revenue'!G57 -> 300 | E17: ='Rates and Eff Dates'!E57 -> 30.18 | F17: =D17*E17 -> 9054 | H17: =TRUNC(E17*($I$76),2) -> 38.57 | I17: =H17*D17 -> 11571
A18: =IF(B18="","",MAX(A$6:A17)+1) -> 10 | B18: 3500 | C18: Power Bracket Included | D18: ='ProForma Revenue'!G58 -> 348 | E18: ='Rates and Eff Dates'!E58 -> 14.18 | F18: =D18*E18 -> 4934.64 | H18: =TRUNC(E18*($I$76),2) -> 18.12 | I18: =H18*D18 -> 6305.76
A19: =IF(B19="","",MAX(A$6:A18)+1) -> 11 | B19: 7000 | C19: Power Bracket Included | D19: ='ProForma Revenue'!G59 -> 300 | E19: ='Rates and Eff Dates'!E59 -> 15.97 | F19: =D19*E19 -> 4791 | H19: =TRUNC(E19*($I$76),2) -> 20.41 | I19: =H19*D19 -> 6123
A20: =IF(B20="","",MAX(A$6:A19)+1)
A21: =IF(B21="","",MAX(A$6:A20)+1) -> 12 | B21: High Pressure Sodium:
A22: =IF(B22="","",MAX(A$6:A21)+1) -> 13 | B22: 3300 | C22: Street and Highway Type | D22: ='ProForma Revenue'!G61 -> 1580 | E22: ='Rates and Eff Dates'!E62 -> 11.75 | F22: =D22*E22 -> 18565 | H22: =TRUNC(E22*($I$76),2) -> 15.01 | I22: =H22*D22 -> 23715.8
A23: =IF(B23="","",MAX(A$6:A22)+1) -> 14 | B23: 9500 | C23: Street and Highway Type | D23: ='ProForma Revenue'!G62 -> 996 | E23: ='Rates and Eff Dates'!E63 -> 13.97 | F23: =D23*E23 -> 13914.12 | H23: =TRUNC(E23*($I$76),2) -> 17.85 | I23: =H23*D23 -> 17778.6
A24: =IF(B24="","",MAX(A$6:A23)+1) -> 15 | B24: 20000 | C24: Street and Highway Type | D24: ='ProForma Revenue'!G63 -> 96 | E24: ='Rates and Eff Dates'!E64 -> 20.83 | F24: =D24*E24 -> 1999.68 | H24: =TRUNC(E24*($I$76),2) -> 26.62 | I24: =H24*D24 -> 2555.52
A25: =IF(B25="","",MAX(A$6:A24)+1) -> 16 | B25: 50000 | C25: Street and Highway Type | D25: ='ProForma Revenue'!G64 -> 72 | E25: ='Rates and Eff Dates'!E65 -> 29.62 | F25: =D25*E25 -> 2132.64 | H25: =TRUNC(E25*($I$76),2) -> 37.86 | I25: =H25*D25 -> 2725.92
A26: =IF(B26="","",MAX(A$6:A25)+1) -> 17 | B26: 140000 | C26: Street and Highway Type | D26: ='ProForma Revenue'!G65 -> 516 | E26: ='Rates and Eff Dates'!E66 -> 60.77 | F26: =D26*E26 -> 31357.32 | H26: =TRUNC(E26*($I$76),2) -> 77.67 | I26: =H26*D26 -> 40077.72
A27: =IF(B27="","",MAX(A$6:A26)+1) -> 18 | B27: 50000 | C27: Flood Light Type | D27: ='ProForma Revenue'!G66 -> 3480 | E27: ='Rates and Eff Dates'!E67 -> 34.38 | F27: =D27*E27 -> 119642.4 | H27: =TRUNC(E27*($I$76),2) -> 43.94 | I27: =H27*D27 -> 152911.2
A28: =IF(B28="","",MAX(A$6:A27)+1)
A29: =IF(B29="","",MAX(A$6:A28)+1) -> 19 | B29: Light Emitting Diode (LED):
A30: =IF(B30="","",MAX(A$6:A29)+1) -> 20 | B30: 10680 | C30: Cobra Head Type | D30: ='ProForma Revenue'!G81 -> 84 | E30: ='ProForma Revenue'!M81 -> 15.1 | F30: =D30*E30 -> 1268.4
A31: =IF(B31="","",MAX(A$6:A30)+1) -> 21 | C31: 28 Watt LED Street | D31: ='ProForma Revenue'!G95 -> 1296 | E31: ='ProForma Revenue'!M95 -> 7.58 | F31: =D31*E31 -> 9823.68
A32: =IF(B32="","",MAX(A$6:A31)+1) -> 22 | C32: 47 Watt LED Street | D32: ='ProForma Revenue'!G96 -> 138 | E32: ='ProForma Revenue'!M96 -> 8.36 | F32: =D32*E32 -> 1153.68
A33: =IF(B33="","",MAX(A$6:A32)+1) -> 23 | C33: 54 Watt LED Street | D33: ='ProForma Revenue'!G97 -> 180 | E33: ='ProForma Revenue'!M97 -> 8.65 | F33: =D33*E33 -> 1557
A34: =IF(B34="","",MAX(A$6:A33)+1) -> 24 | C34: 70 Watt LED Street | D34: ='ProForma Revenue'!G98 -> 12 | E34: ='ProForma Revenue'!M98 -> 12.83 | F34: =D34*E34 -> 153.96
A35: =IF(B35="","",MAX(A$6:A34)+1) -> 25 | C35: 110 Watt LED Flood | D35: ='ProForma Revenue'!G99 -> 1448 | E35: ='ProForma Revenue'!M99 -> 15.08 | F35: =D35*E35 -> 21835.84
A36: =IF(B36="","",MAX(A$6:A35)+1) -> 26 | C36: 110 Watt LED Flood - CREE | D36: ='ProForma Revenue'!G100 -> 12 | E36: ='ProForma Revenue'!M100 -> 25.79 | F36: =D36*E36 -> 309.48
A37: =IF(B37="","",MAX(A$6:A36)+1)
A38: =IF(B38="","",MAX(A$6:A37)+1) -> 27 | B38: New LED Offering
A39: =IF(B39="","",MAX(A$6:A38)+1) -> 28 | B39: Cobra | C39: 20-30 Cobra Head | D39: =D31 -> 1296 | E39: =E31 -> 7.58 | F39: =D39*E39 -> 9823.68 | H39: 9.5 | I39: =H39*D39 -> 12312
A40: =IF(B40="","",MAX(A$6:A39)+1) -> 29 | C40: 31-40 Cobra Head | H40: 10.25 | I40: =H40*D40 -> 0
A41: =IF(B41="","",MAX(A$6:A40)+1) -> 30 | C41: 41-50 Cobra Head | D41: =D32 -> 138 | E41: =E32 -> 8.36 | F41: =D41*E41 -> 1153.68 | H41: 11 | I41: =H41*D41 -> 1518
A42: =IF(B42="","",MAX(A$6:A41)+1) -> 31 | C42: 51-60 Cobra Head | D42: =D33 -> 180 | E42: =E33 -> 8.65 | F42: =D42*E42 -> 1557 | H42: 11.5 | I42: =H42*D42 -> 2070
A43: =IF(B43="","",MAX(A$6:A42)+1) -> 32 | C43: 61-80 Cobra Head | D43: =D34 -> 12 | E43: =E34 -> 12.83 | F43: =D43*E43 -> 153.96 | H43: 16.5 | I43: =H43*D43 -> 198
A44: =IF(B44="","",MAX(A$6:A43)+1) -> 33 | C44: 81-110 Cobra Head | D44: =D30 -> 84 | E44: =E30 -> 15.1 | F44: =D44*E44 -> 1268.4 | H44: 19 | I44: =H44*D44 -> 1596
A45: =IF(B45="","",MAX(A$6:A44)+1) -> 34 | C45: 111-150 Cobra Head | H45: 21 | I45: =H45*D45 -> 0
A46: =IF(B46="","",MAX(A$6:A45)+1)
A47: =IF(B47="","",MAX(A$6:A46)+1) -> 35 | B47: Flood | C47: 40-60 Flood | H47: 16.5 | I47: =H47*D47 -> 0
A48: =IF(B48="","",MAX(A$6:A47)+1) -> 36 | C48: 61-80 Flood | H48: 18 | I48: =H48*D48 -> 0
A49: =IF(B49="","",MAX(A$6:A48)+1) -> 37 | C49: 81-110 Flood | D49: =D35 -> 1448 | E49: =E35 -> 15.08 | F49: =D49*E49 -> 21835.84 | H49: 19 | I49: =H49*D49 -> 27512
A50: =IF(B50="","",MAX(A$6:A49)+1) -> 38 | C50: 111-150 Flood | H50: 24 | I50: =H50*D50 -> 0
A51: =IF(B51="","",MAX(A$6:A50)+1) -> 39 | C51: 350-390 Flood | H51: 30 | I51: =H51*D51 -> 0
A52: =IF(B52="","",MAX(A$6:A51)+1)
A53: =IF(B53="","",MAX(A$6:A52)+1) -> 40 | B53: Yard | C53: 20-30 Yard | H53: =H39+1 -> 10.5 | I53: =H53*D53 -> 0
A54: =IF(B54="","",MAX(A$6:A53)+1) -> 41 | C54: 31-40 Yard | H54: =H40+1 -> 11.25 | I54: =H54*D54 -> 0
A55: =IF(B55="","",MAX(A$6:A54)+1) -> 42 | C55: 41-50 Yard | H55: =H41+1 -> 12 | I55: =H55*D55 -> 0
A56: =IF(B56="","",MAX(A$6:A55)+1) -> 43 | C56: 51-60 Yard | H56: =H42+1 -> 12.5 | I56: =H56*D56 -> 0
A57: =IF(B57="","",MAX(A$6:A56)+1) -> 44 | C57: 61-80 Yard | H57: =H43+1 -> 17.5 | I57: =H57*D57 -> 0
A58: =IF(B58="","",MAX(A$6:A57)+1) -> 45 | C58: 81-110 Yard | H58: =H44+1 -> 20 | I58: =H58*D58 -> 0
A59: =IF(B59="","",MAX(A$6:A58)+1) -> 46 | C59: 111-150 Yard | H59: =H45+1 -> 22 | I59: =H59*D59 -> 0
A60: =IF(B60="","",MAX(A$6:A59)+1)
A61: =IF(B61="","",MAX(A$6:A60)+1) -> 47 | B61: Remian SC | C61: =C36 -> 110 Watt LED Flood - CREE | D61: =D36 -> 12 | E61: =E36 -> 25.79 | F61: =D61*E61 -> 309.48 | H61: =E61 -> 25.79 | I61: =H61*D61 -> 309.48
A62: =IF(B62="","",MAX(A$6:A61)+1)
A63: =IF(B63="","",MAX(A$6:A62)+1) -> 48 | B63: Ornamental Lighting:
A64: =IF(B64="","",MAX(A$6:A63)+1) -> 49 | B64: 3300 | C64: Street and Highway Type | D64: ='ProForma Revenue'!G93 -> 0 | E64: ='ProForma Revenue'!M93 -> 9.43 | F64: =D64*E64 -> 0 | H64: =TRUNC(E64*($I$76),2) -> 12.05 | I64: =H64*D64 -> 0
A65: =IF(B65="","",MAX(A$6:A64)+1)
A66: =IF(B66="","",MAX(A$6:A65)+1) -> 50 | B66: Subtotal Revenue | F66: =SUM(F13:F37) -> 248787.56 | I66: =SUM(I13:I64) -> 317324.32
A67: =IF(B67="","",MAX(A$6:A66)+1)
A68: =IF(B68="","",MAX(A$6:A67)+1) -> 51 | B68: Flat rate agreement lights and pole charges (pole charge) | F68: ='ProForma Revenue'!E102 -> 1690.29 | I68: =F68 -> 1690.29
A69: =IF(B69="","",MAX(A$6:A68)+1)
A70: =IF(B70="","",MAX(A$6:A69)+1) -> 52 | B70: Riders | F70: =-Rider_Revenue!N16 -> 16402.538 | I70: 0
A71: =IF(B71="","",MAX(A$6:A70)+1)
A72: =IF(B72="","",MAX(A$6:A71)+1) -> 53 | B72: Total Revenue | F72: =+F66+F68+F70 -> 266880.39 | I72: =+I66+I68+I70 -> 319014.61
A73: =IF(B73="","",MAX(A$6:A72)+1)
A74: =IF(B74="","",MAX(A$6:A73)+1) -> 54 | B74: =CONCATENATE("Revenue Target_",B7) -> Revenue Target_SD: Outdoor Lighting - Company Owned | I74: ='Revenue Apportionment'!N16 -> 319067.58
A75: =IF(B75="","",MAX(A$6:A74)+1) -> 55 | B75: Difference | I75: =I74-I72 -> 52.973755
A76: =IF(B76="","",MAX(A$6:A75)+1) -> 56 | B76: Non-LED Ratio | I76: =(I74-I68-F66-SUM(I39:I61)+SUM(F30:F36))/SUM(F13:F27)+1 -> 1.2782338
A77: =IF(B77="","",MAX(A$6:A76)+1) -> 57 | B77: SDC: Outdoor Lighting - Customer Owned
A78: =IF(B78="","",MAX(A$6:A77)+1) -> 58 | C78: Customer Owned - All kWh | D78: ='ProForma Revenue'!G109 -> 593942.4 | E78: ='Rates and Eff Dates'!D47 -> 0.06429 | F78: =D78*E78 -> 38184.557 | H78: =TRUNC(I82/($D$78),5) -> 0.09361 | I78: =H78*D78 -> 55598.948
A79: =IF(B79="","",MAX(A$6:A78)+1) -> 59 | C79: Riders | F79: =-Rider_Revenue!N17 -> 8018.217 | I79: 0
A80: =IF(B80="","",MAX(A$6:A79)+1) | F80: =SUM(F78:F79) -> 46202.774 | I80: =SUM(I78:I79) -> 55598.948
A81: =IF(B81="","",MAX(A$6:A80)+1)
A82: =IF(B82="","",MAX(A$6:A81)+1) -> 60 | B82: =CONCATENATE("Revenue Target_",B77) -> Revenue Target_SDC: Outdoor Lighting - Customer Owned | I82: ='Revenue Apportionment'!N17 -> 55601.436
A83: =IF(B83="","",MAX(A$6:A82)+1) -> 61 | B83: Difference | I83: =I82-I80 -> 2.4878887

Sheet Heat Pump Rate Design
A1: Fitchburg Gas and Electric Light Company
A2: Exhibit Unitil-JDT-6
A3: Residential Heat Pump Rate Design
A6: Line
A7: 1 | B7: Assumptions:
A8: =IF(ISBLANK(B8),"",MAX($A$6:A7)+1)
A9: =IF(ISBLANK(B9),"",MAX($A$6:A8)+1) -> 2 | B9: RD-1: Residential | C9: Proposed Rate
A10: =IF(ISBLANK(B10),"",MAX($A$6:A9)+1) -> 3 | B10: Customer Charge | C10: ='Rate Design'!G8 -> 8.5
A11: =IF(ISBLANK(B11),"",MAX($A$6:A10)+1) -> 4 | B11: Distribution Charge | C11: ='Rate Design'!G9 -> 0.10585
A12: =IF(ISBLANK(B12),"",MAX($A$6:A11)+1)
A13: =IF(ISBLANK(B13),"",MAX($A$6:A12)+1) -> 5 | B13: Average Monthly UPC | C13: RD-1 Average Monthly Use | D13: Cost Recovery per Month | E13: Fixed Cost Recovery in Volumetric Rate | F13: Fixed Cost Recovery in Fixed Charge | G13: Avg. Monthly Use with Heat Pump (kWh) | J13: Normal Therm UPC | K13: Therms (Heating Load) | L13: Avg. Temp. | M13: Avg. Temp COP | N13: kWh Conversion | O13: kWh Usage
A14: =IF(ISBLANK(B14),"",MAX($A$6:A13)+1) -> 6 | B14: January | C14: =SUMIFS(Rev_Billing_Det!E:E,Rev_Billing_Det!$A:$A,"RD-1",Rev_Billing_Det!$S:$S,$B14)/SUMIFS(Rev_Billing_Det!C:C,Rev_Billing_Det!$A:$A,"RD-1",Rev_Billing_Det!$S:$S,$B14) -> 684.49087 | D14: =$C$10+$C$11*C14 -> 80.953359 | E14: =($C$11-$C$43)*C14 -> 72.453359 | F14: =$C$10 -> 8.5 | G14: =C14+O14 -> 2137.0376 | J14: 139.19505 | K14: =J14-$K$27 -> 123.93744 | L14: 26.802554 | M14: 2.5 | N14: =K14*$K$28 -> 3631.3669 | O14: =N14/M14 -> 1452.5468
A15: =IF(ISBLANK(B15),"",MAX($A$6:A14)+1) -> 7 | B15: February | C15: =SUMIFS(Rev_Billing_Det!E:E,Rev_Billing_Det!$A:$A,"RD-1",Rev_Billing_Det!$S:$S,$B15)/SUMIFS(Rev_Billing_Det!C:C,Rev_Billing_Det!$A:$A,"RD-1",Rev_Billing_Det!$S:$S,$B15) -> 634.50006 | D15: =$C$10+$C$11*C15 -> 75.661831 | E15: =($C$11-$C$43)*C15 -> 67.161831 | F15: =$C$10 -> 8.5 | G15: =C15+O15 -> 2019.855 | J15: 145.2824 | K15: =J15-$K$27 -> 130.02478 | L15: 28.677307 | M15: 2.75 | N15: =K15*$K$28 -> 3809.726 | O15: =N15/M15 -> 1385.3549
A16: =IF(ISBLANK(B16),"",MAX($A$6:A15)+1) -> 8 | B16: March | C16: =SUMIFS(Rev_Billing_Det!E:E,Rev_Billing_Det!$A:$A,"RD-1",Rev_Billing_Det!$S:$S,$B16)/SUMIFS(Rev_Billing_Det!C:C,Rev_Billing_Det!$A:$A,"RD-1",Rev_Billing_Det!$S:$S,$B16) -> 552.57366 | D16: =$C$10+$C$11*C16 -> 66.989922 | E16: =($C$11-$C$43)*C16 -> 58.489922 | F16: =$C$10 -> 8.5 | G16: =C16+O16 -> 1632.7635 | J16: 125.85726 | K16: =J16-$K$27 -> 110.59964 | L16: 35.628226 | M16: 3 | N16: =K16*$K$28 -> 3240.5694 | O16: =N16/M16 -> 1080.1898
A17: =IF(ISBLANK(B17),"",MAX($A$6:A16)+1) -> 9 | B17: April | C17: =SUMIFS(Rev_Billing_Det!E:E,Rev_Billing_Det!$A:$A,"RD-1",Rev_Billing_Det!$S:$S,$B17)/SUMIFS(Rev_Billing_Det!C:C,Rev_Billing_Det!$A:$A,"RD-1",Rev_Billing_Det!$S:$S,$B17) -> 441.96789 | D17: =$C$10+$C$11*C17 -> 55.282301 | E17: =($C$11-$C$43)*C17 -> 46.782301 | F17: =$C$10 -> 8.5 | G17: =C17+O17 -> 1130.1593 | J17: 97.464783 | K17: =J17-$K$27 -> 82.207166 | L17: 46.415833 | M17: 3.5 | N17: =K17*$K$28 -> 2408.67 | O17: =N17/M17 -> 688.19142
A18: =IF(ISBLANK(B18),"",MAX($A$6:A17)+1) -> 10 | B18: May | C18: =SUMIFS(Rev_Billing_Det!E:E,Rev_Billing_Det!$A:$A,"RD-1",Rev_Billing_Det!$S:$S,$B18)/SUMIFS(Rev_Billing_Det!C:C,Rev_Billing_Det!$A:$A,"RD-1",Rev_Billing_Det!$S:$S,$B18) -> 434.81857 | D18: =$C$10+$C$11*C18 -> 54.525546 | E18: =($C$11-$C$43)*C18 -> 46.025546 | F18: =$C$10 -> 8.5 | G18: =C18+O18 -> 434.81857 | J18: 51.10096
A19: =IF(ISBLANK(B19),"",MAX($A$6:A18)+1) -> 11 | B19: June | C19: =SUMIFS(Rev_Billing_Det!E:E,Rev_Billing_Det!$A:$A,"RD-1",Rev_Billing_Det!$S:$S,$B19)/SUMIFS(Rev_Billing_Det!C:C,Rev_Billing_Det!$A:$A,"RD-1",Rev_Billing_Det!$S:$S,$B19) -> 472.29002 | D19: =$C$10+$C$11*C19 -> 58.491899 | E19: =($C$11-$C$43)*C19 -> 49.991899 | F19: =$C$10 -> 8.5 | G19: =C19+O19 -> 472.29002 | J19: 15.105046
A20: =IF(ISBLANK(B20),"",MAX($A$6:A19)+1) -> 12 | B20: July | C20: =SUMIFS(Rev_Billing_Det!E:E,Rev_Billing_Det!$A:$A,"RD-1",Rev_Billing_Det!$S:$S,$B20)/SUMIFS(Rev_Billing_Det!C:C,Rev_Billing_Det!$A:$A,"RD-1",Rev_Billing_Det!$S:$S,$B20) -> 596.22826 | D20: =$C$10+$C$11*C20 -> 71.610761 | E20: =($C$11-$C$43)*C20 -> 63.110761 | F20: =$C$10 -> 8.5 | G20: =C20+O20 -> 596.22826 | J20: 16.015968
A21: =IF(ISBLANK(B21),"",MAX($A$6:A20)+1) -> 13 | B21: August | C21: =SUMIFS(Rev_Billing_Det!E:E,Rev_Billing_Det!$A:$A,"RD-1",Rev_Billing_Det!$S:$S,$B21)/SUMIFS(Rev_Billing_Det!C:C,Rev_Billing_Det!$A:$A,"RD-1",Rev_Billing_Det!$S:$S,$B21) -> 717.36074 | D21: =$C$10+$C$11*C21 -> 84.432634 | E21: =($C$11-$C$43)*C21 -> 75.932634 | F21: =$C$10 -> 8.5 | G21: =C21+O21 -> 717.36074 | J21: 11.958408
A22: =IF(ISBLANK(B22),"",MAX($A$6:A21)+1) -> 14 | B22: September | C22: =SUMIFS(Rev_Billing_Det!E:E,Rev_Billing_Det!$A:$A,"RD-1",Rev_Billing_Det!$S:$S,$B22)/SUMIFS(Rev_Billing_Det!C:C,Rev_Billing_Det!$A:$A,"RD-1",Rev_Billing_Det!$S:$S,$B22) -> 537.72136 | D22: =$C$10+$C$11*C22 -> 65.417806 | E22: =($C$11-$C$43)*C22 -> 56.917806 | F22: =$C$10 -> 8.5 | G22: =C22+O22 -> 537.72136 | J22: 17.951044
A23: =IF(ISBLANK(B23),"",MAX($A$6:A22)+1) -> 15 | B23: October | C23: =SUMIFS(Rev_Billing_Det!E:E,Rev_Billing_Det!$A:$A,"RD-1",Rev_Billing_Det!$S:$S,$B23)/SUMIFS(Rev_Billing_Det!C:C,Rev_Billing_Det!$A:$A,"RD-1",Rev_Billing_Det!$S:$S,$B23) -> 405.51164 | D23: =$C$10+$C$11*C23 -> 51.423407 | E23: =($C$11-$C$43)*C23 -> 42.923407 | F23: =$C$10 -> 8.5 | G23: =C23+O23 -> 405.51164 | J23: 22.802519
A24: =IF(ISBLANK(B24),"",MAX($A$6:A23)+1) -> 16 | B24: November | C24: =SUMIFS(Rev_Billing_Det!E:E,Rev_Billing_Det!$A:$A,"RD-1",Rev_Billing_Det!$S:$S,$B24)/SUMIFS(Rev_Billing_Det!C:C,Rev_Billing_Det!$A:$A,"RD-1",Rev_Billing_Det!$S:$S,$B24) -> 427.77897 | D24: =$C$10+$C$11*C24 -> 53.780404 | E24: =($C$11-$C$43)*C24 -> 45.280404 | F24: =$C$10 -> 8.5 | G24: =C24+O24 -> 864.75714 | J24: 63.727892 | K24: =J24-$K$27 -> 48.470275 | L24: 40.179306 | M24: 3.25 | N24: =K24*$K$28 -> 1420.1791 | O24: =N24/M24 -> 436.97817
A25: =IF(ISBLANK(B25),"",MAX($A$6:A24)+1) -> 17 | B25: December | C25: =SUMIFS(Rev_Billing_Det!E:E,Rev_Billing_Det!$A:$A,"RD-1",Rev_Billing_Det!$S:$S,$B25)/SUMIFS(Rev_Billing_Det!C:C,Rev_Billing_Det!$A:$A,"RD-1",Rev_Billing_Det!$S:$S,$B25) -> 550.49742 | D25: =$C$10+$C$11*C25 -> 66.770152 | E25: =($C$11-$C$43)*C25 -> 58.270152 | F25: =$C$10 -> 8.5 | G25: =C25+O25 -> 1434.6296 | J25: 105.7831 | K25: =J25-$K$27 -> 90.525482 | L25: 32.670027 | M25: 3 | N25: =K25*$K$28 -> 2652.3966 | O25: =N25/M25 -> 884.13221
A26: =IF(ISBLANK(B26),"",MAX($A$6:A25)+1) | C26: =SUM(C14:C25) -> 6455.7395 | D26: =SUM(D14:D25) -> 785.34002 | E26: =SUM(E14:E25) -> 683.34002 | F26: =SUM(F14:F25) -> 102 | G26: =SUM(G14:G25) -> 12383.133 | O26: =SUM(O14:O25) -> 5927.3933
A27: =IF(ISBLANK(B27),"",MAX($A$6:A26)+1) | J27: Summer Base Load | K27: =AVERAGE(J19:J22) -> 15.257617
A28: =IF(ISBLANK(B28),"",MAX($A$6:A27)+1) -> 18 | B28: Derrivation of Heat Pump Rate | J28: Therm to kWH Factor | K28: 29.3
A29: =IF(ISBLANK(B29),"",MAX($A$6:A28)+1) -> 19 | B29: Customer Charge | C29: =C10 -> 8.5
A30: =IF(ISBLANK(B30),"",MAX($A$6:A29)+1) -> 20 | B30: Customer Charge Revenue | C30: =C29*12 -> 102
A31: =IF(ISBLANK(B31),"",MAX($A$6:A30)+1)
A32: =IF(ISBLANK(B32),"",MAX($A$6:A31)+1) -> 21 | B32: Winter Volumetric Charge Revenue | C32: =SUM(E14:E17,E24:E25) -> 348.43797 | D32: per customer, November through April
A33: =IF(ISBLANK(B33),"",MAX($A$6:A32)+1) -> 22 | B33: Volumetric Fixed Cost Recovery Charge | C33: =TRUNC(C32/SUM(G14:G17,G24:G25),5) -> 0.03779 | D33: Line 21 divided by Heat Pump kWh for Nov. through Apr.
A34: =IF(ISBLANK(B34),"",MAX($A$6:A33)+1)
A35: =IF(ISBLANK(B35),"",MAX($A$6:A34)+1) -> 23 | B35: Results
A36: =IF(ISBLANK(B36),"",MAX($A$6:A35)+1) -> 24 | B36: HP-RES: Residential Heat Pump Service | C36: Proposed Rate
A37: =IF(ISBLANK(B37),"",MAX($A$6:A36)+1) -> 25 | B37: Customer Charge | C37: =C29 -> 8.5
A38: =IF(ISBLANK(B38),"",MAX($A$6:A37)+1) -> 26 | B38: Distribution Charge - Winter | C38: =C33 -> 0.03779
A39: =IF(ISBLANK(B39),"",MAX($A$6:A38)+1) -> 27 | B39: Distribution Charge - Summer | C39: =C11 -> 0.10585
A40: =IF(ISBLANK(B40),"",MAX($A$6:A39)+1)
A41: =IF(ISBLANK(B41),"",MAX($A$6:A40)+1)
B43: Unit Cost of Service | E43: RD-1 | F43: Heat Pump | G43: Difference
B44: Customer (per cust month) | C44: 45.471517 | E44: =$C$10+$C$11*C14 -> 80.953359 | F44: =$C$37+$C$38*G14 -> 89.258652 | G44: =F44-E44 -> 8.3052929
B45: Onsite and Customer Services | C45: 26.68041 | E45: =$C$10+$C$11*C15 -> 75.661831 | F45: =$C$37+$C$38*G15 -> 84.83032 | G45: =F45-E45 -> 9.1684885
B46: Demand & Customer (per cust month) | C46: 73.327456 | E46: =$C$10+$C$11*C16 -> 66.989922 | F46: =$C$37+$C$38*G16 -> 70.202132 | G46: =F46-E46 -> 3.2122092
E47: =$C$10+$C$11*C17 -> 55.282301 | F47: =$C$37+$C$38*G17 -> 51.20872 | G47: =F47-E47 -> -4.0735809
B48: Fixed costs per customer | C48: =C46*12 -> 879.92947 | E48: =$C$10+$C$11*C18 -> 54.525546 | F48: =$C$37+$C$39*G18 -> 54.525546 | G48: =F48-E48 -> 0
E49: =$C$10+$C$11*C19 -> 58.491899 | F49: =$C$37+$C$39*G19 -> 58.491899 | G49: =F49-E49 -> 0
E50: =$C$10+$C$11*C20 -> 71.610761 | F50: =$C$37+$C$39*G20 -> 71.610761 | G50: =F50-E50 -> 0
E51: =$C$10+$C$11*C21 -> 84.432634 | F51: =$C$37+$C$39*G21 -> 84.432634 | G51: =F51-E51 -> 0
E52: =$C$10+$C$11*C22 -> 65.417806 | F52: =$C$37+$C$39*G22 -> 65.417806 | G52: =F52-E52 -> 0
E53: =$C$10+$C$11*C23 -> 51.423407 | F53: =$C$37+$C$39*G23 -> 51.423407 | G53: =F53-E53 -> 0
E54: =$C$10+$C$11*C24 -> 53.780404 | F54: =$C$37+$C$38*G24 -> 41.179172 | G54: =F54-E54 -> -12.601232
E55: =$C$10+$C$11*C25 -> 66.770152 | F55: =$C$37+$C$38*G25 -> 62.714654 | G55: =F55-E55 -> -4.0554986
E56: =SUM(E44:E55) -> 785.34002 | F56: =SUM(F44:F55) -> 785.2957 | G56: =SUM(G44:G55) -> -0.044320495

Sheet EV-RES Rate
B1: Fitchburg Gas and Electric Light Company
B2: d/b/a Unitil
B3: Residential Electric Vehicle Time of Use - Proposed Rate Annualization
B5: As Approved in D.P.U. 21-92, Exhibit JDT-4 Page 2 of 2 - Option 2:
B7: Basic Service | G7: Transmission | K7: Distribution
A8: 1 | B8: Period | C8: Residential TOU Basic Service Rates (w/o REC & BSCA) (after losses) ($/kWh) | D8: Projected Residential Basic Service Purchases (kWh) | E8: Projected Basic Service Revenue ($) | G8: Residential TOU Transmission Rate ($/kWh) | H8: Est Residential Transmission Deliveries (kWh) | I8: Residential Transmission Cost ($) | K8: Residential TOU Base Distribution Rates ($/kWh) | L8: Total Residential Customers Energy (kWh) | M8: Residential TOU Base Distribution Revenues ($)
A9: =+A8+1 -> 2 | B9: Summer Peak | C9: 0.080639053 | D9: 10189579 | E9: =+C9*D9 -> 821678.02 | G9: 0.1143489 | H9: 16149797 | I9: =+G9*H9 -> 1846711.5 | K9: 0.1553335 | L9: 16824679 | M9: =+K9*L9 -> 2613436.2
A10: =+A9+1 -> 3 | B10: Summer Off-Peak | C10: 0.056697193 | D10: 31409076 | E10: =+C10*D10 -> 1780806.4 | G10: 0 | H10: 49781271 | I10: =+G10*H10 -> 0 | K10: 0.03876 | L10: 51861572 | M10: =+K10*L10 -> 2010154.5
A11: =+A10+1 -> 4 | B11: Summer Mid-Peak | C11: 0.063347222 | D11: 12802255 | E11: =+C11*D11 -> 810987.3 | G11: 0.035004864 | H11: 20290713 | I11: =+G11*H11 -> 710273.65 | K11: 0.11068048 | L11: 21138638 | M11: =+K11*L11 -> 2339634.6
A12: =+A11+1 -> 5 | C12: 0.062746593 | D12: =SUM(D9:D11) -> 54400910 | E12: =+C12*D12 -> 3413471.7 | G12: 0.029655907 | H12: =SUM(H9:H11) -> 86221781 | I12: =+G12*H12 -> 2556985.1 | K12: 0.07752 | L12: =SUM(L9:L11) -> 89824888 | M12: =+K12*L12 -> 6963225.3
A13: =+A12+1 -> 6
A14: =+A13+1 -> 7 | B14: Winter Peak | C14: 0.093246476 | D14: 10587775 | E14: =+C14*D14 -> 987272.68 | G14: 0.13732371 | H14: 14795005 | I14: =+G14*H14 -> 2031705 | K14: 0.17308187 | L14: 15413271 | M14: =+K14*L14 -> 2667757.7
A15: =+A14+1 -> 8 | B15: Winter Off-Peak | C15: 0.074093676 | D15: 33921973 | E15: =+C15*D15 -> 2513403.7 | G15: 0.0019134675 | H15: 47401439 | I15: =+G15*H15 -> 90701.114 | K15: 0.03876 | L15: 49382290 | M15: =+K15*L15 -> 1914057.6
A16: =+A15+1 -> 9 | B16: Winter Mid-Peak | C16: 0.085590755 | D16: 13948679 | E16: =+C16*D16 -> 1193878 | G16: 0.012098805 | H16: 19491421 | I16: =+G16*H16 -> 235822.9 | K16: 0.099244506 | L16: 20305945 | M16: =+K16*L16 -> 2015253.4
A17: =+A16+1 -> 10 | C17: 0.080305861 | D17: =SUM(D14:D16) -> 58458427 | E17: =+C17*D17 -> 4694554.3 | G17: 0.02886878 | H17: =SUM(H14:H16) -> 81687865 | I17: =+G17*H17 -> 2358229 | K17: 0.07752 | L17: =SUM(L14:L16) -> 85101506 | M17: =+K17*L17 -> 6597068.7
A18: =+A17+1 -> 11
A19: =+A18+1 -> 12 | B19: Total | C19: =+E19/D19 -> 0.071841872 | D19: =+D12+D17 -> 1.1285934e+08 | E19: =+E12+E17 -> 8108026.1 | G19: =+I19/H19 -> 0.029272971 | H19: =+H12+H17 -> 167909646 | I19: =+I12+I17 -> 4915214.1 | K19: =+M19/L19 -> 0.07752 | L19: =+L12+L17 -> 1.7492639e+08 | M19: =+M12+M17 -> 13560294
B21: Option 2: Two Seasons (Jun-Nov Summer, Dec-May Winter); On-Peak (non-holiday weekdays, 3pm-8pm); Mid-Peak (non-holiday weekdays, 6am-3pm); Off-Peak (all other times)
B23: Proposed Change to Annual Rates:
B25: Basic Service | G25: Transmission | K25: Distribution
B26: Period | C26: Residential TOU Basic Service Rates (w/o REC & BSCA) (after losses) ($/kWh) | D26: Projected Residential Basic Service Purchases (kWh) | E26: Projected Basic Service Revenue ($) | G26: Residential TOU Transmission Rate ($/kWh) | H26: Est Residential Transmission Deliveries (kWh) | I26: Residential Transmission Cost ($) | K26: Residential TOU Base Distribution Rates ($/kWh) | L26: Total Residential Customers Energy (kWh) | M26: Residential TOU Base Distribution Revenues ($)
A27: =+A19+1 -> 13 | B27: Annual Peak | C27: =+E27/D27 -> 0.087063574 | D27: =+D9+D14 -> 20777354 | E27: =+E9+E14 -> 1808950.7 | G27: =+I27/H27 -> 0.12533337 | H27: =+H9+H14 -> 30944802 | I27: =+I9+I14 -> 3878416.5 | K27: =+M27/L27 -> 0.16381916 | L27: =+L9+L14 -> 32237949 | M27: =+M9+M14 -> 5281193.9
A28: =+A27+1 -> 14 | B28: Annul Off-Peak | C28: =+E28/D28 -> 0.065730004 | D28: =+D10+D15 -> 65331049 | E28: =+E10+E15 -> 4294210.1 | G28: =+I28/H28 -> 0.00093330505 | H28: =+H10+H15 -> 97182710 | I28: =+I10+I15 -> 90701.114 | K28: =+M28/L28 -> 0.03876 | L28: =+L10+L15 -> 1.0124386e+08 | M28: =+M10+M15 -> 3924212.1
A29: =+A28+1 -> 15 | B29: Annual Mid-Peak | C29: =+E29/D29 -> 0.074945617 | D29: =+D11+D16 -> 26750934 | E29: =+E11+E16 -> 2004865.3 | G29: =+I29/H29 -> 0.023781946 | H29: =+H11+H16 -> 39782134 | I29: =+I11+I16 -> 946096.55 | K29: =+M29/L29 -> 0.10507738 | L29: =+L11+L16 -> 41444582 | M29: =+M11+M16 -> 4354888
A30: =+A29+1 -> 16 | B30: Total | C30: =+E30/D30 -> 0.071841872 | D30: =+D27+D28+D29 -> 1.1285934e+08 | E30: =+E27+E28+E29 -> 8108026.1 | G30: =+I30/H30 -> 0.029272971 | H30: =+H27+H28+H29 -> 167909646 | I30: =+I27+I28+I29 -> 4915214.1 | K30: =+M30/L30 -> 0.07752 | L30: =+L27+L28+L29 -> 1.7492639e+08 | M30: =+M27+M28+M29 -> 13560294

Sheet Annual EV-RES
B1: Fitchburg Gas and Electric Light Company d/b/a Unitil
B2: Schedule EV-RES Rate Development
B3: Proposed Rates Effective September 1, 2023
C5: Annual | E5: Ratios Applied to
C6: Volumetric | D6: Ratios to | E6: Proposed 9/1/2023
C7: Rates (1) | D7: Current Rate | E7: Rates
A8: 1 | B8: Customer Charge: | E8: 6.39
A9: =+A8+1 -> 2
A10: =+A9+1 -> 3 | B10: 1/1/21 Dist. Rate | C10: =+C53 -> 0.07752 | D10: 9/1/23 Proposed Dist. Rate | E10: ='Rate Design'!G9 -> 0.10585
A11: =+A10+1 -> 4 | B11: Distribution Rate:
A12: =+A11+1 -> 5 | B12: Off Peak kWH (M-F 8 pm - 6 am, all day weekends and weekday holidays) | C12: =+C50 -> 0.03876 | D12: =+C12/C10 -> 0.5 | E12: =TRUNC(+E10*D12,5) -> 0.05292
A13: =+A12+1 -> 6 | B13: Mid Peak kWh (M-F 6 am -3 pm excluding weekday holidays) | C13: =+C51 -> 0.10507738 | D13: =+C13/C10 -> 1.3554873 | E13: =TRUNC(+E10*D13,5) -> 0.14347
A14: =+A13+1 -> 7 | B14: On Peak kWh (M-F 3 pm - 8 pm excluding weekday holidays) | C14: =+C52 -> 0.16381916 | D14: =+C14/C10 -> 2.1132503 | E14: =TRUNC(+E10*D14,5) -> 0.22368
A15: =+A14+1 -> 8
A16: =+A15+1 -> 9 | B16: 1/1/21 External Trans. Rate | C16: =+D53 -> 0.029272971 | D16: 1/1/23 External Trans. Rate | E16: 0.02805
A17: =+A16+1 -> 10 | B17: External Transmission Rate:
A18: =+A17+1 -> 11 | B18: Off Peak kWH (M-F 8 pm - 6 am, all day weekends and weekday holidays) | C18: =+D50 -> 0.00093330505 | D18: =+C18/C16 -> 0.031882827 | E18: =TRUNC(+E16*D18,5) -> 0.00089
A19: =+A18+1 -> 12 | B19: Mid Peak kWh (M-F 6 am -3 pm excluding weekday holidays) | C19: =+D51 -> 0.023781946 | D19: =+C19/C16 -> 0.81241997 | E19: =TRUNC(+E16*D19,5) -> 0.02278
A20: =+A19+1 -> 13 | B20: On Peak kWh (M-F 3 pm - 8 pm excluding weekday holidays) | C20: =+D52 -> 0.12533337 | D20: =+C20/C16 -> 4.2815393 | E20: =TRUNC(+E16*D20,5) -> 0.12009
A21: =+A20+1 -> 14
A22: =+A21+1 -> 15 | B22: 6/1/21 and 12/1/20 BS Rate without REC or Basic Service Cost Adder | C22: =+E53 -> 0.071841872 | D22: 8/1/23 BS Rate (2) | E22: 0.18326
A23: =+A22+1 -> 16 | B23: Basic Service Rate:
A24: =+A23+1 -> 17 | B24: Off Peak kWH (M-F 8 pm - 6 am, all day weekends and weekday holidays) | C24: =+E50 -> 0.065730004 | D24: =+C24/C22 -> 0.9149261 | E24: =TRUNC(+E22*D24,5) -> 0.16766
A25: =+A24+1 -> 18 | B25: Mid Peak kWh (M-F 6 am -3 pm excluding weekday holidays) | C25: =+E51 -> 0.074945617 | D25: =+C25/C22 -> 1.0432024 | E25: =TRUNC(+E22*D25,5) -> 0.19117
A26: =+A25+1 -> 19 | B26: On Peak kWh (M-F 3 pm - 8 pm excluding weekday holidays) | C26: =+E52 -> 0.087063574 | D26: =+C26/C22 -> 1.2118779 | E26: =TRUNC(+E22*D26,5) -> 0.22208
A27: =+A26+1 -> 20 | B27: All Hours REC Rate | E27: 0.02387
A28: =+A27+1 -> 21 | B28: All Hours Basic Service Cost Adder Rate | E28: 0.00493
A29: =+A28+1 -> 22
A30: =+A29+1 -> 23 | B30: Other Distribution | E30: 0.08375
A31: =+A30+1 -> 24 | B31: Internal Transmission + Internal Transmission Service Cost Adjustment ($/kWh) | E31: =0.00394+0.00158 -> 0.00552
A32: =+A31+1 -> 25 | B32: Renewable Resource ($/kWh) | E32: 0.0005
A33: =+A32+1 -> 26 | B33: Energy Efficiency ($/kWh) | E33: 0.0025
A34: =+A33+1 -> 27 | B34: Solar Massachusetts Renewable Target Factor ($/kWh) | E34: 0.00567
A35: =+A34+1 -> 28
A36: =+A35+1 -> 29 | B36: Total kWh Charges:
A37: =+A36+1 -> 30 | B37: Off Peak kWH (8 pm - 6 am, and weekends/holidays) | E37: =+E12+E18+E24+E27+E28 -> 0.25027
A38: =+A37+1 -> 31 | B38: Mid Peak kWh (6 am -3 pm, M-F) | E38: =+E13+E19+E25+E27+E28 -> 0.38622
A39: =+A38+1 -> 32 | B39: On Peak kWh (3 pm - 8 pm, M-F) | E39: =+E14+E20+E26+E27+E28 -> 0.59465
A40: =+A39+1 -> 33 | B40: All hours kWh | E40: =+E30+E31+E32+E33+E34 -> 0.09794
A41: =+A40+1 -> 34
A42: =+A41+1 -> 35 | B42: Grand Total kWh Charges (including All hours kWh rate):
A43: =+A42+1 -> 36 | B43: Off Peak kWH (8 pm - 6 am, and weekends/holidays) | E43: =+E37+E40 -> 0.34821
A44: =+A43+1 -> 37 | B44: Mid Peak kWh (6 am -3 pm, M-F) | E44: =+E38+E40 -> 0.48416
A45: =+A44+1 -> 38 | B45: On Peak kWh (3 pm - 8 pm, M-F) | E45: =+E39+E40 -> 0.69259
A46: =+A45+1 -> 39
A47: =+A46+1 -> 40 | B47: (1) Annualized Rates for Residential EV TOU Ratios - See Exhibit Unitil-JDT-7 Page 1 of 2
A48: =+A47+1 -> 41
A49: =+A48+1 -> 42 | B49: TOU Period | C49: Distribution TOU Rates | D49: Transmission TOU Rates | E49: Basic Service TOU Retail Rates
A50: =+A49+1 -> 43 | B50: Annual Off-Peak | C50: ='EV-RES Rate'!K28 -> 0.03876 | D50: ='EV-RES Rate'!G28 -> 0.00093330505 | E50: ='EV-RES Rate'!C28 -> 0.065730004
A51: =+A50+1 -> 44 | B51: Annual Mid-Peak | C51: ='EV-RES Rate'!K29 -> 0.10507738 | D51: ='EV-RES Rate'!G29 -> 0.023781946 | E51: ='EV-RES Rate'!C29 -> 0.074945617
A52: =+A51+1 -> 45 | B52: Annual Peak | C52: ='EV-RES Rate'!K27 -> 0.16381916 | D52: ='EV-RES Rate'!G27 -> 0.12533337 | E52: ='EV-RES Rate'!C27 -> 0.087063574
A53: =+A52+1 -> 46 | B53: Total | C53: ='EV-RES Rate'!K30 -> 0.07752 | D53: ='EV-RES Rate'!G30 -> 0.029272971 | E53: ='EV-RES Rate'!C30 -> 0.071841872
A54: =+A53+1 -> 47
A55: =+A54+1 -> 48 | B55: (2) Excluding REC and Basic Service Cost Adder

Sheet Demand Charge Alternative
L1: D.P.U. 23-80
L2: Unitil - Electric Division
L3: Exhibit Unitil-JDT-8
L4: Page 1 of 1
A5: Fitchburg Gas and Electric Light Company
A6: Exhibit Unitil-JDT-8
A7: General Service EV Demand Charge Alternative Rates
E8: 100% reduction in demand charge | G8: 75% reduction in demand charge | I8: 50% reduction in demand charge | K8: Using Proposed Rates
D9: Load Factor | E9: 0%-5% | G9: 5%-10% | I9: 10%-15% | K9: > 15%
E10: Base | F10: Base | G10: Base | H10: Base | I10: Base | J10: Base | K10: Base | L10: Base
D11: Test Year | E11: Distribution | F11: Distribution | G11: Distribution | H11: Distribution | I11: Distribution | J11: Distribution | K11: Distribution | L11: Distribution
D12: Billing Units | E12: Rates | F12: Revenue | G12: Rates | H12: Revenue | I12: Rates | J12: Revenue | K12: Rates | L12: Revenue
D13: (a) | E13: (b) | F13: (c) | G13: (d) | H13: (e) | I13: (f) | J13: (g) | K13: (h) | L13: (i)
B14: GD-2: Regular General
A16: 1 | B16: Revenue Allocation Target | F16: =+L16 -> 6262145.3 | H16: =+F16 -> 6262145.3 | J16: =+H16 -> 6262145.3 | L16: =SUM(L18:L22) -> 6262145.3
A18: =A16+1 -> 2 | B18: Customer Charge | C18: No. of bills | D18: ='Rate Design'!C34 -> 18164.621 | E18: =+K18 -> 12 | F18: =$D18*E18 -> 217975.45 | G18: =+E18 -> 12 | H18: =$D18*G18 -> 217975.45 | I18: =+G18 -> 12 | J18: =$D18*I18 -> 217975.45 | K18: ='Rate Design'!G34 -> 12 | L18: =D18*K18 -> 217975.45
A20: =A18+1 -> 3 | B20: Energy-Based Rate | C20: All kWh | D20: ='Rate Design'!C36 -> 86826989 | E20: =+K20 -> 0.03234 | F20: =$D20*E20 -> 2807984.8 | G20: =+E20 -> 0.03234 | H20: =$D20*G20 -> 2807984.8 | I20: =+G20 -> 0.03234 | J20: =$D20*I20 -> 2807984.8 | K20: ='Rate Design'!G36 -> 0.03234 | L20: =K20*D20 -> 2807984.8
A22: =A20+1 -> 4 | B22: Demand-Based Rate | C22: kW | D22: ='Rate Design'!C35 -> 323618.5 | E22: 0 | F22: =($D22*E22) -> 0 | G22: =TRUNC($K22*0.25,2) -> 2.5 | H22: =($D22*G22) -> 809046.25 | I22: =TRUNC($K22*0.5,2) -> 5 | J22: =($D22*I22) -> 1618092.5 | K22: ='Rate Design'!G35 -> 10 | L22: =D22*K22 -> 3236185
A24: =A22+1 -> 5 | B24: Converted Demand-to-Energy Rate | C24: All kWh | D24: =+D20 -> 86826989 | E24: =TRUNC((L22)/D24,5) -> 0.03727 | F24: =($D24*E24) -> 3236041.9 | G24: =TRUNC((L22-H22)/$D24,5) -> 0.02795 | H24: =($D24*G24) -> 2426814.3 | I24: =TRUNC((L22-J22)/$D24,5) -> 0.01863 | J24: =($D24*I24) -> 1617586.8
A26: =A24+1 -> 6 | B26: Total Revenue | F26: =SUM(F18:F25) -> 6262002.2 | H26: =SUM(H18:H25) -> 6261820.9 | J26: =SUM(J18:J25) -> 6261639.6 | L26: =SUM(L18:L25) -> 6262145.3
A28: =A26+1 -> 7 | B28: Difference to Target (Due to Truncation of Energy Charge) | F28: =F26-F16 -> -143.11997 | H28: =H26-H16 -> -324.40745 | J28: =J26-J16 -> -505.69493 | L28: =L26-L16 -> 0
B30: GD-2: Regular General - Distribution Charges
A31: =A28+1 -> 8 | B31: Customer Charge | E31: =+E18 -> 12 | G31: =+G18 -> 12 | I31: =+I18 -> 12 | K31: =+K18 -> 12
A32: =A31+1 -> 9 | B32: Energy-Based Rate | C32: All kWh | E32: =+E20+E24 -> 0.06961 | G32: =+G20+G24 -> 0.06029 | I32: =+I20+I24 -> 0.05097 | K32: =+K20 -> 0.03234
A33: =A32+1 -> 10 | B33: Demand-Based Rate | C33: kW | E33: =+E22 -> 0 | G33: =+G22 -> 2.5 | I33: =+I22 -> 5 | K33: =+K22 -> 10
B35: GD-3: Large General
A37: =A33+1 -> 11 | B37: Revenue Allocation Target | F37: =L37 -> 4245756.2 | H37: =F37 -> 4245756.2 | J37: =H37 -> 4245756.2 | L37: =SUM(L39, L43:L45) -> 4245756.2
A39: =A37+1 -> 12 | B39: Customer Charge | C39: No. of bills | D39: ='Rate Design'!C44 -> 339 | E39: =K39 -> 338.75 | F39: =($D39*E39) -> 114836.25 | G39: =E39 -> 338.75 | H39: =($D39*G39) -> 114836.25 | I39: =G39 -> 338.75 | J39: =($D39*I39) -> 114836.25 | K39: ='Rate Design'!G44 -> 338.75 | L39: =(D39*K39) -> 114836.25
A41: =A39+1 -> 13 | B41: Peak Energy-Based Rate | C41: On Peak kWh | D41: ='Rate Design'!C50 -> 50297243 | E41: =K41 -> 0.01828 | F41: =$D41*E41 -> 919433.6 | G41: =E41 -> 0.01828 | H41: =($D41*G41) -> 919433.6 | I41: =G41 -> 0.01828 | J41: =$D41*I41 -> 919433.6 | K41: ='Rate Design'!G50 -> 0.01828 | L41: =(D41*K41) -> 919433.6
A42: =A41+1 -> 14 | B42: Off Peak Energy-Based Rate | C42: Off Peak kWh | D42: ='Rate Design'!C51 -> 77729812 | E42: =K42 -> 0.00407 | F42: =($D42*E42) -> 316360.33 | G42: =E42 -> 0.00407 | H42: =($D42*G42) -> 316360.33 | I42: =G42 -> 0.00407 | J42: =($D42*I42) -> 316360.33 | K42: ='Rate Design'!G51 -> 0.00407 | L42: =(D42*K42) -> 316360.33
A43: =A42+1 -> 15 | B43: Energy-Based Revenue | D43: =D41+D42 -> 128027055 | F43: =F41+F42 -> 1235793.9 | H43: =H41+H42 -> 1235793.9 | J43: =J41+J42 -> 1235793.9 | L43: =L41+L42 -> 1235793.9
A45: =A43+1 -> 16 | B45: Demand kW | C45: On Peak kW | D45: ='Rate Design'!C45 -> 296936 | E45: 0 | F45: =($D45*E45) -> 0 | G45: =TRUNC($K45*0.25,2) -> 2.43 | H45: =($D45*G45) -> 721554.48 | I45: =TRUNC($K45*0.5,2) -> 4.87 | J45: =($D45*I45) -> 1446078.3 | K45: ='Rate Design'!G45 -> 9.75 | L45: =(K45*D45) -> 2895126
A47: =A45+1 -> 17 | B47: Converted Demand-to-Energy Rate | C47: On Peak kWh | D47: =+D41 -> 50297243 | E47: =TRUNC((L45)/$D49,5) -> 0.02261 | F47: =($D47*E47) -> 1137220.7 | G47: =TRUNC((L45-H45)/$D49,5) -> 0.01697 | H47: =($D47*G47) -> 853544.21 | I47: =TRUNC((L45-J45)/$D49,5) -> 0.01131 | J47: =($D47*I47) -> 568861.82
A48: =A47+1 -> 18 | B48: Converted Demand-to-Energy Rate | C48: Off Peak kWh | D48: =+D42 -> 77729812 | E48: =E47 -> 0.02261 | F48: =($D48*E48) -> 1757471 | G48: =G47 -> 0.01697 | H48: =($D48*G48) -> 1319074.9 | I48: =I47 -> 0.01131 | J48: =($D48*I48) -> 879124.17
A49: =A48+1 -> 19 | B49: Energy-Based Revenue | C49: All kWh | D49: =D47+D48 -> 128027055
A51: =A49+1 -> 20 | B51: Total Revenue | F51: =SUM(F39:F40)+SUM(F43:F50) -> 4245321.9 | H51: =SUM(H39:H40)+SUM(H43:H50) -> 4244803.8 | J51: =SUM(J39:J40)+SUM(J43:J50) -> 4244694.5 | L51: =SUM(L43:L45, L39) -> 4245756.2
A53: =A51+1 -> 21 | B53: Difference to Target (Due to Truncation of Energy Charge) | F53: =F51-F37 -> -434.28645 | H53: =H51-H37 -> -952.39665 | J53: =J51-J37 -> -1061.6879 | L53: =L51-L37 -> 0
B55: GD-3: Large General - Distribution Charges
A56: =A53+1 -> 22 | B56: Customer Charge | E56: =+E39 -> 338.75 | G56: =+G39 -> 338.75 | I56: =+I39 -> 338.75 | K56: =+K39 -> 338.75
A57: =A56+1 -> 23 | B57: Energy-Based Rate | C57: On Peak kWh | E57: =+E41+E47 -> 0.04089 | G57: =+G41+G47 -> 0.03525 | I57: =+I41+I47 -> 0.02959 | K57: =+K41 -> 0.01828
A58: =A57+1 -> 24 | B58: Energy-Based Rate | C58: Off Peak kWh | E58: =+E42+E48 -> 0.02668 | G58: =+G42+G48 -> 0.02104 | I58: =+I42+I48 -> 0.01538 | K58: =+K42 -> 0.00407
A59: =A58+1 -> 25 | B59: Demand-Based Rate | C59: kW | E59: =+E45 -> 0 | G59: =+G45 -> 2.43 | I59: =+I45 -> 4.87 | K59: =+K45 -> 9.75

Sheet Decoupling Target
G1: D.P.U. 23-80
G2: Unitil - Electric Division
G3: Exhibit Unitil-JDT-9
G4: Page 1 of 1
A6: D.P.U. 23-80
A7: Unitil - Electric Division
A8: Annual Target Revenue
A9: Revenue Decoupling Adjustment Clause
B11: Class | C11: Target Revenue | E11: Class Grouping | F11: Distribution Revenue | G11: Allocator
A13: 1 | B13: RD-1 & RD-2 | C13: ='Revenue Apportionment'!N10 -> 20932921 | J13: =C13/$C$27 -> 0.62280092
A14: =+A13+1 -> 2 | B14: Total Residential | C14: =SUM(C13:C13) -> 20932921 | E14: RD-1/RD-2 | F14: =C14 -> 20932921 | G14: =F14/$F$27 -> 0.62585559
A15: =+MAX(A$13:A14)+1 -> 3
A16: =+MAX(A$13:A15)+1 -> 4 | B16: GD-1 | C16: ='Revenue Apportionment'!N11 -> 991010.6 | J16: =C16/$C$27 -> 0.029484767
A17: =+MAX(A$13:A16)+1 -> 5
A18: =+MAX(A$13:A17)+1 -> 6 | B18: GD-2 | C18: ='Revenue Apportionment'!N12 -> 6258272.4 | J18: =C18/$C$27 -> 0.18619751
A19: =+MAX(A$13:A18)+1 -> 7 | B19: GD-4 | C19: ='Revenue Apportionment'!N14 -> 9037.3223 | J19: =C19/$C$27 -> 0.00026888042
A20: =+MAX(A$13:A19)+1 -> 8 | B20: GD-5 | C20: ='Revenue Apportionment'!N15 -> 24153.842 | J20: =C20/$C$27 -> 0.00071863048
A21: =+MAX(A$13:A20)+1 -> 9 | B21: Regular General Service | C21: =SUM(C18:C20) -> 6291463.6 | E21: GD-1/GD-2/GD-4/GD-5 | F21: =C21+C16 -> 7282474.2 | G21: =F21/$F$27 -> 0.2177325
A22: =+MAX(A$13:A21)+1 -> 10
A23: =+MAX(A$13:A22)+1 -> 11 | B23: GD-3/Special Contract | C23: 5020870.7 | E23: GD-3/Special Contract | F23: =C23 -> 5020870.7 | G23: =F23/$F$27 -> 0.15011474 | J23: =C23/$C$27 -> 0.14938206
A24: =+MAX(A$13:A23)+1 -> 12
A25: =+MAX(A$13:A24)+1 -> 13 | B25: Outdoor Lighting | C25: ='Revenue Apportionment'!N16+'Revenue Apportionment'!N17 -> 374669.02 | E25: Outdoor Lighting* | F25: =+F42 -> 210620.99 | G25: =F25/$F$27 -> 0.0062971775 | J25: =C25/$C$27 -> 0.011147236
A26: =+MAX(A$13:A25)+1 -> 14
A27: =+MAX(A$13:A26)+1 -> 15 | B27: TOTAL | C27: =SUM(C25,C23,C21,C14,C16) -> 33610935 | E27: TOTAL | F27: =F25+F23+F21+F14 -> 33446887 | G27: =G25+G23+G21+G14 -> 1 | J27: =SUM(J13:J25) -> 1
A28: =+MAX(A$13:A27)+1 -> 16
A29: =+MAX(A$13:A28)+1 -> 17 | B29: Note: Target Revenues are from Exhibit Unitil-JDT-3, Schedule 1. | E29: * Outdoor Lighting plant removed - see calculation below.
A30: =+MAX(A$13:A29)+1 -> 18
A31: =+MAX(A$13:A30)+1 -> 19 | B31: Calculation for Removal of Outdoor Lighting Plant:
A32: =+MAX(A$13:A31)+1 -> 20 | B32: SD Target Revenue | F32: ='Revenue Apportionment'!N16 -> 319067.58
A33: =+MAX(A$13:A32)+1 -> 21
A34: =+MAX(A$13:A33)+1 -> 22 | B34: SD Lighting Plant Rev Req | E34: 221382.85 | F34: =+E34/E36 -> 0.51414823 | G34: Exhibit Unitil-JDT-3, Schedule 2
A35: =+MAX(A$13:A34)+1 -> 23 | B35: SD Remaining Rev Req | E35: =+E36-E34 -> 209198.91 | F35: =+E35/E36 -> 0.48585177
A36: =+MAX(A$13:A35)+1 -> 24 | B36: SD Total Rev Req Req | E36: 430581.76 | G36: Exhibit Unitil-JDT-3, Schedule 2
A37: =+MAX(A$13:A36)+1 -> 25
A38: =+MAX(A$13:A37)+1 -> 26 | B38: SD Rev Req excl Outdoor Lighting Plant | E38: Line 20 * Line 23 | F38: =+F32*F35 -> 155019.55
A39: =+MAX(A$13:A38)+1 -> 27
A40: =+MAX(A$13:A39)+1 -> 28 | B40: SDC Target Revenue | F40: ='Revenue Apportionment'!N17 -> 55601.436
A41: =+MAX(A$13:A40)+1 -> 29
A42: =+MAX(A$13:A41)+1 -> 30 | B42: Outdoor Lighting Rev Req excluding Outdoor Lighting Plant | E42: Line 26 + Line 28 | F42: =+F38+F40 -> 210620.99

Sheet CONFIDENTIAL
A1: Intentionally blank. This sheet was redacted in its entirety.

Sheet Rates
A1: ='Rate Design Lighting'!A1 -> Fitchburg Gas and Electric Light Company
A2: Workpaper to Exhibit Unitil-JDT-4, Schedule 2
A3: WP - Current and Proposed Rates
A6: Line No. | B6: Description | C6: Current Rate | D6: Proposed Rate | H6: COSA Unit Cost | I6: Current Rate | J6: 20.34% Increase | K6: % of COSA Unit Cost | L6: If <25% then use 25% of Unit Cost | M6: Proposed Charge | N6: Resulting Change
A7: 1 | B7: ='Rate Design'!B7 -> RD-1: Residential | F7: Rate | G7: Component
A8: =A7+1 -> 2 | B8: Customer Charge | C8: =INDEX('Rates and Eff Dates'!$C$39:$C$47,MATCH(LEFT($B7,4),'Rates and Eff Dates'!$A$39:$A$47,0)) -> 7 | D8: ='Rate Design'!G8 -> 8.5 | F8: RD-1 / RD-2 Residential | G8: Customer | H8: 26.68041 | I8: =C8 -> 7 | J8: =I8*(1+('Revenue Apportionment'!$H$21)) -> 8.4239542 | K8: =J8/H8 -> 0.31573556 | L8: =ROUND(IF(K8>25%, J8, H8/4), 2) -> 8.42 | M8: 8.5 | N8: =(M8-I8)/I8 -> 0.21428571
A9: =A8+1 -> 3 | B9: Distribution Charge | C9: =INDEX('Rates and Eff Dates'!$D$39:$D$47,MATCH(LEFT($B7,4),'Rates and Eff Dates'!$A$39:$A$47,0)) -> 0.07903 | D9: ='Rate Design'!G9 -> 0.10585 | F9: =B15 -> GD-1: Small General | G9: Customer | H9: 23.263774 | I9: =C16 -> 10 | J9: =I9*(1+('Revenue Apportionment'!$H$21)) -> 12.03422 | K9: =J9/H9 -> 0.51729441 | L9: =ROUND(IF(K9>25%, J9, H9/4), 2) -> 12.03 | M9: 12 | N9: =(M9-I9)/I9 -> 0.2
A10: =A9+1 -> 4 | F10: =B19 -> GD-2: Regular General | G10: Customer | H10: 47.966259 | I10: =C20 -> 10 | J10: =I10*(1+('Revenue Apportionment'!$H$21)) -> 12.03422 | K10: =J10/H10 -> 0.25088928 | L10: =ROUND(IF(K10>25%, J10, H10/4), 2) -> 12.03 | M10: 12 | N10: =(M10-I10)/I10 -> 0.2
A11: =A10+1 -> 5 | B11: ='Rate Design'!B12 -> RD-2: Residential, Low Income | F11: =F10 -> GD-2: Regular General | G11: Demand | H11: 9.935266 | I11: =C21 -> 9.81 | J11: =I11*(1+('Revenue Apportionment'!$H$21)) -> 11.80557 | K11: =J11/H11 -> 1.188249 | L11: =ROUND(IF(K11>25%, J11, H11/4), 2) -> 11.81 | M11: 10 | N11: =(M11-I11)/I11 -> 0.019367992
A12: =A11+1 -> 6 | B12: Customer Charge | C12: =INDEX('Rates and Eff Dates'!$C$39:$C$47,MATCH(LEFT($B11,4),'Rates and Eff Dates'!$A$39:$A$47,0)) -> 7 | D12: ='Rate Design'!G13 -> 8.5 | F12: =B25 -> GD-3: Large General | G12: Customer | H12: 1548.482 | I12: =C26 -> 300 | J12: =I12*(1+('Revenue Apportionment'!$H$21)) -> 361.02661 | K12: =J12/H12 -> 0.23314873 | L12: =ROUND(IF(K12>25%, J12, H12/4), 2) -> 387.12 | M12: 338.75 | N12: =(M12-I12)/I12 -> 0.12916667
A13: =A12+1 -> 7 | B13: Distribution Charge | C13: =INDEX('Rates and Eff Dates'!$D$39:$D$47,MATCH(LEFT($B11,4),'Rates and Eff Dates'!$A$39:$A$47,0)) -> 0.07903 | D13: ='Rate Design'!G14 -> 0.10585 | F13: =F12 -> GD-3: Large General | G13: Demand | H13: 10.97226 | I13: =C27 -> 8.07 | J13: =I13*(1+('Revenue Apportionment'!$H$21)) -> 9.7116158 | K13: =J13/H13 -> 0.88510625 | L13: =ROUND(IF(K13>25%, J13, H13/4), 2) -> 9.71 | M13: 9.75 | N13: =(M13-I13)/I13 -> 0.20817844
A14: =A13+1 -> 8 | F14: =B33 -> GD-4: Regular General Optional TOU | G14: Customer | H14: =H10 -> 47.966259 | I14: =C34 -> 10 | J14: =I14*(1+('Revenue Apportionment'!$H$21)) -> 12.03422 | K14: =J14/H14 -> 0.25088928 | L14: =ROUND(IF(K14>25%, J14, H14/4), 2) -> 12.03 | M14: 12 | N14: =(M14-I14)/I14 -> 0.2
A15: =A14+1 -> 9 | B15: ='Rate Design'!B25 -> GD-1: Small General | F15: =F14 -> GD-4: Regular General Optional TOU | G15: Demand | H15: =H11 -> 9.935266 | I15: =C35 -> 3.92 | J15: =I15*(1+('Revenue Apportionment'!$H$21)) -> 4.7174144 | K15: =J15/H15 -> 0.4748151 | L15: =ROUND(IF(K15>25%, J15, H15/4), 2) -> 4.72 | M15: 4.75 | N15: =(M15-I15)/I15 -> 0.21173469
A16: =A15+1 -> 10 | B16: Customer Charge | C16: =INDEX('Rates and Eff Dates'!$C$39:$C$47,MATCH(LEFT($B15,4),'Rates and Eff Dates'!$A$39:$A$47,0)) -> 10 | D16: ='Rate Design'!G26 -> 12
A17: =A16+1 -> 11 | B17: Distribution Charge | C17: =INDEX('Rates and Eff Dates'!$D$39:$D$47,MATCH(LEFT($B15,4),'Rates and Eff Dates'!$A$39:$A$47,0)) -> 0.0785 | D17: ='Rate Design'!G27 -> 0.10572
A18: =A17+1 -> 12
A19: =A18+1 -> 13 | B19: ='Rate Design'!B33 -> GD-2: Regular General
A20: =A19+1 -> 14 | B20: Customer Charge | C20: =INDEX('Rates and Eff Dates'!$C$39:$C$47,MATCH(LEFT($B19,4),'Rates and Eff Dates'!$A$39:$A$47,0)) -> 10 | D20: ='Rate Design'!G34 -> 12
A21: =A20+1 -> 15 | B21: Demand Charge | C21: =INDEX('Rates and Eff Dates'!$F$39:$F$47,MATCH(LEFT($B19,4),'Rates and Eff Dates'!$A$39:$A$47,0)) -> 9.81 | D21: ='Rate Design'!G35 -> 10
A22: =A21+1 -> 16 | B22: Distribution Charge | C22: =INDEX('Rates and Eff Dates'!$D$39:$D$47,MATCH(LEFT($B19,4),'Rates and Eff Dates'!$A$39:$A$47,0)) -> 0.02377 | D22: ='Rate Design'!G36 -> 0.03234
A23: =A22+1 -> 17 | B23: Transformer Credit | C23: 0 | D23: ='Rate Design'!G37 -> -0.19
A24: =A23+1 -> 18
A25: =A24+1 -> 19 | B25: ='Rate Design'!B43 -> GD-3: Large General
A26: =A25+1 -> 20 | B26: Customer Charge | C26: =INDEX('Rates and Eff Dates'!$C$39:$C$47,MATCH(LEFT($B25,4),'Rates and Eff Dates'!$A$39:$A$47,0)) -> 300 | D26: ='Rate Design'!G44 -> 338.75
A27: =A26+1 -> 21 | B27: Demand Charge | C27: =INDEX('Rates and Eff Dates'!$F$39:$F$47,MATCH(LEFT($B25,4),'Rates and Eff Dates'!$A$39:$A$47,0)) -> 8.07 | D27: ='Rate Design'!G45 -> 9.75
A28: =A27+1 -> 22 | B28: Distribution Charge
A29: =A28+1 -> 23 | B29: On Peak Billed kWh | C29: =INDEX('Rates and Eff Dates'!$D$39:$D$47,MATCH(LEFT($B25,4),'Rates and Eff Dates'!$A$39:$A$47,0)) -> 0.01952 | D29: ='Rate Design'!G50 -> 0.01828
A30: =A29+1 -> 24 | B30: Off Peak Billed kWh | C30: =INDEX('Rates and Eff Dates'!$E$39:$E$47,MATCH(LEFT($B25,4),'Rates and Eff Dates'!$A$39:$A$47,0)) -> 0.00435 | D30: ='Rate Design'!G51 -> 0.00407
A31: =A30+1 -> 25 | B31: Distribution Charge
A32: =A31+1 -> 26
A33: =A32+1 -> 27 | B33: ='Rate Design'!B56 -> GD-4: Regular General Optional TOU
A34: =A33+1 -> 28 | B34: Customer Charge | C34: =INDEX('Rates and Eff Dates'!$C$39:$C$47,MATCH(LEFT($B33,4),'Rates and Eff Dates'!$A$39:$A$47,0)) -> 10 | D34: ='Rate Design'!G57 -> 12
A35: =A34+1 -> 29 | B35: Demand Charge | C35: =INDEX('Rates and Eff Dates'!$F$39:$F$47,MATCH(LEFT($B33,4),'Rates and Eff Dates'!$A$39:$A$47,0)) -> 3.92 | D35: ='Rate Design'!G58 -> 4.75
A36: =A35+1 -> 30 | B36: Distribution Charge
A37: =A36+1 -> 31 | B37: On Peak Billed kWh | C37: =INDEX('Rates and Eff Dates'!$D$39:$D$47,MATCH(LEFT($B33,4),'Rates and Eff Dates'!$A$39:$A$47,0)) -> 0.01027 | D37: ='Rate Design'!G64 -> 0.02382
A38: =A37+1 -> 32 | B38: Off Peak Billed kWh | C38: =INDEX('Rates and Eff Dates'!$E$39:$E$47,MATCH(LEFT($B33,4),'Rates and Eff Dates'!$A$39:$A$47,0)) -> 0.00223 | D38: ='Rate Design'!G65 -> 0.00517
A39: =A38+1 -> 33 | B39: Transformer Credit | C39: 0 | D39: ='Rate Design'!G60 -> -0.19
A40: =A39+1 -> 34
A41: =A40+1 -> 35 | B41: ='Rate Design'!B70 -> GD-5: Water and/or Space Heating Rider
A42: =A41+1 -> 36 | B42: Customer Charge | C42: =INDEX('Rates and Eff Dates'!$C$39:$C$47,MATCH(LEFT($B41,4),'Rates and Eff Dates'!$A$39:$A$47,0)) -> 0 | D42: ='Rate Design'!G71 -> 0
A43: =A42+1 -> 37 | B43: Distribution Charge | C43: =INDEX('Rates and Eff Dates'!$D$39:$D$47,MATCH(LEFT($B41,4),'Rates and Eff Dates'!$A$39:$A$47,0)) -> 0.06071 | D43: ='Rate Design'!G72 -> 0.07037

Sheet FGE Bill Impact Tabs --->
A1: Sheet intentionally blank.

Sheet RD-1
B3: Fitchburg Gas and Electric Light Company d/b/a Unitil
B4: Basic Service Customer Typical Bill Impacts - 2023 Distribution Rate Proposal
B5: Impact on RD-1 Rate Customers
E7: Res
E8: Average | G8: Current Rates | I8: Proposed Rates | M8: % | P8: Present Rates | R8: %
E9: Monthly | G9: Total | I9: Total | K9: Total | M9: Total | P9: Delivery | R9: Delivery
C10: Decile | E10: kWh | G10: Revenue | I10: Revenue | K10: Difference | M10: Difference | P10: Revenue | R10: Difference
C12: 0.1 | E12: 70.122989 | G12: =$I$31+E12*$I$65 -> 36.246896 | I12: =$P$31+E12*$P$65 -> 38.780509 | K12: =I12-G12 -> 2.5336129 | M12: =I12/G12-1 -> 0.069898753 | P12: =+$I$31+E12*$I$77 -> 21.376615 | R12: =+K12/P12 -> 0.11852264
C13: 0.2 | E13: 182.93414 | G13: =$I$31+E13*$I$65 -> 83.298172 | I13: =$P$31+E13*$P$65 -> 87.494622 | K13: =I13-G13 -> 4.1964493 | M13: =I13/G13-1 -> 0.050378648 | P13: =+$I$31+E13*$I$77 -> 44.505158 | R13: =+K13/P13 -> 0.094291301
C14: 0.3 | E14: 262.31339 | G14: =$I$31+E14*$I$65 -> 116.40567 | I14: =$P$31+E14*$P$65 -> 121.77217 | K14: =I14-G14 -> 5.3664994 | M14: =I14/G14-1 -> 0.046101701 | P14: =+$I$31+E14*$I$77 -> 60.779491 | R14: =+K14/P14 -> 0.088294575
C15: 0.4 | E15: 335.31655 | G15: =$I$31+E15*$I$65 -> 146.85383 | I15: =$P$31+E15*$P$65 -> 153.29639 | K15: =I15-G15 -> 6.4425659 | M15: =I15/G15-1 -> 0.043870603 | P15: =+$I$31+E15*$I$77 -> 75.746599 | R15: =+K15/P15 -> 0.085054194
C16: 0.5 | E16: 410.31906 | G16: =$I$31+E16*$I$65 -> 178.13588 | I16: =$P$31+E16*$P$65 -> 185.68398 | K16: =I16-G16 -> 7.548103 | M16: =I16/G16-1 -> 0.042372728 | P16: =+$I$31+E16*$I$77 -> 91.123615 | R16: =+K16/P16 -> 0.082833666
C17: 0.6 | E17: 493.45217 | G17: =$I$31+E17*$I$65 -> 212.80903 | I17: =$P$31+E17*$P$65 -> 221.58252 | K17: =I17-G17 -> 8.773485 | M17: =I17/G17-1 -> 0.041227033 | P17: =+$I$31+E17*$I$77 -> 108.16756 | R17: =+K17/P17 -> 0.081110128
C18: 0.7 | E18: 593.31135 | G18: =$I$31+E18*$I$65 -> 254.4583 | I18: =$P$31+E18*$P$65 -> 264.70371 | K18: =I18-G18 -> 10.245409 | M18: =I18/G18-1 -> 0.040263609 | P18: =+$I$31+E18*$I$77 -> 128.64069 | R18: =+K18/P18 -> 0.079643611
C19: 0.8 | E19: 724.63237 | G19: =$I$31+E19*$I$65 -> 309.22967 | I19: =$P$31+E19*$P$65 -> 321.41075 | K19: =I19-G19 -> 12.181081 | M19: =I19/G19-1 -> 0.039391696 | P19: =+$I$31+E19*$I$77 -> 155.56413 | R19: =+K19/P19 -> 0.078302635
C20: 0.9 | E20: 928.94127 | G20: =$I$31+E20*$I$65 -> 394.44283 | I20: =$P$31+E20*$P$65 -> 409.63542 | K20: =I20-G20 -> 15.192594 | M20: =I20/G20-1 -> 0.038516594 | P20: =+$I$31+E20*$I$77 -> 197.45154 | R20: =+K20/P20 -> 0.076943408
C21: 1 | E21: 1650.9479 | G21: =$I$31+E21*$I$65 -> 695.57734 | I21: =$P$31+E21*$P$65 -> 721.41231 | K21: =I21-G21 -> 25.834972 | M21: =I21/G21-1 -> 0.037141767 | P21: =+$I$31+E21*$I$77 -> 345.47733 | R21: =+K21/P21 -> 0.074780511
C23: Average | E23: =AVERAGE(E12:E21) -> 565.22912 | G23: =$I$31+E23*$I$65 -> 242.74576 | I23: =$P$31+E23*$P$65 -> 252.57724 | K23: =I23-G23 -> 9.8314772 | M23: =I23/G23-1 -> 0.040501128 | P23: =+$I$31+E23*$I$77 -> 122.88327 | R23: =+K23/P23 -> 0.080006635
C24: 600 kWh | E24: 600 | G24: =$I$31+E24*$I$65 -> 257.248 | I24: =$P$31+E24*$P$65 -> 267.592 | K24: =I24-G24 -> 10.344 | M24: =I24/G24-1 -> 0.040210225 | P24: =+$I$31+E24*$I$77 -> 130.012 | R24: =+K24/P24 -> 0.079561887
B28: Current Rates: | K28: Proposed Rates:
I29: RD-1 | P29: RD-1 | R29: Difference **
B30: Delivery Charges: | K30: Delivery Charges:
B31: Customer Charge | I31: 7 | K31: Customer Charge | P31: 8.5 | R31: =+P31-I31 -> 1.5
I32: kWh | P32: kWh | R32: kWh
B33: Internal Transmission | I33: =0.00394+0.00158 -> 0.00552 | K33: Internal Transmission | P33: =0.00394+0.00158 -> 0.00552 | R33: =+P33-I33 -> 0
B34: External Transmission | I34: 0.02805 | K34: External Transmission | P34: 0.02796 | R34: =+P34-I34 -> -9e-05
H35: Transmission Subtotal | I35: =+I34+I33 -> 0.03357 | O35: Transmission Subtotal | P35: =+P34+P33 -> 0.03348 | R35: =+P35-I35 -> -9e-05
B37: Distribution - Nov. 1, 2023 | I37: 0.07903 | K37: Distribution | P37: 0.10585 | R37: =+P37-I37 -> 0.02682
B39: Pension/PBOP Adjustment Factor | I39: 0.00333 | K39: Pension/PBOP Adjustment Factor | P39: 0.00333 | R39: =+P39-I39 -> 0
B40: Residential Assistance Adjustment Factor | I40: 0.02498 | K40: Residential Assistance Adjustment Factor | P40: 0.02814 | R40: =+P40-I40 -> 0.00316
B41: Net Metering Recovery Surcharge | I41: 0.01508 | K41: Net Metering Recovery Surcharge | P41: 0.01508 | R41: =+P41-I41 -> 0
B42: Revenue Decoupling Adjustment Factor | I42: 0.00172 | K42: Revenue Decoupling Adjustment Factor | P42: 0.00172 | R42: =+P42-I42 -> 0
B43: Attorney General Consultant Expense Factor | I43: 0.00052 | K43: Attorney General Consultant Expense Factor | P43: 0.00052 | R43: =+P43-I43 -> 0
B44: L-T Renewable Contract Adjustment Factor | I44: -0.00275 | K44: L-T Renewable Contract Adjustment Factor | P44: -0.00275 | R44: =+P44-I44 -> 0
B45: Capital Cost Adjustment Factor | I45: 0.00997 | K45: Capital Cost Adjustment Factor | P45: 0.00299 | R45: =+P45-I45 -> -0.00698
B46: Solar Cost Adjustment | I46: -0.00017 | K46: Solar Cost Adjustment | P46: -0.00115 | R46: =+P46-I46 -> -0.00098
B47: Grid Modernization Factor | I47: 0.00368 | K47: Grid Modernization Factor | P47: 0.00368 | R47: =+P47-I47 -> 0
B48: Basic Service Adjustment | I48: -0.0004 | K48: Basic Service Adjustment | P48: =+I48 -> -0.0004 | R48: =+P48-I48 -> 0
B49: Storm Reserve Adjustment Factor | I49: 0.00051 | K49: Storm Reserve Adjustment Factor | P49: 0.00051 | R49: =+P49-I49 -> 0
B50: Exogenous Cost Adjustment Factor | I50: 0.00189 | K50: Exogenous Cost Adjustment Factor | P50: 0.00189 | R50: =+P50-I50 -> 0
H51: Distribution Subtotal | I51: =SUM(I37,I39:I50) -> 0.13739 | O51: Distribution Subtotal | P51: =SUM(P37,P39:P50) -> 0.15941 | R51: =+P51-I51 -> 0.02202
B53: Renewable Resources Charge | I53: 0.0005 | K53: Renewable Resources Charge | P53: 0.0005 | R53: =+P53-I53 -> 0
B55: Energy Efficiency Charge | I55: 0.0025 | K55: Energy Efficiency Charge | P55: 0.0025 | R55: =+P55-I55 -> 0
B56: Energy Efficiency Reconciliation Factor | I56: 0.02539 | K56: Energy Efficiency Reconciliation Factor *** | P56: 0.02097 | R56: =+P56-I56 -> -0.00442
H57: Total Energy Efficiency Charge Subtotal | I57: =SUM(I55:I56) -> 0.02789 | O57: Total Energy Efficiency Charge Subtotal | P57: =SUM(P55:P56) -> 0.02347 | R57: =+P57-I57 -> -0.00442
B59: SMART Factor | I59: 0.00567 | K59: SMART Factor | P59: 0.00491 | R59: =+P59-I59 -> -0.00076
B62: Supplier Charges: | K62: Supplier Charges:
B63: Generation Charge* | I63: 0.21206 | K63: Generation Charge* | P63: 0.21005 | R63: =+P63-I63 -> -0.00201
H65: Total | I65: =SUM(I63,I57,I59,I51,I35,I53) -> 0.41708 | O65: Total | P65: =SUM(P63,P57,P59,P51,P35,P53) -> 0.43182 | R65: =+P65-I65 -> 0.01474
B71: * August 1, 2023 Basic Service, Fixed including Basic Service Costs Adder of $0.00493/kWh at current and $0.00292/kWh at proposed. ** Includes changes in reconciliation mechanisms related to this distribution rate case proposal.
B73: *** Exhibit Unitil-CGDN-6
H77: delivery only | I77: =+I65-I63 -> 0.20502 | O77: delivery only | P77: =+P65-P63 -> 0.22177

Sheet RD-2
U2: Current | X2: Proposed
B3: Fitchburg Gas and Electric Light Company d/b/a Unitil | U3: Plug RD-1 | X3: Plug RD-1
B4: Basic Service Customer Typical Bill Impacts - 2023 Distribution Rate Proposal | U4: Total Rates | X4: Total Rates
B5: Impact on RD-2 Rate Customers | U5: Customer | V5: kWh | X5: Customer | Y5: kWh
U6: 7 | V6: 0.20502 | X6: 8.5 | Y6: 0.22177
E7: Res
E8: Average | G8: Current Rates | I8: Proposed Rates | M8: % | P8: Present Rates | R8: %
E9: Monthly | G9: Total | I9: Total | K9: Total | M9: Total | P9: Delivery | R9: Delivery
C10: Decile | E10: kWh | G10: Revenue | I10: Revenue | K10: Difference | M10: Difference | P10: Revenue | R10: Difference
C12: 0.1 | E12: 70.122989 | G12: =$I$31+$I$67+E12*$I$70 -> 23.736899 | I12: =+$P$31+$P$67+ E12*$P$70 -> 23.268165 | K12: =I12-G12 -> -0.46873414 | M12: =I12/G12-1 -> -0.019747067 | P12: =+$I$31+$I$67+E12*$I$80 -> 8.8666183 | R12: =+K12/P12 -> -0.052865041 | U12: -0.34513291 | W12: -0.40000362
C13: 0.2 | E13: 182.93414 | G13: =$I$31+$I$67+E13*$I$70 -> 54.555779 | I13: =+$P$31+$P$67+ E13*$P$70 -> 52.496407 | K13: =I13-G13 -> -2.0593714 | M13: =I13/G13-1 -> -0.037747998 | P13: =+$I$31+$I$67+E13*$I$80 -> 15.762764 | R13: =+K13/P13 -> -0.13064786 | U13: -0.34505432 | W13: -0.40000418
C14: 0.3 | E14: 262.31339 | G14: =$I$31+$I$67+E14*$I$70 -> 76.241395 | I14: =+$P$31+$P$67+ E14*$P$70 -> 73.062776 | K14: =I14-G14 -> -3.1786188 | M14: =I14/G14-1 -> -0.041691509 | P14: =+$I$31+$I$67+E14*$I$80 -> 20.615217 | R14: =+K14/P14 -> -0.15418798 | U14: -0.34503709 | W14: -0.40000431
C15: 0.4 | E15: 335.31655 | G15: =$I$31+$I$67+E15*$I$70 -> 96.185128 | I15: =+$P$31+$P$67+ E15*$P$70 -> 91.977165 | K15: =I15-G15 -> -4.2079633 | M15: =I15/G15-1 -> -0.043748586 | P15: =+$I$31+$I$67+E15*$I$80 -> 25.077901 | R15: =+K15/P15 -> -0.16779568 | U15: -0.34502811 | W15: -0.40000437
C16: 0.5 | E16: 410.31906 | G16: =$I$31+$I$67+E16*$I$70 -> 116.67507 | I16: =+$P$31+$P$67+ E16*$P$70 -> 111.40957 | K16: =I16-G16 -> -5.2654988 | M16: =I16/G16-1 -> -0.045129598 | P16: =+$I$31+$I$67+E16*$I$80 -> 29.662804 | R16: =+K16/P16 -> -0.17751183 | U16: -0.34502208 | W16: -0.40000442
C17: 0.6 | E17: 493.45217 | G17: =$I$31+$I$67+E17*$I$70 -> 139.3862 | I17: =+$P$31+$P$67+ E17*$P$70 -> 132.94852 | K17: =I17-G17 -> -6.4376756 | M17: =I17/G17-1 -> -0.04618589 | P17: =+$I$31+$I$67+E17*$I$80 -> 34.744731 | R17: =+K17/P17 -> -0.18528495 | U17: -0.34501747 | W17: -0.40000445
C18: 0.7 | E18: 593.31135 | G18: =$I$31+$I$67+E18*$I$70 -> 166.66673 | I18: =+$P$31+$P$67+ E18*$P$70 -> 158.82104 | K18: =I18-G18 -> -7.84569 | M18: =I18/G18-1 -> -0.047074123 | P18: =+$I$31+$I$67+E18*$I$80 -> 40.849123 | R18: =+K18/P18 -> -0.19206508 | U18: -0.34501359 | W18: -0.40000448
C19: 0.8 | E19: 724.63237 | G19: =$I$31+$I$67+E19*$I$70 -> 202.54232 | I19: =+$P$31+$P$67+ E19*$P$70 -> 192.845 | K19: =I19-G19 -> -9.6973164 | M19: =I19/G19-1 -> -0.047877977 | P19: =+$I$31+$I$67+E19*$I$80 -> 48.876777 | R19: =+K19/P19 -> -0.19840335 | U19: -0.34501008 | W19: -0.40000451
C20: 0.9 | E20: 928.94127 | G20: =$I$31+$I$67+E20*$I$70 -> 258.35747 | I20: =+$P$31+$P$67+ E20*$P$70 -> 245.77939 | K20: =I20-G20 -> -12.578072 | M20: =I20/G20-1 -> -0.048684763 | P20: =+$I$31+$I$67+E20*$I$80 -> 61.36618 | R20: =+K20/P20 -> -0.20496749 | U20: -0.34500655 | W20: -0.40000454
C21: 1 | E21: 1650.9479 | G21: =$I$31+$I$67+E21*$I$70 -> 455.60245 | I21: =+$P$31+$P$67+ E21*$P$70 -> 432.84409 | K21: =I21-G21 -> -22.758365 | M21: =I21/G21-1 -> -0.049952245 | P21: =+$I$31+$I$67+E21*$I$80 -> 105.50244 | R21: =+K21/P21 -> -0.2157141 | U21: -0.34500102 | W21: -0.40000458
C23: Average | E23: =AVERAGE(E12:E21) -> 565.22912 | G23: =$I$31+$I$67+E23*$I$70 -> 158.99494 | I23: =+$P$31+$P$67+ E23*$P$70 -> 151.54521 | K23: =I23-G23 -> -7.4497306 | M23: =I23/G23-1 -> -0.046855142 | P23: =+$I$31+$I$67+E23*$I$80 -> 39.132456 | R23: =+K23/P23 -> -0.19037217 | U23: -0.34501454 | W23: -0.40000448
C24: 600 kWh | E24: 600 | G24: =$I$31+$I$67+E24*$I$70 -> 168.494 | I24: =+$P$31+$P$67+ E24*$P$70 -> 160.554 | K24: =I24-G24 -> -7.94 | M24: =I24/G24-1 -> -0.04712334 | P24: =+$I$31+$I$67+E24*$I$80 -> 41.258 | R24: =+K24/P24 -> -0.19244753
B28: Current Rates: | K28: Proposed Rates:
I29: RD-2 | P29: RD-2 | R29: Difference **
B30: Delivery Charges: | K30: Delivery Charges:
B31: Customer Charge | I31: 7 | K31: Customer Charge | P31: 8.5 | R31: =+P31-I31 -> 1.5
I32: kWh | P32: kWh | R32: kWh
B33: Internal Transmission | I33: =0.00394+0.00158 -> 0.00552 | K33: Internal Transmission | P33: 0.00552 | R33: =+P33-I33 -> 0
B34: External Transmission | I34: 0.02805 | K34: External Transmission | P34: 0.02796 | R34: =+P34-I34 -> -9e-05
H35: Transmission Subtotal | I35: =+I34+I33 -> 0.03357 | O35: Transmission Subtotal | P35: =+P34+P33 -> 0.03348 | R35: =+P35-I35 -> -9e-05
B37: Distribution - Nov. 1, 2023 | I37: 0.07903 | K37: Distribution | P37: 0.10585 | R37: =+P37-I37 -> 0.02682
B39: Pension/PBOP Adjustment Factor | I39: 0.00333 | K39: Pension/PBOP Adjustment Factor | P39: 0.00333 | R39: =+P39-I39 -> 0
B40: Residential Assistance Adjustment Factor | I40: 0.02498 | K40: Residential Assistance Adjustment Factor | P40: 0.02814 | R40: =+P40-I40 -> 0.00316
B41: Net Metering Recovery Surcharge | I41: 0.01508 | K41: Net Metering Recovery Surcharge | P41: 0.01508 | R41: =+P41-I41 -> 0
B42: Revenue Decoupling Adjustment Factor | I42: 0.00172 | K42: Revenue Decoupling Adjustment Factor | P42: 0.00172 | R42: =+P42-I42 -> 0
B43: Attorney General Consultant Expense Factor | I43: 0.00052 | K43: Attorney General Consultant Expense Factor | P43: 0.00052 | R43: =+P43-I43 -> 0
B44: L-T Renewable Contract Adjustment Factor | I44: -0.00275 | K44: L-T Renewable Contract Adjustment Factor | P44: -0.00275 | R44: =+P44-I44 -> 0
B45: Capital Cost Adjustment Factor | I45: 0.00997 | K45: Capital Cost Adjustment Factor | P45: 0.00299 | R45: =+P45-I45 -> -0.00698
B46: Solar Cost Adjustment | I46: -0.00017 | K46: Solar Cost Adjustment | P46: -0.00115 | R46: =+P46-I46 -> -0.00098
B47: Grid Modernization Factor | I47: 0.00368 | K47: Grid Modernization Factor | P47: 0.00368 | R47: =+P47-I47 -> 0
B48: Basic Service Adjustment | I48: -0.0004 | K48: Basic Service Adjustment | P48: =+I48 -> -0.0004 | R48: =+P48-I48 -> 0
B49: Storm Reserve Adjustment Factor | I49: 0.00051 | K49: Storm Reserve Adjustment Factor | P49: 0.00051 | R49: =+P49-I49 -> 0
B50: Exogenous Cost Adjustment Factor | I50: 0.00189 | K50: Exogenous Cost Adjustment Factor | P50: 0.00189 | R50: =+P50-I50 -> 0
H51: Distribution Subtotal | I51: =SUM(I37,I39:I50) -> 0.13739 | O51: Distribution Subtotal | P51: =SUM(P37,P39:P50) -> 0.15941 | R51: =+P51-I51 -> 0.02202
B53: Renewable Resources Charge | I53: 0.0005 | K53: Renewable Resources Charge | P53: 0.0005 | R53: =+P53-I53 -> 0
B55: Energy Efficiency Charge | I55: 0.0025 | K55: Energy Efficiency Charge | P55: 0.0025 | R55: =+P55-I55 -> 0
B56: Energy Efficiency Reconciliation Factor | I56: 0.00364 | K56: Energy Efficiency Reconciliation Factor *** | P56: 0.02097 | R56: =+P56-I56 -> 0.01733
H57: Total Energy Efficiency Charge Subtotal | I57: =SUM(I55:I56) -> 0.00614 | O57: Total Energy Efficiency Charge Subtotal | P57: =SUM(P55:P56) -> 0.02347 | R57: =+P57-I57 -> 0.01733
B59: SMART Factor | I59: 0.00567 | K59: SMART Factor | P59: 0.00491 | R59: =+P59-I59 -> -0.00076
R61: =+P61-I61 -> 0
B62: Supplier Charges: | K62: Supplier Charges:
B63: Generation Charge* | I63: 0.21206 | K63: Generation Charge* | P63: 0.21005 | R63: =+P63-I63 -> -0.00201
H65: Total | I65: =SUM(I63,I57,I59,I51,I35,I53) -> 0.39533 | O65: Total | P65: =SUM(P63,P57,P59,P51,P35,P53) -> 0.43182 | R65: =+P65-I65 -> 0.03649
B66: 34.5% Low Income Discount | K66: 40.0% Low Income Discount
B67: Fixed Charges | I67: =ROUND(U6*-0.345,2) -> -2.42 | K67: Fixed Charges | P67: =ROUND(X6*-0.4,2) -> -3.4 | R67: =+P67-I67 -> -0.98
B68: Volumetric Charges - All kWh | I68: =ROUND(V6*-0.345,5)-I56+'RD-1'!I56+ROUND(I63*-0.345,5) -> -0.12214 | K68: Volumetric Charges - All kWh | P68: =ROUND(Y6*-0.4,5)+ROUND(P63*-0.4,5) -> -0.17273 | R68: =+P68-I68 -> -0.05059
H70: Total | I70: =SUM(I68,I63,I57,I59,I53,I51,I35) -> 0.27319 | O70: Total | P70: =SUM(P68,P63,P57,P59,P53,P51,P35) -> 0.25909 | R70: =+P70-I70 -> -0.0141
B77: * August 1, 2023 Basic Service, Fixed including Basic Service Costs Adder of $0.00493/kWh at current and $0.00292/kWh at proposed. ** Includes changes in reconciliation mechanisms related to this distribution rate case proposal.
B79: *** Exhibit Unitil-CGDN-6
I80: =+I70-I63 -> 0.06113 | P80: =+P70-P63 -> 0.04904
I82: =+I70-I68-I63 -> 0.18327 | P82: =+P70-P68-P63 -> 0.22177

Sheet GD-1
B3: Fitchburg Gas and Electric Light Company d/b/a Unitil
B4: Basic Service Customer Typical Bill Impacts - 2023 Distribution Rate Proposal
B5: Impact on GD-1 Rate Customers
E8: Average | G8: Current Rates | I8: Proposed Rates | M8: % | P8: Present Rates | R8: %
E9: Monthly | G9: Total | I9: Total | K9: Total | M9: Total | P9: Delivery | R9: Delivery
C10: Decile | E10: kWh | G10: Revenue | I10: Revenue | K10: Difference | M10: Difference | P10: Revenue | R10: Difference
C12: 0.1 | E12: 0 | G12: =$I$30+E12*$I$65 -> 10 | I12: =+$P$30+E12*$P$65 -> 12 | K12: =I12-G12 -> 2 | M12: =I12/G12-1 -> 0.2 | P12: =+$I$30+E12*$I$74 -> 10 | R12: =+K12/P12 -> 0.2
C13: 0.2 | E13: 4.2945455 | G13: =$I$30+E13*$I$65 -> 11.66332 | I13: =+$P$30+E13*$P$65 -> 13.7438 | K13: =I13-G13 -> 2.0804798 | M13: =I13/G13-1 -> 0.178378 | P13: =+$I$30+E13*$I$74 -> 10.752619 | R13: =+K13/P13 -> 0.19348586
C14: 0.3 | E14: 17.237765 | G14: =$I$30+E14*$I$65 -> 16.676359 | I14: =+$P$30+E14*$P$65 -> 18.999394 | K14: =I14-G14 -> 2.3230357 | M14: =I14/G14-1 -> 0.13930114 | P14: =+$I$30+E14*$I$74 -> 13.020918 | R14: =+K14/P14 -> 0.17840798
C15: 0.4 | E15: 35.155702 | G15: =$I$30+E15*$I$65 -> 23.616155 | I15: =+$P$30+E15*$P$65 -> 26.274973 | K15: =I15-G15 -> 2.6588179 | M15: =I15/G15-1 -> 0.11258471 | P15: =+$I$30+E15*$I$74 -> 16.161037 | R15: =+K15/P15 -> 0.16452025
C16: 0.5 | E16: 60.272156 | G16: =$I$30+E16*$I$65 -> 33.344009 | I16: =+$P$30+E16*$P$65 -> 36.473509 | K16: =I16-G16 -> 3.1295002 | M16: =I16/G16-1 -> 0.093854948 | P16: =+$I$30+E16*$I$74 -> 20.562695 | R16: =+K16/P16 -> 0.15219309
C17: 0.6 | E17: 96.965939 | G17: =$I$30+E17*$I$65 -> 47.555878 | I17: =+$P$30+E17*$P$65 -> 51.37302 | K17: =I17-G17 -> 3.8171417 | M17: =I17/G17-1 -> 0.080266454 | P17: =+$I$30+E17*$I$74 -> 26.993281 | R17: =+K17/P17 -> 0.14141081
C18: 0.7 | E18: 156.9243 | G18: =$I$30+E18*$I$65 -> 70.77835 | I18: =+$P$30+E18*$P$65 -> 75.719111 | K18: =I18-G18 -> 4.9407613 | M18: =I18/G18-1 -> 0.069806111 | P18: =+$I$30+E18*$I$74 -> 37.500983 | R18: =+K18/P18 -> 0.13175018
C19: 0.8 | E19: 260.9537 | G19: =$I$30+E19*$I$65 -> 111.06998 | I19: =+$P$30+E19*$P$65 -> 117.96025 | K19: =I19-G19 -> 6.8902724 | M19: =I19/G19-1 -> 0.062035417 | P19: =+$I$30+E19*$I$74 -> 55.732137 | R19: =+K19/P19 -> 0.12363194
C20: 0.9 | E20: 437.32893 | G20: =$I$30+E20*$I$65 -> 179.38187 | I20: =+$P$30+E20*$P$65 -> 189.57741 | K20: =I20-G20 -> 10.195544 | M20: =I20/G20-1 -> 0.056837094 | P20: =+$I$30+E20*$I$74 -> 86.641894 | R20: =+K20/P20 -> 0.11767453
C21: 1 | E21: 891.58499 | G21: =$I$30+E21*$I$65 -> 355.31978 | I21: =+$P$30+E21*$P$65 -> 374.02808 | K21: =I21-G21 -> 18.708303 | M21: =I21/G21-1 -> 0.052652016 | P21: =+$I$30+E21*$I$74 -> 166.25027 | R21: =+K21/P21 -> 0.11253096
C23: Average | E23: =AVERAGE(E12:E21) -> 196.0718 | G23: =$I$30+E23*$I$65 -> 85.94057 | I23: =+$P$30+E23*$P$65 -> 91.614955 | K23: =I23-G23 -> 5.6743856 | M23: =I23/G23-1 -> 0.066026855 | P23: =+$I$30+E23*$I$74 -> 44.361583 | R23: =+K23/P23 -> 0.12791215
B27: Current Rates: | K27: Proposed Rates:
I28: GD-1 | P28: GD-1 | R28: Difference **
B29: Delivery Charges: | K29: Delivery Charges:
B30: Customer Charge | I30: 10 | K30: Customer Charge | P30: 12 | R30: =+P30-I30 -> 2
I31: kWh | P31: kWh | R31: kWh
B32: Internal Transmission | I32: =0.00323+0.00147 -> 0.0047 | K32: Internal Transmission | P32: =0.00323+0.00147 -> 0.0047 | R32: =+P32-I32 -> 0
B33: External Transmission | I33: 0.02611 | K33: External Transmission | P33: 0.02602 | R33: =+P33-I33 -> -9e-05
H34: Transmission Subtotal | I34: =SUM(I32:I33) -> 0.03081 | O34: Transmission Subtotal | P34: =SUM(P32:P33) -> 0.03072 | R34: =+P34-I34 -> -9e-05
B36: Distribution - Nov. 1, 2023 | I36: 0.0785 | K36: Distribution | P36: 0.10572 | R36: =+P36-I36 -> 0.02722
B38: Pension/PBOP Adjustment Factor | I38: 0.00275 | K38: Pension/PBOP Adjustment Factor | P38: 0.00275 | R38: =+P38-I38 -> 0
B39: Residential Assistance Adjustment Factor | I39: 0.01983 | K39: Residential Assistance Adjustment Factor | P39: 0.02233 | R39: =+P39-I39 -> 0.0025
B40: Net Metering Recovery Surcharge | I40: 0.01197 | K40: Net Metering Recovery Surcharge | P40: 0.01197 | R40: =+P40-I40 -> 0
B41: Revenue Decoupling Adjustment Factor | I41: 0.00136 | K41: Revenue Decoupling Adjustment Factor | P41: 0.00136 | R41: =+P41-I41 -> 0
B42: Attorney General Consultant Expense Factor | I42: 0.00041 | K42: Attorney General Consultant Expense Factor | P42: 0.00041 | R42: =+P42-I42 -> 0
B43: L-T Renewable Contract Adjustment Factor | I43: -0.00275 | K43: L-T Renewable Contract Adjustment Factor | P43: -0.00275 | R43: =+P43-I43 -> 0
B44: Capital Cost Adjustment Factor | I44: 0.01072 | K44: Capital Cost Adjustment Factor | P44: 0.00322 | R44: =+P44-I44 -> -0.0075
B45: Solar Cost Adjustment | I45: -0.00014 | K45: Solar Cost Adjustment | P45: -0.00092 | R45: =+P45-I45 -> -0.00078
B46: Grid Modernization Factor | I46: 0.00296 | K46: Grid Modernization Factor | P46: 0.00296 | R46: =+P46-I46 -> 0
B47: Basic Service Adjustment | I47: -0.00032 | K47: Basic Service Adjustment | P47: =+I47 -> -0.00032 | R47: =+P47-I47 -> 0
B48: Storm Reserve Adjustment Factor | I48: 0.0004 | K48: Storm Reserve Adjustment Factor | P48: 0.0004 | R48: =+P48-I48 -> 0
B49: Exogenous Cost Adjustment Factor | I49: 0.00153 | K49: Exogenous Cost Adjustment Factor | P49: 0.00153 | R49: =+P49-I49 -> 0
H50: Distribution Subtotal | I50: =SUM(I36,I38:I49) -> 0.12722 | O50: Distribution Subtotal | P50: =SUM(P36,P38:P49) -> 0.14866 | R50: =+P50-I50 -> 0.02144
B52: Renewable Resources Charge | I52: 0.0005 | K52: Renewable Resources Charge | P52: =I52 -> 0.0005 | R52: =+P52-I52 -> 0
B54: Energy Efficiency Charge | I54: 0.0025 | K54: Energy Efficiency Charge | P54: =I54 -> 0.0025 | R54: =+P54-I54 -> 0
B55: Energy Efficiency Reconciliation Factor | I55: 0.00972 | K55: Energy Efficiency Reconciliation Factor | P55: 0.00972 | R55: =+P55-I55 -> 0
H56: Total Energy Efficiency Charge Subtotal | I56: =SUM(I54:I55) -> 0.01222 | O56: Total Energy Efficiency Charge Subtotal | P56: =SUM(P54:P55) -> 0.01222 | R56: =+P56-I56 -> 0
B58: SMART Factor | I58: 0.0045 | K58: SMART Factor | P58: 0.0039 | R58: =+P58-I58 -> -0.0006
I60: 0 | K60: Transition Charge Surcharge | P60: 0 | R60: =+P60-I60 -> 0
B62: Supplier Charges: | K62: Supplier Charges:
B63: Generation Charge* | I63: 0.21206 | K63: Generation Charge* | P63: 0.21005 | R63: =+P63-I63 -> -0.00201
H65: Total | I65: =SUM(I63,I52,I56,I58,I50,I34) -> 0.38731 | O65: Total | P65: =SUM(P63,P52,P56,P58,P50,P34) -> 0.40605 | R65: =+P65-I65 -> 0.01874
B71: * August 1, 2023 Basic Service, Fixed including Basic Service Costs Adder of $0.00493/kWh at current and $0.00292/kWh at proposed. ** Includes changes in reconciliation mechanisms related to this distribution rate case proposal.
H74: delivery only | I74: =+I65-I63 -> 0.17525 | O74: delivery only | R74: =+P65-P63 -> 0.196

Sheet GD-2
B3: Fitchburg Gas and Electric Light Company d/b/a Unitil
B4: Basic Service Customer Typical Bill Impacts - 2023 Distribution Rate Proposal
B5: ="Impact on GD-2 Rate Customers" -> Impact on GD-2 Rate Customers
E8: Average | G8: Average | I8: Current Rates | K8: Proposed Rates | O8: % | R8: Present Rates | T8: %
E9: Monthly | G9: Monthly | I9: Total | K9: Total | M9: Total | O9: Total | R9: Delivery | T9: Delivery
C10: Decile | E10: kW | G10: kWh | I10: Revenue | K10: Revenue | M10: Difference | O10: Difference | R10: Revenue | T10: Difference
C12: 0.1 | E12: 2.9968785 | G12: 161.82747 | I12: =(I$66*E12)+(K$66*G12)+K$31 -> 92.024053 | K12: =(Q$66*E12)+(R$66*G12)+R$31 -> 94.768234 | M12: =K12-I12 -> 2.7441806 | O12: =K12/I12-1 -> 0.029820253 | R12: =(I$66*E12)+(K$77*G12)+K$31 -> 58.67303 | T12: =+M12/R12 -> 0.046770732
C13: 0.2 | E13: 4.9404424 | G13: 478.94328 | I13: =(I$66*E13)+(K$66*G13)+K$31 -> 214.2133 | K13: =(Q$66*E13)+(R$66*G13)+R$31 -> 217.66925 | M13: =K13-I13 -> 3.4559428 | O13: =K13/I13-1 -> 0.016133185 | R13: =(I$66*E13)+(K$77*G13)+K$31 -> 115.50788 | T13: =+M13/R13 -> 0.02991954
C14: 0.3 | E14: 6.127412 | G14: 739.97957 | I14: =(I$66*E14)+(K$66*G14)+K$31 -> 310.74387 | K14: =(Q$66*E14)+(R$66*G14)+R$31 -> 314.70725 | M14: =K14-I14 -> 3.9633862 | O14: =K14/I14-1 -> 0.012754511 | R14: =(I$66*E14)+(K$77*G14)+K$31 -> 158.24148 | T14: =+M14/R14 -> 0.025046443
C15: 0.4 | E15: 7.1299659 | G15: 1043.84 | I15: =(I$66*E15)+(K$66*G15)+K$31 -> 419.39128 | K15: =(Q$66*E15)+(R$66*G15)+R$31 -> 423.87332 | M15: =K15-I15 -> 4.4820407 | O15: =K15/I15-1 -> 0.010687014 | R15: =(I$66*E15)+(K$77*G15)+K$31 -> 204.2663 | T15: =+M15/R15 -> 0.021942144
C16: 0.5 | E16: 8.8732275 | G16: 1465.7175 | I16: =(I$66*E16)+(K$66*G16)+K$31 -> 573.68304 | K16: =(Q$66*E16)+(R$66*G16)+R$31 -> 578.95193 | M16: =K16-I16 -> 5.2688881 | O16: =K16/I16-1 -> 0.0091843191 | R16: =(I$66*E16)+(K$77*G16)+K$31 -> 271.61332 | T16: =+M16/R16 -> 0.01939849
C17: 0.6 | E17: 10.264756 | G17: 2055.496 | I17: =(I$66*E17)+(K$66*G17)+K$31 -> 779.12401 | K17: =(Q$66*E17)+(R$66*G17)+R$31 -> 785.29425 | M17: =K17-I17 -> 6.1702393 | O17: =K17/I17-1 -> 0.0079194573 | R17: =(I$66*E17)+(K$77*G17)+K$31 -> 355.50683 | T17: =+M17/R17 -> 0.017356177
C18: 0.7 | E18: 11.772134 | G18: 2982.9313 | I18: =(I$66*E18)+(K$66*G18)+K$31 -> 1095.5041 | K18: =(Q$66*E18)+(R$66*G18)+R$31 -> 1102.9623 | M18: =K18-I18 -> 7.4582713 | O18: =K18/I18-1 -> 0.0068080726 | R18: =(I$66*E18)+(K$77*G18)+K$31 -> 480.75176 | T18: =+M18/R18 -> 0.015513768
C19: 0.8 | E19: 16.528944 | G19: 4564.0011 | I19: =(I$66*E19)+(K$66*G19)+K$31 -> 1656.3165 | K19: =(Q$66*E19)+(R$66*G19)+R$31 -> 1666.3861 | M19: =K19-I19 -> 10.069621 | O19: =K19/I19-1 -> 0.006079527 | R19: =(I$66*E19)+(K$77*G19)+K$31 -> 715.72148 | T19: =+M19/R19 -> 0.014069189
C20: 0.9 | E20: 26.484118 | G20: 7600.5173 | I20: =(I$66*E20)+(K$66*G20)+K$31 -> 2741.4214 | K20: =(Q$66*E20)+(R$66*G20)+R$31 -> 2756.662 | M20: =K20-I20 -> 15.240541 | O20: =K20/I20-1 -> 0.0055593573 | R20: =(I$66*E20)+(K$77*G20)+K$31 -> 1175.0308 | T20: =+M20/R20 -> 0.012970333
C21: 1 | E21: 76.803916 | G21: 26205.952 | I21: =(I$66*E21)+(K$66*G21)+K$31 -> 9285.3601 | K21: =(Q$66*E21)+(R$66*G21)+R$31 -> 9330.2552 | M21: =K21-I21 -> 44.895173 | O21: =K21/I21-1 -> 0.0048350492 | R21: =(I$66*E21)+(K$77*G21)+K$31 -> 3884.5753 | T21: =+M21/R21 -> 0.011557292
C23: Average | E23: =AVERAGE(E12:E21) -> 17.192179 | G23: =AVERAGE(G12:G21) -> 4729.9206 | I23: =(I$66*E23)+(K$66*G23)+K$31 -> 1716.7782 | K23: =(Q$66*E23)+(R$66*G23)+R$31 -> 1727.153 | M23: =K23-I23 -> 10.374828 | O23: =K23/I23-1 -> 0.0060431968 | R23: =(I$66*E23)+(K$77*G23)+K$31 -> 741.98882 | T23: =+M23/R23 -> 0.013982459
B27: Current Rates: | M27: Proposed Rates:
K28: GD-2 | R28: GD-2 | T28: Difference | U28: Difference **
B30: Delivery Charges: | M30: Delivery Charges:
B31: Customer Charge | K31: 10 | M31: Customer Charge | R31: 12 | U31: =+R31-K31 -> 2
I32: kW | K32: kWh | Q32: kW | R32: kWh | T32: kW | U32: kWh
B33: Internal Transmission | K33: =0.00323+0.00147 -> 0.0047 | M33: Internal Transmission | R33: =0.00323+0.00147 -> 0.0047 | U33: =+R33-K33 -> 0
B34: External Transmission | K34: 0.02611 | M34: External Transmission | R34: 0.02602 | U34: =+R34-K34 -> -9e-05
H35: Transmission Subtotal | K35: =SUM(K33:K34) -> 0.03081 | P35: Transmission Subtotal | R35: =SUM(R33:R34) -> 0.03072 | U35: =+R35-K35 -> -9e-05
B37: Distribution - Nov. 1, 2023 | I37: 9.81 | K37: 0.02377 | M37: Distribution | Q37: 10 | R37: 0.03234 | T37: =+Q37-I37 -> 0.19 | U37: =+R37-K37 -> 0.00857
B39: Pension/PBOP Adjustment Factor | K39: 0.00275 | M39: Pension/PBOP Adjustment Factor | R39: 0.00275 | U39: =+R39-K39 -> 0
B40: Residential Assistance Adjustment Factor | K40: 0.01983 | M40: Residential Assistance Adjustment Factor | R40: 0.02233 | U40: =+R40-K40 -> 0.0025
B41: Net Metering Recovery Surcharge | K41: 0.01197 | M41: Net Metering Recovery Surcharge | R41: 0.01197 | U41: =+R41-K41 -> 0
B42: Revenue Decoupling Adjustment Factor | K42: 0.00136 | M42: Revenue Decoupling Adjustment Factor | R42: 0.00136 | U42: =+R42-K42 -> 0
B43: Attorney General Consultant Expense Factor | K43: 0.00041 | M43: Attorney General Consultant Expense Factor | R43: 0.00041 | U43: =+R43-K43 -> 0
B44: L-T Renewable Contract Adjustment Factor | K44: -0.00275 | M44: L-T Renewable Contract Adjustment Factor | R44: -0.00275 | U44: =+R44-K44 -> 0
B45: Capital Cost Adjustment Factor | K45: 0.0093 | M45: Capital Cost Adjustment Factor | R45: 0.00279 | U45: =+R45-K45 -> -0.00651
B46: Solar Cost Adjustment | K46: -0.00014 | M46: Solar Cost Adjustment | R46: -0.00092 | U46: =+R46-K46 -> -0.00078
B47: Grid Modernization Factor | K47: 0.00296 | M47: Grid Modernization Factor | R47: 0.00296 | U47: =+R47-K47 -> 0
B48: Basic Service Adjustment | K48: -0.00032 | M48: Basic Service Adjustment | R48: =+K48 -> -0.00032 | U48: =+R48-K48 -> 0
B49: Storm Reserve Adjustment Factor | K49: 0.0004 | M49: Storm Reserve Adjustment Factor | R49: 0.0004 | U49: =+R49-K49 -> 0
B50: Exogenous Cost Adjustment Factor | K50: 0.00153 | M50: Exogenous Cost Adjustment Factor | R50: 0.00153 | U50: =+R50-K50 -> 0
H51: Distribution Subtotal | I51: =SUM(I37:I50) -> 9.81 | K51: =SUM(K37,K39:K50) -> 0.07107 | P51: Distribution Subtotal | Q51: =SUM(Q37:Q50) -> 10 | R51: =SUM(R37,R39:R50) -> 0.07485 | T51: =+Q51-I51 -> 0.19 | U51: =+R51-K51 -> 0.00378
B53: Renewable Resources Charge | K53: 0.0005 | M53: Renewable Resources Charge | R53: 0.0005 | U53: =+R53-K53 -> 0
B55: Energy Efficiency Charge | K55: 0.0025 | M55: Energy Efficiency Charge | R55: 0.0025 | U55: =+R55-K55 -> 0
B56: Energy Efficiency Reconciliation Factor | K56: 0.00972 | M56: Energy Efficiency Reconciliation Factor | R56: 0.00972 | U56: =+R56-K56 -> 0
H57: Total Energy Efficiency Charge Subtotal | K57: =SUM(K55:K56) -> 0.01222 | R57: =SUM(R55:R56) -> 0.01222 | U57: =+R57-K57 -> 0
B59: SMART Factor | K59: 0.0045 | M59: SMART Factor | R59: 0.0039 | U59: =+R59-K59 -> -0.0006
B61: Transition Charge Surcharge | K61: 0 | M61: Transition Charge Surcharge | R61: 0 | U61: =+R61-K61 -> 0
B63: Supplier Charges: | M63: Supplier Charges:
B64: Generation Charge* | K64: 0.20609 | M64: Generation Charge* | R64: 0.20408 | U64: =+R64-K64 -> -0.00201
H66: Totals | I66: =I51 -> 9.81 | K66: =SUM(K64,K57,K59,K53,K51,K35) -> 0.32519 | P66: Totals | Q66: =Q51 -> 10 | R66: =SUM(R64,R57,R59,R53,R51,R35) -> 0.32627 | T66: =+Q66-I66 -> 0.19 | U66: =+R66-K66 -> 0.00108
B73: * August 1, 2023 Basic Service, Fixed including Basic Service Costs Adder of $0.00493/kWh at current and $0.00292/kWh at proposed. ** Includes changes in reconciliation mechanisms related to this distribution rate case proposal.
H77: delivery only | I77: =+I66 -> 9.81 | K77: =+K66-K64 -> 0.1191 | P77: delivery only | Q77: =+Q66 -> 10 | R77: =+R66-R64 -> 0.12219

Sheet GD-3
B3: Fitchburg Gas and Electric Light Company d/b/a Unitil
B4: Basic Service Customer Typical Bill Impacts - 2023 Distribution Rate Proposal
B5: Impact on GD-3 Rate Customers
D7: 2022 | F7: 2022 | H7: 2022
D8: Average | F8: Average | H8: Average | J8: Current Rates | L8: Proposed Rates | P8: % | R8: Present Rates | S8: %
D9: Monthly | F9: On Peak | H9: Off Peak | J9: Total | L9: Total | N9: Total | P9: Total | R9: Delivery | S9: Delivery
B10: Sequence | D10: kVA | F10: kWh | H10: kWh | J10: Revenue | L10: Revenue | N10: Difference | P10: Difference | R10: Revenue | S10: Difference
B12: 1 | D12: 713.54167 | F12: 113225 | H12: 157675 | J12: =+D12*$F$81+F12*$H$81+H12*$H$82+$H$46 -> 44984.019 | L12: =+D12*$N$81+F12*$P$81+H12*$P$82+$P$46 -> 45124.039 | N12: =L12-J12 -> 140.019 | P12: =L12/J12-1 -> 0.0031126387 | R12: =+D12*$F$81+F12*$H$94+H12*$H$95+$H$46 -> 22694.368 | S12: =+N12/R12 -> 0.0061697688
B13: =+B12+1 -> 2 | D13: 405.5 | F13: 73180 | H13: 119320 | J13: =+D13*$F$81+F13*$H$81+H13*$H$82+$H$46 -> 31122.401 | L13: =+D13*$N$81+F13*$P$81+H13*$P$82+$P$46 -> 31069.513 | N13: =L13-J13 -> -52.8878 | P13: =L13/J13-1 -> -0.0016993483 | R13: =+D13*$F$81+F13*$H$94+H13*$H$95+$H$46 -> 15283.501 | S13: =+N13/R13 -> -0.0034604507
B14: =+B13+1 -> 3 | D14: 1945.375 | F14: 317461 | H14: 518445.08 | J14: =+D14*$F$81+F14*$H$81+H14*$H$82+$H$46 -> 135626.76 | L14: =+D14*$N$81+F14*$P$81+H14*$P$82+$P$46 -> 135577.92 | N14: =L14-J14 -> -48.839764 | P14: =L14/J14-1 -> -0.00036010419 | R14: =+D14*$F$81+F14*$H$94+H14*$H$95+$H$46 -> 66848.408 | S14: =+N14/R14 -> -0.00073060475
B15: =+B14+1 -> 4 | D15: 687.58333 | F15: 119892 | H15: 220772 | J15: =+D15*$F$81+F15*$H$81+H15*$H$82+$H$46 -> 54457.76 | L15: =+D15*$N$81+F15*$P$81+H15*$P$82+$P$46 -> 54293.13 | N15: =L15-J15 -> -164.62992 | P15: =L15/J15-1 -> -0.0030230755 | R15: =+D15*$F$81+F15*$H$94+H15*$H$95+$H$46 -> 26427.926 | S15: =+N15/R15 -> -0.0062293924
B16: =+B15+1 -> 5 | D16: 535.25 | F16: 95060.083 | H16: 147003.75 | J16: =+D16*$F$81+F16*$H$81+H16*$H$82+$H$46 -> 39308.996 | L16: =+D16*$N$81+F16*$P$81+H16*$P$82+$P$46 -> 39272.176 | N16: =L16-J16 -> -36.820672 | P16: =L16/J16-1 -> -0.00093669834 | R16: =+D16*$F$81+F16*$H$94+H16*$H$95+$H$46 -> 19391.984 | S16: =+N16/R16 -> -0.0018987573
B17: =+B16+1 -> 6 | D17: 503.20833 | F17: 60140 | H17: 99425 | J17: =+D17*$F$81+F17*$H$81+H17*$H$82+$H$46 -> 27189.468 | L17: =+D17*$N$81+F17*$P$81+H17*$P$82+$P$46 -> 27433.461 | N17: =L17-J17 -> 243.99335 | P17: =L17/J17-1 -> 0.0089738185 | R17: =+D17*$F$81+F17*$H$94+H17*$H$95+$H$46 -> 14060.46 | S17: =+N17/R17 -> 0.017353156
B18: =+B17+1 -> 7 | D18: 221.58333 | F18: 48733.333 | H18: 91546.667 | J18: =+D18*$F$81+F18*$H$81+H18*$H$82+$H$46 -> 22094.92 | L18: =+D18*$N$81+F18*$P$81+H18*$P$82+$P$46 -> 21947.124 | N18: =L18-J18 -> -147.796 | P18: =L18/J18-1 -> -0.0066891394 | R18: =+D18*$F$81+F18*$H$94+H18*$H$95+$H$46 -> 10552.682 | S18: =+N18/R18 -> -0.014005539
B19: =+B18+1 -> 8 | D19: 554.95833 | F19: 82611.833 | H19: 143269.17 | J19: =+D19*$F$81+F19*$H$81+H19*$H$82+$H$46 -> 37056.491 | L19: =+D19*$N$81+F19*$P$81+H19*$P$82+$P$46 -> 37123.798 | N19: =L19-J19 -> 67.30699 | P19: =L19/J19-1 -> 0.0018163347 | R19: =+D19*$F$81+F19*$H$94+H19*$H$95+$H$46 -> 18471.002 | S19: =+N19/R19 -> 0.0036439274
B20: =+B19+1 -> 9 | D20: 1394.4583 | F20: 264046.42 | H20: 374299 | J20: =+D20*$F$81+F20*$H$81+H20*$H$82+$H$46 -> 103235.61 | L20: =+D20*$N$81+F20*$P$81+H20*$P$82+$P$46 -> 103033.6 | N20: =L20-J20 -> -202.00533 | P20: =L20/J20-1 -> -0.0019567409 | R20: =+D20*$F$81+F20*$H$94+H20*$H$95+$H$46 -> 50712.545 | S20: =+N20/R20 -> -0.0039833404
B21: =+B20+1 -> 10 | D21: 871.83333 | F21: 108293.33 | H21: 118453.33 | J21: =+D21*$F$81+F21*$H$81+H21*$H$82+$H$46 -> 40122.16 | L21: =+D21*$N$81+F21*$P$81+H21*$P$82+$P$46 -> 40694.003 | N21: =L21-J21 -> 571.84307 | P21: =L21/J21-1 -> 0.01425255 | R21: =+D21*$F$81+F21*$H$94+H21*$H$95+$H$46 -> 21465.444 | S21: =+N21/R21 -> 0.02664017
B22: =+B21+1 -> 11 | D22: 656.83333 | F22: 81720 | H22: 43160 | J22: =+D22*$F$81+F22*$H$81+H22*$H$82+$H$46 -> 23992.605 | L22: =+D22*$N$81+F22*$P$81+H22*$P$82+$P$46 -> 24600.572 | N22: =L22-J22 -> 607.9668 | P22: =L22/J22-1 -> 0.025339757 | R22: =+D22*$F$81+F22*$H$94+H22*$H$95+$H$46 -> 13717.479 | S22: =+N22/R22 -> 0.044320593
B23: =+B22+1 -> 12 | D23: 611.75 | F23: 93120 | H23: 130659 | J23: =+D23*$F$81+F23*$H$81+H23*$H$82+$H$46 -> 37385.499 | L23: =+D23*$N$81+F23*$P$81+H23*$P$82+$P$46 -> 37545.8 | N23: =L23-J23 -> 160.30145 | P23: =L23/J23-1 -> 0.0042877976 | R23: =+D23*$F$81+F23*$H$94+H23*$H$95+$H$46 -> 18972.962 | S23: =+N23/R23 -> 0.0084489415
B24: =+B23+1 -> 13 | D24: 782.5 | F24: 100000 | H24: 102000 | J24: =+D24*$F$81+F24*$H$81+H24*$H$82+$H$46 -> 35876.475 | L24: =+D24*$N$81+F24*$P$81+H24*$P$82+$P$46 -> 36396.525 | N24: =L24-J24 -> 520.05 | P24: =L24/J24-1 -> 0.014495571 | R24: =+D24*$F$81+F24*$H$94+H24*$H$95+$H$46 -> 19255.915 | S24: =+N24/R24 -> 0.027007286
... B39: =+B38+1 -> 28 | D39: 1557.25 | F39: 309114.75 | H39: 485202.08 | J39: =+D39*$F$81+F39*$H$81+H39*$H$82+$H$46 -> 126655.7 | L39: =+D39*$N$81+F39*$P$81+H39*$P$82+$P$46 -> 126114.62 | N39: =L39-J39 -> -541.0766 | P39: =L39/J39-1 -> -0.0042720274 | R39: =+D39*$F$81+F39*$H$94+H39*$H$95+$H$46 -> 61299.306 | S39: =+N39/R39 -> -0.0088267981
B43: Current Rates: | K43: Proposed Rates:
H44: GD-3 | P44: GD-3 | R44: Difference | S44: Difference **
B45: Delivery Charges: | K45: Delivery Charges:
B46: Customer Charge | H46: 300 | K46: Customer Charge | P46: 338.75 | S46: =+P46-H46 -> 38.75
F47: All kVA | H47: kWh | N47: All kVA | P47: kWh | R47: All kVA | S47: kWh
B48: Internal Transmission | H48: =0.0031+0.00108 -> 0.00418 | I48: All | K48: Internal Transmission | P48: =0.0031+0.00108 -> 0.00418 | S48: =+P48-H48 -> 0 | T48: All
B49: External Transmission | H49: 0.01931 | I49: All | K49: External Transmission | P49: 0.01925 | S49: =+P49-H49 -> -6e-05 | T49: All
E50: Transmission Subtotals | H50: =SUM(H49,H48) -> 0.02349 | I50: All | M50: Transmission Subtotals | P50: =SUM(P49,P48) -> 0.02343 | S50: =+P50-H50 -> -6e-05 | T50: All
B52: Distribution - Nov. 1, 2023 | F52: 8.07 | H52: 0.01952 | I52: On Peak | K52: Distribution | N52: 9.75 | P52: 0.01828 | R52: =+N52-F52 -> 1.68 | S52: =+P52-H52 -> -0.00124 | T52: On Peak
H53: 0.00435 | I53: Off Peak | P53: 0.00407 | S53: =+P53-H53 -> -0.00028 | T53: Off Peak
B55: Pension/PBOP Adjustment Factor | H55: 0.00066 | I55: All | K55: Pension/PBOP Adjustment Factor | P55: 0.00066 | S55: =+P55-H55 -> 0 | T55: All
B56: Residential Assistance Adjustment Factor | H56: 0.00664 | I56: All | K56: Residential Assistance Adjustment Factor | P56: 0.00748 | S56: =+P56-H56 -> 0.00084 | T56: All
B57: Net Metering Recovery Surcharge | H57: 0.00401 | I57: All | K57: Net Metering Recovery Surcharge | P57: 0.00401 | S57: =+P57-H57 -> 0 | T57: All
B58: Revenue Decoupling Adjustment Factor | H58: 0.00045 | I58: All | K58: Revenue Decoupling Adjustment Factor | P58: 0.00045 | S58: =+P58-H58 -> 0 | T58: All
B59: Attorney General Consultant Expense Factor | H59: 0.00014 | I59: All | K59: Attorney General Consultant Expense Factor | P59: 0.00014 | S59: =+P59-H59 -> 0 | T59: All
B60: L-T Renewable Contract Adjustment Factor | H60: -0.00275 | I60: All | K60: L-T Renewable Contract Adjustment Factor | P60: -0.00275 | S60: =+P60-H60 -> 0 | T60: All
B61: Capital Cost Adjustment Factor | H61: 0.00238 | I61: All | K61: Capital Cost Adjustment Factor | P61: 0.00071 | S61: =+P61-H61 -> -0.00167 | T61: All
B62: Solar Cost Adjustment | H62: -4e-05 | I62: All | K62: Solar Cost Adjustment | P62: -0.0003 | S62: =+P62-H62 -> -0.00026 | T62: All
B63: Grid Modernization Factor | H63: 0.00098 | I63: All | K63: Grid Modernization Factor | P63: 0.00098 | S63: =+P63-H63 -> 0 | T63: All
B64: Basic Service Adjustment | H64: -0.0001 | I64: All | K64: Basic Service Adjustment | P64: =+H64 -> -0.0001 | S64: =+P64-H64 -> 0 | T64: All
B65: Storm Reserve Adjustment Factor | H65: 0.00013 | I65: All | K65: Storm Reserve Adjustment Factor | P65: 0.00013 | S65: =+P65-H65 -> 0 | T65: All
B66: Exogenous Cost Adjustment Factor | H66: 0.0005 | I66: All | K66: Exogenous Cost Adjustment Factor | P66: 0.0005 | S66: =+P66-H66 -> 0 | T66: All
E67: Distribution Subtotals | F67: =SUM(F52:F66) -> 8.07 | H67: =SUM(H52,H55:H66) -> 0.03252 | I67: On Peak | M67: Distribution Subtotals | N67: =SUM(N52:N64) -> 9.75 | P67: =SUM(P52,P55:P66) -> 0.03019 | R67: =+N67-F67 -> 1.68 | S67: =+P67-H67 -> -0.00233 | T67: On Peak
H68: =SUM(H53,H55:H66) -> 0.01735 | I68: Off Peak | P68: =SUM(P53,P55:P66) -> 0.01598 | S68: =+P68-H68 -> -0.00137 | T68: Off Peak
B70: Renewable Resources Charge | H70: 0.0005 | I70: All | K70: Renewable Resources Charge | P70: 0.0005 | S70: =+P70-H70 -> 0 | T70: All
B72: Energy Efficiency Charge | H72: 0.0025 | I72: All | K72: Energy Efficiency Charge | P72: 0.0025 | S72: =+P72-H72 -> 0 | T72: All
B73: Energy Efficiency Reconciliation Factor | H73: 0.00972 | I73: All | K73: Energy Efficiency Reconciliation Factor | P73: 0.00972 | S73: =+P73-H73 -> 0 | T73: All
E74: Total Energy Efficiency Charge Subtotal | H74: =SUM(H72:H73) -> 0.01222 | I74: All | M74: Total Energy Efficiency Charge Subtotal | P74: =SUM(P72:P73) -> 0.01222 | S74: =+P74-H74 -> 0 | T74: All
B76: SMART Factor | H76: 0.00151 | I76: All | K76: SMART Factor | P76: 0.0013 | S76: =+P76-H76 -> -0.00021 | T76: All
B78: Supplier Charges: | K78: Supplier Charges:
B79: Generation Charge* | H79: 0.08228 | I79: All | K79: Generation Charge* | P79: 0.08027 | S79: =+P79-H79 -> -0.00201 | T79: All
E81: Totals | F81: =+F67 -> 8.07 | H81: =SUM(H50,H67,H70,H74,H76,H79) -> 0.15252 | I81: On Peak | M81: Totals | N81: =+N67 -> 9.75 | P81: =SUM(P50,P67,P70,P74,P76,P79) -> 0.14791 | R81: =+N81-F81 -> 1.68 | S81: =+P81-H81 -> -0.00461 | T81: On Peak
H82: =SUM(H50,H68,H70,H74,H76,H79) -> 0.13735 | I82: Off Peak | P82: =SUM(P50,P68,P70,P74,P76,P79) -> 0.1337 | S82: =+P82-H82 -> -0.00365 | T82: Off Peak
B86: * Market Variable Basic Service rate for July 2023 including Basic Service Costs Adder of $0.00493/kWh at current and $0.00292/kWh at proposed.
B87: **Includes changes in reconciliation mechanisms related to this distribution rate case proposal
G94: delivery only | H94: =+H81-H79 -> 0.07024 | O94: delivery only | P94: =+P81-P79 -> 0.06764
H95: =+H82-H79 -> 0.05507 | P95: =+P82-P79 -> 0.05343

Sheet GD-4
B3: Fitchburg Gas and Electric Light Company d/b/a Unitil
B4: Basic Service Customer Typical Bill Impacts - 2023 Distribution Rate Proposal
B5: Impact on GD-4 Rate Customers
E7: 2022 | G7: 2022 | I7: 2022
E8: Average | G8: On Peak | I8: Off Peak | K8: Current Rates | M8: Proposed Rates | Q8: % | S8: Present Rates | U8: %
E9: Monthly | G9: Monthly | I9: Monthly | K9: Total | M9: Total | O9: Total | Q9: Total | S9: Delivery | U9: Delivery
C10: Sequence | E10: kW | G10: kWh | I10: kWh | K10: Revenue | M10: Revenue | O10: Difference | Q10: Difference | S10: Revenue | U10: Difference
C12: 1 | E12: 96.875 | G12: 3370.75 | I12: 18009.667 | K12: =+$K$20+E12*$I$56+G12*$K$56+I12*$K$57 -> 6909.0144 | M12: =+$S$20+E12*$R$56+G12*$S$56+I12*$S$57 -> 6929.9034 | O12: =M12-K12 -> 20.889012 | Q12: =M12/K12-1 -> 0.0030234431 | S12: =+$K$20+G12*$K$72+I12*$K$73+E12*$I$72 -> 2502.7243 | U12: =+O12/S12 -> 0.0083465094
C13: =+C12+1 -> 2 | E13: 2.917 | G13: 293.33333 | I13: 548.33333 | K13: =+$K$20+E13*$I$56+G13*$K$56+I13*$K$57 -> 279.36512 | M13: =+$S$20+E13*$R$56+G13*$S$56+I13*$S$57 -> 283.06892 | O13: =M13-K13 -> 3.7037933 | Q13: =M13/K13-1 -> 0.013257895 | S13: =+$K$20+G13*$K$72+I13*$K$73+E13*$I$72 -> 105.90604 | U13: =+O13/S13 -> 0.034972447
B17: Current Rates: | N17: Proposed Rates:
K18: GD-4 | S18: GD-4 | U18: Difference | V18: Difference **
B19: Delivery Charges: | N19: Delivery Charges:
B20: Customer Charge | K20: 10 | N20: Customer Charge | S20: 12 | V20: =+S20-K20 -> 2
I21: All kW | K21: kWh | R21: All kW | S21: kWh | U21: All kW | V21: kWh
B22: Internal Transmission | K22: =0.00323+0.00147 -> 0.0047 | L22: All | N22: Internal Transmission | S22: =0.00323+0.00147 -> 0.0047 | V22: =+S22-K22 -> 0 | W22: All
B23: External Transmission Charge | K23: 0.02611 | L23: All | N23: External Transmission | S23: 0.02602 | V23: =+S23-K23 -> -9e-05 | W23: All
H24: Transmission Subtotals | K24: =SUM(K23,K22) -> 0.03081 | L24: All | Q24: Transmission Subtotals | S24: =SUM(S23,S22) -> 0.03072 | V24: =+S24-K24 -> -9e-05 | W24: All
B26: Distribution - Nov. 1, 2023 | I26: 3.92 | K26: 0.01027 | L26: On Peak | N26: Distribution | R26: 4.75 | S26: 0.02382 | U26: =+R26-I26 -> 0.83 | V26: =+S26-K26 -> 0.01355 | W26: On Peak
K27: 0.00223 | L27: Off Peak | S27: 0.00517 | V27: =+S27-K27 -> 0.00294 | W27: Off Peak
B29: Pension/PBOP Adjustment Factor | K29: 0.00275 | L29: All | N29: Pension/PBOP Adjustment Factor | S29: 0.00275 | V29: =+S29-K29 -> 0 | W29: All
B30: Residential Assistance Adjustment Factor | K30: 0.01983 | L30: All | N30: Residential Assistance Adjustment Factor | S30: 0.02233 | V30: =+S30-K30 -> 0.0025 | W30: All
B31: Net Metering Recovery Surcharge | K31: 0.01197 | L31: All | N31: Net Metering Recovery Surcharge | S31: 0.01197 | V31: =+S31-K31 -> 0 | W31: All
B32: Revenue Decoupling Adjustment Factor | K32: 0.00136 | L32: All | N32: Revenue Decoupling Adjustment Factor | S32: 0.00136 | V32: =+S32-K32 -> 0 | W32: All
B33: Attorney General Consultant Expense Factor | K33: 0.00041 | L33: All | N33: Attorney General Consultant Expense Factor | S33: 0.00041 | V33: =+S33-K33 -> 0 | W33: All
B34: L-T Renewable Contract Adjustment Factor | K34: -0.00275 | L34: All | N34: L-T Renewable Contract Adjustment Factor | S34: -0.00275 | V34: =+S34-K34 -> 0 | W34: All
B35: Capital Cost Adjustment Factor | K35: 0.0093 | L35: All | N35: Capital Cost Adjustment Factor | S35: 0.00279 | V35: =+S35-K35 -> -0.00651 | W35: All
B36: Solar Cost Adjustment | K36: -0.00014 | L36: All | N36: Solar Cost Adjustment | S36: -0.00092 | V36: =+S36-K36 -> -0.00078 | W36: All
B37: Grid Modernization Factor | K37: 0.00296 | L37: All | N37: Grid Modernization Factor | S37: 0.00296 | V37: =+S37-K37 -> 0 | W37: All
B38: Basic Service Adjustment | K38: -0.00032 | L38: All | N38: Basic Service Adjustment | S38: =+K38 -> -0.00032 | V38: =+S38-K38 -> 0 | W38: All
B39: Storm Reserve Adjustment Factor | K39: 0.0004 | L39: All | N39: Storm Reserve Adjustment Factor | S39: 0.0004 | V39: =+S39-K39 -> 0 | W39: All
B40: Exogenous Cost Adjustment Factor | K40: 0.00153 | L40: All | N40: Exogenous Cost Adjustment Factor | S40: 0.00153 | V40: =+S40-K40 -> 0 | W40: All
H41: Distribution Subtotals | I41: =SUM(I26:I40) -> 3.92 | K41: =SUM(K26,K29:K40) -> 0.05757 | L41: On Peak | Q41: Distribution Subtotals | R41: =SUM(R26:R40) -> 4.75 | S41: =SUM(S26,S29:S40) -> 0.06633 | U41: =SUM(U26:U38) -> 0.83 | V41: =+S41-K41 -> 0.00876 | W41: On Peak
K42: =SUM(K27,K29:K40) -> 0.04953 | L42: Off Peak | S42: =SUM(S27,S29:S40) -> 0.04768 | V42: =+S42-K42 -> -0.00185 | W42: Off Peak
B44: Renewable Resources Charge | K44: 0.0005 | L44: All | N44: Renewable Resources Charge | S44: 0.0005 | V44: =+S44-K44 -> 0 | W44: All
B46: Energy Efficiency Charge | K46: 0.0025 | L46: All | N46: Energy Efficiency Charge | S46: 0.0025 | V46: =+S46-K46 -> 0 | W46: All
B47: Energy Efficiency Reconciliation Factor | K47: 0.00972 | L47: All | N47: Energy Efficiency Reconciliation Factor | S47: 0.00972 | V47: =+S47-K47 -> 0 | W47: All
H48: Total Energy Efficiency Charge Subtotal | K48: =SUM(K46:K47) -> 0.01222 | L48: All | Q48: Total Energy Efficiency Charge Subtotal | S48: =SUM(S46:S47) -> 0.01222 | V48: =+S48-K48 -> 0 | W48: All
B50: SMART Factor | K50: 0.0045 | L50: All | N50: SMART Factor | S50: 0.0039 | V50: =+S50-K50 -> -0.0006 | W50: All
B51: SMART Factor | K51: 0 | L51: All | N51: Transition Charge Surcharge | S51: 0 | V51: =+S51-K51 -> 0 | W51: All
B53: Supplier Charges: | N53: Supplier Charges:
B54: Generation Charge* | K54: 0.20609 | L54: All | N54: Generation Charge* | S54: 0.20408 | V54: =+S54-K54 -> -0.00201 | W54: All
H56: Totals | I56: =SUM(I50,I41) -> 3.92 | K56: =SUM(K54,K41,K24,K44,K48,K50) -> 0.31169 | L56: On Peak | Q56: Totals | R56: =SUM(R50,R41) -> 4.75 | S56: =SUM(S54,S41,S24,S44,S48,S50) -> 0.31775 | U56: =+R56-I56 -> 0.83 | V56: =+S56-K56 -> 0.00606 | W56: On Peak
K57: =SUM(K24,K42,K44,K48,K50,K54) -> 0.30365 | L57: Off Peak | S57: =SUM(S24,S42,S44,S48,S50,S54) -> 0.2991 | V57: =+S57-K57 -> -0.00455 | W57: Off Peak
B63: * August 1, 2023 Basic Service, Fixed including Basic Service Costs Adder of $0.00493/kWh at current and $0.00292/kWh at proposed. ** Includes changes in reconciliation mechanisms related to this distribution rate case proposal.
B68: Load Factor | D68: 0.75
B69: On Peak % | D69: 0.25
H72: delivery only | I72: =+I56 -> 3.92 | K72: =+K56-K54 -> 0.1056 | Q72: delivery only | R72: =+R56 -> 4.75 | S72: =+S56-S54 -> 0.11367
K73: =+K57-K54 -> 0.09756 | S73: =+S57-S54 -> 0.09502

Sheet GD-5
B3: Fitchburg Gas and Electric Light Company d/b/a Unitil
B4: Basic Service Customer Typical Bill Impacts - 2023 Distribution Rate Proposal
B5: Impact on GD-5 Rate Customers
E8: Average | G8: Current Rates | I8: Proposed Rates | M8: % | O8: Present Rates | P8: %
E9: Monthly | G9: Total | I9: Total | K9: Total | M9: Total | O9: Delivery | P9: Delivery
C10: Decile | E10: kWh | G10: Revenue | I10: Revenue | K10: Difference | M10: Difference | O10: Revenue | P10: Difference
C12: 0.1 | E12: 59.428571 | G12: =$I$30+E12*$I$64 -> 21.520869 | I12: =$P$30+E12*$P$64 -> 21.649829 | K12: =I12-G12 -> 0.12896 | M12: =I12/G12-1 -> 0.0059923232 | O12: =$I$30+E12*$I$75 -> 9.2732343 | P12: =+K12/O12 -> 0.013906691
C13: 0.2 | E13: 306.875 | G13: =$I$30+E13*$I$64 -> 111.12864 | I13: =$P$30+E13*$P$64 -> 111.79456 | K13: =I13-G13 -> 0.66591875 | M13: =I13/G13-1 -> 0.0059923232 | O13: =$I$30+E13*$I$75 -> 47.884775 | P13: =+K13/O13 -> 0.013906691
C14: 0.3 | E14: 530 | G14: =$I$30+E14*$I$64 -> 191.9289 | I14: =$P$30+E14*$P$64 -> 193.079 | K14: =I14-G14 -> 1.1501 | M14: =I14/G14-1 -> 0.0059923232 | O14: =$I$30+E14*$I$75 -> 82.7012 | P14: =+K14/O14 -> 0.013906691
C15: 0.4 | E15: 755.5 | G15: =$I$30+E15*$I$64 -> 273.58922 | I15: =$P$30+E15*$P$64 -> 275.22865 | K15: =I15-G15 -> 1.639435 | M15: =I15/G15-1 -> 0.0059923232 | O15: =$I$30+E15*$I$75 -> 117.88822 | P15: =+K15/O15 -> 0.013906691
C16: 0.5 | E16: 1226.5714 | G16: =$I$30+E16*$I$64 -> 444.17831 | I16: =$P$30+E16*$P$64 -> 446.83997 | K16: =I16-G16 -> 2.66166 | M16: =I16/G16-1 -> 0.0059923232 | O16: =$I$30+E16*$I$75 -> 191.39421 | P16: =+K16/O16 -> 0.013906691
C17: 0.6 | E17: 1949.4286 | G17: =$I$30+E17*$I$64 -> 705.94657 | I17: =$P$30+E17*$P$64 -> 710.17683 | K17: =I17-G17 -> 4.23026 | M17: =I17/G17-1 -> 0.0059923232 | O17: =$I$30+E17*$I$75 -> 304.18883 | P17: =+K17/O17 -> 0.013906691
C18: 0.7 | E18: 3711.75 | G18: =$I$30+E18*$I$64 -> 1344.136 | I18: =$P$30+E18*$P$64 -> 1352.1905 | K18: =I18-G18 -> 8.0544975 | M18: =I18/G18-1 -> 0.0059923232 | O18: =$I$30+E18*$I$75 -> 579.18147 | P18: =+K18/O18 -> 0.013906691
C19: 0.8 | E19: 5360.1429 | G19: =$I$30+E19*$I$64 -> 1941.0685 | I19: =$P$30+E19*$P$64 -> 1952.7 | K19: =I19-G19 -> 11.63151 | M19: =I19/G19-1 -> 0.0059923232 | O19: =$I$30+E19*$I$75 -> 836.39669 | P19: =+K19/O19 -> 0.013906691
C20: 0.9 | E20: 9570 | G20: =$I$30+E20*$I$64 -> 3465.5841 | I20: =$P$30+E20*$P$64 -> 3486.351 | K20: =I20-G20 -> 20.7669 | M20: =I20/G20-1 -> 0.0059923232 | O20: =$I$30+E20*$I$75 -> 1493.3028 | P20: =+K20/O20 -> 0.013906691
C21: 1 | E21: 23508.571 | G21: =$I$30+E21*$I$64 -> 8513.159 | I21: =$P$30+E21*$P$64 -> 8564.1726 | K21: =I21-G21 -> 51.0136 | M21: =I21/G21-1 -> 0.0059923232 | O21: =$I$30+E21*$I$75 -> 3668.2775 | P21: =+K21/O21 -> 0.013906691
C23: Average | E23: =AVERAGE(E12:E21) -> 4697.8268 | G23: =$I$30+E23*$I$64 -> 1701.224 | I23: =$P$30+E23*$P$64 -> 1711.4183 | K23: =I23-G23 -> 10.194284 | M23: =I23/G23-1 -> 0.0059923232 | O23: =$I$30+E23*$I$75 -> 733.04889 | P23: =+K23/O23 -> 0.013906691
B27: Current Rates: | K27: Proposed Rates:
I28: GD-5 | P28: GD-5 | R28: Difference **
B29: Delivery Charges: | K29: Delivery Charges:
B30: Customer Charge | I30: 0 | K30: Customer Charge | P30: 0 | R30: =+P30-I30 -> 0
I31: kWh | P31: kWh | R31: kWh
B32: Internal Transmission | I32: =0.00323+0.00147 -> 0.0047 | K32: Internal Transmission | P32: =0.00323+0.00147 -> 0.0047 | R32: =+P32-I32 -> 0
B33: External Transmission | I33: 0.02611 | K33: External Transmission | P33: 0.02602 | R33: =+P33-I33 -> -9e-05
H34: Transmission Subtotal | I34: =SUM(I32:I33) -> 0.03081 | O34: Transmission Subtotal | P34: =SUM(P32:P33) -> 0.03072 | R34: =+P34-I34 -> -9e-05
B36: Distribution - Nov. 1, 2023 | I36: 0.06071 | K36: Distribution | P36: 0.07037 | R36: =+P36-I36 -> 0.00966
B38: Pension/PBOP Adjustment Factor | I38: 0.00275 | K38: Pension/PBOP Adjustment Factor | P38: 0.00275 | R38: =+P38-I38 -> 0
B39: Residential Assistance Adjustment Factor | I39: 0.01983 | K39: Residential Assistance Adjustment Factor | P39: 0.02233 | R39: =+P39-I39 -> 0.0025
B40: Net Metering Recovery Surcharge | I40: 0.01197 | K40: Net Metering Recovery Surcharge | P40: 0.01197 | R40: =+P40-I40 -> 0
B41: Revenue Decoupling Adjustment Factor | I41: 0.00136 | K41: Revenue Decoupling Adjustment Factor | P41: 0.00136 | R41: =+P41-I41 -> 0
B42: Attorney General Consultant Expense Factor | I42: 0.00041 | K42: Attorney General Consultant Expense Factor | P42: 0.00041 | R42: =+P42-I42 -> 0
B43: L-T Renewable Contract Adjustment Factor | I43: -0.00275 | K43: L-T Renewable Contract Adjustment Factor | P43: -0.00275 | R43: =+P43-I43 -> 0
B44: Capital Cost Adjustment Factor | I44: 0.0093 | K44: Capital Cost Adjustment Factor | P44: 0.00279 | R44: =+P44-I44 -> -0.00651
B45: Solar Cost Adjustment | I45: -0.00014 | K45: Solar Cost Adjustment | P45: -0.00092 | R45: =+P45-I45 -> -0.00078
B46: Grid Modernization Factor | I46: 0.00296 | K46: Grid Modernization Factor | P46: 0.00296 | R46: =+P46-I46 -> 0
B47: Basic Service Adjustment | I47: -0.00032 | K47: Basic Service Adjustment | P47: =+I47 -> -0.00032 | R47: =+P47-I47 -> 0
B48: Storm Reserve Adjustment Factor | I48: 0.0004 | K48: Storm Reserve Adjustment Factor | P48: 0.0004 | R48: =+P48-I48 -> 0
B49: Exogenous Cost Adjustment Factor | I49: 0.00153 | K49: Exogenous Cost Adjustment Factor | P49: 0.00153 | R49: =+P49-I49 -> 0
H50: Distribution Subtotal | I50: =SUM(I36,I38:I49) -> 0.10801 | O50: Distribution Subtotal | P50: =SUM(P36,P38:P49) -> 0.11288 | R50: =+P50-I50 -> 0.00487
B52: Renewable Resources Charge | I52: 0.0005 | K52: Renewable Resources Charge | P52: 0.0005 | R52: =+P52-I52 -> 0
B54: Energy Efficiency Charge | I54: 0.0025 | K54: Energy Efficiency Charge | P54: 0.0025 | R54: =+P54-I54 -> 0
B55: Energy Efficiency Reconciliation Factor | I55: 0.00972 | K55: Energy Efficiency Reconciliation Factor | P55: 0.00972 | R55: =+P55-I55 -> 0
H56: Total Energy Efficiency Charge Subtotal | I56: =SUM(I54:I55) -> 0.01222 | O56: Total Energy Efficiency Charge Subtotal | P56: =SUM(P54:P55) -> 0.01222 | R56: =+P56-I56 -> 0
B58: SMART Factor | I58: 0.0045 | K58: SMART Factor | P58: 0.0039 | R58: =+P58-I58 -> -0.0006
B59: SMART Factor | I59: 0 | K59: Transition Charge Surcharge | P59: 0 | R59: =+P59-I59 -> 0
B61: Supplier Charges: | K61: Supplier Charges:
B62: Generation Charge* | I62: 0.20609 | K62: Generation Charge* | P62: 0.20408 | R62: =+P62-I62 -> -0.00201
H64: Total | I64: =SUM(I62,I52,I56,I58,I50,I34) -> 0.36213 | O64: Total | P64: =SUM(P62,P52,P56,P58,P50,P34) -> 0.3643 | R64: =+P64-I64 -> 0.00217
B69: * August 1, 2023 Basic Service, Fixed including Basic Service Costs Adder of $0.00493/kWh at current and $0.00292/kWh at proposed. ** Includes changes in reconciliation mechanisms related to this distribution rate case proposal.
H75: delivery only | I75: =+I64-I62 -> 0.15604 | O75: delivery only | P75: =+P64-P62 -> 0.16022

Sheet SD
B3: Fitchburg Gas and Electric Light Company d/b/a Unitil
B4: Basic Service Customer Typical Bill Impacts - 2023 Distribution Rate Proposal
B5: Impact on Company Owned Outdoor Lighting SD Rate Customers
I7: Current Rates | J7: Proposed Rates | L7: % | M7: Present Rates | N7: %
G8: Average | H8: % of | I8: Total | J8: Total | K8: Total | L8: Total | M8: Delivery | N8: Delivery
D9: Lumens | E9: Luminaire | G9: Monthly kWh | H9: Lights | I9: Revenue | J9: Revenue | K9: Difference | L9: Difference | M9: Revenue | N9: Difference
D11: Mercury Vapor:
C12: 1 | D12: 3500 | E12: Street and Highway Type | G12: 39.25 | H12: =H113/$H$159 -> 0.0043344772 | I12: =+G12*E$98+E113 -> 26.058003 | J12: =+G12*K$98+K113 -> 29.223365 | K12: =J12-I12 -> 3.1653625 | L12: =(J12/I12-1) -> 0.12147372 | M12: =+G12*$E$98-G12*$E$96+E113 -> 17.96897 | N12: =+K12/M12 -> 0.17615715
C13: =+C12+1 -> 2 | D13: 7000 | E13: Street and Highway Type | G13: 68.25 | H13: =H114/$H$159 -> 0.007585335 | I13: =+G13*E$98+E114 -> 36.786972 | J13: =+G13*K$98+K114 -> 39.922985 | K13: =J13-I13 -> 3.1360125 | L13: =(J13/I13-1) -> 0.085247909 | M13: =+G13*$E$98-G13*$E$96+E114 -> 22.72133 | N13: =+K13/M13 -> 0.13802064
C14: =+C13+1 -> 3 | D14: 20000 | E14: Street and Highway Type | G14: 157.25 | H14: =H115/$H$159 -> 0 | I14: =+G14*E$98+E115 -> 77.441743 | J14: =+G14*K$98+K115 -> 82.649405 | K14: =J14-I14 -> 5.2076625 | L14: =(J14/I14-1) -> 0.067246195 | M14: =+G14*$E$98-G14*$E$96+E115 -> 45.03409 | N14: =+K14/M14 -> 0.11563823
C15: =+C14+1 -> 4 | D15: 60000 | E15: Street and Highway Type | G15: 369 | H15: =H116/$H$159 -> 0.007585335 | I15: =+G15*E$98+E116 -> 169.86517 | J15: =+G15*K$98+K116 -> 178.78482 | K15: =J15-I15 -> 8.91965 | L15: =(J15/I15-1) -> 0.052510176 | M15: =+G15*$E$98-G15*$E$96+E116 -> 93.81796 | N15: =+K15/M15 -> 0.095074014
C16: =+C15+1 -> 5 | D16: 20000 | E16: Flood Light Type | G16: 157.25 | H16: =H117/$H$159 -> 0.027090482 | I16: =+G16*E$98+E117 -> 80.331742 | J16: =+G16*K$98+K117 -> 86.339405 | K16: =J16-I16 -> 6.0076625 | L16: =(J16/I16-1) -> 0.074785661 | M16: =+G16*$E$98-G16*$E$96+E117 -> 47.92409 | N16: =+K16/M16 -> 0.12535788
C17: =+C16+1 -> 6 | D17: 3500 | E17: Power Bracket Included | G17: 39.25 | H17: =H118/$H$159 -> 0.031424959 | I17: =+G17*E$98+E118 -> 26.698003 | J17: =+G17*K$98+K118 -> 30.043365 | K17: =J17-I17 -> 3.3453625 | L17: =(J17/I17-1) -> 0.12530385 | M17: =+G17*$E$98-G17*$E$96+E118 -> 18.60897 | N17: =+K17/M17 -> 0.1797715
C18: =+C17+1 -> 7 | D18: 7000 | E18: Power Bracket Included | G18: 68.25 | H18: =H119/$H$159 -> 0.027090482 | I18: =+G18*E$98+E119 -> 37.736973 | J18: =+G18*K$98+K119 -> 41.142985 | K18: =J18-I18 -> 3.4060125 | L18: =(J18/I18-1) -> 0.090256644 | M18: =+G18*$E$98-G18*$E$96+E119 -> 23.67133 | N18: =+K18/M18 -> 0.14388767
D20: High Pressure Sodium:
C21: =+C18+1 -> 8 | D21: 3300 | E21: Street and Highway Type | G21: 20 | H21: =H122/$H$159 -> 0.14267654 | I21: =+G21*E$98+E122 -> 18.1286 | J21: =+G21*K$98+K122 -> 21.0856 | K21: =J21-I21 -> 2.957 | L21: =(J21/I21-1) -> 0.16311243 | M21: =+G21*$E$98-G21*$E$96+E122 -> 14.0068 | N21: =+K21/M21 -> 0.21111175
C22: =+C21+1 -> 9 | D22: 9500 | E22: Street and Highway Type | G22: 40.25 | H22: =H123/$H$159 -> 0.089940401 | I22: =+G22*E$98+E123 -> 26.806933 | J22: =+G22*K$98+K123 -> 30.077145 | K22: =J22-I22 -> 3.2702125 | L22: =(J22/I22-1) -> 0.1219913 | M22: =+G22*$E$98-G22*$E$96+E123 -> 18.51181 | N22: =+K22/M22 -> 0.17665547
C23: =+C22+1 -> 10 | D23: 20000 | E23: Street and Highway Type | G23: 85 | H23: =H124/$H$159 -> 0.0086689543 | I23: =+G23*E$98+E124 -> 47.93905 | J23: =+G23*K$98+K124 -> 52.4413 | K23: =J23-I23 -> 4.50225 | L23: =(J23/I23-1) -> 0.093916129 | M23: =+G23*$E$98-G23*$E$96+E124 -> 30.4214 | N23: =+K23/M23 -> 0.14799615
C24: =+C23+1 -> 11 | D24: 50000 | E24: Street and Highway Type | G24: 161.25 | H24: =H125/$H$159 -> 0.0065017157 | I24: =+G24*E$98+E125 -> 81.047462 | J24: =+G24*K$98+K125 -> 86.844525 | K24: =J24-I24 -> 5.7970625 | L24: =(J24/I24-1) -> 0.071526761 | M24: =+G24*$E$98-G24*$E$96+E125 -> 47.81545 | N24: =+K24/M24 -> 0.12123827
C25: =+C24+1 -> 12 | D25: 140000 | E25: Street and Highway Type | G25: 378 | H25: =H126/$H$159 -> 0.046595629 | I25: =+G25*E$98+E126 -> 181.32554 | J25: =+G25*K$98+K126 -> 192.49884 | K25: =J25-I25 -> 11.1733 | L25: =(J25/I25-1) -> 0.061620112 | M25: =+G25*$E$98-G25*$E$96+E126 -> 103.42352 | N25: =+K25/M25 -> 0.10803442
C26: =+C25+1 -> 13 | D26: 50000 | E26: Flood Light Type | G26: 161.25 | H26: =H127/$H$159 -> 0.31424959 | I26: =+G26*E$98+E127 -> 85.807462 | J26: =+G26*K$98+K127 -> 92.924525 | K26: =J26-I26 -> 7.1170625 | L26: =(J26/I26-1) -> 0.082942232 | M26: =+G26*$E$98-G26*$E$96+E127 -> 52.57545 | N26: =+K26/M26 -> 0.13536855
D28: Metal Halide:
C29: =+C26+1 -> 14 | D29: 3700 | E29: Cobra Head Type | G29: 39.5 | H29: 0 | I29: =+G29*E$98+E130 -> 29.197735
C30: =+C29+1 -> 15 | D30: 5000 | E30: Cobra Head Type | G30: 57.5 | H30: 0 | I30: =+G30*E$98+E131 -> 37.308475
C31: =+C30+1 -> 16 | D31: 10000 | E31: Cobra Head Type | G31: 124.75 | H31: 0 | I31: =+G31*E$98+E132 -> 63.226517
C32: =+C31+1 -> 17 | D32: 3700 | E32: Flood Light Type | G32: 39.5 | H32: 0 | I32: =+G32*E$98+E133 -> 29.547735
C33: =+C32+1 -> 18 | D33: 5000 | E33: Flood Light Type | G33: 57.5 | H33: 0 | I33: =+G33*E$98+E134 -> 37.948475
C34: =+C33+1 -> 19 | D34: 10000 | E34: Flood Light Type | G34: 124.75 | H34: 0 | I34: =+G34*E$98+E135 -> 63.076518
C35: =+C34+1 -> 20 | D35: 47000 | E35: Flood Light Type | G35: 361.25 | H35: 0 | I35: =+G35*E$98+E136 -> 165.27346
C36: =+C35+1 -> 21 | D36: 3700 | E36: Power Bracket Included | G36: 39.5 | H36: 0 | I36: =+G36*E$98+E137 -> 29.487735
C37: =+C36+1 -> 22 | D37: 5000 | E37: Power Bracket Included | G37: 57.5 | H37: 0 | I37: =+G37*E$98+E138 -> 37.618475
C38: =+C37+1 -> 23 | D38: 10000 | E38: Power Bracket Included | G38: 124.75 | H38: 0 | I38: =+G38*E$98+E139 -> 63.606518
D40: Light Emitting Diode (LED):
C41: =+C38+1 -> 24 | D41: 3850 | E41: Cobra Head Type | G41: 17.25 | H41: =H142/$H$159 -> 0 | I41: =+G41*E$98+E142 -> 15.751542 | J41: =+G41*K$98+K142 -> 15.490205 | K41: =J41-I41 -> -0.2613375 | L41: =(J41/I41-1) -> -0.016591232 | M41: =+G41*$E$98-G41*$E$96+E142 -> 12.19649 | N41: =+K41/M41 -> -0.021427271
C42: =+C41+1 -> 25 | D42: 6100 | E42: Cobra Head Type | G42: 29.25 | H42: =H143/$H$159 -> 0 | I42: =+G42*E$98+E143 -> 21.488703 | J42: =+G42*K$98+K143 -> 21.045565 | K42: =J42-I42 -> -0.4431375 | L42: =(J42/I42-1) -> -0.020621883 | M42: =+G42*$E$98-G42*$E$96+E143 -> 15.46057 | N42: =+K42/M42 -> -0.02866243
C43: =+C42+1 -> 26 | D43: 10680 | E43: Cobra Head Type | G43: 33.25 | H43: =H144/$H$159 -> 0.007585335 | I43: =+G43*E$98+E144 -> 25.704422 | J43: =+G43*K$98+K144 -> 29.100685 | K43: =J43-I43 -> 3.3962625 | L43: =(J43/I43-1) -> 0.13212756 | M43: =+G43*$E$98-G43*$E$96+E144 -> 18.85193 | N43: =+K43/M43 -> 0.18015463
C44: =+C43+1 -> 27 | E44: 28 Watt LED Street | G44: 9.25 | H44: =H145/$H$159 -> 0.11703088 | I44: =+G44*E$98+E145 -> 10.530102 | J44: =+G44*K$98+K145 -> 12.309965 | K44: =J44-I44 -> 1.7798625 | L44: =(J44/I44-1) -> 0.16902613 | M44: =+G44*$E$98-G44*$E$96+E145 -> 8.62377 | N44: =+K44/M44 -> 0.2063903
C45: =+C44+1 -> 28 | E45: 47 Watt LED Street | G45: 15.5 | H45: =H146/$H$159 -> 0.012461622 | I45: =+G45*E$98+E146 -> 13.303415 | J45: =+G45*K$98+K146 -> 15.70859 | K45: =J45-I45 -> 2.405175 | L45: =(J45/I45-1) -> 0.1807938 | M45: =+G45*$E$98-G45*$E$96+E146 -> 10.10902 | N45: =+K45/M45 -> 0.23792366
C46: =+C45+1 -> 29 | E46: 54 Watt LED Street | G46: 17.5 | H46: =H147/$H$159 -> 0.016254289 | I46: =+G46*E$98+E147 -> 14.231275 | J46: =+G46*K$98+K147 -> 16.81615 | K46: =J46-I46 -> 2.584875 | L46: =(J46/I46-1) -> 0.18163341 | M46: =+G46*$E$98-G46*$E$96+E147 -> 10.6247 | N46: =+K46/M46 -> 0.24328922
C47: =+C46+1 -> 30 | E47: 70 Watt LED Street | G47: 23 | H47: =H148/$H$159 -> 0.0010836193 | I47: =+G47*E$98+E148 -> 20.16539 | J47: =+G47*K$98+K148 -> 23.48694 | K47: =J47-I47 -> 3.32155 | L47: =(J47/I47-1) -> 0.16471539 | M47: =+G47*$E$98-G47*$E$96+E148 -> 15.42532 | N47: =+K47/M47 -> 0.21533103
C48: =+C47+1 -> 31 | E48: 110 Watt LED Flood | G48: 36.25 | H48: =H149/$H$159 -> 0.13075673 | I48: =+G48*E$98+E149 -> 26.641213 | J48: =+G48*K$98+K149 -> 30.012025 | K48: =J48-I48 -> 3.3708125 | L48: =(J48/I48-1) -> 0.12652624 | M48: =+G48*$E$98-G48*$E$96+E149 -> 19.17045 | N48: =+K48/M48 -> 0.17583377
C49: =+C48+1 -> 32 | E49: 110 Watt LED Flood - CREE | G49: 65.25 | H49: =H150/$H$159 -> 0.0010836193 | I49: =+G49*E$98+E150 -> 46.600183 | J49: =+G49*K$98+K150 -> 45.611645 | K49: =J49-I49 -> -0.9885375 | L49: =(J49/I49-1) -> -0.021213168 | M49: =+G49*$E$98-G49*$E$96+E150 -> 33.15281 | N49: =+K49/M49 -> -0.029817608
C50: =+C49+1 -> 33
C51: =+C50+1 -> 34
C52: =+C51+1 -> 35
C53: =+C52+1 -> 36
D55: Ornamental Lighting:
C56: =+C53+1 -> 37 | D56: 3300 | E56: Street and Highway Type | G56: 20 | H56: 0 | I56: =+G56*E$98+E157 -> 15.8986 | J56: =+G56*K$98+K157 -> 15.5956 | K56: =J56-I56 -> -0.303 | L56: =(J56/I56-1) -> -0.019058282 | M56: =+G56*$E$98-G56*$E$96+E157 -> 11.7768 | N56: =+K56/M56 -> -0.025728551
D58: Other
C59: 38 | D59: various | E59: Miscellaneous Special Agreement | G59: 17 | H59: =H160/$H$159 -> 0 | I59: =+G59*E$98+E158 -> 15.42181 | J59: =+G59*K$98+K158 -> 15.16426 | K59: =J59-I59 -> -0.25755 | L59: =(J59/I59-1) -> -0.016700374 | M59: =+G59*$E$98-G59*$E$96+E158 -> 11.91828 | N59: =+K59/M59 -> -0.021609662
B62: Current Rates: | I62: Proposed Rates:
E63: SD | K63: SD | L63: Difference **
B64: Delivery Charges: | I64: Delivery Charges:
B65: Customer Charge | E65: 0 | I65: =B65 -> Customer Charge | K65: 0 | L65: =+K65-E65 -> 0
E66: kWh | K66: kWh
B67: Internal Transmission | E67: =0.00318+0.00157 -> 0.00475 | I67: =B67 -> Internal Transmission | K67: =0.00318+0.00157 -> 0.00475 | L67: =+K67-E67 -> 0
B68: External Transmission | E68: 0.02796 | I68: =B68 -> External Transmission | K68: 0.02787 | L68: =+K68-E68 -> -9e-05
D69: Transmission Subtotal | E69: =SUM(E67:E68) -> 0.03271 | J69: Transmission Subtotal | K69: =SUM(K67:K68) -> 0.03262 | L69: =+K69-E69 -> -9e-05
B71: Distribution - Nov. 1, 2023 | E71: 0 | I71: Distribution | K71: 0 | L71: =+K71-E71 -> 0
B73: Pension/PBOP Adjustment Factor | E73: 0.00975 | I73: Pension/PBOP Adjustment Factor | K73: 0.00975 | L73: =+K73-E73 -> 0
B74: Residential Assistance Adjustment Factor | E74: 0.01879 | I74: Residential Assistance Adjustment Factor | K74: 0.02116 | L74: =+K74-E74 -> 0.00237
B75: Net Metering Recovery Surcharge | E75: 0.01134 | I75: Net Metering Recovery Surcharge | K75: 0.01134 | L75: =+K75-E75 -> 0
B76: Revenue Decoupling Adjustment Factor | E76: 0.00129 | I76: Revenue Decoupling Adjustment Factor | K76: 0.00129 | L76: =+K76-E76 -> 0
B77: Attorney General Consultant Expense Factor | E77: 0.00039 | I77: Attorney General Consultant Expense Factor | K77: 0.00039 | L77: =+K77-E77 -> 0
B78: L-T Renewable Contract Adjustment Factor | E78: -0.00275 | I78: L-T Renewable Contract Adjustment Factor | K78: -0.00275 | L78: =+K78-E78 -> 0
B79: Capital Cost Adjustment Factor | E79: 0.02019 | I79: Capital Cost Adjustment Factor | K79: 0.00607 | L79: =+K79-E79 -> -0.01412
B80: Solar Cost Adjustment | E80: -0.00013 | I80: Solar Cost Adjustment | K80: -0.00086 | L80: =+K80-E80 -> -0.00073
B81: Grid Modernization Factor | E81: 0.00276 | I81: Grid Modernization Factor | K81: 0.00276 | L81: =+K81-E81 -> 0
B82: Basic Service Adjustment | E82: -0.0003 | I82: Basic Service Adjustment | K82: =+E82 -> -0.0003 | L82: =+K82-E82 -> 0
B83: Storm Reserve Adjustment Factor | E83: 0.00038 | I83: Storm Reserve Adjustment Factor | K83: 0.00038 | L83: =+K83-E83 -> 0
B84: Exogenous Cost Adjustment Factor | E84: 0.00143 | I84: Exogenous Cost Adjustment Factor | K84: 0.00143 | L84: =+K84-E84 -> 0
D85: Distribution Subtotal | E85: =SUM(E71:E84) -> 0.06314 | J85: Distribution Subtotal | K85: =SUM(K71:K84) -> 0.05066 | L85: =+K85-E85 -> -0.01248
B87: Renewable Resources Charge | E87: 0.0005 | I87: Renewable Resources Charge | K87: 0.0005 | L87: =+K87-E87 -> 0
B89: Energy Efficiency Charge | E89: 0.0025 | I89: Energy Efficiency Charge | K89: 0.0025 | L89: =+K89-E89 -> 0
B90: Energy Efficiency Reconciliation Factor | E90: 0.00972 | I90: Energy Efficiency Reconciliation Factor | K90: 0.00972 | L90: =+K90-E90 -> 0
D91: Total Energy Efficiency Charge Subtotal | E91: =SUM(E89:E90) -> 0.01222 | J91: Total Energy Efficiency Charge Subtotal | K91: =SUM(K89:K90) -> 0.01222 | L91: =+K91-E91 -> 0
B93: SMART Factor | E93: 0.00427 | I93: SMART Factor | K93: 0.0037 | L93: =+K93-E93 -> -0.00057
B95: Supplier Charges: | I95: Supplier Charges:
B96: Generation Charge* | E96: 0.20609 | I96: =B96 -> Generation Charge* | K96: 0.20408 | L96: =+K96-E96 -> -0.00201
D98: Total | E98: =SUM(E96,E87,E91,E93,E85,E69) -> 0.31893 | J98: Total | K98: =SUM(K96,K87,K91,K93,K85,K69) -> 0.30378 | L98: =+K98-E98 -> -0.01515
B107: * August 1, 2023 Basic Service, Fixed including Basic Service Costs Adder of $0.00493/kWh at current and $0.00292/kWh at proposed. ** Includes changes in reconciliation mechanisms related to this distribution rate case proposal.
C112: Luminaire: | E112: Distribution Charge | J112: Luminaire: | K112: Distribution Charge | M112: Difference
C113: 1 | E113: 13.54 | H113: 48 | J113: 1 | K113: 17.3 | M113: =K113-E113 -> 3.76 | P113: =K113/E113-1 -> 0.27769572 | R113: 1.1486853
C114: =+C113+1 -> 2 | E114: 15.02 | H114: 84 | J114: =+J113+1 -> 2 | K114: 19.19 | M114: =K114-E114 -> 4.17 | P114: =K114/E114-1 -> 0.27762983
C115: =+C114+1 -> 3 | E115: 27.29 | H115: 0 | J115: =+J114+1 -> 3 | K115: 34.88 | M115: =K115-E115 -> 7.59 | P115: =K115/E115-1 -> 0.27812385
C116: =+C115+1 -> 4 | E116: 52.18 | H116: 84 | J116: =+J115+1 -> 4 | K116: 66.69 | M116: =K116-E116 -> 14.51 | P116: =K116/E116-1 -> 0.27807589
C117: =+C116+1 -> 5 | E117: 30.18 | H117: 300 | J117: =+J116+1 -> 5 | K117: 38.57 | M117: =K117-E117 -> 8.39 | P117: =K117/E117-1 -> 0.27799867
C118: =+C117+1 -> 6 | E118: 14.18 | H118: 348 | J118: =+J117+1 -> 6 | K118: 18.12 | M118: =K118-E118 -> 3.94 | P118: =K118/E118-1 -> 0.27785614
C119: =+C118+1 -> 7 | E119: 15.97 | H119: 300 | J119: =+J118+1 -> 7 | K119: 20.41 | M119: =K119-E119 -> 4.44 | P119: =K119/E119-1 -> 0.27802129
C122: =+C119+1 -> 8 | E122: 11.75 | H122: 1580 | J122: =+J119+1 -> 8 | K122: 15.01 | M122: =K122-E122 -> 3.26 | P122: =K122/E122-1 -> 0.27744681
C123: =+C122+1 -> 9 | E123: 13.97 | H123: 996 | J123: =+J122+1 -> 9 | K123: 17.85 | M123: =K123-E123 -> 3.88 | P123: =K123/E123-1 -> 0.27773801
C124: =+C123+1 -> 10 | E124: 20.83 | H124: 96 | J124: =+J123+1 -> 10 | K124: 26.62 | M124: =K124-E124 -> 5.79 | P124: =K124/E124-1 -> 0.27796447
C125: =+C124+1 -> 11 | E125: 29.62 | H125: 72 | J125: =+J124+1 -> 11 | K125: 37.86 | M125: =K125-E125 -> 8.24 | P125: =K125/E125-1 -> 0.27819041
C126: =+C125+1 -> 12 | E126: 60.77 | H126: 516 | J126: =+J125+1 -> 12 | K126: 77.67 | M126: =K126-E126 -> 16.9 | P126: =K126/E126-1 -> 0.27809775
C127: =+C126+1 -> 13 | E127: 34.38 | H127: 3480 | J127: =+J126+1 -> 13 | K127: 43.94 | M127: =K127-E127 -> 9.56 | P127: =K127/E127-1 -> 0.27806864
C130: =+C127+1 -> 14 | E130: 16.6 | J130: =+J127+1 -> 14 | K130: 16.6 | M130: =K130-E130 -> 0 | P130: =K130/E130-1 -> 0
C131: =+C130+1 -> 15 | E131: 18.97 | J131: =+J130+1 -> 15 | K131: 18.97 | M131: =K131-E131 -> 0 | P131: =K131/E131-1 -> 0
C132: =+C131+1 -> 16 | E132: 23.44 | J132: =+J131+1 -> 16 | K132: 23.44 | M132: =K132-E132 -> 0 | P132: =K132/E132-1 -> 0
C133: =+C132+1 -> 17 | E133: 16.95 | J133: =+J132+1 -> 17 | K133: 16.95 | M133: =K133-E133 -> 0 | P133: =K133/E133-1 -> 0
C134: =+C133+1 -> 18 | E134: 19.61 | J134: =+J133+1 -> 18 | K134: 19.61 | M134: =K134-E134 -> 0 | P134: =K134/E134-1 -> 0
...

Sheet SDC
B3: Fitchburg Gas and Electric Light Company d/b/a Unitil
B4: Basic Service Customer Typical Bill Impacts - 2023 Distribution Rate Proposal
B5: Impact on SDC Rate Customers
I7: Current Rates | J7: Proposed Rates | L7: % | N7: Present Rates | O7: %
G8: Average | H8: % of | I8: Total | J8: Total | K8: Total | L8: Total | N8: Delivery | O8: Delivery
D9: Lumens | E9: Luminaire | G9: Monthly kWh | H9: Lights | I9: Revenue | J9: Revenue | K9: Difference | L9: Difference | N9: Revenue | O9: Difference
D11: Light Emitting Diode (LED):
C12: 1 | D12: 14408 | E12: LED XSPR BXSPRA 03FC | G12: 42.5 | H12: 0.10624049 | I12: =G12*$E$58 -> 16.15 | J12: =+G12*K$58 -> 16.84785 | K12: =J12-I12 -> 0.69785 | L12: =(J12/I12-1) -> 0.043210526 | N12: =+G12*$E$58-G12*$E$56 -> 7.391175 | O12: =+K12/N12 -> 0.094416652
C13: =+C12+1 -> 2 | D13: 3819 | E13: LED XSP2L BXSPA 03HL | G13: 8.9 | H13: 0.76651446 | I13: =G13*$E$58 -> 3.382 | J13: =+G13*K$58 -> 3.528138 | K13: =J13-I13 -> 0.146138 | L13: =(J13/I13-1) -> 0.043210526 | N13: =+G13*$E$58-G13*$E$56 -> 1.547799 | O13: =+K13/N13 -> 0.094416652
C14: =+C13+1 -> 3 | D14: 3500 | E14: MV 100 Watt Street and Highway | G14: 39.25 | H14: 0.000304414 | I14: =G14*$E$58 -> 14.915 | J14: =+G14*K$58 -> 15.559485 | K14: =J14-I14 -> 0.644485 | L14: =(J14/I14-1) -> 0.043210526 | N14: =+G14*$E$58-G14*$E$56 -> 6.8259675 | O14: =+K14/N14 -> 0.094416652
C15: 4 | D15: 3300 | E15: HP 50 Watt Street and Highway | G15: 20 | H15: 0.077016743 | I15: =G15*$E$58 -> 7.6 | J15: =+G15*K$58 -> 7.9284 | K15: =J15-I15 -> 0.3284 | L15: =(J15/I15-1) -> 0.043210526 | N15: =+G15*$E$58-G15*$E$56 -> 3.4782 | O15: =+K15/N15 -> 0.094416652
C16: 5 | D16: 9500 | E16: HP 100 Watt Street and Highway | G16: 40.25 | H16: 0.017656012 | I16: =G16*$E$58 -> 15.295 | J16: =+G16*K$58 -> 15.955905 | K16: =J16-I16 -> 0.660905 | L16: =(J16/I16-1) -> 0.043210526 | N16: =+G16*$E$58-G16*$E$56 -> 6.9998775 | O16: =+K16/N16 -> 0.094416652
C17: 6 | D17: 3300 | E17: ORNAMENTAL LIGHTING | G17: 20 | H17: 0.020700152 | I17: =G17*$E$58 -> 7.6 | J17: =+G17*K$58 -> 7.9284 | K17: =J17-I17 -> 0.3284 | L17: =(J17/I17-1) -> 0.043210526 | N17: =+G17*$E$58-G17*$E$56 -> 3.4782 | O17: =+K17/N17 -> 0.094416652
C18: 7 | D18: 50000 | E18: HP 400 Watt Street and Highway | G18: 161.25 | H18: 0.00091324201 | I18: =G18*$E$58 -> 61.275 | J18: =+G18*K$58 -> 63.922725 | K18: =J18-I18 -> 2.647725 | L18: =(J18/I18-1) -> 0.043210526 | N18: =+G18*$E$58-G18*$E$56 -> 28.042988 | O18: =+K18/N18 -> 0.094416652
C19: 8 | D19: 20000 | E19: HP 200 Watt Street and Highway | G19: 85 | H19: 0.01065449 | I19: =G19*$E$58 -> 32.3 | J19: =+G19*K$58 -> 33.6957 | K19: =J19-I19 -> 1.3957 | L19: =(J19/I19-1) -> 0.043210526 | N19: =+G19*$E$58-G19*$E$56 -> 14.78235 | O19: =+K19/N19 -> 0.094416652
B22: Current Rates: | I22: Proposed Rates:
E23: SDC | K23: SDC | L23: Difference **
B24: Delivery Charges: | I24: Delivery Charges:
B25: Customer Charge | E25: 0 | I25: =B25 -> Customer Charge | K25: 0 | L25: =+K25-E25 -> 0
E26: kWh | K26: kWh
B27: Internal Transmission | E27: =0.00318+0.00157 -> 0.00475 | I27: =B27 -> Internal Transmission | K27: =0.00318+0.00157 -> 0.00475 | L27: =+K27-E27 -> 0
B28: External Transmission | E28: 0.02796 | I28: =B28 -> External Transmission | K28: 0.02787 | L28: =+K28-E28 -> -9e-05
D29: Transmission Subtotal | E29: =SUM(E27:E28) -> 0.03271 | J29: Transmission Subtotal | K29: =SUM(K27:K28) -> 0.03262 | L29: =+K29-E29 -> -9e-05
B31: Distribution - Nov. 1, 2023 | E31: 0.06429 | I31: Distribution | K31: 0.09361 | L31: =+K31-E31 -> 0.02932
B33: Pension/PBOP Adjustment Factor | E33: 0.00975 | I33: Pension/PBOP Adjustment Factor | K33: 0.00975 | L33: =+K33-E33 -> 0
B34: Residential Assistance Adjustment Factor | E34: 0.01879 | I34: Residential Assistance Adjustment Factor | K34: 0.02116 | L34: =+K34-E34 -> 0.00237
B35: Net Metering Recovery Surcharge | E35: 0.01134 | I35: Net Metering Recovery Surcharge | K35: 0.01134 | L35: =+K35-E35 -> 0
B36: Revenue Decoupling Adjustment Factor | E36: 0.00129 | I36: Revenue Decoupling Adjustment Factor | K36: 0.00129 | L36: =+K36-E36 -> 0
B37: Attorney General Consultant Expense Factor | E37: 0.00039 | I37: Attorney General Consultant Expense Factor | K37: 0.00039 | L37: =+K37-E37 -> 0
B38: L-T Renewable Contract Adjustment Factor | E38: -0.00275 | I38: L-T Renewable Contract Adjustment Factor | K38: -0.00275 | L38: =+K38-E38 -> 0
B39: Capital Cost Adjustment Factor | E39: 0.01697 | I39: Capital Cost Adjustment Factor | K39: 0.0051 | L39: =+K39-E39 -> -0.01187
B40: Solar Cost Adjustment | E40: -0.00013 | I40: Solar Cost Adjustment | K40: -0.00086 | L40: =+K40-E40 -> -0.00073
B41: Grid Modernization Factor | E41: 0.00276 | I41: Grid Modernization Factor | K41: 0.00276 | L41: =+K41-E41 -> 0
B42: Basic Service Adjustment | E42: -0.0003 | I42: Basic Service Adjustment | K42: =+E42 -> -0.0003 | L42: =+K42-E42 -> 0
B43: Storm Reserve Adjustment Factor | E43: 0.00038 | I43: Storm Reserve Adjustment Factor | K43: 0.00038 | L43: =+K43-E43 -> 0
B44: Exogenous Cost Adjustment Factor | E44: 0.00143 | I44: Exogenous Cost Adjustment Factor | K44: 0.00143 | L44: =+K44-E44 -> 0
D45: Distribution Subtotal | E45: =SUM(E31:E44) -> 0.12421 | J45: Distribution Subtotal | K45: =SUM(K31:K44) -> 0.1433 | L45: =+K45-E45 -> 0.01909
B47: Renewable Resources Charge | E47: 0.0005 | I47: Renewable Resources Charge | K47: 0.0005 | L47: =+K47-E47 -> 0
B49: Energy Efficiency Charge | E49: 0.0025 | I49: Energy Efficiency Charge | K49: 0.0025 | L49: =+K49-E49 -> 0
B50: Energy Efficiency Reconciliation Factor | E50: 0.00972 | I50: Energy Efficiency Reconciliation Factor | K50: 0.00972 | L50: =+K50-E50 -> 0
D51: Total Energy Efficiency Charge Subtotal | E51: =SUM(E49:E50) -> 0.01222 | J51: Total Energy Efficiency Charge Subtotal | K51: =SUM(K49:K50) -> 0.01222 | L51: =+K51-E51 -> 0
B53: SMART Factor | E53: 0.00427 | I53: SMART Factor | K53: 0.0037 | L53: =+K53-E53 -> -0.00057
B55: Supplier Charges: | I55: Supplier Charges:
B56: Generation Charge* | E56: 0.20609 | I56: =B56 -> Generation Charge* | K56: 0.20408 | L56: =+K56-E56 -> -0.00201
D58: Total | E58: =SUM(E56,E47,E51,E53,E45,E29) -> 0.38 | J58: Total | K58: =SUM(K56,K47,K51,K53,K45,K29) -> 0.39642 | L58: =+K58-E58 -> 0.01642
B64: * August 1, 2023 Basic Service, Fixed including Basic Service Costs Adder of $0.00493/kWh at current and $0.00292/kWh at proposed. ** Includes changes in reconciliation mechanisms related to this distribution rate case proposal.
D70: delivery only | E70: =+E58-E56 -> 0.17391 | J70: delivery only | K70: =+K58-K56 -> 0.19234

Sheet Support Files --->
A1: Sheet intentionally blank.

Sheet ProForma Revenue
A1: Fitchburg Gas and Electric Light Company
A2: INCLUDED IN WORKPAPERS TO EXHIBIT UNITIL-JDT-3
A3: ProForma Revenue
A4: This sheet partially redacted.
A6: [A] | B6: [B] | C6: [C] | D6: [D] | E6: [E] | G6: [F] | H6: [G] | J6: [H] | K6: [I] | M6: [J] | N6: [K] | P6: [L] | Q6: [M]
A7: Line No. | B7: Description | C7: 2022 Billing Determinants | D7: 2022 Rates | E7: Revenue at 2022 Rates | G7: TY Billing Determinants | H7: TY Lighting Revenue Adjustment | J7: Rates Effective Jan. 1, 2023 | K7: Jan. 1, 2023 Annualization Adjustment | M7: Rates Effective Nov. 1, 2023 | N7: Nov. 1, 2023 Annualization Adjustment | P7: Test Year Revenue Adjustment | Q7: Test Year Revenue
E8: =C6&" x "&D6 -> [C] x [D] | H8: ="("&G6&"-"&C6&") x "&$D6 -> ([F]-[C]) x [D] | K8: ="("&J6&"-"&D6&") x "&$G6 -> ([H]-[D]) x [F] | N8: ="("&M6&"-"&J6&") x "&$G6 -> ([J]-[H]) x [F] | P8: =H6&" + "&K6&" + "&N6 -> [G] + [I] + [K] | Q8: =E6&" + "&P6 -> [E] + [L]
A9: =IF(AND(B9="",E9=""),"",MAX(A$7:A7)+1) -> 1 | B9: RD-1: Residential
A10: =IF(AND(B10="",E10=""),"",MAX(A$7:A9)+1) -> 2 | B10: Customer Charge | C10: =SUMIFS(Rev_Billing_Det!$C$180:$C$186,Rev_Billing_Det!$A$180:$A$186,LEFT($B9,4)) -> 254959.9 | D10: =INDEX('Rates and Eff Dates'!$C$9:$C$17,MATCH(LEFT($B9,4),'Rates and Eff Dates'!$A$9:$A$17,0)) -> 7 | E10: =D10*C10 -> 1784719.3 | G10: =C10 -> 254959.9 | H10: =ROUND((G10-C10)*D10,2) -> 0 | J10: =INDEX('Rates and Eff Dates'!$C$24:$C$32,MATCH(LEFT($B9,4),'Rates and Eff Dates'!$A$24:$A$32,0)) -> 7 | K10: =(J10-D10)*$G10 -> 0 | M10: =INDEX('Rates and Eff Dates'!$C$39:$C$47,MATCH(LEFT($B9,4),'Rates and Eff Dates'!$A$39:$A$47,0)) -> 7 | N10: =(M10-J10)*$G10 -> 0 | P10: =H10+K10+N10 -> 0 | Q10: =E10+P10 -> 1784719.3 | S10: RD-1: Residential
A11: =IF(AND(B11="",E11=""),"",MAX(A$7:A10)+1) -> 3 | B11: Distribution Charge | C11: =SUMIFS(Rev_Billing_Det!$E$180:$E$186,Rev_Billing_Det!$A$180:$A$186,LEFT($B9,4)) -> 137275588 | D11: =INDEX('Rates and Eff Dates'!$D$9:$D$17,MATCH(LEFT($B9,4),'Rates and Eff Dates'!$A$9:$A$17,0)) -> 0.07752 | E11: =D11*C11 -> 10641604 | G11: =C11 -> 137275588 | H11: =ROUND((G11-C11)*D11,2) -> 0 | J11: =INDEX('Rates and Eff Dates'!$D$24:$D$32,MATCH(LEFT($B9,4),'Rates and Eff Dates'!$A$24:$A$32,0)) -> 0.07976 | K11: =(J11-D11)*$G11 -> 307497.32 | M11: =INDEX('Rates and Eff Dates'!$D$39:$D$47,MATCH(LEFT($B9,4),'Rates and Eff Dates'!$A$39:$A$47,0)) -> 0.07903 | N11: =(M11-J11)*$G11 -> -100211.18 | P11: =H11+K11+N11 -> 207286.14 | Q11: =E11+P11 -> 10848890 | S11: RD-1: Residential
A12: =IF(AND(B12="",E12=""),"",MAX(A$7:A11)+1) -> 4 | E12: =SUBTOTAL(9,E10:E11) -> 12426323 | H12: =SUBTOTAL(9,H10:H11) -> 0 | K12: =SUBTOTAL(9,K10:K11) -> 307497.32 | N12: =SUBTOTAL(9,N10:N11) -> -100211.18 | P12: =SUBTOTAL(9,P10:P11) -> 207286.14 | Q12: =SUBTOTAL(9,Q10:Q11) -> 12633609 | S12: =SUMPRODUCT(C10:C11,M10:M11) -> 12633609 | T12: =Q12=S12 -> TRUE
A13: =IF(AND(B13="",E13=""),"",MAX(A$7:A12)+1)
A14: =IF(AND(B14="",E14=""),"",MAX(A$7:A13)+1) -> 5 | B14: RD-2: Residential, Low Income
A15: =IF(AND(B15="",E15=""),"",MAX(A$7:A14)+1) -> 6 | B15: Customer Charge | C15: =SUMIFS(Rev_Billing_Det!$C$180:$C$186,Rev_Billing_Det!$A$180:$A$186,LEFT($B14,4)) -> 61437.474 | D15: =INDEX('Rates and Eff Dates'!$C$9:$C$17,MATCH(LEFT($B14,4),'Rates and Eff Dates'!$A$9:$A$17,0)) -> 7 | E15: =D15*C15 -> 430062.32 | G15: =C15 -> 61437.474 | H15: =ROUND((G15-C15)*D15,2) -> 0 | J15: =INDEX('Rates and Eff Dates'!$C$24:$C$32,MATCH(LEFT($B14,4),'Rates and Eff Dates'!$A$24:$A$32,0)) -> 7 | K15: =(J15-D15)*$G15 -> 0 | M15: =INDEX('Rates and Eff Dates'!$C$39:$C$47,MATCH(LEFT($B14,4),'Rates and Eff Dates'!$A$39:$A$47,0)) -> 7 | N15: =(M15-J15)*$G15 -> 0 | P15: =H15+K15+N15 -> 0 | Q15: =E15+P15 -> 430062.32 | S15: RD-2: Residential, Low Income
A16: =IF(AND(B16="",E16=""),"",MAX(A$7:A15)+1) -> 7 | B16: Distribution Charge | C16: =SUMIFS(Rev_Billing_Det!$E$180:$E$186,Rev_Billing_Det!$A$180:$A$186,LEFT($B14,4)) -> 35064508 | D16: =INDEX('Rates and Eff Dates'!$D$9:$D$17,MATCH(LEFT($B14,4),'Rates and Eff Dates'!$A$9:$A$17,0)) -> 0.07752 | E16: =D16*C16 -> 2718200.7 | G16: =C16 -> 35064508 | H16: =ROUND((G16-C16)*D16,2) -> 0 | J16: =INDEX('Rates and Eff Dates'!$D$24:$D$32,MATCH(LEFT($B14,4),'Rates and Eff Dates'!$A$24:$A$32,0)) -> 0.07976 | K16: =(J16-D16)*$G16 -> 78544.498 | M16: =INDEX('Rates and Eff Dates'!$D$39:$D$47,MATCH(LEFT($B14,4),'Rates and Eff Dates'!$A$39:$A$47,0)) -> 0.07903 | N16: =(M16-J16)*$G16 -> -25597.091 | P16: =H16+K16+N16 -> 52947.407 | Q16: =E16+P16 -> 2771148.1 | S16: RD-2: Residential, Low Income
A17: =IF(AND(B17="",E17=""),"",MAX(A$7:A16)+1) -> 8 | E17: =SUBTOTAL(9,E15:E16) -> 3148263 | H17: =SUBTOTAL(9,H15:H16) -> 0 | K17: =SUBTOTAL(9,K15:K16) -> 78544.498 | N17: =SUBTOTAL(9,N15:N16) -> -25597.091 | P17: =SUBTOTAL(9,P15:P16) -> 52947.407 | Q17: =SUBTOTAL(9,Q15:Q16) -> 3201210.4 | S17: =SUMPRODUCT(C15:C16,M15:M16) -> 3201210.4 | T17: =Q17=S17 -> TRUE
A18: =IF(AND(B18="",E18=""),"",MAX(A$7:A17)+1)
A19: =IF(AND(B19="",E19=""),"",MAX(A$7:A18)+1) -> 9 | B19: GD-1: Small General
A20: =IF(AND(B20="",E20=""),"",MAX(A$7:A19)+1) -> 10 | B20: Customer Charge | C20: =SUMIFS(Rev_Billing_Det!$C$180:$C$186,Rev_Billing_Det!$A$180:$A$186,LEFT($B19,4)) -> 30492.186 | D20: =INDEX('Rates and Eff Dates'!$C$9:$C$17,MATCH(LEFT($B19,4),'Rates and Eff Dates'!$A$9:$A$17,0)) -> 10 | E20: =D20*C20 -> 304921.86 | G20: =C20 -> 30492.186 | H20: =ROUND((G20-C20)*D20,2) -> 0 | J20: =INDEX('Rates and Eff Dates'!$C$24:$C$32,MATCH(LEFT($B19,4),'Rates and Eff Dates'!$A$24:$A$32,0)) -> 10 | K20: =(J20-D20)*$G20 -> 0 | M20: =INDEX('Rates and Eff Dates'!$C$39:$C$47,MATCH(LEFT($B19,4),'Rates and Eff Dates'!$A$39:$A$47,0)) -> 10 | N20: =(M20-J20)*$G20 -> 0 | P20: =H20+K20+N20 -> 0 | Q20: =E20+P20 -> 304921.86 | S20: GD-1: Small General
A21: =IF(AND(B21="",E21=""),"",MAX(A$7:A20)+1) -> 11 | B21: Distribution Charge | C21: =SUMIFS(Rev_Billing_Det!$E$180:$E$186,Rev_Billing_Det!$A$180:$A$186,LEFT($B19,4)) -> 5912347 | D21: =INDEX('Rates and Eff Dates'!$D$9:$D$17,MATCH(LEFT($B19,4),'Rates and Eff Dates'!$A$9:$A$17,0)) -> 0.07701 | E21: =D21*C21 -> 455309.84 | G21: =C21 -> 5912347 | H21: =ROUND((G21-C21)*D21,2) -> 0 | J21: =INDEX('Rates and Eff Dates'!$D$24:$D$32,MATCH(LEFT($B19,4),'Rates and Eff Dates'!$A$24:$A$32,0)) -> 0.07923 | K21: =(J21-D21)*$G21 -> 13125.41 | M21: =INDEX('Rates and Eff Dates'!$D$39:$D$47,MATCH(LEFT($B19,4),'Rates and Eff Dates'!$A$39:$A$47,0)) -> 0.0785 | N21: =(M21-J21)*$G21 -> -4316.0133 | P21: =H21+K21+N21 -> 8809.397 | Q21: =E21+P21 -> 464119.24 | S21: GD-1: Small General
A22: =IF(AND(B22="",E22=""),"",MAX(A$7:A21)+1) -> 12 | E22: =SUBTOTAL(9,E20,E21) -> 760231.7 | H22: =SUBTOTAL(9,H20,H21) -> 0 | K22: =SUBTOTAL(9,K20:K21) -> 13125.41 | N22: =SUBTOTAL(9,N20:N21) -> -4316.0133 | P22: =SUBTOTAL(9,P20:P21) -> 8809.397 | Q22: =SUBTOTAL(9,Q20:Q21) -> 769041.1 | S22: =SUMPRODUCT(C20:C21,M20:M21) -> 769041.1 | T22: =Q22=S22 -> TRUE
A23: =IF(AND(B23="",E23=""),"",MAX(A$7:A22)+1)
A24: =IF(AND(B24="",E24=""),"",MAX(A$7:A23)+1) -> 13 | B24: GD-2: Regular General
A25: =IF(AND(B25="",E25=""),"",MAX(A$7:A24)+1) -> 14 | B25: Customer Charge | C25: =SUMIFS(Rev_Billing_Det!$C$180:$C$186,Rev_Billing_Det!$A$180:$A$186,LEFT($B24,4)) -> 18164.621 | D25: =INDEX('Rates and Eff Dates'!$C$9:$C$17,MATCH(LEFT($B24,4),'Rates and Eff Dates'!$A$9:$A$17,0)) -> 10 | E25: =C25*D25 -> 181646.21 | G25: =C25 -> 18164.621 | H25: =ROUND((G25-C25)*D25,2) -> 0 | J25: =INDEX('Rates and Eff Dates'!$C$24:$C$32,MATCH(LEFT($B24,4),'Rates and Eff Dates'!$A$24:$A$32,0)) -> 10 | K25: =(J25-D25)*$G25 -> 0 | M25: =INDEX('Rates and Eff Dates'!$C$39:$C$47,MATCH(LEFT($B24,4),'Rates and Eff Dates'!$A$39:$A$47,0)) -> 10 | N25: =(M25-J25)*$G25 -> 0 | P25: =H25+K25+N25 -> 0 | Q25: =E25+P25 -> 181646.21 | S25: GD-2: Regular General
A26: =IF(AND(B26="",E26=""),"",MAX(A$7:A25)+1) -> 15 | B26: Distribution Charge | C26: =SUMIFS(Rev_Billing_Det!$E$180:$E$186,Rev_Billing_Det!$A$180:$A$186,LEFT($B24,4)) -> 86826989 | D26: =INDEX('Rates and Eff Dates'!$D$9:$D$17,MATCH(LEFT($B24,4),'Rates and Eff Dates'!$A$9:$A$17,0)) -> 0.02326 | E26: =C26*D26 -> 2019595.8 | G26: =C26 -> 86826989 | H26: =ROUND((G26-C26)*D26,2) -> 0 | J26: =INDEX('Rates and Eff Dates'!$D$24:$D$32,MATCH(LEFT($B24,4),'Rates and Eff Dates'!$A$24:$A$32,0)) -> 0.02396 | K26: =(J26-D26)*$G26 -> 60778.892 | M26: =INDEX('Rates and Eff Dates'!$D$39:$D$47,MATCH(LEFT($B24,4),'Rates and Eff Dates'!$A$39:$A$47,0)) -> 0.02377 | N26: =(M26-J26)*$G26 -> -16497.128 | P26: =H26+K26+N26 -> 44281.764 | Q26: =E26+P26 -> 2063877.5 | S26: GD-2: Regular General
A27: =IF(AND(B27="",E27=""),"",MAX(A$7:A26)+1) -> 16 | B27: Demand Charge | C27: =SUMIFS(Rev_Billing_Det!$M$180:$M$186,Rev_Billing_Det!$A$180:$A$186,LEFT($B24,4)) -> 323618.5 | D27: =INDEX('Rates and Eff Dates'!$F$9:$F$17,MATCH(LEFT($B24,4),'Rates and Eff Dates'!$A$9:$A$17,0)) -> 9.64 | E27: =C27*D27 -> 3119682.3 | G27: =C27 -> 323618.5 | H27: =ROUND((G27-C27)*D27,2) -> 0 | J27: =INDEX('Rates and Eff Dates'!$F$24:$F$32,MATCH(LEFT($B24,4),'Rates and Eff Dates'!$A$24:$A$32,0)) -> 9.91 | K27: =(J27-D27)*$G27 -> 87376.995 | M27: =INDEX('Rates and Eff Dates'!$F$39:$F$47,MATCH(LEFT($B24,4),'Rates and Eff Dates'!$A$39:$A$47,0)) -> 9.81 | N27: =(M27-J27)*$G27 -> -32361.85 | P27: =H27+K27+N27 -> 55015.145 | Q27: =E27+P27 -> 3174697.5 | S27: GD-2: Regular General
A28: =IF(AND(B28="",E28=""),"",MAX(A$7:A27)+1) -> 17 | B28: Transformer Credit | C28: =E28/D28 -> 24209.105 | D28: -0.19 | E28: =Rev_Billing_Det!D208 -> -4599.73 | G28: =C28 -> 24209.105 | H28: =ROUND((G28-C28)*D28,2) -> 0 | J28: =D28 -> -0.19 | K28: =(J28-D28)*$G28 -> 0 | M28: =D28 -> -0.19 | N28: =(M28-J28)*$G28 -> 0 | P28: =H28+K28+N28 -> 0 | Q28: =E28+P28 -> -4599.73
A29: =IF(AND(B29="",E29=""),"",MAX(A$7:A28)+1) -> 18 | E29: =SUBTOTAL(9,E25:E28) -> 5316324.6 | H29: =SUBTOTAL(9,H25:H28) -> 0 | K29: =SUBTOTAL(9,K25:K28) -> 148155.89 | N29: =SUBTOTAL(9,N25:N28) -> -48858.978 | P29: =SUBTOTAL(9,P25:P28) -> 99296.909 | Q29: =SUBTOTAL(9,Q25:Q28) -> 5415621.5 | S29: =SUMPRODUCT(C24:C27,M24:M27)+Q28 -> 5415621.5 | T29: =Q29=S29 -> TRUE
A30: =IF(AND(B30="",E30=""),"",MAX(A$7:A29)+1)
A31: =IF(AND(B31="",E31=""),"",MAX(A$7:A30)+1) -> 19 | B31: GD-3: Large General
A32: =IF(AND(B32="",E32=""),"",MAX(A$7:A31)+1) -> 20 | B32: Customer Charge | C32: =SUMIFS(Rev_Billing_Det!$C$180:$C$186,Rev_Billing_Det!$A$180:$A$186,LEFT($B31,4)) -> 339 | D32: =INDEX('Rates and Eff Dates'!$C$9:$C$17,MATCH(LEFT($B31,4),'Rates and Eff Dates'!$A$9:$A$17,0)) -> 300 | E32: =C32*D32 -> 101700 | G32: =C32 -> 339 | H32: =ROUND((G32-C32)*D32,2) -> 0 | J32: =INDEX('Rates and Eff Dates'!$C$24:$C$32,MATCH(LEFT($B31,4),'Rates and Eff Dates'!$A$24:$A$32,0)) -> 300 | K32: =(J32-D32)*$G32 -> 0 | M32: =INDEX('Rates and Eff Dates'!$C$39:$C$47,MATCH(LEFT($B31,4),'Rates and Eff Dates'!$A$39:$A$47,0)) -> 300 | N32: =(M32-J32)*$G32 -> 0 | P32: =H32+K32+N32 -> 0 | Q32: =E32+P32 -> 101700 | S32: GD-3: Large General
A33: =IF(AND(B33="",E33=""),"",MAX(A$7:A32)+1) -> 21 | B33: On Peak Billed kWh | C33: =SUMIFS(Rev_Billing_Det!$E$180:$E$186,Rev_Billing_Det!$A$180:$A$186,LEFT($B31,4)) -> 50297243 | D33: =INDEX('Rates and Eff Dates'!$D$9:$D$17,MATCH(LEFT($B31,4),'Rates and Eff Dates'!$A$9:$A$17,0)) -> 0.01909 | E33: =C33*D33 -> 960174.37 | G33: =C33 -> 50297243 | H33: =ROUND((G33-C33)*D33,2) -> 0 | J33: =INDEX('Rates and Eff Dates'!$D$24:$D$32,MATCH(LEFT($B31,4),'Rates and Eff Dates'!$A$24:$A$32,0)) -> 0.01968 | K33: =(J33-D33)*$G33 -> 29675.373 | M33: =INDEX('Rates and Eff Dates'!$D$39:$D$47,MATCH(LEFT($B31,4),'Rates and Eff Dates'!$A$39:$A$47,0)) -> 0.01952 | N33: =(M33-J33)*$G33 -> -8047.5589 | P33: =H33+K33+N33 -> 21627.814 | Q33: =E33+P33 -> 981802.18 | S33: GD-3: Large General
A34: =IF(AND(B34="",E34=""),"",MAX(A$7:A33)+1) -> 22 | B34: Off Peak Billed kWh | C34: =SUMIFS(Rev_Billing_Det!$F$180:$F$186,Rev_Billing_Det!$A$180:$A$186,LEFT($B31,4)) -> 77729812 | D34: =INDEX('Rates and Eff Dates'!$E$9:$E$17,MATCH(LEFT($B31,4),'Rates and Eff Dates'!$A$9:$A$17,0)) -> 0.00426 | E34: =C34*D34 -> 331129 | G34: =C34 -> 77729812 | H34: =ROUND((G34-C34)*D34,2) -> 0 | J34: =INDEX('Rates and Eff Dates'!$E$24:$E$32,MATCH(LEFT($B31,4),'Rates and Eff Dates'!$A$24:$A$32,0)) -> 0.00439 | K34: =(J34-D34)*$G34 -> 10104.876 | M34: =INDEX('Rates and Eff Dates'!$E$39:$E$47,MATCH(LEFT($B31,4),'Rates and Eff Dates'!$A$39:$A$47,0)) -> 0.00435 | N34: =(M34-J34)*$G34 -> -3109.1925 | P34: =H34+K34+N34 -> 6995.6831 | Q34: =E34+P34 -> 338124.68 | S34: GD-3: Large General
A35: =IF(AND(B35="",E35=""),"",MAX(A$7:A34)+1) -> 23 | B35: Demand Charge | C35: =SUMIFS(Rev_Billing_Det!$M$180:$M$186,Rev_Billing_Det!$A$180:$A$186,LEFT($B31,4)) -> 296936 | D35: =INDEX('Rates and Eff Dates'!$F$9:$F$17,MATCH(LEFT($B31,4),'Rates and Eff Dates'!$A$9:$A$17,0)) -> 7.93 | E35: =C35*D35 -> 2354702.5 | G35: =C35 -> 296936 | H35: =ROUND((G35-C35)*D35,2) -> 0 | J35: =INDEX('Rates and Eff Dates'!$F$24:$F$32,MATCH(LEFT($B31,4),'Rates and Eff Dates'!$A$24:$A$32,0)) -> 8.15 | K35: =(J35-D35)*$G35 -> 65325.92 | M35: =INDEX('Rates and Eff Dates'!$F$39:$F$47,MATCH(LEFT($B31,4),'Rates and Eff Dates'!$A$39:$A$47,0)) -> 8.07 | N35: =(M35-J35)*$G35 -> -23754.88 | P35: =H35+K35+N35 -> 41571.04 | Q35: =E35+P35 -> 2396273.5 | S35: GD-3: Large General
A36: =IF(AND(B36="",E36=""),"",MAX(A$7:A35)+1) -> 24 | E36: =SUBTOTAL(9,E32:E35) -> 3747705.8 | H36: =SUBTOTAL(9,H32:H35) -> 0 | K36: =SUBTOTAL(9,K32:K35) -> 105106.17 | N36: =SUBTOTAL(9,N32:N35) -> -34911.631 | P36: =SUBTOTAL(9,P32:P35) -> 70194.538 | Q36: =SUBTOTAL(9,Q32:Q35) -> 3817900.4 | S36: =SUMPRODUCT(C32:C35,M32:M35) -> 3817900.4 | T36: =Q36=S36 -> TRUE
A37: =IF(AND(B37="",E37=""),"",MAX(A$7:A36)+1)
A38: =IF(AND(B38="",E38=""),"",MAX(A$7:A37)+1) -> 25 | B38: GD-4: Regular General Optional TOU
A39: =IF(AND(B39="",E39=""),"",MAX(A$7:A38)+1) -> 26 | B39: Customer Charge | C39: =SUMIFS(Rev_Billing_Det!$C$180:$C$186,Rev_Billing_Det!$A$180:$A$186,LEFT($B38,4)) -> 33 | D39: =INDEX('Rates and Eff Dates'!$C$9:$C$17,MATCH(LEFT($B38,4),'Rates and Eff Dates'!$A$9:$A$17,0)) -> 10 | E39: =C39*D39 -> 330 | G39: =C39 -> 33 | H39: =ROUND((G39-C39)*D39,2) -> 0 | J39: =INDEX('Rates and Eff Dates'!$C$24:$C$32,MATCH(LEFT($B38,4),'Rates and Eff Dates'!$A$24:$A$32,0)) -> 10 | K39: =(J39-D39)*$G39 -> 0 | M39: =INDEX('Rates and Eff Dates'!$C$39:$C$47,MATCH(LEFT($B38,4),'Rates and Eff Dates'!$A$39:$A$47,0)) -> 10 | N39: =(M39-J39)*$G39 -> 0 | P39: =H39+K39+N39 -> 0 | Q39: =E39+P39 -> 330 | S39: GD-4: Regular General Optional TOU
A40: =IF(AND(B40="",E40=""),"",MAX(A$7:A39)+1) -> 27 | B40: On Peak Billed kWh | C40: =SUMIFS(Rev_Billing_Det!$E$180:$E$186,Rev_Billing_Det!$A$180:$A$186,LEFT($B38,4)) -> 54449 | D40: =INDEX('Rates and Eff Dates'!$D$9:$D$17,MATCH(LEFT($B38,4),'Rates and Eff Dates'!$A$9:$A$17,0)) -> 0.01003 | E40: =C40*D40 -> 546.12347 | G40: =C40 -> 54449 | H40: =ROUND((G40-C40)*D40,2) -> 0 | J40: =INDEX('Rates and Eff Dates'!$D$24:$D$32,MATCH(LEFT($B38,4),'Rates and Eff Dates'!$A$24:$A$32,0)) -> 0.01033 | K40: =(J40-D40)*$G40 -> 16.3347 | M40: =INDEX('Rates and Eff Dates'!$D$39:$D$47,MATCH(LEFT($B38,4),'Rates and Eff Dates'!$A$39:$A$47,0)) -> 0.01027 | N40: =(M40-J40)*$G40 -> -3.26694 | P40: =H40+K40+N40 -> 13.06776 | Q40: =E40+P40 -> 559.19123 | S40: GD-4: Regular General Optional TOU
A41: =IF(AND(B41="",E41=""),"",MAX(A$7:A40)+1) -> 28 | B41: Off Peak Billed kWh | C41: =SUMIFS(Rev_Billing_Det!$F$180:$F$186,Rev_Billing_Det!$A$180:$A$186,LEFT($B38,4)) -> 241496 | D41: =INDEX('Rates and Eff Dates'!$E$9:$E$17,MATCH(LEFT($B38,4),'Rates and Eff Dates'!$A$9:$A$17,0)) -> 0.00219 | E41: =C41*D41 -> 528.87624 | G41: =C41 -> 241496 | H41: =ROUND((G41-C41)*D41,2) -> 0 | J41: =INDEX('Rates and Eff Dates'!$E$24:$E$32,MATCH(LEFT($B38,4),'Rates and Eff Dates'!$A$24:$A$32,0)) -> 0.00225 | K41: =(J41-D41)*$G41 -> 14.48976 | M41: =INDEX('Rates and Eff Dates'!$E$39:$E$47,MATCH(LEFT($B38,4),'Rates and Eff Dates'!$A$39:$A$47,0)) -> 0.00223 | N41: =(M41-J41)*$G41 -> -4.82992 | P41: =H41+K41+N41 -> 9.65984 | Q41: =E41+P41 -> 538.53608 | S41: GD-4: Regular General Optional TOU
A42: =IF(AND(B42="",E42=""),"",MAX(A$7:A41)+1) -> 29 | B42: Demand Charge | C42: =SUMIFS(Rev_Billing_Det!$M$180:$M$186,Rev_Billing_Det!$A$180:$A$186,LEFT($B38,4)) -> 1329.5 | D42: =INDEX('Rates and Eff Dates'!$F$9:$F$17,MATCH(LEFT($B38,4),'Rates and Eff Dates'!$A$9:$A$17,0)) -> 3.85 | E42: =C42*D42 -> 5118.575 | G42: =C42 -> 1329.5 | H42: =ROUND((G42-C42)*D42,2) -> 0 | J42: =INDEX('Rates and Eff Dates'!$F$24:$F$32,MATCH(LEFT($B38,4),'Rates and Eff Dates'!$A$24:$A$32,0)) -> 3.96 | K42: =(J42-D42)*$G42 -> 146.245 | M42: =INDEX('Rates and Eff Dates'!$F$39:$F$47,MATCH(LEFT($B38,4),'Rates and Eff Dates'!$A$39:$A$47,0)) -> 3.92 | N42: =(M42-J42)*$G42 -> -53.18 | P42: =H42+K42+N42 -> 93.065 | Q42: =E42+P42 -> 5211.64
A43: =IF(AND(B43="",E43=""),"",MAX(A$7:A42)+1) -> 30 | B43: Transformer Credit | C43: =E43/D43 -> 1162.6316 | D43: -0.19 | E43: =Rev_Billing_Det!E208 -> -220.9 | G43: =C43 -> 1162.6316 | H43: =ROUND((G43-C43)*D43,2) -> 0 | J43: =D43 -> -0.19 | K43: =(J43-D43)*$G43 -> 0 | M43: =D43 -> -0.19 | N43: =(M43-J43)*$G43 -> 0 | P43: =H43+K43+N43 -> 0 | Q43: =E43+P43 -> -220.9
A44: =IF(AND(B44="",E44=""),"",MAX(A$7:A43)+1) -> 31 | E44: =SUBTOTAL(9,E39:E43) -> 6302.6747 | H44: =SUBTOTAL(9,H39:H43) -> 0 | K44: =SUBTOTAL(9,K39:K43) -> 177.06946 | N44: =SUBTOTAL(9,N39:N43) -> -61.27686 | P44: =SUBTOTAL(9,P39:P43) -> 115.7926 | Q44: =SUBTOTAL(9,Q39:Q43) -> 6418.4673 | S44: =SUMPRODUCT(C39:C42,M39:M42)+Q43 -> 6418.4673 | T44: =Q44=S44 -> TRUE
A45: =IF(AND(B45="",E45=""),"",MAX(A$7:A44)+1)
A46: =IF(AND(B46="",E46=""),"",MAX(A$7:A45)+1) -> 32 | B46: GD-5: Water and/or Space Heating Rider
A47: =IF(AND(B47="",E47=""),"",MAX(A$7:A46)+1) -> 33 | B47: Customer Charge | C47: =SUMIFS(Rev_Billing_Det!$C$180:$C$186,Rev_Billing_Det!$A$180:$A$186,LEFT($B46,4)) -> 78 | D47: =INDEX('Rates and Eff Dates'!$C$9:$C$17,MATCH(LEFT($B46,4),'Rates and Eff Dates'!$A$9:$A$17,0)) -> 0 | E47: =D47*C47 -> 0 | G47: =C47 -> 78 | H47: =ROUND((G47-C47)*D47,2) -> 0 | J47: =INDEX('Rates and Eff Dates'!$C$24:$C$32,MATCH(LEFT($B46,4),'Rates and Eff Dates'!$A$24:$A$32,0)) -> 0 | K47: =(J47-D47)*$G47 -> 0 | M47: =INDEX('Rates and Eff Dates'!$C$39:$C$47,MATCH(LEFT($B46,4),'Rates and Eff Dates'!$A$39:$A$47,0)) -> 0 | N47: =(M47-J47)*$G47 -> 0 | P47: =H47+K47+N47 -> 0 | Q47: =E47+P47 -> 0 | S47: GD-5: Water and/or Space Heating Rider
A48: =IF(AND(B48="",E48=""),"",MAX(A$7:A47)+1) -> 34 | B48: Distribution Charge | C48: =SUMIFS(Rev_Billing_Det!$E$180:$E$186,Rev_Billing_Det!$A$180:$A$186,LEFT($B46,4)) -> 343192 | D48: =INDEX('Rates and Eff Dates'!$D$9:$D$17,MATCH(LEFT($B46,4),'Rates and Eff Dates'!$A$9:$A$17,0)) -> 0.05956 | E48: =D48*C48 -> 20440.516 | G48: =C48 -> 343192 | H48: =ROUND((G48-C48)*D48,2) -> 0 | J48: =INDEX('Rates and Eff Dates'!$D$24:$D$32,MATCH(LEFT($B46,4),'Rates and Eff Dates'!$A$24:$A$32,0)) -> 0.06128 | K48: =(J48-D48)*$G48 -> 590.29024 | M48: =INDEX('Rates and Eff Dates'!$D$39:$D$47,MATCH(LEFT($B46,4),'Rates and Eff Dates'!$A$39:$A$47,0)) -> 0.06071 | N48: =(M48-J48)*$G48 -> -195.61944 | P48: =H48+K48+N48 -> 394.6708 | Q48: =E48+P48 -> 20835.186 | S48: GD-5: Water and/or Space Heating Rider
A49: =IF(AND(B49="",E49=""),"",MAX(A$7:A48)+1) -> 35 | E49: =SUBTOTAL(9,E47:E48) -> 20440.516 | H49: =SUBTOTAL(9,H47:H48) -> 0 | K49: =SUBTOTAL(9,K47:K48) -> 590.29024 | N49: =SUBTOTAL(9,N47:N48) -> -195.61944 | P49: =SUBTOTAL(9,P47:P48) -> 394.6708 | Q49: =SUBTOTAL(9,Q47:Q48) -> 20835.186 | S49: =SUMPRODUCT(C45:C48,M45:M48) -> 20835.186 | T49: =Q49=S49 -> TRUE
A50: =IF(AND(B50="",E50=""),"",MAX(A$7:A49)+1)
A51: =IF(AND(B51="",E51=""),"",MAX(A$7:A50)+1) -> 36 | B51: SD: Outdoor Lighting - Company Owned
A52: =IF(AND(B52="",E52=""),"",MAX(A$7:A51)+1) -> 37 | B52: ='Rates and Eff Dates'!A52 -> Mercury Vapor Luminaires | C52: Fixture Count
A53: =IF(AND(B53="",E53=""),"",MAX(A$7:A52)+1) -> 38 | B53: ='Rates and Eff Dates'!B53 -> MV-3500 Street and Highway Type | C53: =INDEX('Outdoor Lighting Update'!I:I,MATCH($B53,'Outdoor Lighting Update'!O:O,0)) -> 59.266366 | D53: =INDEX('Rates and Eff Dates'!C:C,MATCH($B53,'Rates and Eff Dates'!$B:$B,0)) -> 13.29 | E53: =C53*D53 -> 787.65 | G53: =ROUND(INDEX('Atrium + Updated Rates'!$E:$E,MATCH($B53,'Atrium + Updated Rates'!$O:$O,0)),0) -> 48 | H53: =ROUND((G53-C53)*D53,2) -> -149.73 | J53: =INDEX('Rates and Eff Dates'!D:D,MATCH($B53,'Rates and Eff Dates'!$B:$B,0)) -> 13.67 | K53: =(J53-D53)*$G53 -> 18.24 | M53: =INDEX('Rates and Eff Dates'!E:E,MATCH($B53,'Rates and Eff Dates'!$B:$B,0)) -> 13.54 | N53: =(M53-J53)*$G53 -> -6.24 | P53: =H53+K53+N53 -> -137.73 | Q53: =E53+P53 -> 649.92
A54: =IF(AND(B54="",E54=""),"",MAX(A$7:A53)+1) -> 39 | B54: ='Rates and Eff Dates'!B54 -> MV-7000 Street and Highway Type | C54: =INDEX('Outdoor Lighting Update'!I:I,MATCH($B54,'Outdoor Lighting Update'!O:O,0)) -> 84 | D54: =INDEX('Rates and Eff Dates'!C:C,MATCH($B54,'Rates and Eff Dates'!$B:$B,0)) -> 14.74 | E54: =C54*D54 -> 1238.16 | G54: =ROUND(INDEX('Atrium + Updated Rates'!$E:$E,MATCH($B54,'Atrium + Updated Rates'!$O:$O,0)),0) -> 84 | H54: =ROUND((G54-C54)*D54,2) -> 0 | J54: =INDEX('Rates and Eff Dates'!D:D,MATCH($B54,'Rates and Eff Dates'!$B:$B,0)) -> 15.16 | K54: =(J54-D54)*$G54 -> 35.28 | M54: =INDEX('Rates and Eff Dates'!E:E,MATCH($B54,'Rates and Eff Dates'!$B:$B,0)) -> 15.02 | N54: =(M54-J54)*$G54 -> -11.76 | P54: =H54+K54+N54 -> 23.52 | Q54: =E54+P54 -> 1261.68
A55: =IF(AND(B55="",E55=""),"",MAX(A$7:A54)+1) -> 40 | B55: ='Rates and Eff Dates'!B55 -> MV-20000 Street and Highway Type | C55: =INDEX('Outdoor Lighting Update'!I:I,MATCH($B55,'Outdoor Lighting Update'!O:O,0)) -> 0 | D55: =INDEX('Rates and Eff Dates'!C:C,MATCH($B55,'Rates and Eff Dates'!$B:$B,0)) -> 26.78 | E55: =C55*D55 -> 0 | G55: =ROUND(INDEX('Atrium + Updated Rates'!$E:$E,MATCH($B55,'Atrium + Updated Rates'!$O:$O,0)),0) -> 0 | H55: =ROUND((G55-C55)*D55,2) -> 0 | J55: =INDEX('Rates and Eff Dates'!D:D,MATCH($B55,'Rates and Eff Dates'!$B:$B,0)) -> 27.55 | K55: =(J55-D55)*$G55 -> 0 | M55: =INDEX('Rates and Eff Dates'!E:E,MATCH($B55,'Rates and Eff Dates'!$B:$B,0)) -> 27.29 | N55: =(M55-J55)*$G55 -> 0 | P55: =H55+K55+N55 -> 0 | Q55: =E55+P55 -> 0
A56: =IF(AND(B56="",E56=""),"",MAX(A$7:A55)+1) -> 41 | B56: ='Rates and Eff Dates'!B56 -> MV-60000 Street and Highway Type | C56: =INDEX('Outdoor Lighting Update'!I:I,MATCH($B56,'Outdoor Lighting Update'!O:O,0)) -> 84 | D56: =INDEX('Rates and Eff Dates'!C:C,MATCH($B56,'Rates and Eff Dates'!$B:$B,0)) -> 51.19 | E56: =C56*D56 -> 4299.96 | G56: =ROUND(INDEX('Atrium + Updated Rates'!$E:$E,MATCH($B56,'Atrium + Updated Rates'!$O:$O,0)),0) -> 84 | H56: =ROUND((G56-C56)*D56,2) -> 0 | J56: =INDEX('Rates and Eff Dates'!D:D,MATCH($B56,'Rates and Eff Dates'!$B:$B,0)) -> 52.67 | K56: =(J56-D56)*$G56 -> 124.32 | M56: =INDEX('Rates and Eff Dates'!E:E,MATCH($B56,'Rates and Eff Dates'!$B:$B,0)) -> 52.18 | N56: =(M56-J56)*$G56 -> -41.16 | P56: =H56+K56+N56 -> 83.16 | Q56: =E56+P56 -> 4383.12
A57: =IF(AND(B57="",E57=""),"",MAX(A$7:A56)+1) -> 42 | B57: ='Rates and Eff Dates'!B57 -> MV-20000 Flood Light Type | C57: =INDEX('Outdoor Lighting Update'!I:I,MATCH($B57,'Outdoor Lighting Update'!O:O,0)) -> 300 | D57: =INDEX('Rates and Eff Dates'!C:C,MATCH($B57,'Rates and Eff Dates'!$B:$B,0)) -> 29.61 | E57: =C57*D57 -> 8883 | G57: =ROUND(INDEX('Atrium + Updated Rates'!$E:$E,MATCH($B57,'Atrium + Updated Rates'!$O:$O,0)),0) -> 300 | H57: =ROUND((G57-C57)*D57,2) -> 0 | J57: =INDEX('Rates and Eff Dates'!D:D,MATCH($B57,'Rates and Eff Dates'!$B:$B,0)) -> 30.46 | K57: =(J57-D57)*$G57 -> 255 | M57: =INDEX('Rates and Eff Dates'!E:E,MATCH($B57,'Rates and Eff Dates'!$B:$B,0)) -> 30.18 | N57: =(M57-J57)*$G57 -> -84 | P57: =H57+K57+N57 -> 171 | Q57: =E57+P57 -> 9054
A58: =IF(AND(B58="",E58=""),"",MAX(A$7:A57)+1) -> 43 | B58: ='Rates and Eff Dates'!B58 -> MV-3500 Power Bracket Included | C58: =INDEX('Outdoor Lighting Update'!I:I,MATCH($B58,'Outdoor Lighting Update'!O:O,0)) -> 402.06609 | D58: =INDEX('Rates and Eff Dates'!C:C,MATCH($B58,'Rates and Eff Dates'!$B:$B,0)) -> 13.92 | E58: =C58*D58 -> 5596.76 | G58: =ROUND(INDEX('Atrium + Updated Rates'!$E:$E,MATCH($B58,'Atrium + Updated Rates'!$O:$O,0)),0) -> 348 | H58: =ROUND((G58-C58)*D58,2) -> -752.6 | J58: =INDEX('Rates and Eff Dates'!D:D,MATCH($B58,'Rates and Eff Dates'!$B:$B,0)) -> 14.32 | K58: =(J58-D58)*$G58 -> 139.2 | M58: =INDEX('Rates and Eff Dates'!E:E,MATCH($B58,'Rates and Eff Dates'!$B:$B,0)) -> 14.18 | N58: =(M58-J58)*$G58 -> -48.72 | P58: =H58+K58+N58 -> -662.12 | Q58: =E58+P58 -> 4934.64
A59: =IF(AND(B59="",E59=""),"",MAX(A$7:A58)+1) -> 44 | B59: ='Rates and Eff Dates'!B59 -> MV-7000 Power Bracket Included | C59: =INDEX('Outdoor Lighting Update'!I:I,MATCH($B59,'Outdoor Lighting Update'!O:O,0)) -> 323.96618 | D59: =INDEX('Rates and Eff Dates'!C:C,MATCH($B59,'Rates and Eff Dates'!$B:$B,0)) -> 15.67 | E59: =C59*D59 -> 5076.55 | G59: =ROUND(INDEX('Atrium + Updated Rates'!$E:$E,MATCH($B59,'Atrium + Updated Rates'!$O:$O,0)),0) -> 300 | H59: =ROUND((G59-C59)*D59,2) -> -375.55 | J59: =INDEX('Rates and Eff Dates'!D:D,MATCH($B59,'Rates and Eff Dates'!$B:$B,0)) -> 16.12 | K59: =(J59-D59)*$G59 -> 135 | M59: =INDEX('Rates and Eff Dates'!E:E,MATCH($B59,'Rates and Eff Dates'!$B:$B,0)) -> 15.97 | N59: =(M59-J59)*$G59 -> -45 | P59: =H59+K59+N59 -> -285.55 | Q59: =E59+P59 -> 4791
A60: =IF(AND(B60="",E60=""),"",MAX(A$7:A59)+1) -> 45 | B60: ='Rates and Eff Dates'!A61 -> High Pressure Sodium Luminaires
A61: =IF(AND(B61="",E61=""),"",MAX(A$7:A60)+1) -> 46 | B61: ='Rates and Eff Dates'!B62 -> HPS-3300 Street and Highway Type | C61: =INDEX('Outdoor Lighting Update'!I:I,MATCH($B61,'Outdoor Lighting Update'!O:O,0)) -> 3914.9662 | D61: =INDEX('Rates and Eff Dates'!C:C,MATCH($B61,'Rates and Eff Dates'!$B:$B,0)) -> 11.53 | E61: =C61*D61 -> 45139.56 | G61: =ROUND(INDEX('Atrium + Updated Rates'!$E:$E,MATCH($B61,'Atrium + Updated Rates'!$O:$O,0)),0) -> 1580 | H61: =ROUND((G61-C61)*D61,2) -> -26922.16 | J61: =INDEX('Rates and Eff Dates'!D:D,MATCH($B61,'Rates and Eff Dates'!$B:$B,0)) -> 11.86 | K61: =(J61-D61)*$G61 -> 521.4 | M61: =INDEX('Rates and Eff Dates'!E:E,MATCH($B61,'Rates and Eff Dates'!$B:$B,0)) -> 11.75 | N61: =(M61-J61)*$G61 -> -173.8 | P61: =H61+K61+N61 -> -26574.56 | Q61: =E61+P61 -> 18565
A62: =IF(AND(B62="",E62=""),"",MAX(A$7:A61)+1) -> 47 | B62: ='Rates and Eff Dates'!B63 -> HPS-9500 Street and Highway Type | C62: =INDEX('Outdoor Lighting Update'!I:I,MATCH($B62,'Outdoor Lighting Update'!O:O,0)) -> 1585.6214 | D62: =INDEX('Rates and Eff Dates'!C:C,MATCH($B62,'Rates and Eff Dates'!$B:$B,0)) -> 13.71 | E62: =C62*D62 -> 21738.87 | G62: =ROUND(INDEX('Atrium + Updated Rates'!$E:$E,MATCH($B62,'Atrium + Updated Rates'!$O:$O,0)),0) -> 996 | H62: =ROUND((G62-C62)*D62,2) -> -8083.71 | J62: =INDEX('Rates and Eff Dates'!D:D,MATCH($B62,'Rates and Eff Dates'!$B:$B,0)) -> 14.1 | K62: =(J62-D62)*$G62 -> 388.44 | M62: =INDEX('Rates and Eff Dates'!E:E,MATCH($B62,'Rates and Eff Dates'!$B:$B,0)) -> 13.97 | N62: =(M62-J62)*$G62 -> -129.48 | P62: =H62+K62+N62 -> -7824.75 | Q62: =E62+P62 -> 13914.12
A63: =IF(AND(B63="",E63=""),"",MAX(A$7:A62)+1) -> 48 | B63: ='Rates and Eff Dates'!B64 -> HPS-20000 Street and Highway Type | C63: =INDEX('Outdoor Lighting Update'!I:I,MATCH($B63,'Outdoor Lighting Update'!O:O,0)) -> 402 | D63: =INDEX('Rates and Eff Dates'!C:C,MATCH($B63,'Rates and Eff Dates'!$B:$B,0)) -> 20.44 | E63: =C63*D63 -> 8216.88 | G63: =ROUND(INDEX('Atrium + Updated Rates'!$E:$E,MATCH($B63,'Atrium + Updated Rates'!$O:$O,0)),0) -> 96 | H63: =ROUND((G63-C63)*D63,2) -> -6254.64 | J63: =INDEX('Rates and Eff Dates'!D:D,MATCH($B63,'Rates and Eff Dates'!$B:$B,0)) -> 21.03 | K63: =(J63-D63)*$G63 -> 56.64 | M63: =INDEX('Rates and Eff Dates'!E:E,MATCH($B63,'Rates and Eff Dates'!$B:$B,0)) -> 20.83 | N63: =(M63-J63)*$G63 -> -19.2 | P63: =H63+K63+N63 -> -6217.2 | Q63: =E63+P63 -> 1999.68
A64: =IF(AND(B64="",E64=""),"",MAX(A$7:A63)+1) -> 49 | B64: ='Rates and Eff Dates'!B65 -> HPS-50000 Street and Highway Type | C64: =INDEX('Outdoor Lighting Update'!I:I,MATCH($B64,'Outdoor Lighting Update'!O:O,0)) -> 111 | D64: =INDEX('Rates and Eff Dates'!C:C,MATCH($B64,'Rates and Eff Dates'!$B:$B,0)) -> 29.06 | E64: =C64*D64 -> 3225.66 | G64: =ROUND(INDEX('Atrium + Updated Rates'!$E:$E,MATCH($B64,'Atrium + Updated Rates'!$O:$O,0)),0) -> 72 | H64: =ROUND((G64-C64)*D64,2) -> -1133.34 | J64: =INDEX('Rates and Eff Dates'!D:D,MATCH($B64,'Rates and Eff Dates'!$B:$B,0)) -> 29.9 | K64: =(J64-D64)*$G64 -> 60.48 | M64: =INDEX('Rates and Eff Dates'!E:E,MATCH($B64,'Rates and Eff Dates'!$B:$B,0)) -> 29.62 | N64: =(M64-J64)*$G64 -> -20.16 | P64: =H64+K64+N64 -> -1093.02 | Q64: =E64+P64 -> 2132.64
A65: =IF(AND(B65="",E65=""),"",MAX(A$7:A64)+1) -> 50 | B65: ='Rates and Eff Dates'!B66 -> HPS-140000 Street and Highway Type | C65: =INDEX('Outdoor Lighting Update'!I:I,MATCH($B65,'Outdoor Lighting Update'!O:O,0)) -> 795.7313 | D65: =INDEX('Rates and Eff Dates'!C:C,MATCH($B65,'Rates and Eff Dates'!$B:$B,0)) -> 59.62 | E65: =C65*D65 -> 47441.5 | G65: =ROUND(INDEX('Atrium + Updated Rates'!$E:$E,MATCH($B65,'Atrium + Updated Rates'!$O:$O,0)),0) -> 516 | H65: =ROUND((G65-C65)*D65,2) -> -16677.58 | J65: =INDEX('Rates and Eff Dates'!D:D,MATCH($B65,'Rates and Eff Dates'!$B:$B,0)) -> 61.34 | K65: =(J65-D65)*$G65 -> 887.52 | M65: =INDEX('Rates and Eff Dates'!E:E,MATCH($B65,'Rates and Eff Dates'!$B:$B,0)) -> 60.77 | N65: =(M65-J65)*$G65 -> -294.12 | P65: =H65+K65+N65 -> -16084.18 | Q65: =E65+P65 -> 31357.32
A66: =IF(AND(B66="",E66=""),"",MAX(A$7:A65)+1) -> 51 | B66: ='Rates and Eff Dates'!B67 -> HPS-50000 Flood Light Type | C66: =INDEX('Outdoor Lighting Update'!I:I,MATCH($B66,'Outdoor Lighting Update'!O:O,0)) -> 4031.4133 | D66: =INDEX('Rates and Eff Dates'!C:C,MATCH($B66,'Rates and Eff Dates'!$B:$B,0)) -> 33.73 | E66: =C66*D66 -> 135979.57 | G66: =ROUND(INDEX('Atrium + Updated Rates'!$E:$E,MATCH($B66,'Atrium + Updated Rates'!$O:$O,0)),0) -> 3480 | H66: =ROUND((G66-C66)*D66,2) -> -18599.17 | J66: =INDEX('Rates and Eff Dates'!D:D,MATCH($B66,'Rates and Eff Dates'!$B:$B,0)) -> 34.7 | K66: =(J66-D66)*$G66 -> 3375.6 | M66: =INDEX('Rates and Eff Dates'!E:E,MATCH($B66,'Rates and Eff Dates'!$B:$B,0)) -> 34.38 | N66: =(M66-J66)*$G66 -> -1113.6 | P66: =H66+K66+N66 -> -16337.17 | Q66: =E66+P66 -> 119642.4
A67: =IF(AND(B67="",E67=""),"",MAX(A$7:A66)+1) -> 52 | B67: ='Rates and Eff Dates'!A69 -> Metal Halide Luminaires
A68: =IF(AND(B68="",E68=""),"",MAX(A$7:A67)+1) -> 53 | B68: ='Rates and Eff Dates'!B70 -> MH-3700 Cobra Head Type | D68: =INDEX('Rates and Eff Dates'!C:C,MATCH($B68,'Rates and Eff Dates'!$B:$B,0)) -> 16.14 | E68: =C68*D68 -> 0 | H68: =ROUND((G68-C68)*D68,2) -> 0 | J68: =INDEX('Rates and Eff Dates'!D:D,MATCH($B68,'Rates and Eff Dates'!$B:$B,0)) -> 16.6 | K68: =(J68-D68)*$G68 -> 0 | M68: =INDEX('Rates and Eff Dates'!E:E,MATCH($B68,'Rates and Eff Dates'!$B:$B,0)) -> 16.44 | N68: =(M68-J68)*$G68 -> 0 | P68: =H68+K68+N68 -> 0 | Q68: =E68+P68 -> 0
A69: =IF(AND(B69="",E69=""),"",MAX(A$7:A68)+1) -> 54 | B69: ='Rates and Eff Dates'!B71 -> MH-5000 Cobra Head Type | D69: =INDEX('Rates and Eff Dates'!C:C,MATCH($B69,'Rates and Eff Dates'!$B:$B,0)) -> 18.44 | E69: =C69*D69 -> 0 | H69: =ROUND((G69-C69)*D69,2) -> 0 | J69: =INDEX('Rates and Eff Dates'!D:D,MATCH($B69,'Rates and Eff Dates'!$B:$B,0)) -> 18.97 | K69: =(J69-D69)*$G69 -> 0 | M69: =INDEX('Rates and Eff Dates'!E:E,MATCH($B69,'Rates and Eff Dates'!$B:$B,0)) -> 18.79 | N69: =(M69-J69)*$G69 -> 0 | P69: =H69+K69+N69 -> 0 | Q69: =E69+P69 -> 0
A70: =IF(AND(B70="",E70=""),"",MAX(A$7:A69)+1) -> 55 | B70: ='Rates and Eff Dates'!B72 -> MH-10000 Cobra Head Type | D70: =INDEX('Rates and Eff Dates'!C:C,MATCH($B70,'Rates and Eff Dates'!$B:$B,0)) -> 22.79 | E70: =C70*D70 -> 0 | H70: =ROUND((G70-C70)*D70,2) -> 0 | J70: =INDEX('Rates and Eff Dates'!D:D,MATCH($B70,'Rates and Eff Dates'!$B:$B,0)) -> 23.44 | K70: =(J70-D70)*$G70 -> 0 | M70: =INDEX('Rates and Eff Dates'!E:E,MATCH($B70,'Rates and Eff Dates'!$B:$B,0)) -> 23.22 | N70: =(M70-J70)*$G70 -> 0 | P70: =H70+K70+N70 -> 0 | Q70: =E70+P70 -> 0
A71: =IF(AND(B71="",E71=""),"",MAX(A$7:A70)+1) -> 56 | B71: ='Rates and Eff Dates'!B73 -> MH-3700 Flood Light Type | D71: =INDEX('Rates and Eff Dates'!C:C,MATCH($B71,'Rates and Eff Dates'!$B:$B,0)) -> 16.48 | E71: =C71*D71 -> 0 | H71: =ROUND((G71-C71)*D71,2) -> 0 | J71: =INDEX('Rates and Eff Dates'!D:D,MATCH($B71,'Rates and Eff Dates'!$B:$B,0)) -> 16.95 | K71: =(J71-D71)*$G71 -> 0 | M71: =INDEX('Rates and Eff Dates'!E:E,MATCH($B71,'Rates and Eff Dates'!$B:$B,0)) -> 16.79 | N71: =(M71-J71)*$G71 -> 0 | P71: =H71+K71+N71 -> 0 | Q71: =E71+P71 -> 0
A72: =IF(AND(B72="",E72=""),"",MAX(A$7:A71)+1) -> 57 | B72: ='Rates and Eff Dates'!B74 -> MH-5000 Flood Light Type | D72: =INDEX('Rates and Eff Dates'!C:C,MATCH($B72,'Rates and Eff Dates'!$B:$B,0)) -> 19.06 | E72: =C72*D72 -> 0 | H72: =ROUND((G72-C72)*D72,2) -> 0 | J72: =INDEX('Rates and Eff Dates'!D:D,MATCH($B72,'Rates and Eff Dates'!$B:$B,0)) -> 19.61 | K72: =(J72-D72)*$G72 -> 0 | M72: =INDEX('Rates and Eff Dates'!E:E,MATCH($B72,'Rates and Eff Dates'!$B:$B,0)) -> 19.43 | N72: =(M72-J72)*$G72 -> 0 | P72: =H72+K72+N72 -> 0 | Q72: =E72+P72 -> 0
A73: =IF(AND(B73="",E73=""),"",MAX(A$7:A72)+1) -> 58 | B73: ='Rates and Eff Dates'!B75 -> MH-10000 Flood Light Type | D73: =INDEX('Rates and Eff Dates'!C:C,MATCH($B73,'Rates and Eff Dates'!$B:$B,0)) -> 22.64 | E73: =C73*D73 -> 0 | H73: =ROUND((G73-C73)*D73,2) -> 0 | J73: =INDEX('Rates and Eff Dates'!D:D,MATCH($B73,'Rates and Eff Dates'!$B:$B,0)) -> 23.29 | K73: =(J73-D73)*$G73 -> 0 | M73: =INDEX('Rates and Eff Dates'!E:E,MATCH($B73,'Rates and Eff Dates'!$B:$B,0)) -> 23.07 | N73: =(M73-J73)*$G73 -> 0 | P73: =H73+K73+N73 -> 0 | Q73: =E73+P73 -> 0
A74: =IF(AND(B74="",E74=""),"",MAX(A$7:A73)+1) -> 59 | B74: ='Rates and Eff Dates'!B76 -> MH-47000 Flood Light Type | D74: =INDEX('Rates and Eff Dates'!C:C,MATCH($B74,'Rates and Eff Dates'!$B:$B,0)) -> 48.66 | E74: =C74*D74 -> 0 | H74: =ROUND((G74-C74)*D74,2) -> 0 | J74: =INDEX('Rates and Eff Dates'!D:D,MATCH($B74,'Rates and Eff Dates'!$B:$B,0)) -> 50.06 | K74: =(J74-D74)*$G74 -> 0 | M74: =INDEX('Rates and Eff Dates'!E:E,MATCH($B74,'Rates and Eff Dates'!$B:$B,0)) -> 49.6 | N74: =(M74-J74)*$G74 -> 0 | P74: =H74+K74+N74 -> 0 | Q74: =E74+P74 -> 0
A75: =IF(AND(B75="",E75=""),"",MAX(A$7:A74)+1) -> 60 | B75: ='Rates and Eff Dates'!B77 -> MH-3700 Power Bracket Included | D75: =INDEX('Rates and Eff Dates'!C:C,MATCH($B75,'Rates and Eff Dates'!$B:$B,0)) -> 16.42 | E75: =C75*D75 -> 0 | H75: =ROUND((G75-C75)*D75,2) -> 0 | J75: =INDEX('Rates and Eff Dates'!D:D,MATCH($B75,'Rates and Eff Dates'!$B:$B,0)) -> 16.89 | K75: =(J75-D75)*$G75 -> 0 | M75: =INDEX('Rates and Eff Dates'!E:E,MATCH($B75,'Rates and Eff Dates'!$B:$B,0)) -> 16.73 | N75: =(M75-J75)*$G75 -> 0 | P75: =H75+K75+N75 -> 0 | Q75: =E75+P75 -> 0
A76: =IF(AND(B76="",E76=""),"",MAX(A$7:A75)+1) -> 61 | B76: ='Rates and Eff Dates'!B78 -> MH-5000 Power Bracket Included | D76: =INDEX('Rates and Eff Dates'!C:C,MATCH($B76,'Rates and Eff Dates'!$B:$B,0)) -> 18.74 | E76: =C76*D76 -> 0 | H76: =ROUND((G76-C76)*D76,2) -> 0 | J76: =INDEX('Rates and Eff Dates'!D:D,MATCH($B76,'Rates and Eff Dates'!$B:$B,0)) -> 19.28 | K76: =(J76-D76)*$G76 -> 0 | M76: =INDEX('Rates and Eff Dates'!E:E,MATCH($B76,'Rates and Eff Dates'!$B:$B,0)) -> 19.1 | N76: =(M76-J76)*$G76 -> 0 | P76: =H76+K76+N76 -> 0 | Q76: =E76+P76 -> 0
A77: =IF(AND(B77="",E77=""),"",MAX(A$7:A76)+1) -> 62 | B77: ='Rates and Eff Dates'!B79 -> MH-10000 Power Bracket Included | D77: =INDEX('Rates and Eff Dates'!C:C,MATCH($B77,'Rates and Eff Dates'!$B:$B,0)) -> 23.15 | E77: =C77*D77 -> 0 | H77: =ROUND((G77-C77)*D77,2) -> 0 | J77: =INDEX('Rates and Eff Dates'!D:D,MATCH($B77,'Rates and Eff Dates'!$B:$B,0)) -> 23.82 | K77: =(J77-D77)*$G77 -> 0 | M77: =INDEX('Rates and Eff Dates'!E:E,MATCH($B77,'Rates and Eff Dates'!$B:$B,0)) -> 23.6 | N77: =(M77-J77)*$G77 -> 0 | P77: =H77+K77+N77 -> 0 | Q77: =E77+P77 -> 0
A78: =IF(AND(B78="",E78=""),"",MAX(A$7:A77)+1) -> 63 | B78: ='Rates and Eff Dates'!A81 -> Light Emitting Diode Luminaires
A79: =IF(AND(B79="",E79=""),"",MAX(A$7:A78)+1) -> 64 | B79: ='Rates and Eff Dates'!B82 -> LED-3850 Cobra Head Type | D79: =INDEX('Rates and Eff Dates'!C:C,MATCH($B79,'Rates and Eff Dates'!$B:$B,0)) -> 9.97 | E79: =C79*D79 -> 0 | H79: =ROUND((G79-C79)*D79,2) -> 0 | J79: =INDEX('Rates and Eff Dates'!D:D,MATCH($B79,'Rates and Eff Dates'!$B:$B,0)) -> 10.25 | K79: =(J79-D79)*$G79 -> 0 | M79: =INDEX('Rates and Eff Dates'!E:E,MATCH($B79,'Rates and Eff Dates'!$B:$B,0)) -> 10.15 | N79: =(M79-J79)*$G79 -> 0 | P79: =H79+K79+N79 -> 0 | Q79: =E79+P79 -> 0
A80: =IF(AND(B80="",E80=""),"",MAX(A$7:A79)+1) -> 65 | B80: ='Rates and Eff Dates'!B83 -> LED-6100 Cobra Head Type | D80: =INDEX('Rates and Eff Dates'!C:C,MATCH($B80,'Rates and Eff Dates'!$B:$B,0)) -> 11.82 | E80: =C80*D80 -> 0 | H80: =ROUND((G80-C80)*D80,2) -> 0 | J80: =INDEX('Rates and Eff Dates'!D:D,MATCH($B80,'Rates and Eff Dates'!$B:$B,0)) -> 12.16 | K80: =(J80-D80)*$G80 -> 0 | M80: =INDEX('Rates and Eff Dates'!E:E,MATCH($B80,'Rates and Eff Dates'!$B:$B,0)) -> 12.04 | N80: =(M80-J80)*$G80 -> 0 | P80: =H80+K80+N80 -> 0 | Q80: =E80+P80 -> 0
A81: =IF(AND(B81="",E81=""),"",MAX(A$7:A80)+1) -> 66 | B81: ='Rates and Eff Dates'!B84 -> LED-10680 Cobra Head Type | C81: =INDEX('Outdoor Lighting Update'!I:I,MATCH($B81,'Outdoor Lighting Update'!O:O,0)) -> 84 | D81: =INDEX('Rates and Eff Dates'!C:C,MATCH($B81,'Rates and Eff Dates'!$B:$B,0)) -> 14.82 | E81: =C81*D81 -> 1244.88 | G81: =ROUND(INDEX('Atrium + Updated Rates'!$E:$E,MATCH($B81,'Atrium + Updated Rates'!$O:$O,0)),0) -> 84 | H81: =ROUND((G81-C81)*D81,2) -> 0 | J81: =INDEX('Rates and Eff Dates'!D:D,MATCH($B81,'Rates and Eff Dates'!$B:$B,0)) -> 15.24 | K81: =(J81-D81)*$G81 -> 35.28 | M81: =INDEX('Rates and Eff Dates'!E:E,MATCH($B81,'Rates and Eff Dates'!$B:$B,0)) -> 15.1 | N81: =(M81-J81)*$G81 -> -11.76 | P81: =H81+K81+N81 -> 23.52 | Q81: =E81+P81 -> 1268.4
A82: =IF(AND(B82="",E82=""),"",MAX(A$7:A81)+1) -> 67 | B82: ='Rates and Eff Dates'!B85 -> LED-20000 Cobra Head Type | D82: =INDEX('Rates and Eff Dates'!C:C,MATCH($B82,'Rates and Eff Dates'!$B:$B,0)) -> 23.88 | E82: =C82*D82 -> 0 | H82: =ROUND((G82-C82)*D82,2) -> 0 | J82: =INDEX('Rates and Eff Dates'!D:D,MATCH($B82,'Rates and Eff Dates'!$B:$B,0)) -> 24.57 | K82: =(J82-D82)*$G82 -> 0 | M82: =INDEX('Rates and Eff Dates'!E:E,MATCH($B82,'Rates and Eff Dates'!$B:$B,0)) -> 24.34 | N82: =(M82-J82)*$G82 -> 0 | P82: =H82+K82+N82 -> 0 | Q82: =E82+P82 -> 0
A83: =IF(AND(B83="",E83=""),"",MAX(A$7:A82)+1) -> 68 | B83: ='Rates and Eff Dates'!B86 -> LED-4572 Flood Light Type | D83: =INDEX('Rates and Eff Dates'!C:C,MATCH($B83,'Rates and Eff Dates'!$B:$B,0)) -> 15.59 | E83: =C83*D83 -> 0 | H83: =ROUND((G83-C83)*D83,2) -> 0 | J83: =INDEX('Rates and Eff Dates'!D:D,MATCH($B83,'Rates and Eff Dates'!$B:$B,0)) -> 16.04 | K83: =(J83-D83)*$G83 -> 0 | M83: =INDEX('Rates and Eff Dates'!E:E,MATCH($B83,'Rates and Eff Dates'!$B:$B,0)) -> 15.89 | N83: =(M83-J83)*$G83 -> 0 | P83: =H83+K83+N83 -> 0 | Q83: =E83+P83 -> 0
A84: =IF(AND(B84="",E84=""),"",MAX(A$7:A83)+1) -> 69 | B84: ='Rates and Eff Dates'!B87 -> LED-6810 Flood Light Type | D84: =INDEX('Rates and Eff Dates'!C:C,MATCH($B84,'Rates and Eff Dates'!$B:$B,0)) -> 16.39 | E84: =C84*D84 -> 0 | H84: =ROUND((G84-C84)*D84,2) -> 0 | J84: =INDEX('Rates and Eff Dates'!D:D,MATCH($B84,'Rates and Eff Dates'!$B:$B,0)) -> 16.86 | K84: =(J84-D84)*$G84 -> 0 | M84: =INDEX('Rates and Eff Dates'!E:E,MATCH($B84,'Rates and Eff Dates'!$B:$B,0)) -> 16.7 | N84: =(M84-J84)*$G84 -> 0 | P84: =H84+K84+N84 -> 0 | Q84: =E84+P84 -> 0
A85: =IF(AND(B85="",E85=""),"",MAX(A$7:A84)+1) -> 70 | B85: ='Rates and Eff Dates'!B88 -> LED-11253 Flood Light Type | D85: =INDEX('Rates and Eff Dates'!C:C,MATCH($B85,'Rates and Eff Dates'!$B:$B,0)) -> 25.39 | E85: =C85*D85 -> 0 | H85: =ROUND((G85-C85)*D85,2) -> 0 | J85: =INDEX('Rates and Eff Dates'!D:D,MATCH($B85,'Rates and Eff Dates'!$B:$B,0)) -> 26.12 | K85: =(J85-D85)*$G85 -> 0 | M85: =INDEX('Rates and Eff Dates'!E:E,MATCH($B85,'Rates and Eff Dates'!$B:$B,0)) -> 25.88 | N85: =(M85-J85)*$G85 -> 0 | P85: =H85+K85+N85 -> 0 | Q85: =E85+P85 -> 0
A86: =IF(AND(B86="",E86=""),"",MAX(A$7:A85)+1) -> 71 | B86: ='Rates and Eff Dates'!B89 -> LED-15300 Flood Light Type | D86: =INDEX('Rates and Eff Dates'!C:C,MATCH($B86,'Rates and Eff Dates'!$B:$B,0)) -> 25.3 | E86: =C86*D86 -> 0 | H86: =ROUND((G86-C86)*D86,2) -> 0 | J86: =INDEX('Rates and Eff Dates'!D:D,MATCH($B86,'Rates and Eff Dates'!$B:$B,0)) -> 26.03 | K86: =(J86-D86)*$G86 -> 0 | M86: =INDEX('Rates and Eff Dates'!E:E,MATCH($B86,'Rates and Eff Dates'!$B:$B,0)) -> 25.79 | N86: =(M86-J86)*$G86 -> 0 | P86: =H86+K86+N86 -> 0 | Q86: =E86+P86 -> 0
A87: =IF(AND(B87="",E87=""),"",MAX(A$7:A86)+1) -> 72 | B87: ='Rates and Eff Dates'!B90 -> LED-50403 Flood Light Type | D87: =INDEX('Rates and Eff Dates'!C:C,MATCH($B87,'Rates and Eff Dates'!$B:$B,0)) -> 54.63 | E87: =C87*D87 -> 0 | H87: =ROUND((G87-C87)*D87,2) -> 0 | J87: =INDEX('Rates and Eff Dates'!D:D,MATCH($B87,'Rates and Eff Dates'!$B:$B,0)) -> 56.21 | K87: =(J87-D87)*$G87 -> 0 | M87: =INDEX('Rates and Eff Dates'!E:E,MATCH($B87,'Rates and Eff Dates'!$B:$B,0)) -> 55.69 | N87: =(M87-J87)*$G87 -> 0 | P87: =H87+K87+N87 -> 0 | Q87: =E87+P87 -> 0
A88: =IF(AND(B88="",E88=""),"",MAX(A$7:A87)+1) -> 73 | B88: ='Rates and Eff Dates'!B91 -> LED-2887 Power Bracket Included | D88: =INDEX('Rates and Eff Dates'!C:C,MATCH($B88,'Rates and Eff Dates'!$B:$B,0)) -> 10.61 | E88: =C88*D88 -> 0 | H88: =ROUND((G88-C88)*D88,2) -> 0 | J88: =INDEX('Rates and Eff Dates'!D:D,MATCH($B88,'Rates and Eff Dates'!$B:$B,0)) -> 10.91 | K88: =(J88-D88)*$G88 -> 0 | M88: =INDEX('Rates and Eff Dates'!E:E,MATCH($B88,'Rates and Eff Dates'!$B:$B,0)) -> 10.81 | N88: =(M88-J88)*$G88 -> 0 | P88: =H88+K88+N88 -> 0 | Q88: =E88+P88 -> 0
A89: =IF(AND(B89="",E89=""),"",MAX(A$7:A88)+1) -> 74 | B89: ='Rates and Eff Dates'!B92 -> LED-6100 Power Bracket Included | D89: =INDEX('Rates and Eff Dates'!C:C,MATCH($B89,'Rates and Eff Dates'!$B:$B,0)) -> 11.82 | E89: =C89*D89 -> 0 | H89: =ROUND((G89-C89)*D89,2) -> 0 | J89: =INDEX('Rates and Eff Dates'!D:D,MATCH($B89,'Rates and Eff Dates'!$B:$B,0)) -> 12.16 | K89: =(J89-D89)*$G89 -> 0 | M89: =INDEX('Rates and Eff Dates'!E:E,MATCH($B89,'Rates and Eff Dates'!$B:$B,0)) -> 12.04 | N89: =(M89-J89)*$G89 -> 0 | P89: =H89+K89+N89 -> 0 | Q89: =E89+P89 -> 0
A90: =IF(AND(B90="",E90=""),"",MAX(A$7:A89)+1) -> 75 | B90: ='Rates and Eff Dates'!B93 -> LED-12290 Power Bracket Included | D90: =INDEX('Rates and Eff Dates'!C:C,MATCH($B90,'Rates and Eff Dates'!$B:$B,0)) -> 17.64 | E90: =C90*D90 -> 0 | H90: =ROUND((G90-C90)*D90,2) -> 0 | J90: =INDEX('Rates and Eff Dates'!D:D,MATCH($B90,'Rates and Eff Dates'!$B:$B,0)) -> 18.15 | K90: =(J90-D90)*$G90 -> 0 | M90: =INDEX('Rates and Eff Dates'!E:E,MATCH($B90,'Rates and Eff Dates'!$B:$B,0)) -> 17.98 | N90: =(M90-J90)*$G90 -> 0 | P90: =H90+K90+N90 -> 0 | Q90: =E90+P90 -> 0
A91: =IF(AND(B91="",E91=""),"",MAX(A$7:A90)+1) -> 76 | B91: ='Rates and Eff Dates'!B94 -> LED-17200 Power Bracket Included | D91: =INDEX('Rates and Eff Dates'!C:C,MATCH($B91,'Rates and Eff Dates'!$B:$B,0)) -> 21.06 | E91: =C91*D91 -> 0 | H91: =ROUND((G91-C91)*D91,2) -> 0 | J91: =INDEX('Rates and Eff Dates'!D:D,MATCH($B91,'Rates and Eff Dates'!$B:$B,0)) -> 21.66 | K91: =(J91-D91)*$G91 -> 0 | M91: =INDEX('Rates and Eff Dates'!E:E,MATCH($B91,'Rates and Eff Dates'!$B:$B,0)) -> 21.46 | N91: =(M91-J91)*$G91 -> 0 | P91: =H91+K91+N91 -> 0 | Q91: =E91+P91 -> 0
A92: =IF(AND(B92="",E92=""),"",MAX(A$7:A91)+1) -> 77 | B92: ='Rates and Eff Dates'!A97 -> Ornamental Lighting Luminaires
A93: =IF(AND(B93="",E93=""),"",MAX(A$7:A92)+1) -> 78 | B93: ='Rates and Eff Dates'!B98 -> 3300 Street and Highway-Ornament | C93: =INDEX('Outdoor Lighting Update'!I:I,MATCH($B93,'Outdoor Lighting Update'!O:O,0)) -> 18 | D93: =INDEX('Rates and Eff Dates'!C:C,MATCH($B93,'Rates and Eff Dates'!$B:$B,0)) -> 9.26 | E93: =C93*D93 -> 166.68 | G93: =ROUND(INDEX('Atrium + Updated Rates'!$E:$E,MATCH($B93,'Atrium + Updated Rates'!$O:$O,0)),0) -> 0 | H93: =ROUND((G93-C93)*D93,2) -> -166.68 | J93: =INDEX('Rates and Eff Dates'!D:D,MATCH($B93,'Rates and Eff Dates'!$B:$B,0)) -> 9.52 | K93: =(J93-D93)*$G93 -> 0 | M93: =INDEX('Rates and Eff Dates'!E:E,MATCH($B93,'Rates and Eff Dates'!$B:$B,0)) -> 9.43 | N93: =(M93-J93)*$G93 -> 0 | P93: =H93+K93+N93 -> -166.68 | Q93: =E93+P93 -> 0
A94: =IF(AND(B94="",E94=""),"",MAX(A$7:A93)+1) -> 79 | B94: ='Rates and Eff Dates'!A100 -> Special Agreement Luminaires
